Compiled from "CasUsernamePasswordAuthenticationFilter.java"
public class com.virtual.plat.security.CasUsernamePasswordAuthenticationFilter extends org.springframework.security.web.authentication.UsernamePasswordAuthenticationFilter {
  private boolean postOnly;

  private static org.apache.commons.logging.Log log;

  private java.lang.String isForceParameter;

  private int maxFailCount;

  private long lockTime;

  private boolean checkPasswordAttack;

  private com.virtual.plat.server.param.ParameterMgr parameterMgr;

  private com.virtual.plat.server.operator.OperatorMgr operatorMgr;

  private com.virtual.common.StringManager sm;

  private void readLoginConfig();
    Code:
       0: aload_0
       1: getfield      #1                  // Field parameterMgr:Lcom/virtual/plat/server/param/ParameterMgr;
       4: ldc           #2                  // String login.max.fail.counts
       6: invokeinterface #3,  2            // InterfaceMethod com/virtual/plat/server/param/ParameterMgr.queryByName:(Ljava/lang/String;)Lcom/virtual/plat/server/entity/Parameter;
      11: astore_1
      12: aload_0
      13: aload_1
      14: invokevirtual #4                  // Method com/virtual/plat/server/entity/Parameter.getValue:()Ljava/lang/String;
      17: invokestatic  #5                  // Method java/lang/Integer.parseInt:(Ljava/lang/String;)I
      20: putfield      #6                  // Field maxFailCount:I
      23: goto          37
      26: astore_1
      27: getstatic     #8                  // Field log:Lorg/apache/commons/logging/Log;
      30: aconst_null
      31: aload_1
      32: invokeinterface #9,  3            // InterfaceMethod org/apache/commons/logging/Log.error:(Ljava/lang/Object;Ljava/lang/Throwable;)V
      37: aload_0
      38: getfield      #1                  // Field parameterMgr:Lcom/virtual/plat/server/param/ParameterMgr;
      41: ldc           #10                 // String login.fail.lock.time
      43: invokeinterface #3,  2            // InterfaceMethod com/virtual/plat/server/param/ParameterMgr.queryByName:(Ljava/lang/String;)Lcom/virtual/plat/server/entity/Parameter;
      48: astore_1
      49: aload_0
      50: aload_1
      51: invokevirtual #4                  // Method com/virtual/plat/server/entity/Parameter.getValue:()Ljava/lang/String;
      54: invokestatic  #5                  // Method java/lang/Integer.parseInt:(Ljava/lang/String;)I
      57: i2l
      58: putfield      #11                 // Field lockTime:J
      61: goto          75
      64: astore_1
      65: getstatic     #8                  // Field log:Lorg/apache/commons/logging/Log;
      68: aconst_null
      69: aload_1
      70: invokeinterface #9,  3            // InterfaceMethod org/apache/commons/logging/Log.error:(Ljava/lang/Object;Ljava/lang/Throwable;)V
      75: return
    Exception table:
       from    to  target type
           0    23    26   Class java/lang/Exception
          37    61    64   Class java/lang/Exception

  public boolean isCheckPasswordAttack();
    Code:
       0: aload_0
       1: getfield      #12                 // Field checkPasswordAttack:Z
       4: ireturn

  public void setCheckPasswordAttack(boolean);
    Code:
       0: aload_0
       1: iload_1
       2: putfield      #12                 // Field checkPasswordAttack:Z
       5: return

  public com.virtual.plat.security.CasUsernamePasswordAuthenticationFilter();
    Code:
       0: aload_0
       1: invokespecial #13                 // Method org/springframework/security/web/authentication/UsernamePasswordAuthenticationFilter."<init>":()V
       4: aload_0
       5: iconst_1
       6: putfield      #14                 // Field postOnly:Z
       9: aload_0
      10: ldc           #15                 // String isForce
      12: putfield      #16                 // Field isForceParameter:Ljava/lang/String;
      15: aload_0
      16: iconst_3
      17: putfield      #6                  // Field maxFailCount:I
      20: aload_0
      21: lconst_1
      22: putfield      #11                 // Field lockTime:J
      25: aload_0
      26: iconst_1
      27: putfield      #12                 // Field checkPasswordAttack:Z
      30: aload_0
      31: ldc           #17                 // class com/virtual/plat/server/operator/OperatorMgr
      33: invokestatic  #18                 // Method com/virtual/common/StringManager.getManager:(Ljava/lang/Class;)Lcom/virtual/common/StringManager;
      36: putfield      #19                 // Field sm:Lcom/virtual/common/StringManager;
      39: return

  public void doFilter(javax.servlet.ServletRequest, javax.servlet.ServletResponse, javax.servlet.FilterChain) throws java.io.IOException, javax.servlet.ServletException;
    Code:
       0: aload_0
       1: aload_1
       2: aload_2
       3: aload_3
       4: invokespecial #20                 // Method org/springframework/security/web/authentication/UsernamePasswordAuthenticationFilter.doFilter:(Ljavax/servlet/ServletRequest;Ljavax/servlet/ServletResponse;Ljavax/servlet/FilterChain;)V
       7: return

  public org.springframework.security.core.Authentication attemptAuthentication(javax.servlet.http.HttpServletRequest, javax.servlet.http.HttpServletResponse) throws org.springframework.security.core.AuthenticationException;
    Code:
       0: aload_1
       1: ldc           #21                 // String auth
       3: invokeinterface #22,  2           // InterfaceMethod javax/servlet/http/HttpServletRequest.getParameter:(Ljava/lang/String;)Ljava/lang/String;
       8: astore_3
       9: aload_1
      10: ldc           #23                 // String encrypt
      12: invokeinterface #22,  2           // InterfaceMethod javax/servlet/http/HttpServletRequest.getParameter:(Ljava/lang/String;)Ljava/lang/String;
      17: astore        4
      19: aload_1
      20: ldc           #24                 // String cert
      22: invokeinterface #22,  2           // InterfaceMethod javax/servlet/http/HttpServletRequest.getParameter:(Ljava/lang/String;)Ljava/lang/String;
      27: astore        5
      29: aload_1
      30: ldc           #25                 // String signText
      32: invokeinterface #22,  2           // InterfaceMethod javax/servlet/http/HttpServletRequest.getParameter:(Ljava/lang/String;)Ljava/lang/String;
      37: astore        6
      39: aload         5
      41: invokestatic  #26                 // Method org/apache/commons/lang/StringUtils.isNotEmpty:(Ljava/lang/String;)Z
      44: ifeq          54
      47: aload         5
      49: invokestatic  #27                 // Method com/virtual/common/FuncUtil.decryptData:(Ljava/lang/String;)Ljava/lang/String;
      52: astore        5
      54: aload         6
      56: invokestatic  #26                 // Method org/apache/commons/lang/StringUtils.isNotEmpty:(Ljava/lang/String;)Z
      59: ifeq          69
      62: aload         6
      64: invokestatic  #27                 // Method com/virtual/common/FuncUtil.decryptData:(Ljava/lang/String;)Ljava/lang/String;
      67: astore        6
      69: new           #28                 // class java/util/HashMap
      72: dup
      73: invokespecial #29                 // Method java/util/HashMap."<init>":()V
      76: astore        7
      78: aconst_null
      79: astore        8
      81: aconst_null
      82: astore        9
      84: iconst_0
      85: istore        10
      87: aload_3
      88: invokestatic  #30                 // Method org/apache/commons/lang/StringUtils.isNotBlank:(Ljava/lang/String;)Z
      91: ifeq          208
      94: aload_3
      95: invokestatic  #31                 // Method com/virtual/common/FuncUtil.decryptURI:(Ljava/lang/String;)Ljava/util/Map;
      98: astore        7
     100: aload         7
     102: ldc           #32                 // String name
     104: invokeinterface #33,  2           // InterfaceMethod java/util/Map.get:(Ljava/lang/Object;)Ljava/lang/Object;
     109: checkcast     #34                 // class java/lang/String
     112: astore        8
     114: aload         7
     116: ldc           #35                 // String password
     118: invokeinterface #33,  2           // InterfaceMethod java/util/Map.get:(Ljava/lang/Object;)Ljava/lang/Object;
     123: checkcast     #34                 // class java/lang/String
     126: astore        9
     128: aload         8
     130: invokestatic  #26                 // Method org/apache/commons/lang/StringUtils.isNotEmpty:(Ljava/lang/String;)Z
     133: ifeq          540
     136: aconst_null
     137: astore        11
     139: aload_0
     140: getfield      #36                 // Field operatorMgr:Lcom/virtual/plat/server/operator/OperatorMgr;
     143: aload         8
     145: invokeinterface #37,  2           // InterfaceMethod com/virtual/plat/server/operator/OperatorMgr.queryOperatorByLoginName:(Ljava/lang/String;)Lcom/virtual/plat/server/entity/Operator;
     150: astore        11
     152: new           #38                 // class com/virtual/plat/server/util/MD5
     155: dup
     156: invokespecial #39                 // Method com/virtual/plat/server/util/MD5."<init>":()V
     159: astore        12
     161: aload         12
     163: aload         11
     165: invokevirtual #40                 // Method com/virtual/plat/server/entity/Operator.getPassword:()Ljava/lang/String;
     168: invokevirtual #41                 // Method com/virtual/plat/server/util/MD5.toMD5:(Ljava/lang/String;)Ljava/lang/String;
     171: astore        13
     173: aload         9
     175: aload         13
     177: invokevirtual #42                 // Method java/lang/String.equals:(Ljava/lang/Object;)Z
     180: ifeq          190
     183: aload         11
     185: invokevirtual #40                 // Method com/virtual/plat/server/entity/Operator.getPassword:()Ljava/lang/String;
     188: astore        9
     190: goto          205
     193: astore        12
     195: getstatic     #8                  // Field log:Lorg/apache/commons/logging/Log;
     198: aload         12
     200: invokeinterface #43,  2           // InterfaceMethod org/apache/commons/logging/Log.error:(Ljava/lang/Object;)V
     205: goto          540
     208: aload_0
     209: getfield      #14                 // Field postOnly:Z
     212: ifeq          261
     215: aload_1
     216: invokeinterface #44,  1           // InterfaceMethod javax/servlet/http/HttpServletRequest.getMethod:()Ljava/lang/String;
     221: ldc           #45                 // String POST
     223: invokevirtual #42                 // Method java/lang/String.equals:(Ljava/lang/Object;)Z
     226: ifne          261
     229: new           #46                 // class org/springframework/security/authentication/AuthenticationServiceException
     232: dup
     233: new           #47                 // class java/lang/StringBuilder
     236: dup
     237: invokespecial #48                 // Method java/lang/StringBuilder."<init>":()V
     240: ldc           #49                 // String Authentication method not supported:
     242: invokevirtual #50                 // Method java/lang/StringBuilder.append:(Ljava/lang/String;)Ljava/lang/StringBuilder;
     245: aload_1
     246: invokeinterface #44,  1           // InterfaceMethod javax/servlet/http/HttpServletRequest.getMethod:()Ljava/lang/String;
     251: invokevirtual #50                 // Method java/lang/StringBuilder.append:(Ljava/lang/String;)Ljava/lang/StringBuilder;
     254: invokevirtual #51                 // Method java/lang/StringBuilder.toString:()Ljava/lang/String;
     257: invokespecial #52                 // Method org/springframework/security/authentication/AuthenticationServiceException."<init>":(Ljava/lang/String;)V
     260: athrow
     261: invokestatic  #53                 // Method java/lang/System.currentTimeMillis:()J
     264: lstore        11
     266: aload_0
     267: getfield      #12                 // Field checkPasswordAttack:Z
     270: ifeq          440
     273: aload_0
     274: invokespecial #54                 // Method readLoginConfig:()V
     277: aload_1
     278: invokestatic  #55                 // Method com/virtual/plat/server/ServerUtils.getIpAddr:(Ljavax/servlet/http/HttpServletRequest;)Ljava/lang/String;
     281: astore        13
     283: getstatic     #56                 // Field com/virtual/plat/security/CasAuthenticationFailureHandler.LOGIN_FAILS:Ljava/util/Map;
     286: aload         13
     288: invokeinterface #33,  2           // InterfaceMethod java/util/Map.get:(Ljava/lang/Object;)Ljava/lang/Object;
     293: checkcast     #57                 // class com/virtual/plat/security/CasAuthenticationFailureHandler$LoginFailInfo
     296: astore        14
     298: aload         14
     300: ifnull        440
     303: aload         14
     305: invokevirtual #58                 // Method com/virtual/plat/security/CasAuthenticationFailureHandler$LoginFailInfo.getFailCount:()I
     308: invokestatic  #59                 // Method java/lang/Integer.valueOf:(I)Ljava/lang/Integer;
     311: astore        15
     313: aload         14
     315: invokevirtual #60                 // Method com/virtual/plat/security/CasAuthenticationFailureHandler$LoginFailInfo.getLastLoginFailedTime:()Ljava/lang/Long;
     318: astore        16
     320: aload         16
     322: ifnull        440
     325: lload         11
     327: aload         16
     329: invokevirtual #61                 // Method java/lang/Long.longValue:()J
     332: lsub
     333: invokestatic  #62                 // Method java/lang/Math.abs:(J)J
     336: aload_0
     337: getfield      #11                 // Field lockTime:J
     340: ldc2_w        #63                 // long 60000l
     343: lmul
     344: lcmp
     345: ifle          357
     348: aload         14
     350: iconst_0
     351: invokevirtual #65                 // Method com/virtual/plat/security/CasAuthenticationFailureHandler$LoginFailInfo.setFailCount:(I)V
     354: goto          440
     357: aload         15
     359: ifnull        440
     362: aload         15
     364: invokevirtual #66                 // Method java/lang/Integer.intValue:()I
     367: iconst_1
     368: iadd
     369: aload_0
     370: getfield      #6                  // Field maxFailCount:I
     373: if_icmple     440
     376: lload         11
     378: aload         16
     380: invokevirtual #61                 // Method java/lang/Long.longValue:()J
     383: lsub
     384: invokestatic  #62                 // Method java/lang/Math.abs:(J)J
     387: aload_0
     388: getfield      #11                 // Field lockTime:J
     391: ldc2_w        #63                 // long 60000l
     394: lmul
     395: lcmp
     396: ifge          440
     399: new           #67                 // class com/virtual/plat/security/CasAuthenticationException
     402: dup
     403: aload_0
     404: getfield      #19                 // Field sm:Lcom/virtual/common/StringManager;
     407: ldc           #68                 // String login.attackFail
     409: iconst_2
     410: anewarray     #69                 // class java/lang/Object
     413: dup
     414: iconst_0
     415: aload_0
     416: getfield      #6                  // Field maxFailCount:I
     419: invokestatic  #59                 // Method java/lang/Integer.valueOf:(I)Ljava/lang/Integer;
     422: aastore
     423: dup
     424: iconst_1
     425: aload_0
     426: getfield      #11                 // Field lockTime:J
     429: invokestatic  #70                 // Method java/lang/Long.valueOf:(J)Ljava/lang/Long;
     432: aastore
     433: invokevirtual #71                 // Method com/virtual/common/StringManager.getString:(Ljava/lang/String;[Ljava/lang/Object;)Ljava/lang/String;
     436: invokespecial #72                 // Method com/virtual/plat/security/CasAuthenticationException."<init>":(Ljava/lang/String;)V
     439: athrow
     440: aload         5
     442: invokestatic  #26                 // Method org/apache/commons/lang/StringUtils.isNotEmpty:(Ljava/lang/String;)Z
     445: ifeq          458
     448: aload         5
     450: invokestatic  #73                 // Method com/virtual/plat/server/cer/CertiUtility.getCnByCertStr:(Ljava/lang/String;)Ljava/lang/String;
     453: astore        8
     455: goto          465
     458: aload_0
     459: aload_1
     460: invokevirtual #74                 // Method obtainUsername:(Ljavax/servlet/http/HttpServletRequest;)Ljava/lang/String;
     463: astore        8
     465: aload_0
     466: aload_1
     467: invokevirtual #75                 // Method obtainPassword:(Ljavax/servlet/http/HttpServletRequest;)Ljava/lang/String;
     470: astore        9
     472: aload_0
     473: aload_1
     474: invokespecial #76                 // Method botainIsForce:(Ljavax/servlet/http/HttpServletRequest;)Ljava/lang/String;
     477: astore        13
     479: aload         8
     481: ifnonnull     488
     484: ldc           #77                 // String
     486: astore        8
     488: aload         9
     490: ifnonnull     497
     493: ldc           #77                 // String
     495: astore        9
     497: ldc           #78                 // String true
     499: aload         4
     501: invokevirtual #79                 // Method java/lang/String.equalsIgnoreCase:(Ljava/lang/String;)Z
     504: ifeq          521
     507: aload         8
     509: invokestatic  #27                 // Method com/virtual/common/FuncUtil.decryptData:(Ljava/lang/String;)Ljava/lang/String;
     512: astore        8
     514: aload         9
     516: invokestatic  #27                 // Method com/virtual/common/FuncUtil.decryptData:(Ljava/lang/String;)Ljava/lang/String;
     519: astore        9
     521: aload         8
     523: invokevirtual #80                 // Method java/lang/String.trim:()Ljava/lang/String;
     526: astore        8
     528: aload         13
     530: ifnull        540
     533: aload         13
     535: invokestatic  #81                 // Method java/lang/Boolean.parseBoolean:(Ljava/lang/String;)Z
     538: istore        10
     540: new           #82                 // class org/springframework/security/authentication/UsernamePasswordAuthenticationToken
     543: dup
     544: aload         8
     546: aload         9
     548: invokespecial #83                 // Method org/springframework/security/authentication/UsernamePasswordAuthenticationToken."<init>":(Ljava/lang/Object;Ljava/lang/Object;)V
     551: astore        11
     553: aload_0
     554: aload_1
     555: aload         11
     557: iload         10
     559: aconst_null
     560: aconst_null
     561: aload         5
     563: aload         6
     565: invokevirtual #84                 // Method setDetails:(Ljavax/servlet/http/HttpServletRequest;Lorg/springframework/security/authentication/UsernamePasswordAuthenticationToken;ZLjava/lang/String;Ljava/lang/String;Ljava/lang/String;Ljava/lang/String;)V
     568: aload_0
     569: invokevirtual #85                 // Method getAuthenticationManager:()Lorg/springframework/security/authentication/AuthenticationManager;
     572: aload         11
     574: invokeinterface #86,  2           // InterfaceMethod org/springframework/security/authentication/AuthenticationManager.authenticate:(Lorg/springframework/security/core/Authentication;)Lorg/springframework/security/core/Authentication;
     579: areturn
    Exception table:
       from    to  target type
         139   190   193   Class java/lang/Exception

  protected void setDetails(javax.servlet.http.HttpServletRequest, org.springframework.security.authentication.UsernamePasswordAuthenticationToken, boolean);
    Code:
       0: new           #87                 // class com/virtual/plat/security/CasWebAuthenticationDetails
       3: dup
       4: aload_1
       5: invokespecial #88                 // Method com/virtual/plat/security/CasWebAuthenticationDetails."<init>":(Ljavax/servlet/http/HttpServletRequest;)V
       8: astore        4
      10: aload         4
      12: iload_3
      13: invokevirtual #89                 // Method com/virtual/plat/security/CasWebAuthenticationDetails.setForce:(Z)V
      16: aload_2
      17: aload         4
      19: invokevirtual #90                 // Method org/springframework/security/authentication/UsernamePasswordAuthenticationToken.setDetails:(Ljava/lang/Object;)V
      22: return

  protected void setDetails(javax.servlet.http.HttpServletRequest, org.springframework.security.authentication.UsernamePasswordAuthenticationToken, boolean, java.lang.String, java.lang.String, java.lang.String, java.lang.String);
    Code:
       0: new           #87                 // class com/virtual/plat/security/CasWebAuthenticationDetails
       3: dup
       4: aload_1
       5: invokespecial #88                 // Method com/virtual/plat/security/CasWebAuthenticationDetails."<init>":(Ljavax/servlet/http/HttpServletRequest;)V
       8: astore        8
      10: aload         8
      12: iload_3
      13: invokevirtual #89                 // Method com/virtual/plat/security/CasWebAuthenticationDetails.setForce:(Z)V
      16: aload         8
      18: aload         4
      20: invokevirtual #91                 // Method com/virtual/plat/security/CasWebAuthenticationDetails.setTicket:(Ljava/lang/String;)V
      23: aload         8
      25: aload         5
      27: invokevirtual #92                 // Method com/virtual/plat/security/CasWebAuthenticationDetails.setLoginType:(Ljava/lang/String;)V
      30: aload         6
      32: invokestatic  #26                 // Method org/apache/commons/lang/StringUtils.isNotEmpty:(Ljava/lang/String;)Z
      35: ifeq          45
      38: aload         8
      40: aload         6
      42: invokevirtual #93                 // Method com/virtual/plat/security/CasWebAuthenticationDetails.setCert:(Ljava/lang/String;)V
      45: aload         7
      47: invokestatic  #26                 // Method org/apache/commons/lang/StringUtils.isNotEmpty:(Ljava/lang/String;)Z
      50: ifeq          60
      53: aload         8
      55: aload         7
      57: invokevirtual #94                 // Method com/virtual/plat/security/CasWebAuthenticationDetails.setSignText:(Ljava/lang/String;)V
      60: aload_2
      61: aload         8
      63: invokevirtual #90                 // Method org/springframework/security/authentication/UsernamePasswordAuthenticationToken.setDetails:(Ljava/lang/Object;)V
      66: return

  private java.lang.String botainIsForce(javax.servlet.http.HttpServletRequest);
    Code:
       0: aload_1
       1: aload_0
       2: getfield      #16                 // Field isForceParameter:Ljava/lang/String;
       5: invokeinterface #22,  2           // InterfaceMethod javax/servlet/http/HttpServletRequest.getParameter:(Ljava/lang/String;)Ljava/lang/String;
      10: areturn

  public java.lang.String getIsForceParameter();
    Code:
       0: aload_0
       1: getfield      #16                 // Field isForceParameter:Ljava/lang/String;
       4: areturn

  public void setIsForceParameter(java.lang.String);
    Code:
       0: aload_1
       1: ldc           #95                 // String isForce parameter must not be empty or null
       3: invokestatic  #96                 // Method org/springframework/util/Assert.hasText:(Ljava/lang/String;Ljava/lang/String;)V
       6: aload_0
       7: aload_1
       8: putfield      #16                 // Field isForceParameter:Ljava/lang/String;
      11: return

  static {};
    Code:
       0: ldc           #97                 // class com/virtual/plat/server/controller/LoginController
       2: invokestatic  #98                 // Method org/apache/commons/logging/LogFactory.getLog:(Ljava/lang/Class;)Lorg/apache/commons/logging/Log;
       5: putstatic     #8                  // Field log:Lorg/apache/commons/logging/Log;
       8: return
}
