Compiled from "BaseServlet.java"
public class com.virtual.plat.server.servlet.BaseServlet extends javax.servlet.http.HttpServlet {
  private static final long serialVersionUID;

  protected static org.apache.commons.logging.Log log;

  protected com.google.gson.Gson gson;

  protected com.google.gson.Gson filterJson;

  protected org.springframework.web.context.WebApplicationContext context;

  public com.virtual.plat.server.servlet.BaseServlet();
    Code:
       0: aload_0
       1: invokespecial #1                  // Method javax/servlet/http/HttpServlet."<init>":()V
       4: aload_0
       5: aconst_null
       6: putfield      #2                  // Field gson:Lcom/google/gson/Gson;
       9: aload_0
      10: aconst_null
      11: putfield      #3                  // Field filterJson:Lcom/google/gson/Gson;
      14: aload_0
      15: aconst_null
      16: putfield      #4                  // Field context:Lorg/springframework/web/context/WebApplicationContext;
      19: return

  public void init();
    Code:
       0: aload_0
       1: invokespecial #5                  // Method javax/servlet/http/HttpServlet.init:()V
       4: goto          18
       7: astore_1
       8: getstatic     #7                  // Field log:Lorg/apache/commons/logging/Log;
      11: aconst_null
      12: aload_1
      13: invokeinterface #8,  3            // InterfaceMethod org/apache/commons/logging/Log.error:(Ljava/lang/Object;Ljava/lang/Throwable;)V
      18: aload_0
      19: aload_0
      20: invokevirtual #9                  // Method getServletContext:()Ljavax/servlet/ServletContext;
      23: invokestatic  #10                 // Method org/springframework/web/context/support/WebApplicationContextUtils.getWebApplicationContext:(Ljavax/servlet/ServletContext;)Lorg/springframework/web/context/WebApplicationContext;
      26: putfield      #4                  // Field context:Lorg/springframework/web/context/WebApplicationContext;
      29: aload_0
      30: new           #11                 // class com/google/gson/Gson
      33: dup
      34: invokespecial #12                 // Method com/google/gson/Gson."<init>":()V
      37: putfield      #2                  // Field gson:Lcom/google/gson/Gson;
      40: new           #13                 // class com/google/gson/GsonBuilder
      43: dup
      44: invokespecial #14                 // Method com/google/gson/GsonBuilder."<init>":()V
      47: astore_1
      48: aload_1
      49: invokevirtual #15                 // Method com/google/gson/GsonBuilder.excludeFieldsWithoutExposeAnnotation:()Lcom/google/gson/GsonBuilder;
      52: pop
      53: aload_0
      54: aload_1
      55: invokevirtual #16                 // Method com/google/gson/GsonBuilder.create:()Lcom/google/gson/Gson;
      58: putfield      #3                  // Field filterJson:Lcom/google/gson/Gson;
      61: return
    Exception table:
       from    to  target type
           0     4     7   Class javax/servlet/ServletException

  protected void write(javax.servlet.http.HttpServletResponse, java.lang.String);
    Code:
       0: aconst_null
       1: astore_3
       2: aload_1
       3: ldc           #17                 // String UTF-8
       5: invokeinterface #18,  2           // InterfaceMethod javax/servlet/http/HttpServletResponse.setCharacterEncoding:(Ljava/lang/String;)V
      10: aload_1
      11: invokeinterface #19,  1           // InterfaceMethod javax/servlet/http/HttpServletResponse.getWriter:()Ljava/io/PrintWriter;
      16: astore_3
      17: aload_3
      18: aload_2
      19: invokevirtual #20                 // Method java/io/PrintWriter.println:(Ljava/lang/String;)V
      22: aload_3
      23: invokevirtual #21                 // Method java/io/PrintWriter.close:()V
      26: goto          58
      29: astore        4
      31: getstatic     #7                  // Field log:Lorg/apache/commons/logging/Log;
      34: aconst_null
      35: aload         4
      37: invokeinterface #8,  3            // InterfaceMethod org/apache/commons/logging/Log.error:(Ljava/lang/Object;Ljava/lang/Throwable;)V
      42: aload_3
      43: invokevirtual #21                 // Method java/io/PrintWriter.close:()V
      46: goto          58
      49: astore        5
      51: aload_3
      52: invokevirtual #21                 // Method java/io/PrintWriter.close:()V
      55: aload         5
      57: athrow
      58: return
    Exception table:
       from    to  target type
          10    22    29   Class java/io/IOException
          10    22    49   any
          29    42    49   any
          49    51    49   any

  protected void doPost(javax.servlet.http.HttpServletRequest, javax.servlet.http.HttpServletResponse) throws javax.servlet.ServletException, java.io.IOException;
    Code:
       0: aload_0
       1: aload_1
       2: aload_2
       3: invokevirtual #23                 // Method doGet:(Ljavax/servlet/http/HttpServletRequest;Ljavax/servlet/http/HttpServletResponse;)V
       6: return

  protected com.virtual.plat.server.entity.PagingLoadConfig getPagingConfig(javax.servlet.http.HttpServletRequest);
    Code:
       0: aload_1
       1: ldc           #24                 // String page
       3: invokeinterface #25,  2           // InterfaceMethod javax/servlet/http/HttpServletRequest.getParameter:(Ljava/lang/String;)Ljava/lang/String;
       8: astore_2
       9: aload_1
      10: ldc           #26                 // String rows
      12: invokeinterface #25,  2           // InterfaceMethod javax/servlet/http/HttpServletRequest.getParameter:(Ljava/lang/String;)Ljava/lang/String;
      17: astore_3
      18: iconst_0
      19: istore        4
      21: bipush        10
      23: istore        5
      25: aload_2
      26: ifnull        42
      29: aload_2
      30: invokestatic  #27                 // Method org/apache/commons/lang/StringUtils.isNotEmpty:(Ljava/lang/String;)Z
      33: ifeq          42
      36: aload_2
      37: invokestatic  #28                 // Method java/lang/Integer.parseInt:(Ljava/lang/String;)I
      40: istore        4
      42: aload_3
      43: ifnull        59
      46: aload_3
      47: invokestatic  #27                 // Method org/apache/commons/lang/StringUtils.isNotEmpty:(Ljava/lang/String;)Z
      50: ifeq          59
      53: aload_3
      54: invokestatic  #28                 // Method java/lang/Integer.parseInt:(Ljava/lang/String;)I
      57: istore        5
      59: iload         5
      61: iload         4
      63: iconst_1
      64: isub
      65: imul
      66: istore        6
      68: aload_1
      69: ldc           #29                 // String sort
      71: invokeinterface #25,  2           // InterfaceMethod javax/servlet/http/HttpServletRequest.getParameter:(Ljava/lang/String;)Ljava/lang/String;
      76: astore        7
      78: aload_1
      79: ldc           #30                 // String order
      81: invokeinterface #25,  2           // InterfaceMethod javax/servlet/http/HttpServletRequest.getParameter:(Ljava/lang/String;)Ljava/lang/String;
      86: astore        8
      88: new           #31                 // class com/virtual/plat/server/entity/PagingLoadConfig
      91: dup
      92: invokespecial #32                 // Method com/virtual/plat/server/entity/PagingLoadConfig."<init>":()V
      95: astore        9
      97: aload         9
      99: iload         5
     101: invokevirtual #33                 // Method com/virtual/plat/server/entity/PagingLoadConfig.setLimit:(I)V
     104: aload         9
     106: iload         6
     108: invokevirtual #34                 // Method com/virtual/plat/server/entity/PagingLoadConfig.setOffset:(I)V
     111: aload         8
     113: ifnull        153
     116: ldc           #35                 // String asc
     118: aload         8
     120: invokevirtual #36                 // Method java/lang/String.equals:(Ljava/lang/Object;)Z
     123: ifeq          136
     126: aload         9
     128: ldc           #38                 // String Asc
     130: invokevirtual #39                 // Method com/virtual/plat/server/entity/PagingLoadConfig.setSortDir:(Ljava/lang/String;)V
     133: goto          153
     136: ldc           #40                 // String desc
     138: aload         8
     140: invokevirtual #36                 // Method java/lang/String.equals:(Ljava/lang/Object;)Z
     143: ifeq          153
     146: aload         9
     148: ldc           #41                 // String Desc
     150: invokevirtual #39                 // Method com/virtual/plat/server/entity/PagingLoadConfig.setSortDir:(Ljava/lang/String;)V
     153: aload         7
     155: ifnull        165
     158: aload         9
     160: aload         7
     162: invokevirtual #42                 // Method com/virtual/plat/server/entity/PagingLoadConfig.setSortField:(Ljava/lang/String;)V
     165: aload         9
     167: areturn

  public void destroy();
    Code:
       0: aload_0
       1: invokespecial #43                 // Method javax/servlet/http/HttpServlet.destroy:()V
       4: return

  static {};
    Code:
       0: ldc           #44                 // class com/virtual/plat/server/servlet/BaseServlet
       2: invokestatic  #45                 // Method org/apache/commons/logging/LogFactory.getLog:(Ljava/lang/Class;)Lorg/apache/commons/logging/Log;
       5: putstatic     #7                  // Field log:Lorg/apache/commons/logging/Log;
       8: return
}
