Compiled from "ClientReceiveListener.java"
public class com.virtual.plat.server.rs.ext.event.ClientReceiveListener implements javax.servlet.ServletContextListener {
  private static org.apache.commons.logging.Log log;

  public com.virtual.plat.server.rs.ext.event.ClientReceiveListener();
    Code:
       0: aload_0
       1: invokespecial #1                  // Method java/lang/Object."<init>":()V
       4: return

  public void contextInitialized(javax.servlet.ServletContextEvent);
    Code:
       0: getstatic     #2                  // Field log:Lorg/apache/commons/logging/Log;
       3: ldc           #3                  // String =============================ClientReceiveListener:contextInitialized()===============================
       5: invokeinterface #4,  2            // InterfaceMethod org/apache/commons/logging/Log.info:(Ljava/lang/Object;)V
      10: aload_1
      11: invokevirtual #5                  // Method javax/servlet/ServletContextEvent.getServletContext:()Ljavax/servlet/ServletContext;
      14: invokestatic  #6                  // Method org/springframework/web/context/support/WebApplicationContextUtils.getWebApplicationContext:(Ljavax/servlet/ServletContext;)Lorg/springframework/web/context/WebApplicationContext;
      17: putstatic     #7                  // Field com/virtual/plat/server/CometUtils.ctx:Lorg/springframework/web/context/WebApplicationContext;
      20: getstatic     #7                  // Field com/virtual/plat/server/CometUtils.ctx:Lorg/springframework/web/context/WebApplicationContext;
      23: ldc           #8                  // String publicCloudMgr
      25: invokeinterface #9,  2            // InterfaceMethod org/springframework/web/context/WebApplicationContext.getBean:(Ljava/lang/String;)Ljava/lang/Object;
      30: checkcast     #10                 // class com/virtual/plat/server/publiccloud/PublicCloudMgr
      33: astore_2
      34: new           #11                 // class com/virtual/plat/server/entity/QueryConfig
      37: dup
      38: invokespecial #12                 // Method com/virtual/plat/server/entity/QueryConfig."<init>":()V
      41: astore_3
      42: aload_3
      43: ldc           #13                 // String flag
      45: iconst_2
      46: invokestatic  #15                 // Method java/lang/Integer.valueOf:(I)Ljava/lang/Integer;
      49: invokevirtual #16                 // Method com/virtual/plat/server/entity/QueryConfig.addRestriction:(Ljava/lang/String;Ljava/lang/Object;)Lcom/virtual/plat/server/entity/QueryConfig;
      52: pop
      53: aload_2
      54: aload_3
      55: invokeinterface #17,  2           // InterfaceMethod com/virtual/plat/server/publiccloud/PublicCloudMgr.queryAllPublicCloud:(Lcom/virtual/plat/server/entity/QueryConfig;)Lcom/virtual/plat/server/entity/QueryResult;
      60: astore        4
      62: aload         4
      64: ifnull        240
      67: aload         4
      69: invokevirtual #18                 // Method com/virtual/plat/server/entity/QueryResult.getData:()Ljava/util/List;
      72: ifnull        240
      75: aload         4
      77: invokevirtual #18                 // Method com/virtual/plat/server/entity/QueryResult.getData:()Ljava/util/List;
      80: invokeinterface #19,  1           // InterfaceMethod java/util/List.size:()I
      85: ifle          240
      88: aload         4
      90: invokevirtual #18                 // Method com/virtual/plat/server/entity/QueryResult.getData:()Ljava/util/List;
      93: invokeinterface #20,  1           // InterfaceMethod java/util/List.iterator:()Ljava/util/Iterator;
      98: astore        5
     100: aload         5
     102: invokeinterface #21,  1           // InterfaceMethod java/util/Iterator.hasNext:()Z
     107: ifeq          240
     110: aload         5
     112: invokeinterface #22,  1           // InterfaceMethod java/util/Iterator.next:()Ljava/lang/Object;
     117: checkcast     #14                 // class com/virtual/plat/server/entity/PublicCloud
     120: astore        6
     122: new           #23                 // class java/lang/StringBuilder
     125: dup
     126: invokespecial #24                 // Method java/lang/StringBuilder."<init>":()V
     129: aload         6
     131: invokevirtual #25                 // Method com/virtual/plat/server/entity/PublicCloud.getProtocal:()Ljava/lang/String;
     134: invokevirtual #26                 // Method java/lang/StringBuilder.append:(Ljava/lang/String;)Ljava/lang/StringBuilder;
     137: ldc           #27                 // String ://
     139: invokevirtual #26                 // Method java/lang/StringBuilder.append:(Ljava/lang/String;)Ljava/lang/StringBuilder;
     142: aload         6
     144: invokevirtual #28                 // Method com/virtual/plat/server/entity/PublicCloud.getUri:()Ljava/lang/String;
     147: invokevirtual #26                 // Method java/lang/StringBuilder.append:(Ljava/lang/String;)Ljava/lang/StringBuilder;
     150: ldc           #29                 // String :
     152: invokevirtual #26                 // Method java/lang/StringBuilder.append:(Ljava/lang/String;)Ljava/lang/StringBuilder;
     155: aload         6
     157: invokevirtual #30                 // Method com/virtual/plat/server/entity/PublicCloud.getPort:()Ljava/lang/Integer;
     160: invokevirtual #31                 // Method java/lang/StringBuilder.append:(Ljava/lang/Object;)Ljava/lang/StringBuilder;
     163: ldc           #32                 // String /
     165: invokevirtual #26                 // Method java/lang/StringBuilder.append:(Ljava/lang/String;)Ljava/lang/StringBuilder;
     168: aload         6
     170: invokevirtual #33                 // Method com/virtual/plat/server/entity/PublicCloud.getUserName:()Ljava/lang/String;
     173: invokevirtual #26                 // Method java/lang/StringBuilder.append:(Ljava/lang/String;)Ljava/lang/StringBuilder;
     176: invokevirtual #34                 // Method java/lang/StringBuilder.toString:()Ljava/lang/String;
     179: astore        7
     181: getstatic     #2                  // Field log:Lorg/apache/commons/logging/Log;
     184: new           #23                 // class java/lang/StringBuilder
     187: dup
     188: invokespecial #24                 // Method java/lang/StringBuilder."<init>":()V
     191: ldc           #35                 // String =============================publicCloud:===============================
     193: invokevirtual #26                 // Method java/lang/StringBuilder.append:(Ljava/lang/String;)Ljava/lang/StringBuilder;
     196: aload         7
     198: invokevirtual #26                 // Method java/lang/StringBuilder.append:(Ljava/lang/String;)Ljava/lang/StringBuilder;
     201: invokevirtual #34                 // Method java/lang/StringBuilder.toString:()Ljava/lang/String;
     204: invokeinterface #4,  2            // InterfaceMethod org/apache/commons/logging/Log.info:(Ljava/lang/Object;)V
     209: getstatic     #36                 // Field com/virtual/plat/server/CometUtils.connections:Ljava/util/concurrent/ConcurrentHashMap;
     212: aload         7
     214: invokevirtual #37                 // Method java/util/concurrent/ConcurrentHashMap.containsKey:(Ljava/lang/Object;)Z
     217: ifne          237
     220: getstatic     #38                 // Field com/virtual/plat/server/CometUtils.threadPool:Ljava/util/concurrent/ExecutorService;
     223: new           #39                 // class com/virtual/plat/server/rs/ext/event/ReceiveMsgThread
     226: dup
     227: aload         6
     229: invokespecial #40                 // Method com/virtual/plat/server/rs/ext/event/ReceiveMsgThread."<init>":(Lcom/virtual/plat/server/entity/PublicCloud;)V
     232: invokeinterface #41,  2           // InterfaceMethod java/util/concurrent/ExecutorService.execute:(Ljava/lang/Runnable;)V
     237: goto          100
     240: return

  public void contextDestroyed(javax.servlet.ServletContextEvent);
    Code:
       0: return

  static {};
    Code:
       0: ldc           #42                 // class com/virtual/plat/server/rs/ext/event/ClientReceiveListener
       2: invokestatic  #43                 // Method org/apache/commons/logging/LogFactory.getLog:(Ljava/lang/Class;)Lorg/apache/commons/logging/Log;
       5: putstatic     #2                  // Field log:Lorg/apache/commons/logging/Log;
       8: return
}
