Compiled from "LoginFilter.java"
public class com.virtual.plat.server.filter.LoginFilter implements javax.servlet.Filter {
  public com.virtual.plat.server.filter.LoginFilter();
    Code:
       0: aload_0
       1: invokespecial #1                  // Method java/lang/Object."<init>":()V
       4: return

  public void destroy();
    Code:
       0: return

  public void doFilter(javax.servlet.ServletRequest, javax.servlet.ServletResponse, javax.servlet.FilterChain) throws java.io.IOException, javax.servlet.ServletException;
    Code:
       0: aload_1
       1: checkcast     #2                  // class javax/servlet/http/HttpServletRequest
       4: astore        4
       6: aload_2
       7: checkcast     #3                  // class javax/servlet/http/HttpServletResponse
      10: astore        5
      12: aload         4
      14: invokeinterface #4,  1            // InterfaceMethod javax/servlet/http/HttpServletRequest.getSession:()Ljavax/servlet/http/HttpSession;
      19: astore        6
      21: aload         4
      23: invokeinterface #5,  1            // InterfaceMethod javax/servlet/http/HttpServletRequest.getRequestURI:()Ljava/lang/String;
      28: astore        7
      30: aload         7
      32: ldc           #6                  // String login.svc
      34: invokevirtual #7                  // Method java/lang/String.indexOf:(Ljava/lang/String;)I
      37: iconst_m1
      38: if_icmpgt     104
      41: aload         7
      43: ldc           #8                  // String LicenseService
      45: invokevirtual #7                  // Method java/lang/String.indexOf:(Ljava/lang/String;)I
      48: iconst_m1
      49: if_icmpgt     104
      52: aload         7
      54: ldc           #9                  // String fileUploadProgressService.svc
      56: invokevirtual #7                  // Method java/lang/String.indexOf:(Ljava/lang/String;)I
      59: iconst_m1
      60: if_icmpgt     104
      63: aload         7
      65: ldc           #10                 // String syscfg.svc
      67: invokevirtual #7                  // Method java/lang/String.indexOf:(Ljava/lang/String;)I
      70: iconst_m1
      71: if_icmpgt     104
      74: aload         7
      76: ldc           #11                 // String .svc
      78: invokevirtual #7                  // Method java/lang/String.indexOf:(Ljava/lang/String;)I
      81: ifge          113
      84: aload         7
      86: ldc           #12                 // String Service
      88: invokevirtual #13                 // Method java/lang/String.endsWith:(Ljava/lang/String;)Z
      91: ifne          113
      94: aload         7
      96: ldc           #14                 // String .jsp
      98: invokevirtual #13                 // Method java/lang/String.endsWith:(Ljava/lang/String;)Z
     101: ifne          113
     104: aload_3
     105: aload_1
     106: aload_2
     107: invokeinterface #15,  3           // InterfaceMethod javax/servlet/FilterChain.doFilter:(Ljavax/servlet/ServletRequest;Ljavax/servlet/ServletResponse;)V
     112: return
     113: aload         6
     115: getstatic     #16                 // Field com/virtual/plat/client/operator/LoginService.ATTR_LOGIN_INFO_IN_SESSION:Ljava/lang/String;
     118: invokeinterface #17,  2           // InterfaceMethod javax/servlet/http/HttpSession.getAttribute:(Ljava/lang/String;)Ljava/lang/Object;
     123: checkcast     #18                 // class com/virtual/plat/client/operator/LoginInfo
     126: astore        8
     128: aload         8
     130: ifnonnull     151
     133: aload         5
     135: sipush        403
     138: invokeinterface #19,  2           // InterfaceMethod javax/servlet/http/HttpServletResponse.setStatus:(I)V
     143: aload         5
     145: invokeinterface #20,  1           // InterfaceMethod javax/servlet/http/HttpServletResponse.flushBuffer:()V
     150: return
     151: aload_3
     152: aload_1
     153: aload_2
     154: invokeinterface #15,  3           // InterfaceMethod javax/servlet/FilterChain.doFilter:(Ljavax/servlet/ServletRequest;Ljavax/servlet/ServletResponse;)V
     159: return

  public void init(javax.servlet.FilterConfig) throws javax.servlet.ServletException;
    Code:
       0: return
}
