Compiled from "ValidateCodeServlet.java"
public class com.virtual.plat.server.ValidateCodeServlet extends javax.servlet.http.HttpServlet {
  private static org.apache.commons.logging.Log log;

  private static final java.lang.String INIT_PARAM_PIC_WIDTH;

  private static final java.lang.String INIT_PARAM_PIC_HEIGHT;

  private static final java.lang.String INIT_PARAM_CODE_LENGTH;

  private static final java.lang.String INIT_PARAM_CODE_BASE;

  public static final java.lang.String SESSION_ATTR_NAME;

  private int pictureWidth;

  private int pictureHeight;

  private int codeLength;

  private java.lang.String codeBase;

  private java.util.Random random;

  private java.awt.Font pictureFont;

  public com.virtual.plat.server.ValidateCodeServlet();
    Code:
       0: aload_0
       1: invokespecial #1                  // Method javax/servlet/http/HttpServlet."<init>":()V
       4: aload_0
       5: bipush        60
       7: putfield      #2                  // Field pictureWidth:I
      10: aload_0
      11: bipush        25
      13: putfield      #3                  // Field pictureHeight:I
      16: aload_0
      17: iconst_4
      18: putfield      #4                  // Field codeLength:I
      21: aload_0
      22: ldc           #5                  // String abcdefghijklmnopqrstuvwxyzABCDEFGHIJKLMNOPQRSTUVWXYZ0123456789
      24: putfield      #6                  // Field codeBase:Ljava/lang/String;
      27: aload_0
      28: new           #7                  // class java/util/Random
      31: dup
      32: invokespecial #8                  // Method java/util/Random."<init>":()V
      35: putfield      #9                  // Field random:Ljava/util/Random;
      38: aload_0
      39: new           #10                 // class java/awt/Font
      42: dup
      43: ldc           #11                 // String Times New Roman
      45: iconst_0
      46: bipush        17
      48: invokespecial #12                 // Method java/awt/Font."<init>":(Ljava/lang/String;II)V
      51: putfield      #13                 // Field pictureFont:Ljava/awt/Font;
      54: return

  public void init() throws javax.servlet.ServletException;
    Code:
       0: aload_0
       1: ldc           #15                 // String picture.width
       3: invokevirtual #16                 // Method getInitParameter:(Ljava/lang/String;)Ljava/lang/String;
       6: astore_1
       7: aload_1
       8: ifnull        19
      11: aload_0
      12: aload_1
      13: invokestatic  #17                 // Method java/lang/Integer.parseInt:(Ljava/lang/String;)I
      16: putfield      #2                  // Field pictureWidth:I
      19: aload_0
      20: ldc           #18                 // String picture.height
      22: invokevirtual #16                 // Method getInitParameter:(Ljava/lang/String;)Ljava/lang/String;
      25: astore_1
      26: aload_1
      27: ifnull        38
      30: aload_0
      31: aload_1
      32: invokestatic  #17                 // Method java/lang/Integer.parseInt:(Ljava/lang/String;)I
      35: putfield      #3                  // Field pictureHeight:I
      38: aload_0
      39: ldc           #19                 // String code.length
      41: invokevirtual #16                 // Method getInitParameter:(Ljava/lang/String;)Ljava/lang/String;
      44: astore_1
      45: aload_1
      46: ifnull        57
      49: aload_0
      50: aload_1
      51: invokestatic  #17                 // Method java/lang/Integer.parseInt:(Ljava/lang/String;)I
      54: putfield      #4                  // Field codeLength:I
      57: aload_0
      58: ldc           #20                 // String code.base
      60: invokevirtual #16                 // Method getInitParameter:(Ljava/lang/String;)Ljava/lang/String;
      63: astore_1
      64: aload_1
      65: ifnull        73
      68: aload_0
      69: aload_1
      70: putfield      #6                  // Field codeBase:Ljava/lang/String;
      73: goto          96
      76: astore_1
      77: getstatic     #22                 // Field log:Lorg/apache/commons/logging/Log;
      80: ldc           #23                 // String Parse init parameters failed
      82: invokeinterface #24,  2           // InterfaceMethod org/apache/commons/logging/Log.error:(Ljava/lang/Object;)V
      87: new           #25                 // class javax/servlet/ServletException
      90: dup
      91: aload_1
      92: invokespecial #26                 // Method javax/servlet/ServletException."<init>":(Ljava/lang/Throwable;)V
      95: athrow
      96: return
    Exception table:
       from    to  target type
           0    73    76   Class java/lang/Exception

  protected void doGet(javax.servlet.http.HttpServletRequest, javax.servlet.http.HttpServletResponse) throws javax.servlet.ServletException, java.io.IOException;
    Code:
       0: aload_2
       1: ldc           #27                 // String Pragma
       3: ldc           #28                 // String No-cache
       5: invokeinterface #29,  3           // InterfaceMethod javax/servlet/http/HttpServletResponse.setHeader:(Ljava/lang/String;Ljava/lang/String;)V
      10: aload_2
      11: ldc           #30                 // String Cache-Control
      13: ldc           #31                 // String no-cache
      15: invokeinterface #29,  3           // InterfaceMethod javax/servlet/http/HttpServletResponse.setHeader:(Ljava/lang/String;Ljava/lang/String;)V
      20: aload_2
      21: ldc           #32                 // String Expires
      23: lconst_0
      24: invokeinterface #33,  4           // InterfaceMethod javax/servlet/http/HttpServletResponse.setDateHeader:(Ljava/lang/String;J)V
      29: new           #34                 // class java/awt/image/BufferedImage
      32: dup
      33: aload_0
      34: getfield      #2                  // Field pictureWidth:I
      37: aload_0
      38: getfield      #3                  // Field pictureHeight:I
      41: iconst_1
      42: invokespecial #35                 // Method java/awt/image/BufferedImage."<init>":(III)V
      45: astore_3
      46: aload_3
      47: invokevirtual #36                 // Method java/awt/image/BufferedImage.createGraphics:()Ljava/awt/Graphics2D;
      50: astore        4
      52: aload         4
      54: aload_0
      55: sipush        180
      58: sipush        250
      61: invokevirtual #37                 // Method getRandomColor:(II)Ljava/awt/Color;
      64: invokevirtual #38                 // Method java/awt/Graphics.setColor:(Ljava/awt/Color;)V
      67: aload         4
      69: iconst_0
      70: iconst_0
      71: aload_0
      72: getfield      #2                  // Field pictureWidth:I
      75: aload_0
      76: getfield      #3                  // Field pictureHeight:I
      79: invokevirtual #39                 // Method java/awt/Graphics.fillRect:(IIII)V
      82: aload         4
      84: aload_0
      85: getfield      #13                 // Field pictureFont:Ljava/awt/Font;
      88: invokevirtual #40                 // Method java/awt/Graphics.setFont:(Ljava/awt/Font;)V
      91: new           #41                 // class java/lang/StringBuilder
      94: dup
      95: invokespecial #42                 // Method java/lang/StringBuilder."<init>":()V
      98: astore        5
     100: iconst_0
     101: istore        6
     103: iload         6
     105: aload_0
     106: getfield      #4                  // Field codeLength:I
     109: if_icmpge     202
     112: aload_0
     113: getfield      #6                  // Field codeBase:Ljava/lang/String;
     116: aload_0
     117: getfield      #9                  // Field random:Ljava/util/Random;
     120: aload_0
     121: getfield      #6                  // Field codeBase:Ljava/lang/String;
     124: invokevirtual #43                 // Method java/lang/String.length:()I
     127: invokevirtual #44                 // Method java/util/Random.nextInt:(I)I
     130: invokevirtual #45                 // Method java/lang/String.charAt:(I)C
     133: istore        7
     135: aload         5
     137: iload         7
     139: invokevirtual #46                 // Method java/lang/StringBuilder.append:(C)Ljava/lang/StringBuilder;
     142: pop
     143: aload         4
     145: aload_0
     146: bipush        10
     148: sipush        150
     151: invokevirtual #37                 // Method getRandomColor:(II)Ljava/awt/Color;
     154: invokevirtual #38                 // Method java/awt/Graphics.setColor:(Ljava/awt/Color;)V
     157: aload         4
     159: iload         7
     161: invokestatic  #47                 // Method java/lang/String.valueOf:(C)Ljava/lang/String;
     164: bipush        13
     166: iload         6
     168: imul
     169: bipush        6
     171: iadd
     172: aload_0
     173: getfield      #9                  // Field random:Ljava/util/Random;
     176: iconst_5
     177: invokevirtual #44                 // Method java/util/Random.nextInt:(I)I
     180: iadd
     181: bipush        14
     183: aload_0
     184: getfield      #9                  // Field random:Ljava/util/Random;
     187: bipush        6
     189: invokevirtual #44                 // Method java/util/Random.nextInt:(I)I
     192: iadd
     193: invokevirtual #48                 // Method java/awt/Graphics.drawString:(Ljava/lang/String;II)V
     196: iinc          6, 1
     199: goto          103
     202: aload_1
     203: invokeinterface #49,  1           // InterfaceMethod javax/servlet/http/HttpServletRequest.getSession:()Ljavax/servlet/http/HttpSession;
     208: getstatic     #50                 // Field SESSION_ATTR_NAME:Ljava/lang/String;
     211: aload         5
     213: invokevirtual #51                 // Method java/lang/StringBuilder.toString:()Ljava/lang/String;
     216: invokeinterface #52,  3           // InterfaceMethod javax/servlet/http/HttpSession.setAttribute:(Ljava/lang/String;Ljava/lang/Object;)V
     221: aload         4
     223: invokevirtual #53                 // Method java/awt/Graphics.dispose:()V
     226: aload_3
     227: ldc           #54                 // String JPEG
     229: aload_2
     230: invokeinterface #55,  1           // InterfaceMethod javax/servlet/http/HttpServletResponse.getOutputStream:()Ljavax/servlet/ServletOutputStream;
     235: invokestatic  #56                 // Method javax/imageio/ImageIO.write:(Ljava/awt/image/RenderedImage;Ljava/lang/String;Ljava/io/OutputStream;)Z
     238: pop
     239: aload_0
     240: aload_1
     241: aload_2
     242: invokespecial #57                 // Method javax/servlet/http/HttpServlet.doGet:(Ljavax/servlet/http/HttpServletRequest;Ljavax/servlet/http/HttpServletResponse;)V
     245: return

  protected void doPost(javax.servlet.http.HttpServletRequest, javax.servlet.http.HttpServletResponse) throws javax.servlet.ServletException, java.io.IOException;
    Code:
       0: aload_0
       1: aload_1
       2: aload_2
       3: invokevirtual #58                 // Method doGet:(Ljavax/servlet/http/HttpServletRequest;Ljavax/servlet/http/HttpServletResponse;)V
       6: return

  protected java.awt.Color getRandomColor(int, int);
    Code:
       0: iload_1
       1: aload_0
       2: getfield      #9                  // Field random:Ljava/util/Random;
       5: iload_2
       6: iload_1
       7: isub
       8: invokevirtual #44                 // Method java/util/Random.nextInt:(I)I
      11: iadd
      12: istore_3
      13: iload_1
      14: aload_0
      15: getfield      #9                  // Field random:Ljava/util/Random;
      18: iload_2
      19: iload_1
      20: isub
      21: invokevirtual #44                 // Method java/util/Random.nextInt:(I)I
      24: iadd
      25: istore        4
      27: iload_1
      28: aload_0
      29: getfield      #9                  // Field random:Ljava/util/Random;
      32: iload_2
      33: iload_1
      34: isub
      35: invokevirtual #44                 // Method java/util/Random.nextInt:(I)I
      38: iadd
      39: istore        5
      41: new           #59                 // class java/awt/Color
      44: dup
      45: iload_3
      46: iload         4
      48: iload         5
      50: invokespecial #60                 // Method java/awt/Color."<init>":(III)V
      53: areturn

  static {};
    Code:
       0: ldc           #14                 // class com/virtual/plat/server/ValidateCodeServlet
       2: invokestatic  #61                 // Method org/apache/commons/logging/LogFactory.getLog:(Ljava/lang/Class;)Lorg/apache/commons/logging/Log;
       5: putstatic     #22                 // Field log:Lorg/apache/commons/logging/Log;
       8: new           #41                 // class java/lang/StringBuilder
      11: dup
      12: invokespecial #42                 // Method java/lang/StringBuilder."<init>":()V
      15: ldc           #14                 // class com/virtual/plat/server/ValidateCodeServlet
      17: invokevirtual #62                 // Method java/lang/StringBuilder.append:(Ljava/lang/Object;)Ljava/lang/StringBuilder;
      20: ldc           #63                 // String _CODE
      22: invokevirtual #64                 // Method java/lang/StringBuilder.append:(Ljava/lang/String;)Ljava/lang/StringBuilder;
      25: invokevirtual #51                 // Method java/lang/StringBuilder.toString:()Ljava/lang/String;
      28: putstatic     #50                 // Field SESSION_ATTR_NAME:Ljava/lang/String;
      31: return
}
