Compiled from "CheckEntryServlet.java"
public class com.virtual.plat.server.servlet.CheckEntryServlet extends javax.servlet.http.HttpServlet {
  private static final long serialVersionUID;

  public com.virtual.plat.server.servlet.CheckEntryServlet();
    Code:
       0: aload_0
       1: invokespecial #1                  // Method javax/servlet/http/HttpServlet."<init>":()V
       4: return

  public void doGet(javax.servlet.http.HttpServletRequest, javax.servlet.http.HttpServletResponse) throws javax.servlet.ServletException, java.io.IOException;
    Code:
       0: aload_1
       1: ldc           #2                  // String index.jsp
       3: invokeinterface #3,  2            // InterfaceMethod javax/servlet/http/HttpServletRequest.getRequestDispatcher:(Ljava/lang/String;)Ljavax/servlet/RequestDispatcher;
       8: astore_3
       9: aload_3
      10: aload_1
      11: aload_2
      12: invokeinterface #4,  3            // InterfaceMethod javax/servlet/RequestDispatcher.forward:(Ljavax/servlet/ServletRequest;Ljavax/servlet/ServletResponse;)V
      17: return

  public void doPost(javax.servlet.http.HttpServletRequest, javax.servlet.http.HttpServletResponse) throws javax.servlet.ServletException, java.io.IOException;
    Code:
       0: aload_0
       1: aload_1
       2: aload_2
       3: invokevirtual #5                  // Method doGet:(Ljavax/servlet/http/HttpServletRequest;Ljavax/servlet/http/HttpServletResponse;)V
       6: return
}
