Compiled from "PasswordProtectDigestAuthenticationFilter.java"
public class com.virtual.plat.server.rs.ext.event.PasswordProtectDigestAuthenticationFilter extends com.virtual.plat.server.rs.ext.event.DigestAuthenticationFilterExt {
  private static org.apache.commons.logging.Log log;

  public static final int MAX_FAIL_COUNT;

  public static final long LOCK_TIME;

  private java.util.Map<java.lang.String, com.virtual.plat.server.rs.ext.event.PasswordProtectDigestAuthenticationFilter$AuthFailInfo> authMap;

  public com.virtual.plat.server.rs.ext.event.PasswordProtectDigestAuthenticationFilter();
    Code:
       0: aload_0
       1: invokespecial #1                  // Method com/virtual/plat/server/rs/ext/event/DigestAuthenticationFilterExt."<init>":()V
       4: aload_0
       5: new           #2                  // class java/util/HashMap
       8: dup
       9: invokespecial #3                  // Method java/util/HashMap."<init>":()V
      12: putfield      #4                  // Field authMap:Ljava/util/Map;
      15: return

  public void doFilter(javax.servlet.ServletRequest, javax.servlet.ServletResponse, javax.servlet.FilterChain) throws java.io.IOException, javax.servlet.ServletException;
    Code:
       0: aload_0
       1: aload_1
       2: aload_2
       3: invokespecial #5                  // Method check:(Ljavax/servlet/ServletRequest;Ljavax/servlet/ServletResponse;)Z
       6: ifeq          40
       9: aload_0
      10: aload_1
      11: aload_2
      12: aload_3
      13: invokespecial #6                  // Method com/virtual/plat/server/rs/ext/event/DigestAuthenticationFilterExt.doFilter:(Ljavax/servlet/ServletRequest;Ljavax/servlet/ServletResponse;Ljavax/servlet/FilterChain;)V
      16: invokestatic  #7                  // Method org/springframework/security/core/context/SecurityContextHolder.getContext:()Lorg/springframework/security/core/context/SecurityContext;
      19: invokeinterface #8,  1            // InterfaceMethod org/springframework/security/core/context/SecurityContext.getAuthentication:()Lorg/springframework/security/core/Authentication;
      24: ifnonnull     35
      27: aload_0
      28: aload_1
      29: invokespecial #9                  // Method fail:(Ljavax/servlet/ServletRequest;)V
      32: goto          40
      35: aload_0
      36: aload_1
      37: invokespecial #10                 // Method success:(Ljavax/servlet/ServletRequest;)V
      40: return

  private boolean check(javax.servlet.ServletRequest, javax.servlet.ServletResponse) throws java.io.IOException, javax.servlet.ServletException;
    Code:
       0: aload_1
       1: invokeinterface #11,  1           // InterfaceMethod javax/servlet/ServletRequest.getRemoteAddr:()Ljava/lang/String;
       6: astore_3
       7: aconst_null
       8: astore        4
      10: aload_0
      11: getfield      #4                  // Field authMap:Ljava/util/Map;
      14: dup
      15: astore        5
      17: monitorenter
      18: aload_0
      19: getfield      #4                  // Field authMap:Ljava/util/Map;
      22: aload_3
      23: invokeinterface #12,  2           // InterfaceMethod java/util/Map.get:(Ljava/lang/Object;)Ljava/lang/Object;
      28: checkcast     #13                 // class com/virtual/plat/server/rs/ext/event/PasswordProtectDigestAuthenticationFilter$AuthFailInfo
      31: astore        4
      33: aload         5
      35: monitorexit
      36: goto          47
      39: astore        6
      41: aload         5
      43: monitorexit
      44: aload         6
      46: athrow
      47: aload         4
      49: ifnull        61
      52: aload         4
      54: getfield      #14                 // Field com/virtual/plat/server/rs/ext/event/PasswordProtectDigestAuthenticationFilter$AuthFailInfo.failCount:I
      57: iconst_5
      58: if_icmpgt     63
      61: iconst_1
      62: ireturn
      63: invokestatic  #15                 // Method java/lang/System.currentTimeMillis:()J
      66: aload         4
      68: getfield      #16                 // Field com/virtual/plat/server/rs/ext/event/PasswordProtectDigestAuthenticationFilter$AuthFailInfo.lastFailTime:J
      71: lsub
      72: invokestatic  #17                 // Method java/lang/Math.abs:(J)J
      75: ldc2_w        #18                 // long 60000l
      78: lcmp
      79: ifle          90
      82: aload         4
      84: iconst_4
      85: putfield      #14                 // Field com/virtual/plat/server/rs/ext/event/PasswordProtectDigestAuthenticationFilter$AuthFailInfo.failCount:I
      88: iconst_1
      89: ireturn
      90: getstatic     #20                 // Field log:Lorg/apache/commons/logging/Log;
      93: new           #21                 // class java/lang/StringBuilder
      96: dup
      97: invokespecial #22                 // Method java/lang/StringBuilder."<init>":()V
     100: ldc           #23                 // String Authentication rejected for host
     102: invokevirtual #24                 // Method java/lang/StringBuilder.append:(Ljava/lang/String;)Ljava/lang/StringBuilder;
     105: aload_3
     106: invokevirtual #24                 // Method java/lang/StringBuilder.append:(Ljava/lang/String;)Ljava/lang/StringBuilder;
     109: invokevirtual #25                 // Method java/lang/StringBuilder.toString:()Ljava/lang/String;
     112: invokeinterface #26,  2           // InterfaceMethod org/apache/commons/logging/Log.info:(Ljava/lang/Object;)V
     117: getstatic     #20                 // Field log:Lorg/apache/commons/logging/Log;
     120: new           #21                 // class java/lang/StringBuilder
     123: dup
     124: invokespecial #22                 // Method java/lang/StringBuilder."<init>":()V
     127: ldc           #27                 // String Authentication is forbidden until
     129: invokevirtual #24                 // Method java/lang/StringBuilder.append:(Ljava/lang/String;)Ljava/lang/StringBuilder;
     132: new           #28                 // class java/util/Date
     135: dup
     136: aload         4
     138: getfield      #16                 // Field com/virtual/plat/server/rs/ext/event/PasswordProtectDigestAuthenticationFilter$AuthFailInfo.lastFailTime:J
     141: ldc2_w        #18                 // long 60000l
     144: ladd
     145: invokespecial #29                 // Method java/util/Date."<init>":(J)V
     148: invokevirtual #30                 // Method java/lang/StringBuilder.append:(Ljava/lang/Object;)Ljava/lang/StringBuilder;
     151: invokevirtual #25                 // Method java/lang/StringBuilder.toString:()Ljava/lang/String;
     154: invokeinterface #26,  2           // InterfaceMethod org/apache/commons/logging/Log.info:(Ljava/lang/Object;)V
     159: aload_2
     160: checkcast     #31                 // class javax/servlet/http/HttpServletResponse
     163: sipush        403
     166: new           #21                 // class java/lang/StringBuilder
     169: dup
     170: invokespecial #22                 // Method java/lang/StringBuilder."<init>":()V
     173: ldc           #27                 // String Authentication is forbidden until
     175: invokevirtual #24                 // Method java/lang/StringBuilder.append:(Ljava/lang/String;)Ljava/lang/StringBuilder;
     178: new           #28                 // class java/util/Date
     181: dup
     182: aload         4
     184: getfield      #16                 // Field com/virtual/plat/server/rs/ext/event/PasswordProtectDigestAuthenticationFilter$AuthFailInfo.lastFailTime:J
     187: ldc2_w        #18                 // long 60000l
     190: ladd
     191: invokespecial #29                 // Method java/util/Date."<init>":(J)V
     194: invokevirtual #30                 // Method java/lang/StringBuilder.append:(Ljava/lang/Object;)Ljava/lang/StringBuilder;
     197: invokevirtual #25                 // Method java/lang/StringBuilder.toString:()Ljava/lang/String;
     200: invokeinterface #32,  3           // InterfaceMethod javax/servlet/http/HttpServletResponse.sendError:(ILjava/lang/String;)V
     205: iconst_0
     206: ireturn
    Exception table:
       from    to  target type
          18    36    39   any
          39    44    39   any

  private void fail(javax.servlet.ServletRequest);
    Code:
       0: aload_1
       1: invokeinterface #11,  1           // InterfaceMethod javax/servlet/ServletRequest.getRemoteAddr:()Ljava/lang/String;
       6: astore_2
       7: aconst_null
       8: astore_3
       9: aload_0
      10: getfield      #4                  // Field authMap:Ljava/util/Map;
      13: dup
      14: astore        4
      16: monitorenter
      17: aload_0
      18: getfield      #4                  // Field authMap:Ljava/util/Map;
      21: aload_2
      22: invokeinterface #12,  2           // InterfaceMethod java/util/Map.get:(Ljava/lang/Object;)Ljava/lang/Object;
      27: checkcast     #13                 // class com/virtual/plat/server/rs/ext/event/PasswordProtectDigestAuthenticationFilter$AuthFailInfo
      30: astore_3
      31: aload_3
      32: ifnonnull     55
      35: new           #13                 // class com/virtual/plat/server/rs/ext/event/PasswordProtectDigestAuthenticationFilter$AuthFailInfo
      38: dup
      39: invokespecial #33                 // Method com/virtual/plat/server/rs/ext/event/PasswordProtectDigestAuthenticationFilter$AuthFailInfo."<init>":()V
      42: astore_3
      43: aload_0
      44: getfield      #4                  // Field authMap:Ljava/util/Map;
      47: aload_2
      48: aload_3
      49: invokeinterface #34,  3           // InterfaceMethod java/util/Map.put:(Ljava/lang/Object;Ljava/lang/Object;)Ljava/lang/Object;
      54: pop
      55: aload         4
      57: monitorexit
      58: goto          69
      61: astore        5
      63: aload         4
      65: monitorexit
      66: aload         5
      68: athrow
      69: aload_3
      70: invokestatic  #15                 // Method java/lang/System.currentTimeMillis:()J
      73: putfield      #16                 // Field com/virtual/plat/server/rs/ext/event/PasswordProtectDigestAuthenticationFilter$AuthFailInfo.lastFailTime:J
      76: aload_3
      77: dup
      78: getfield      #14                 // Field com/virtual/plat/server/rs/ext/event/PasswordProtectDigestAuthenticationFilter$AuthFailInfo.failCount:I
      81: iconst_1
      82: iadd
      83: putfield      #14                 // Field com/virtual/plat/server/rs/ext/event/PasswordProtectDigestAuthenticationFilter$AuthFailInfo.failCount:I
      86: getstatic     #20                 // Field log:Lorg/apache/commons/logging/Log;
      89: new           #21                 // class java/lang/StringBuilder
      92: dup
      93: invokespecial #22                 // Method java/lang/StringBuilder."<init>":()V
      96: ldc           #35                 // String Authentication failed for host
      98: invokevirtual #24                 // Method java/lang/StringBuilder.append:(Ljava/lang/String;)Ljava/lang/StringBuilder;
     101: aload_2
     102: invokevirtual #24                 // Method java/lang/StringBuilder.append:(Ljava/lang/String;)Ljava/lang/StringBuilder;
     105: ldc           #36                 // String :
     107: invokevirtual #24                 // Method java/lang/StringBuilder.append:(Ljava/lang/String;)Ljava/lang/StringBuilder;
     110: aload_3
     111: getfield      #14                 // Field com/virtual/plat/server/rs/ext/event/PasswordProtectDigestAuthenticationFilter$AuthFailInfo.failCount:I
     114: invokevirtual #37                 // Method java/lang/StringBuilder.append:(I)Ljava/lang/StringBuilder;
     117: invokevirtual #25                 // Method java/lang/StringBuilder.toString:()Ljava/lang/String;
     120: invokeinterface #26,  2           // InterfaceMethod org/apache/commons/logging/Log.info:(Ljava/lang/Object;)V
     125: return
    Exception table:
       from    to  target type
          17    58    61   any
          61    66    61   any

  private void success(javax.servlet.ServletRequest);
    Code:
       0: aload_0
       1: getfield      #4                  // Field authMap:Ljava/util/Map;
       4: dup
       5: astore_2
       6: monitorenter
       7: aload_0
       8: getfield      #4                  // Field authMap:Ljava/util/Map;
      11: aload_1
      12: invokeinterface #11,  1           // InterfaceMethod javax/servlet/ServletRequest.getRemoteAddr:()Ljava/lang/String;
      17: invokeinterface #38,  2           // InterfaceMethod java/util/Map.remove:(Ljava/lang/Object;)Ljava/lang/Object;
      22: pop
      23: aload_2
      24: monitorexit
      25: goto          33
      28: astore_3
      29: aload_2
      30: monitorexit
      31: aload_3
      32: athrow
      33: return
    Exception table:
       from    to  target type
           7    25    28   any
          28    31    28   any

  static {};
    Code:
       0: ldc           #39                 // class com/virtual/plat/server/rs/ext/event/PasswordProtectDigestAuthenticationFilter
       2: invokestatic  #40                 // Method org/apache/commons/logging/LogFactory.getLog:(Ljava/lang/Class;)Lorg/apache/commons/logging/Log;
       5: putstatic     #20                 // Field log:Lorg/apache/commons/logging/Log;
       8: return
}
