Compiled from "TokenServlet.java"
public class com.virtual.plat.server.file.TokenServlet extends javax.servlet.http.HttpServlet {
  private static final long serialVersionUID;

  static final java.lang.String FILE_NAME_FIELD;

  static final java.lang.String FILE_SIZE_FIELD;

  static final java.lang.String TOKEN_FIELD;

  static final java.lang.String SERVER_FIELD;

  static final java.lang.String SUCCESS;

  static final java.lang.String MESSAGE;

  static final java.lang.String CLOUD_ID;

  private com.virtual.plat.server.publiccloud.PublicCloudMgr publicCloudMgr;

  private com.virtual.common.StringManager sm;

  public com.virtual.plat.server.file.TokenServlet();
    Code:
       0: aload_0
       1: invokespecial #1                  // Method javax/servlet/http/HttpServlet."<init>":()V
       4: aload_0
       5: aconst_null
       6: putfield      #2                  // Field publicCloudMgr:Lcom/virtual/plat/server/publiccloud/PublicCloudMgr;
       9: aload_0
      10: ldc           #3                  // class com/virtual/plat/server/file/TokenServlet
      12: invokestatic  #4                  // Method com/virtual/common/StringManager.getManager:(Ljava/lang/Class;)Lcom/virtual/common/StringManager;
      15: putfield      #5                  // Field sm:Lcom/virtual/common/StringManager;
      18: return

  public void init() throws javax.servlet.ServletException;
    Code:
       0: aload_0
       1: invokespecial #6                  // Method javax/servlet/http/HttpServlet.init:()V
       4: aload_0
       5: aload_0
       6: invokevirtual #7                  // Method getServletContext:()Ljavax/servlet/ServletContext;
       9: invokestatic  #8                  // Method org/springframework/web/context/support/WebApplicationContextUtils.getWebApplicationContext:(Ljavax/servlet/ServletContext;)Lorg/springframework/web/context/WebApplicationContext;
      12: ldc           #9                  // String publicCloudMgr
      14: invokeinterface #10,  2           // InterfaceMethod org/springframework/web/context/WebApplicationContext.getBean:(Ljava/lang/String;)Ljava/lang/Object;
      19: checkcast     #11                 // class com/virtual/plat/server/publiccloud/PublicCloudMgr
      22: putfield      #2                  // Field publicCloudMgr:Lcom/virtual/plat/server/publiccloud/PublicCloudMgr;
      25: return

  protected void doGet(javax.servlet.http.HttpServletRequest, javax.servlet.http.HttpServletResponse) throws javax.servlet.ServletException, java.io.IOException;
    Code:
       0: aload_1
       1: ldc           #12                 // String name
       3: invokeinterface #13,  2           // InterfaceMethod javax/servlet/http/HttpServletRequest.getParameter:(Ljava/lang/String;)Ljava/lang/String;
       8: astore_3
       9: aload_1
      10: ldc           #14                 // String size
      12: invokeinterface #13,  2           // InterfaceMethod javax/servlet/http/HttpServletRequest.getParameter:(Ljava/lang/String;)Ljava/lang/String;
      17: astore        4
      19: aload_3
      20: aload         4
      22: invokestatic  #15                 // Method com/virtual/plat/server/file/util/IoUtil.generateToken:(Ljava/lang/String;Ljava/lang/String;)Ljava/lang/String;
      25: astore        5
      27: aload_2
      28: invokeinterface #16,  1           // InterfaceMethod javax/servlet/http/HttpServletResponse.getWriter:()Ljava/io/PrintWriter;
      33: astore        6
      35: new           #17                 // class com/google/gson/JsonObject
      38: dup
      39: invokespecial #18                 // Method com/google/gson/JsonObject."<init>":()V
      42: astore        7
      44: aload         7
      46: ldc           #19                 // String token
      48: aload         5
      50: invokevirtual #20                 // Method com/google/gson/JsonObject.addProperty:(Ljava/lang/String;Ljava/lang/String;)V
      53: aload_1
      54: ldc           #21                 // String cloudId
      56: invokeinterface #13,  2           // InterfaceMethod javax/servlet/http/HttpServletRequest.getParameter:(Ljava/lang/String;)Ljava/lang/String;
      61: astore        8
      63: aconst_null
      64: astore        9
      66: aload         8
      68: invokestatic  #22                 // Method org/apache/commons/lang/StringUtils.isNotBlank:(Ljava/lang/String;)Z
      71: ifeq          96
      74: aload_0
      75: aload         8
      77: invokespecial #23                 // Method getUploadServer:(Ljava/lang/String;)Ljava/lang/String;
      80: astore        9
      82: goto          87
      85: astore        10
      87: aload         7
      89: ldc           #25                 // String server
      91: aload         9
      93: invokevirtual #20                 // Method com/google/gson/JsonObject.addProperty:(Ljava/lang/String;Ljava/lang/String;)V
      96: aload         9
      98: ifnull        124
     101: aload         7
     103: ldc           #26                 // String success
     105: iconst_1
     106: invokestatic  #27                 // Method java/lang/Boolean.valueOf:(Z)Ljava/lang/Boolean;
     109: invokevirtual #28                 // Method com/google/gson/JsonObject.addProperty:(Ljava/lang/String;Ljava/lang/Boolean;)V
     112: aload         7
     114: ldc           #29                 // String message
     116: ldc           #30                 // String
     118: invokevirtual #20                 // Method com/google/gson/JsonObject.addProperty:(Ljava/lang/String;Ljava/lang/String;)V
     121: goto          151
     124: aload         7
     126: ldc           #26                 // String success
     128: iconst_0
     129: invokestatic  #27                 // Method java/lang/Boolean.valueOf:(Z)Ljava/lang/Boolean;
     132: invokevirtual #28                 // Method com/google/gson/JsonObject.addProperty:(Ljava/lang/String;Ljava/lang/Boolean;)V
     135: aload         7
     137: ldc           #29                 // String message
     139: aload_0
     140: getfield      #5                  // Field sm:Lcom/virtual/common/StringManager;
     143: ldc           #31                 // String upload.server.fail
     145: invokevirtual #32                 // Method com/virtual/common/StringManager.getString:(Ljava/lang/String;)Ljava/lang/String;
     148: invokevirtual #20                 // Method com/google/gson/JsonObject.addProperty:(Ljava/lang/String;Ljava/lang/String;)V
     151: aload_0
     152: aload_1
     153: invokespecial #33                 // Method changeSessionOutTime:(Ljavax/servlet/http/HttpServletRequest;)V
     156: aload         6
     158: aload         7
     160: invokevirtual #34                 // Method com/google/gson/JsonObject.toString:()Ljava/lang/String;
     163: invokevirtual #35                 // Method java/io/PrintWriter.write:(Ljava/lang/String;)V
     166: return
    Exception table:
       from    to  target type
          74    82    85   Class java/lang/Exception

  private void changeSessionOutTime(javax.servlet.http.HttpServletRequest);
    Code:
       0: aload_1
       1: invokeinterface #36,  1           // InterfaceMethod javax/servlet/http/HttpServletRequest.getSession:()Ljavax/servlet/http/HttpSession;
       6: astore_2
       7: aload_2
       8: invokeinterface #37,  1           // InterfaceMethod javax/servlet/http/HttpSession.getMaxInactiveInterval:()I
      13: istore_3
      14: aload_2
      15: getstatic     #38                 // Field com/virtual/plat/client/operator/LoginService.ATTR_LOGIN_INFO_IN_SESSION:Ljava/lang/String;
      18: invokeinterface #39,  2           // InterfaceMethod javax/servlet/http/HttpSession.getAttribute:(Ljava/lang/String;)Ljava/lang/Object;
      23: checkcast     #40                 // class com/virtual/plat/client/operator/LoginInfo
      26: astore        4
      28: aload         4
      30: ifnull        41
      33: aload         4
      35: invokevirtual #41                 // Method com/virtual/plat/client/operator/LoginInfo.isOnline:()Z
      38: ifne          42
      41: return
      42: iload_3
      43: ldc           #42                 // int 86400
      45: if_icmpge     64
      48: aload_2
      49: ldc           #42                 // int 86400
      51: invokeinterface #43,  2           // InterfaceMethod javax/servlet/http/HttpSession.setMaxInactiveInterval:(I)V
      56: aload         4
      58: ldc2_w        #44                 // long 86280l
      61: invokevirtual #46                 // Method com/virtual/plat/client/operator/LoginInfo.setIdleTimeout:(J)V
      64: return

  private java.lang.String getUploadServer(java.lang.String);
    Code:
       0: aload_1
       1: invokestatic  #47                 // Method java/lang/Long.parseLong:(Ljava/lang/String;)J
       4: invokestatic  #48                 // Method java/lang/Long.valueOf:(J)Ljava/lang/Long;
       7: astore_2
       8: aload_0
       9: getfield      #2                  // Field publicCloudMgr:Lcom/virtual/plat/server/publiccloud/PublicCloudMgr;
      12: aload_2
      13: invokeinterface #49,  2           // InterfaceMethod com/virtual/plat/server/publiccloud/PublicCloudMgr.queryPublicCloudById:(Ljava/lang/Long;)Lcom/virtual/plat/server/entity/PublicCloud;
      18: astore_3
      19: new           #50                 // class java/lang/StringBuilder
      22: dup
      23: invokespecial #51                 // Method java/lang/StringBuilder."<init>":()V
      26: aload_3
      27: invokevirtual #52                 // Method com/virtual/plat/server/entity/PublicCloud.getProtocal:()Ljava/lang/String;
      30: invokevirtual #53                 // Method java/lang/StringBuilder.append:(Ljava/lang/String;)Ljava/lang/StringBuilder;
      33: ldc           #54                 // String ://
      35: invokevirtual #53                 // Method java/lang/StringBuilder.append:(Ljava/lang/String;)Ljava/lang/StringBuilder;
      38: aload_3
      39: invokevirtual #55                 // Method com/virtual/plat/server/entity/PublicCloud.getUri:()Ljava/lang/String;
      42: invokevirtual #53                 // Method java/lang/StringBuilder.append:(Ljava/lang/String;)Ljava/lang/StringBuilder;
      45: ldc           #56                 // String :
      47: invokevirtual #53                 // Method java/lang/StringBuilder.append:(Ljava/lang/String;)Ljava/lang/StringBuilder;
      50: aload_3
      51: invokevirtual #57                 // Method com/virtual/plat/server/entity/PublicCloud.getPort:()Ljava/lang/Integer;
      54: invokevirtual #58                 // Method java/lang/StringBuilder.append:(Ljava/lang/Object;)Ljava/lang/StringBuilder;
      57: ldc           #59                 // String /cas/
      59: invokevirtual #53                 // Method java/lang/StringBuilder.append:(Ljava/lang/String;)Ljava/lang/StringBuilder;
      62: invokevirtual #60                 // Method java/lang/StringBuilder.toString:()Ljava/lang/String;
      65: areturn

  protected void doHead(javax.servlet.http.HttpServletRequest, javax.servlet.http.HttpServletResponse) throws javax.servlet.ServletException, java.io.IOException;
    Code:
       0: aload_0
       1: aload_1
       2: aload_2
       3: invokespecial #61                 // Method javax/servlet/http/HttpServlet.doHead:(Ljavax/servlet/http/HttpServletRequest;Ljavax/servlet/http/HttpServletResponse;)V
       6: return

  public void destroy();
    Code:
       0: aload_0
       1: invokespecial #62                 // Method javax/servlet/http/HttpServlet.destroy:()V
       4: return
}
