Compiled from "RpcServiceServlet.java"
public abstract class com.virtual.plat.server.RpcServiceServlet extends com.google.gwt.user.server.rpc.RemoteServiceServlet {
  protected org.apache.commons.logging.Log log;

  public com.virtual.plat.server.RpcServiceServlet();
    Code:
       0: aload_0
       1: invokespecial #1                  // Method com/google/gwt/user/server/rpc/RemoteServiceServlet."<init>":()V
       4: aload_0
       5: aload_0
       6: invokevirtual #2                  // Method java/lang/Object.getClass:()Ljava/lang/Class;
       9: invokestatic  #3                  // Method org/apache/commons/logging/LogFactory.getLog:(Ljava/lang/Class;)Lorg/apache/commons/logging/Log;
      12: putfield      #4                  // Field log:Lorg/apache/commons/logging/Log;
      15: return

  public void init() throws javax.servlet.ServletException;
    Code:
       0: aload_0
       1: invokespecial #5                  // Method com/google/gwt/user/server/rpc/RemoteServiceServlet.init:()V
       4: aload_0
       5: invokevirtual #6                  // Method doInjection:()V
       8: goto          44
      11: astore_1
      12: aload_0
      13: getfield      #4                  // Field log:Lorg/apache/commons/logging/Log;
      16: aconst_null
      17: aload_1
      18: invokeinterface #8,  3            // InterfaceMethod org/apache/commons/logging/Log.error:(Ljava/lang/Object;Ljava/lang/Throwable;)V
      23: aload_1
      24: instanceof    #9                  // class javax/servlet/ServletException
      27: ifeq          35
      30: aload_1
      31: checkcast     #9                  // class javax/servlet/ServletException
      34: athrow
      35: new           #9                  // class javax/servlet/ServletException
      38: dup
      39: aload_1
      40: invokespecial #10                 // Method javax/servlet/ServletException."<init>":(Ljava/lang/Throwable;)V
      43: athrow
      44: return
    Exception table:
       from    to  target type
           4     8    11   Class java/lang/Throwable

  protected void doUnexpectedFailure(java.lang.Throwable);
    Code:
       0: aload_0
       1: aload_1
       2: invokespecial #11                 // Method com/google/gwt/user/server/rpc/RemoteServiceServlet.doUnexpectedFailure:(Ljava/lang/Throwable;)V
       5: aload_0
       6: getfield      #4                  // Field log:Lorg/apache/commons/logging/Log;
       9: ldc           #12                 // String Unexpected server error
      11: aload_1
      12: invokeinterface #8,  3            // InterfaceMethod org/apache/commons/logging/Log.error:(Ljava/lang/Object;Ljava/lang/Throwable;)V
      17: return

  protected void doInjection() throws javax.servlet.ServletException;
    Code:
       0: aload_0
       1: invokevirtual #13                 // Method getServletContext:()Ljavax/servlet/ServletContext;
       4: invokestatic  #14                 // Method org/springframework/web/context/support/WebApplicationContextUtils.getWebApplicationContext:(Ljavax/servlet/ServletContext;)Lorg/springframework/web/context/WebApplicationContext;
       7: astore_1
       8: aload_1
       9: ifnonnull     24
      12: aload_0
      13: getfield      #4                  // Field log:Lorg/apache/commons/logging/Log;
      16: ldc           #15                 // String Can not find Spring web application context, failed to do injection
      18: invokeinterface #16,  2           // InterfaceMethod org/apache/commons/logging/Log.error:(Ljava/lang/Object;)V
      23: return
      24: aload_0
      25: invokevirtual #2                  // Method java/lang/Object.getClass:()Ljava/lang/Class;
      28: invokevirtual #17                 // Method java/lang/Class.getDeclaredFields:()[Ljava/lang/reflect/Field;
      31: astore_2
      32: aload_2
      33: arraylength
      34: istore_3
      35: iconst_0
      36: istore        4
      38: iload         4
      40: iload_3
      41: if_icmpge     519
      44: aload_2
      45: iload         4
      47: aaload
      48: astore        5
      50: aload         5
      52: invokevirtual #18                 // Method java/lang/reflect/Field.getDeclaredAnnotations:()[Ljava/lang/annotation/Annotation;
      55: astore        6
      57: aload         6
      59: arraylength
      60: istore        7
      62: iconst_0
      63: istore        8
      65: iload         8
      67: iload         7
      69: if_icmpge     513
      72: aload         6
      74: iload         8
      76: aaload
      77: astore        9
      79: aload         9
      81: instanceof    #19                 // class javax/annotation/Resource
      84: ifeq          507
      87: aload         9
      89: checkcast     #19                 // class javax/annotation/Resource
      92: astore        10
      94: aload         10
      96: invokeinterface #20,  1           // InterfaceMethod javax/annotation/Resource.name:()Ljava/lang/String;
     101: ifnull        181
     104: aload         10
     106: invokeinterface #20,  1           // InterfaceMethod javax/annotation/Resource.name:()Ljava/lang/String;
     111: invokevirtual #21                 // Method java/lang/String.trim:()Ljava/lang/String;
     114: ldc           #22                 // String
     116: invokevirtual #23                 // Method java/lang/String.equals:(Ljava/lang/Object;)Z
     119: ifne          181
     122: aload_0
     123: aload         10
     125: invokeinterface #20,  1           // InterfaceMethod javax/annotation/Resource.name:()Ljava/lang/String;
     130: aload         5
     132: aload_1
     133: invokespecial #24                 // Method injectWithBeanName:(Ljava/lang/String;Ljava/lang/reflect/Field;Lorg/springframework/web/context/WebApplicationContext;)Z
     136: ifne          507
     139: aload_0
     140: getfield      #4                  // Field log:Lorg/apache/commons/logging/Log;
     143: new           #25                 // class java/lang/StringBuilder
     146: dup
     147: invokespecial #26                 // Method java/lang/StringBuilder."<init>":()V
     150: ldc           #27                 // String Can not find bean with name \'
     152: invokevirtual #28                 // Method java/lang/StringBuilder.append:(Ljava/lang/String;)Ljava/lang/StringBuilder;
     155: aload         10
     157: invokeinterface #20,  1           // InterfaceMethod javax/annotation/Resource.name:()Ljava/lang/String;
     162: invokevirtual #28                 // Method java/lang/StringBuilder.append:(Ljava/lang/String;)Ljava/lang/StringBuilder;
     165: ldc           #29                 // String \', auto-injection failed
     167: invokevirtual #28                 // Method java/lang/StringBuilder.append:(Ljava/lang/String;)Ljava/lang/StringBuilder;
     170: invokevirtual #30                 // Method java/lang/StringBuilder.toString:()Ljava/lang/String;
     173: invokeinterface #31,  2           // InterfaceMethod org/apache/commons/logging/Log.warn:(Ljava/lang/Object;)V
     178: goto          507
     181: ldc           #32                 // class java/lang/Object
     183: aload         10
     185: invokeinterface #33,  1           // InterfaceMethod javax/annotation/Resource.type:()Ljava/lang/Class;
     190: invokevirtual #34                 // Method java/lang/Object.equals:(Ljava/lang/Object;)Z
     193: ifne          463
     196: aload_1
     197: aload         10
     199: invokeinterface #33,  1           // InterfaceMethod javax/annotation/Resource.type:()Ljava/lang/Class;
     204: invokestatic  #35                 // Method org/springframework/beans/factory/BeanFactoryUtils.beansOfTypeIncludingAncestors:(Lorg/springframework/beans/factory/ListableBeanFactory;Ljava/lang/Class;)Ljava/util/Map;
     207: invokeinterface #36,  1           // InterfaceMethod java/util/Map.values:()Ljava/util/Collection;
     212: astore        11
     214: aload         5
     216: invokevirtual #37                 // Method java/lang/reflect/Field.getType:()Ljava/lang/Class;
     219: ldc           #38                 // class java/util/Collection
     221: invokevirtual #39                 // Method java/lang/Class.isAssignableFrom:(Ljava/lang/Class;)Z
     224: ifeq          287
     227: aload         5
     229: iconst_1
     230: invokevirtual #40                 // Method java/lang/reflect/Field.setAccessible:(Z)V
     233: aload         5
     235: aload_0
     236: aload         11
     238: invokevirtual #41                 // Method java/lang/reflect/Field.set:(Ljava/lang/Object;Ljava/lang/Object;)V
     241: goto          460
     244: astore        12
     246: aload_0
     247: getfield      #4                  // Field log:Lorg/apache/commons/logging/Log;
     250: new           #25                 // class java/lang/StringBuilder
     253: dup
     254: invokespecial #26                 // Method java/lang/StringBuilder."<init>":()V
     257: ldc           #43                 // String Failed to do injection for
     259: invokevirtual #28                 // Method java/lang/StringBuilder.append:(Ljava/lang/String;)Ljava/lang/StringBuilder;
     262: aload         5
     264: invokevirtual #44                 // Method java/lang/StringBuilder.append:(Ljava/lang/Object;)Ljava/lang/StringBuilder;
     267: invokevirtual #30                 // Method java/lang/StringBuilder.toString:()Ljava/lang/String;
     270: aload         12
     272: invokeinterface #8,  3            // InterfaceMethod org/apache/commons/logging/Log.error:(Ljava/lang/Object;Ljava/lang/Throwable;)V
     277: new           #9                  // class javax/servlet/ServletException
     280: dup
     281: aload         12
     283: invokespecial #10                 // Method javax/servlet/ServletException."<init>":(Ljava/lang/Throwable;)V
     286: athrow
     287: aload         11
     289: invokeinterface #45,  1           // InterfaceMethod java/util/Collection.size:()I
     294: iconst_1
     295: if_icmpne     368
     298: aload         5
     300: iconst_1
     301: invokevirtual #40                 // Method java/lang/reflect/Field.setAccessible:(Z)V
     304: aload         5
     306: aload_0
     307: aload         11
     309: invokeinterface #46,  1           // InterfaceMethod java/util/Collection.iterator:()Ljava/util/Iterator;
     314: invokeinterface #47,  1           // InterfaceMethod java/util/Iterator.next:()Ljava/lang/Object;
     319: invokevirtual #41                 // Method java/lang/reflect/Field.set:(Ljava/lang/Object;Ljava/lang/Object;)V
     322: goto          460
     325: astore        12
     327: aload_0
     328: getfield      #4                  // Field log:Lorg/apache/commons/logging/Log;
     331: new           #25                 // class java/lang/StringBuilder
     334: dup
     335: invokespecial #26                 // Method java/lang/StringBuilder."<init>":()V
     338: ldc           #43                 // String Failed to do injection for
     340: invokevirtual #28                 // Method java/lang/StringBuilder.append:(Ljava/lang/String;)Ljava/lang/StringBuilder;
     343: aload         5
     345: invokevirtual #44                 // Method java/lang/StringBuilder.append:(Ljava/lang/Object;)Ljava/lang/StringBuilder;
     348: invokevirtual #30                 // Method java/lang/StringBuilder.toString:()Ljava/lang/String;
     351: aload         12
     353: invokeinterface #8,  3            // InterfaceMethod org/apache/commons/logging/Log.error:(Ljava/lang/Object;Ljava/lang/Throwable;)V
     358: new           #9                  // class javax/servlet/ServletException
     361: dup
     362: aload         12
     364: invokespecial #10                 // Method javax/servlet/ServletException."<init>":(Ljava/lang/Throwable;)V
     367: athrow
     368: aload         11
     370: invokeinterface #45,  1           // InterfaceMethod java/util/Collection.size:()I
     375: iconst_1
     376: if_icmple     421
     379: aload_0
     380: getfield      #4                  // Field log:Lorg/apache/commons/logging/Log;
     383: new           #25                 // class java/lang/StringBuilder
     386: dup
     387: invokespecial #26                 // Method java/lang/StringBuilder."<init>":()V
     390: ldc           #48                 // String Find more than one beans of type \'
     392: invokevirtual #28                 // Method java/lang/StringBuilder.append:(Ljava/lang/String;)Ljava/lang/StringBuilder;
     395: aload         10
     397: invokeinterface #33,  1           // InterfaceMethod javax/annotation/Resource.type:()Ljava/lang/Class;
     402: invokevirtual #44                 // Method java/lang/StringBuilder.append:(Ljava/lang/Object;)Ljava/lang/StringBuilder;
     405: ldc           #49                 // String , auto-injection failed
     407: invokevirtual #28                 // Method java/lang/StringBuilder.append:(Ljava/lang/String;)Ljava/lang/StringBuilder;
     410: invokevirtual #30                 // Method java/lang/StringBuilder.toString:()Ljava/lang/String;
     413: invokeinterface #16,  2           // InterfaceMethod org/apache/commons/logging/Log.error:(Ljava/lang/Object;)V
     418: goto          460
     421: aload_0
     422: getfield      #4                  // Field log:Lorg/apache/commons/logging/Log;
     425: new           #25                 // class java/lang/StringBuilder
     428: dup
     429: invokespecial #26                 // Method java/lang/StringBuilder."<init>":()V
     432: ldc           #50                 // String Can not find bean of type \'
     434: invokevirtual #28                 // Method java/lang/StringBuilder.append:(Ljava/lang/String;)Ljava/lang/StringBuilder;
     437: aload         10
     439: invokeinterface #33,  1           // InterfaceMethod javax/annotation/Resource.type:()Ljava/lang/Class;
     444: invokevirtual #44                 // Method java/lang/StringBuilder.append:(Ljava/lang/Object;)Ljava/lang/StringBuilder;
     447: ldc           #49                 // String , auto-injection failed
     449: invokevirtual #28                 // Method java/lang/StringBuilder.append:(Ljava/lang/String;)Ljava/lang/StringBuilder;
     452: invokevirtual #30                 // Method java/lang/StringBuilder.toString:()Ljava/lang/String;
     455: invokeinterface #16,  2           // InterfaceMethod org/apache/commons/logging/Log.error:(Ljava/lang/Object;)V
     460: goto          507
     463: aload_0
     464: aload         5
     466: invokevirtual #51                 // Method java/lang/reflect/Field.getName:()Ljava/lang/String;
     469: aload         5
     471: aload_1
     472: invokespecial #24                 // Method injectWithBeanName:(Ljava/lang/String;Ljava/lang/reflect/Field;Lorg/springframework/web/context/WebApplicationContext;)Z
     475: ifne          507
     478: aload_0
     479: getfield      #4                  // Field log:Lorg/apache/commons/logging/Log;
     482: new           #25                 // class java/lang/StringBuilder
     485: dup
     486: invokespecial #26                 // Method java/lang/StringBuilder."<init>":()V
     489: ldc           #52                 // String Either beanName or beansType attribute must be set for @Resource annotation, failed to do injection for
     491: invokevirtual #28                 // Method java/lang/StringBuilder.append:(Ljava/lang/String;)Ljava/lang/StringBuilder;
     494: aload         5
     496: invokevirtual #44                 // Method java/lang/StringBuilder.append:(Ljava/lang/Object;)Ljava/lang/StringBuilder;
     499: invokevirtual #30                 // Method java/lang/StringBuilder.toString:()Ljava/lang/String;
     502: invokeinterface #16,  2           // InterfaceMethod org/apache/commons/logging/Log.error:(Ljava/lang/Object;)V
     507: iinc          8, 1
     510: goto          65
     513: iinc          4, 1
     516: goto          38
     519: return
    Exception table:
       from    to  target type
         227   241   244   Class java/lang/Exception
         298   322   325   Class java/lang/Exception

  private boolean injectWithBeanName(java.lang.String, java.lang.reflect.Field, org.springframework.web.context.WebApplicationContext) throws javax.servlet.ServletException;
    Code:
       0: aconst_null
       1: astore        4
       3: aload_3
       4: aload_1
       5: invokeinterface #53,  2           // InterfaceMethod org/springframework/web/context/WebApplicationContext.getBean:(Ljava/lang/String;)Ljava/lang/Object;
      10: astore        4
      12: aload         4
      14: ifnonnull     19
      17: iconst_0
      18: ireturn
      19: aload         4
      21: invokevirtual #2                  // Method java/lang/Object.getClass:()Ljava/lang/Class;
      24: aload_2
      25: invokevirtual #2                  // Method java/lang/Object.getClass:()Ljava/lang/Class;
      28: invokevirtual #39                 // Method java/lang/Class.isAssignableFrom:(Ljava/lang/Class;)Z
      31: ifeq          36
      34: iconst_0
      35: ireturn
      36: goto          43
      39: astore        5
      41: iconst_0
      42: ireturn
      43: aload_2
      44: iconst_1
      45: invokevirtual #40                 // Method java/lang/reflect/Field.setAccessible:(Z)V
      48: aload_2
      49: aload_0
      50: aload         4
      52: invokevirtual #41                 // Method java/lang/reflect/Field.set:(Ljava/lang/Object;Ljava/lang/Object;)V
      55: iconst_1
      56: ireturn
      57: astore        5
      59: aload_0
      60: getfield      #4                  // Field log:Lorg/apache/commons/logging/Log;
      63: new           #25                 // class java/lang/StringBuilder
      66: dup
      67: invokespecial #26                 // Method java/lang/StringBuilder."<init>":()V
      70: ldc           #43                 // String Failed to do injection for
      72: invokevirtual #28                 // Method java/lang/StringBuilder.append:(Ljava/lang/String;)Ljava/lang/StringBuilder;
      75: aload_1
      76: invokevirtual #28                 // Method java/lang/StringBuilder.append:(Ljava/lang/String;)Ljava/lang/StringBuilder;
      79: invokevirtual #30                 // Method java/lang/StringBuilder.toString:()Ljava/lang/String;
      82: aload         5
      84: invokeinterface #8,  3            // InterfaceMethod org/apache/commons/logging/Log.error:(Ljava/lang/Object;Ljava/lang/Throwable;)V
      89: new           #9                  // class javax/servlet/ServletException
      92: dup
      93: aload         5
      95: invokespecial #10                 // Method javax/servlet/ServletException."<init>":(Ljava/lang/Throwable;)V
      98: athrow
    Exception table:
       from    to  target type
           3    18    39   Class java/lang/Exception
          19    35    39   Class java/lang/Exception
          43    56    57   Class java/lang/Exception
}
