Compiled from "VmWorkFlowServlet.java"
public class com.virtual.ssv.server.vmworkflow.VmWorkFlowServlet extends com.virtual.ssv.server.BaseServlet {
  private static final long serialVersionUID;

  public void init();
    Code:
       0: aload_0
       1: invokespecial #1                  // Method com/virtual/ssv/server/BaseServlet.init:()V
       4: return

  public com.virtual.ssv.server.vmworkflow.VmWorkFlowServlet();
    Code:
       0: aload_0
       1: invokespecial #2                  // Method com/virtual/ssv/server/BaseServlet."<init>":()V
       4: return

  protected void doGet(javax.servlet.http.HttpServletRequest, javax.servlet.http.HttpServletResponse) throws javax.servlet.ServletException, java.io.IOException;
    Code:
       0: aload_1
       1: invokeinterface #3,  1            // InterfaceMethod javax/servlet/http/HttpServletRequest.getSession:()Ljavax/servlet/http/HttpSession;
       6: astore_3
       7: aload_3
       8: ldc           #4                  // String loginInfo
      10: invokeinterface #5,  2            // InterfaceMethod javax/servlet/http/HttpSession.getAttribute:(Ljava/lang/String;)Ljava/lang/Object;
      15: checkcast     #6                  // class com/virtual/ssv/server/user/LoginInfo
      18: astore        4
      20: aload         4
      22: ifnull        227
      25: aload_0
      26: aload_1
      27: aload_2
      28: invokevirtual #7                  // Method checkUserState:(Ljavax/servlet/http/HttpServletRequest;Ljavax/servlet/http/HttpServletResponse;)V
      31: aload_1
      32: ldc           #8                  // String way
      34: invokeinterface #9,  2            // InterfaceMethod javax/servlet/http/HttpServletRequest.getParameter:(Ljava/lang/String;)Ljava/lang/String;
      39: astore        5
      41: ldc           #10                 // String list
      43: aload         5
      45: invokevirtual #11                 // Method java/lang/String.equals:(Ljava/lang/Object;)Z
      48: ifeq          62
      51: aload_0
      52: aload_1
      53: aload_2
      54: aload         4
      56: invokespecial #12                 // Method getList:(Ljavax/servlet/http/HttpServletRequest;Ljavax/servlet/http/HttpServletResponse;Lcom/virtual/ssv/server/user/LoginInfo;)V
      59: goto          227
      62: ldc           #13                 // String revoke
      64: aload         5
      66: invokevirtual #11                 // Method java/lang/String.equals:(Ljava/lang/Object;)Z
      69: ifeq          83
      72: aload_0
      73: aload_1
      74: aload_2
      75: aload         4
      77: invokespecial #14                 // Method revokeVmWorkflow:(Ljavax/servlet/http/HttpServletRequest;Ljavax/servlet/http/HttpServletResponse;Lcom/virtual/ssv/server/user/LoginInfo;)V
      80: goto          227
      83: ldc           #15                 // String getWorkflow
      85: aload         5
      87: invokevirtual #11                 // Method java/lang/String.equals:(Ljava/lang/Object;)Z
      90: ifeq          104
      93: aload_0
      94: aload_1
      95: aload_2
      96: aload         4
      98: invokespecial #16                 // Method getVmWorkflow:(Ljavax/servlet/http/HttpServletRequest;Ljavax/servlet/http/HttpServletResponse;Lcom/virtual/ssv/server/user/LoginInfo;)V
     101: goto          227
     104: ldc           #17                 // String updateWorkflow
     106: aload         5
     108: invokevirtual #11                 // Method java/lang/String.equals:(Ljava/lang/Object;)Z
     111: ifeq          125
     114: aload_0
     115: aload_1
     116: aload_2
     117: aload         4
     119: invokespecial #18                 // Method updateWorkflow:(Ljavax/servlet/http/HttpServletRequest;Ljavax/servlet/http/HttpServletResponse;Lcom/virtual/ssv/server/user/LoginInfo;)V
     122: goto          227
     125: ldc           #19                 // String queryApplyVmExtend
     127: aload         5
     129: invokevirtual #11                 // Method java/lang/String.equals:(Ljava/lang/Object;)Z
     132: ifeq          146
     135: aload_0
     136: aload_1
     137: aload_2
     138: aload         4
     140: invokevirtual #20                 // Method queryApplyVmExtend:(Ljavax/servlet/http/HttpServletRequest;Ljavax/servlet/http/HttpServletResponse;Lcom/virtual/ssv/server/user/LoginInfo;)V
     143: goto          227
     146: ldc           #21                 // String checkDomainReName
     148: aload         5
     150: invokevirtual #11                 // Method java/lang/String.equals:(Ljava/lang/Object;)Z
     153: ifeq          167
     156: aload_0
     157: aload_1
     158: aload_2
     159: aload         4
     161: invokespecial #22                 // Method checkDomainReName:(Ljavax/servlet/http/HttpServletRequest;Ljavax/servlet/http/HttpServletResponse;Lcom/virtual/ssv/server/user/LoginInfo;)V
     164: goto          227
     167: ldc           #23                 // String validateIpAddress
     169: aload         5
     171: invokevirtual #11                 // Method java/lang/String.equals:(Ljava/lang/Object;)Z
     174: ifeq          188
     177: aload_0
     178: aload_1
     179: aload_2
     180: aload         4
     182: invokevirtual #24                 // Method validateIpAddress:(Ljavax/servlet/http/HttpServletRequest;Ljavax/servlet/http/HttpServletResponse;Lcom/virtual/ssv/server/user/LoginInfo;)V
     185: goto          227
     188: ldc           #25                 // String queryPreName
     190: aload         5
     192: invokevirtual #11                 // Method java/lang/String.equals:(Ljava/lang/Object;)Z
     195: ifeq          209
     198: aload_0
     199: aload_1
     200: aload_2
     201: aload         4
     203: invokespecial #26                 // Method queryDomainPreName:(Ljavax/servlet/http/HttpServletRequest;Ljavax/servlet/http/HttpServletResponse;Lcom/virtual/ssv/server/user/LoginInfo;)V
     206: goto          227
     209: ldc           #27                 // String getSysMask
     211: aload         5
     213: invokevirtual #11                 // Method java/lang/String.equals:(Ljava/lang/Object;)Z
     216: ifeq          227
     219: aload_0
     220: aload_1
     221: aload_2
     222: aload         4
     224: invokespecial #28                 // Method getSysMask:(Ljavax/servlet/http/HttpServletRequest;Ljavax/servlet/http/HttpServletResponse;Lcom/virtual/ssv/server/user/LoginInfo;)V
     227: return

  private void getSysMask(javax.servlet.http.HttpServletRequest, javax.servlet.http.HttpServletResponse, com.virtual.ssv.server.user.LoginInfo);
    Code:
       0: aload_1
       1: ldc           #29                 // String ip
       3: invokeinterface #9,  2            // InterfaceMethod javax/servlet/http/HttpServletRequest.getParameter:(Ljava/lang/String;)Ljava/lang/String;
       8: astore        4
      10: aload         4
      12: ifnull        39
      15: aload         4
      17: ldc           #30                 // String
      19: if_acmpeq     39
      22: aload_0
      23: aload_2
      24: aload_0
      25: getfield      #31                 // Field gson:Lcom/google/gson/Gson;
      28: aload         4
      30: invokestatic  #32                 // Method com/virtual/ssv/server/IPv4Util.getSubnetmask:(Ljava/lang/String;)Ljava/lang/String;
      33: invokevirtual #33                 // Method com/google/gson/Gson.toJson:(Ljava/lang/Object;)Ljava/lang/String;
      36: invokevirtual #34                 // Method write:(Ljavax/servlet/http/HttpServletResponse;Ljava/lang/String;)V
      39: return

  private void queryDomainPreName(javax.servlet.http.HttpServletRequest, javax.servlet.http.HttpServletResponse, com.virtual.ssv.server.user.LoginInfo);
    Code:
       0: aload_3
       1: invokevirtual #35                 // Method com/virtual/ssv/server/user/LoginInfo.getOrgId:()Ljava/lang/Long;
       4: astore        4
       6: aload         4
       8: ifnull        95
      11: aconst_null
      12: astore        5
      14: aload_0
      15: getfield      #36                 // Field reqHandle:Lcom/virtual/ssv/server/rs/client/RequestHandle;
      18: aload         4
      20: invokevirtual #37                 // Method com/virtual/ssv/server/rs/client/RequestHandle.queryOrgInfo:(Ljava/lang/Long;)Lcom/virtual/ssv/server/rs/client/entity/Organization;
      23: astore        5
      25: aload         5
      27: ifnull        51
      30: aload_1
      31: invokeinterface #3,  1            // InterfaceMethod javax/servlet/http/HttpServletRequest.getSession:()Ljavax/servlet/http/HttpSession;
      36: ldc           #38                 // String domainPreName
      38: aload         5
      40: invokevirtual #39                 // Method com/virtual/ssv/server/rs/client/entity/Organization.getDomainPreName:()Ljava/lang/String;
      43: invokeinterface #40,  3           // InterfaceMethod javax/servlet/http/HttpSession.setAttribute:(Ljava/lang/String;Ljava/lang/Object;)V
      48: goto          66
      51: aload_1
      52: invokeinterface #3,  1            // InterfaceMethod javax/servlet/http/HttpServletRequest.getSession:()Ljavax/servlet/http/HttpSession;
      57: ldc           #38                 // String domainPreName
      59: ldc           #30                 // String
      61: invokeinterface #40,  3           // InterfaceMethod javax/servlet/http/HttpSession.setAttribute:(Ljava/lang/String;Ljava/lang/Object;)V
      66: goto          81
      69: astore        6
      71: getstatic     #42                 // Field log:Lorg/apache/commons/logging/Log;
      74: aload         6
      76: invokeinterface #43,  2           // InterfaceMethod org/apache/commons/logging/Log.error:(Ljava/lang/Object;)V
      81: aload_0
      82: aload_2
      83: aload_0
      84: getfield      #31                 // Field gson:Lcom/google/gson/Gson;
      87: aload         5
      89: invokevirtual #33                 // Method com/google/gson/Gson.toJson:(Ljava/lang/Object;)Ljava/lang/String;
      92: invokevirtual #34                 // Method write:(Ljavax/servlet/http/HttpServletResponse;Ljava/lang/String;)V
      95: return
    Exception table:
       from    to  target type
          14    66    69   Class java/lang/Exception

  private void checkDomainReName(javax.servlet.http.HttpServletRequest, javax.servlet.http.HttpServletResponse, com.virtual.ssv.server.user.LoginInfo);
    Code:
       0: ldc           #30                 // String
       2: astore        4
       4: aload_1
       5: ldc           #44                 // String domainName
       7: invokeinterface #9,  2            // InterfaceMethod javax/servlet/http/HttpServletRequest.getParameter:(Ljava/lang/String;)Ljava/lang/String;
      12: astore        5
      14: aload         5
      16: ifnull        34
      19: aload_0
      20: getfield      #36                 // Field reqHandle:Lcom/virtual/ssv/server/rs/client/RequestHandle;
      23: aload         5
      25: aload_3
      26: invokevirtual #35                 // Method com/virtual/ssv/server/user/LoginInfo.getOrgId:()Ljava/lang/Long;
      29: invokevirtual #45                 // Method com/virtual/ssv/server/rs/client/RequestHandle.checkDomainReName:(Ljava/lang/String;Ljava/lang/Long;)Ljava/lang/String;
      32: astore        4
      34: goto          49
      37: astore        5
      39: getstatic     #42                 // Field log:Lorg/apache/commons/logging/Log;
      42: aload         5
      44: invokeinterface #43,  2           // InterfaceMethod org/apache/commons/logging/Log.error:(Ljava/lang/Object;)V
      49: aload_0
      50: aload_2
      51: aload_0
      52: getfield      #46                 // Field filterJson:Lcom/google/gson/Gson;
      55: aload         4
      57: invokevirtual #33                 // Method com/google/gson/Gson.toJson:(Ljava/lang/Object;)Ljava/lang/String;
      60: invokevirtual #34                 // Method write:(Ljavax/servlet/http/HttpServletResponse;Ljava/lang/String;)V
      63: return
    Exception table:
       from    to  target type
           4    34    37   Class java/lang/Exception

  public void validateIpAddress(javax.servlet.http.HttpServletRequest, javax.servlet.http.HttpServletResponse, com.virtual.ssv.server.user.LoginInfo);
    Code:
       0: ldc           #30                 // String
       2: astore        4
       4: aload_1
       5: ldc           #29                 // String ip
       7: invokeinterface #9,  2            // InterfaceMethod javax/servlet/http/HttpServletRequest.getParameter:(Ljava/lang/String;)Ljava/lang/String;
      12: astore        5
      14: aload_1
      15: ldc           #47                 // String mask
      17: invokeinterface #9,  2            // InterfaceMethod javax/servlet/http/HttpServletRequest.getParameter:(Ljava/lang/String;)Ljava/lang/String;
      22: astore        6
      24: aload         5
      26: aload         6
      28: invokestatic  #48                 // Method com/virtual/ssv/server/ParamsValidator.validateIpAddress:(Ljava/lang/String;Ljava/lang/String;)Ljava/lang/String;
      31: astore        4
      33: aload_0
      34: aload_2
      35: aload_0
      36: getfield      #46                 // Field filterJson:Lcom/google/gson/Gson;
      39: aload         4
      41: invokevirtual #33                 // Method com/google/gson/Gson.toJson:(Ljava/lang/Object;)Ljava/lang/String;
      44: invokevirtual #34                 // Method write:(Ljavax/servlet/http/HttpServletResponse;Ljava/lang/String;)V
      47: return

  private void updateWorkflow(javax.servlet.http.HttpServletRequest, javax.servlet.http.HttpServletResponse, com.virtual.ssv.server.user.LoginInfo);
    Code:
       0: new           #49                 // class java/util/Date
       3: dup
       4: invokespecial #50                 // Method java/util/Date."<init>":()V
       7: astore        4
       9: new           #51                 // class com/virtual/ssv/server/entity/ResultJson
      12: dup
      13: invokespecial #52                 // Method com/virtual/ssv/server/entity/ResultJson."<init>":()V
      16: astore        5
      18: aload_1
      19: ldc           #53                 // String xml
      21: invokeinterface #9,  2            // InterfaceMethod javax/servlet/http/HttpServletRequest.getParameter:(Ljava/lang/String;)Ljava/lang/String;
      26: astore        6
      28: aload_1
      29: ldc           #54                 // String extendXml
      31: invokeinterface #9,  2            // InterfaceMethod javax/servlet/http/HttpServletRequest.getParameter:(Ljava/lang/String;)Ljava/lang/String;
      36: astore        7
      38: aload         6
      40: ifnull        408
      43: aload         6
      45: ldc           #55                 // class com/virtual/ssv/server/rs/client/entity/RsVmWorkflow
      47: invokestatic  #56                 // Method com/virtual/common/FuncUtil.convertXmlToObject:(Ljava/lang/String;Ljava/lang/Class;)Ljava/lang/Object;
      50: checkcast     #55                 // class com/virtual/ssv/server/rs/client/entity/RsVmWorkflow
      53: astore        8
      55: aload         8
      57: aload_3
      58: invokevirtual #57                 // Method com/virtual/ssv/server/user/LoginInfo.getId:()Ljava/lang/Long;
      61: invokevirtual #58                 // Method com/virtual/ssv/server/rs/client/entity/RsVmWorkflow.setUserId:(Ljava/lang/Long;)V
      64: aload         8
      66: aload_3
      67: invokevirtual #59                 // Method com/virtual/ssv/server/user/LoginInfo.getUserName:()Ljava/lang/String;
      70: invokevirtual #60                 // Method com/virtual/ssv/server/rs/client/entity/RsVmWorkflow.setUsreName:(Ljava/lang/String;)V
      73: aload         8
      75: aload_3
      76: invokevirtual #35                 // Method com/virtual/ssv/server/user/LoginInfo.getOrgId:()Ljava/lang/Long;
      79: invokevirtual #61                 // Method com/virtual/ssv/server/rs/client/entity/RsVmWorkflow.setOrgId:(Ljava/lang/Long;)V
      82: aload         8
      84: invokevirtual #62                 // Method com/virtual/ssv/server/rs/client/entity/RsVmWorkflow.getDomainName:()Ljava/lang/String;
      87: ifnull        147
      90: ldc           #63                 // String undefined
      92: aload         8
      94: invokevirtual #62                 // Method com/virtual/ssv/server/rs/client/entity/RsVmWorkflow.getDomainName:()Ljava/lang/String;
      97: invokevirtual #64                 // Method java/lang/String.equalsIgnoreCase:(Ljava/lang/String;)Z
     100: ifne          147
     103: aload_0
     104: getfield      #36                 // Field reqHandle:Lcom/virtual/ssv/server/rs/client/RequestHandle;
     107: aload         8
     109: invokevirtual #62                 // Method com/virtual/ssv/server/rs/client/entity/RsVmWorkflow.getDomainName:()Ljava/lang/String;
     112: aload_3
     113: invokevirtual #35                 // Method com/virtual/ssv/server/user/LoginInfo.getOrgId:()Ljava/lang/Long;
     116: invokevirtual #45                 // Method com/virtual/ssv/server/rs/client/RequestHandle.checkDomainReName:(Ljava/lang/String;Ljava/lang/Long;)Ljava/lang/String;
     119: astore        9
     121: aload         9
     123: ifnull        147
     126: aload         9
     128: ldc           #65                 // String true
     130: invokevirtual #11                 // Method java/lang/String.equals:(Ljava/lang/Object;)Z
     133: ifeq          147
     136: new           #66                 // class com/virtual/common/AppException
     139: dup
     140: sipush        1002
     143: invokespecial #68                 // Method com/virtual/common/AppException."<init>":(I)V
     146: athrow
     147: aload_0
     148: getfield      #36                 // Field reqHandle:Lcom/virtual/ssv/server/rs/client/RequestHandle;
     151: aload         8
     153: invokevirtual #69                 // Method com/virtual/ssv/server/rs/client/entity/RsVmWorkflow.getId:()Ljava/lang/Long;
     156: invokevirtual #70                 // Method com/virtual/ssv/server/rs/client/RequestHandle.getVmWorkflow:(Ljava/lang/Long;)Lcom/virtual/ssv/server/rs/client/entity/VmWorkflow;
     159: astore        9
     161: aload         7
     163: invokestatic  #71                 // Method org/apache/commons/lang/StringUtils.isNotEmpty:(Ljava/lang/String;)Z
     166: ifeq          211
     169: aload         7
     171: ldc           #72                 // class com/virtual/ssv/server/rs/client/entity/RsVmWorkflowAppend
     173: invokestatic  #56                 // Method com/virtual/common/FuncUtil.convertXmlToObject:(Ljava/lang/String;Ljava/lang/Class;)Ljava/lang/Object;
     176: checkcast     #72                 // class com/virtual/ssv/server/rs/client/entity/RsVmWorkflowAppend
     179: astore        10
     181: aload         10
     183: aload         9
     185: invokevirtual #73                 // Method com/virtual/ssv/server/rs/client/entity/VmWorkflow.getVmWorkflowAppend:()Lcom/virtual/ssv/server/rs/client/entity/RsVmWorkflowAppend;
     188: invokevirtual #74                 // Method com/virtual/ssv/server/rs/client/entity/RsVmWorkflowAppend.getId:()Ljava/lang/Long;
     191: invokevirtual #75                 // Method com/virtual/ssv/server/rs/client/entity/RsVmWorkflowAppend.setId:(Ljava/lang/Long;)V
     194: aload         10
     196: aload         9
     198: invokevirtual #76                 // Method com/virtual/ssv/server/rs/client/entity/VmWorkflow.getId:()Ljava/lang/Long;
     201: invokevirtual #77                 // Method com/virtual/ssv/server/rs/client/entity/RsVmWorkflowAppend.setVmWorkflowId:(Ljava/lang/Long;)V
     204: aload         8
     206: aload         10
     208: invokevirtual #78                 // Method com/virtual/ssv/server/rs/client/entity/RsVmWorkflow.setVmWorkflowAppend:(Lcom/virtual/ssv/server/rs/client/entity/RsVmWorkflowAppend;)V
     211: aload         8
     213: invokevirtual #79                 // Method com/virtual/ssv/server/rs/client/entity/RsVmWorkflow.getTitle:()Ljava/lang/String;
     216: invokestatic  #80                 // Method org/apache/commons/lang/StringUtils.isEmpty:(Ljava/lang/String;)Z
     219: ifeq          230
     222: aload         8
     224: invokevirtual #62                 // Method com/virtual/ssv/server/rs/client/entity/RsVmWorkflow.getDomainName:()Ljava/lang/String;
     227: goto          235
     230: aload         8
     232: invokevirtual #79                 // Method com/virtual/ssv/server/rs/client/entity/RsVmWorkflow.getTitle:()Ljava/lang/String;
     235: astore        10
     237: aload_0
     238: getfield      #36                 // Field reqHandle:Lcom/virtual/ssv/server/rs/client/RequestHandle;
     241: aload         8
     243: aload         10
     245: invokevirtual #81                 // Method com/virtual/ssv/server/rs/client/RequestHandle.updateVmWorkflow:(Lcom/virtual/ssv/server/rs/client/entity/RsVmWorkflow;Ljava/lang/String;)Lcom/virtual/ssv/server/entity/ResultJson;
     248: astore        5
     250: new           #49                 // class java/util/Date
     253: dup
     254: invokespecial #50                 // Method java/util/Date."<init>":()V
     257: astore        11
     259: new           #82                 // class com/virtual/ssv/server/rs/client/entity/RsOperateLog
     262: dup
     263: invokespecial #83                 // Method com/virtual/ssv/server/rs/client/entity/RsOperateLog."<init>":()V
     266: astore        12
     268: aload         12
     270: aload_3
     271: invokevirtual #57                 // Method com/virtual/ssv/server/user/LoginInfo.getId:()Ljava/lang/Long;
     274: invokevirtual #84                 // Method com/virtual/ssv/server/rs/client/entity/RsOperateLog.setUserId:(Ljava/lang/Long;)V
     277: aload         12
     279: aload_3
     280: invokevirtual #35                 // Method com/virtual/ssv/server/user/LoginInfo.getOrgId:()Ljava/lang/Long;
     283: invokevirtual #85                 // Method com/virtual/ssv/server/rs/client/entity/RsOperateLog.setOrgId:(Ljava/lang/Long;)V
     286: aload         12
     288: aload_3
     289: invokevirtual #86                 // Method com/virtual/ssv/server/user/LoginInfo.getLoginName:()Ljava/lang/String;
     292: invokevirtual #87                 // Method com/virtual/ssv/server/rs/client/entity/RsOperateLog.setLoginName:(Ljava/lang/String;)V
     295: aload         12
     297: aload_3
     298: invokevirtual #59                 // Method com/virtual/ssv/server/user/LoginInfo.getUserName:()Ljava/lang/String;
     301: invokevirtual #88                 // Method com/virtual/ssv/server/rs/client/entity/RsOperateLog.setUserName:(Ljava/lang/String;)V
     304: aload         12
     306: aload_3
     307: invokevirtual #89                 // Method com/virtual/ssv/server/user/LoginInfo.getLoginIp:()Ljava/lang/String;
     310: invokevirtual #90                 // Method com/virtual/ssv/server/rs/client/entity/RsOperateLog.setAddress:(Ljava/lang/String;)V
     313: aload         12
     315: bipush        30
     317: invokestatic  #92                 // Method java/lang/Integer.valueOf:(I)Ljava/lang/Integer;
     320: invokevirtual #93                 // Method com/virtual/ssv/server/rs/client/entity/RsOperateLog.setCategory:(Ljava/lang/Integer;)V
     323: aload         12
     325: aload_0
     326: getfield      #94                 // Field logSm:Lcom/virtual/common/StringManager;
     329: ldc           #95                 // String editWorkflow
     331: iconst_1
     332: anewarray     #96                 // class java/lang/Object
     335: dup
     336: iconst_0
     337: aload         10
     339: aastore
     340: invokevirtual #97                 // Method com/virtual/common/StringManager.getString:(Ljava/lang/String;[Ljava/lang/Object;)Ljava/lang/String;
     343: invokevirtual #98                 // Method com/virtual/ssv/server/rs/client/entity/RsOperateLog.setDescription:(Ljava/lang/String;)V
     346: aload         5
     348: invokevirtual #99                 // Method com/virtual/ssv/server/entity/ResultJson.getState:()I
     351: iconst_1
     352: if_icmpne     366
     355: aload         12
     357: getstatic     #100                // Field com/virtual/ssv/server/rs/client/entity/RsOperateLog.RESULT_SUCCESS:Ljava/lang/Integer;
     360: invokevirtual #101                // Method com/virtual/ssv/server/rs/client/entity/RsOperateLog.setResult:(Ljava/lang/Integer;)V
     363: goto          384
     366: aload         12
     368: getstatic     #102                // Field com/virtual/ssv/server/rs/client/entity/RsOperateLog.RESULT_FAILURE:Ljava/lang/Integer;
     371: invokevirtual #101                // Method com/virtual/ssv/server/rs/client/entity/RsOperateLog.setResult:(Ljava/lang/Integer;)V
     374: aload         12
     376: aload         5
     378: invokevirtual #103                // Method com/virtual/ssv/server/entity/ResultJson.getMessage:()Ljava/lang/String;
     381: invokevirtual #104                // Method com/virtual/ssv/server/rs/client/entity/RsOperateLog.setFailureReason:(Ljava/lang/String;)V
     384: aload         12
     386: aload         4
     388: invokevirtual #105                // Method com/virtual/ssv/server/rs/client/entity/RsOperateLog.setStartTime:(Ljava/util/Date;)V
     391: aload         12
     393: aload         11
     395: invokevirtual #106                // Method com/virtual/ssv/server/rs/client/entity/RsOperateLog.setEndTime:(Ljava/util/Date;)V
     398: aload_0
     399: getfield      #36                 // Field reqHandle:Lcom/virtual/ssv/server/rs/client/RequestHandle;
     402: aload         12
     404: invokevirtual #107                // Method com/virtual/ssv/server/rs/client/RequestHandle.addUserLog:(Lcom/virtual/ssv/server/rs/client/entity/RsOperateLog;)Ljava/lang/Long;
     407: pop
     408: goto          492
     411: astore        6
     413: aload         6
     415: invokevirtual #108                // Method com/virtual/common/AppException.getErrorCode:()I
     418: bipush        102
     420: if_icmpne     436
     423: aload         5
     425: bipush        102
     427: invokestatic  #109                // Method com/virtual/common/ErrorCodes.getErrorMessage:(I)Ljava/lang/String;
     430: invokevirtual #110                // Method com/virtual/ssv/server/entity/ResultJson.setErrorMsg:(Ljava/lang/String;)V
     433: goto          492
     436: aload         6
     438: invokevirtual #108                // Method com/virtual/common/AppException.getErrorCode:()I
     441: bipush        103
     443: if_icmpne     459
     446: aload         5
     448: bipush        103
     450: invokestatic  #109                // Method com/virtual/common/ErrorCodes.getErrorMessage:(I)Ljava/lang/String;
     453: invokevirtual #110                // Method com/virtual/ssv/server/entity/ResultJson.setErrorMsg:(Ljava/lang/String;)V
     456: goto          492
     459: aload         6
     461: invokevirtual #108                // Method com/virtual/common/AppException.getErrorCode:()I
     464: bipush        11
     466: if_icmpne     482
     469: aload         5
     471: bipush        11
     473: invokestatic  #109                // Method com/virtual/common/ErrorCodes.getErrorMessage:(I)Ljava/lang/String;
     476: invokevirtual #110                // Method com/virtual/ssv/server/entity/ResultJson.setErrorMsg:(Ljava/lang/String;)V
     479: goto          492
     482: aload         5
     484: aload         6
     486: invokevirtual #111                // Method com/virtual/common/AppException.getMessage:()Ljava/lang/String;
     489: invokevirtual #110                // Method com/virtual/ssv/server/entity/ResultJson.setErrorMsg:(Ljava/lang/String;)V
     492: aload_0
     493: aload_2
     494: aload_0
     495: getfield      #46                 // Field filterJson:Lcom/google/gson/Gson;
     498: aload         5
     500: invokevirtual #33                 // Method com/google/gson/Gson.toJson:(Ljava/lang/Object;)Ljava/lang/String;
     503: invokevirtual #34                 // Method write:(Ljavax/servlet/http/HttpServletResponse;Ljava/lang/String;)V
     506: return
    Exception table:
       from    to  target type
          18   408   411   Class com/virtual/common/AppException

  private void getVmWorkflow(javax.servlet.http.HttpServletRequest, javax.servlet.http.HttpServletResponse, com.virtual.ssv.server.user.LoginInfo);
    Code:
       0: new           #51                 // class com/virtual/ssv/server/entity/ResultJson
       3: dup
       4: invokespecial #52                 // Method com/virtual/ssv/server/entity/ResultJson."<init>":()V
       7: astore        4
       9: aload_1
      10: ldc           #112                // String workflowId
      12: invokeinterface #9,  2            // InterfaceMethod javax/servlet/http/HttpServletRequest.getParameter:(Ljava/lang/String;)Ljava/lang/String;
      17: astore        5
      19: aload         5
      21: invokestatic  #71                 // Method org/apache/commons/lang/StringUtils.isNotEmpty:(Ljava/lang/String;)Z
      24: ifeq          183
      27: aload_0
      28: getfield      #36                 // Field reqHandle:Lcom/virtual/ssv/server/rs/client/RequestHandle;
      31: aload         5
      33: invokestatic  #113                // Method java/lang/Long.parseLong:(Ljava/lang/String;)J
      36: invokestatic  #114                // Method java/lang/Long.valueOf:(J)Ljava/lang/Long;
      39: invokevirtual #70                 // Method com/virtual/ssv/server/rs/client/RequestHandle.getVmWorkflow:(Ljava/lang/Long;)Lcom/virtual/ssv/server/rs/client/entity/VmWorkflow;
      42: astore        6
      44: aload         6
      46: invokevirtual #115                // Method com/virtual/ssv/server/rs/client/entity/VmWorkflow.getExpireDate:()Ljava/util/Date;
      49: astore        7
      51: aload         7
      53: ifnull        79
      56: new           #116                // class java/text/SimpleDateFormat
      59: dup
      60: ldc           #117                // String yyyy-MM-dd
      62: invokespecial #118                // Method java/text/SimpleDateFormat."<init>":(Ljava/lang/String;)V
      65: astore        8
      67: aload         6
      69: aload         8
      71: aload         7
      73: invokevirtual #119                // Method java/text/SimpleDateFormat.format:(Ljava/util/Date;)Ljava/lang/String;
      76: invokevirtual #120                // Method com/virtual/ssv/server/rs/client/entity/VmWorkflow.setExpireDateStr:(Ljava/lang/String;)V
      79: aload_0
      80: getfield      #36                 // Field reqHandle:Lcom/virtual/ssv/server/rs/client/RequestHandle;
      83: aload_3
      84: invokevirtual #35                 // Method com/virtual/ssv/server/user/LoginInfo.getOrgId:()Ljava/lang/Long;
      87: invokevirtual #37                 // Method com/virtual/ssv/server/rs/client/RequestHandle.queryOrgInfo:(Ljava/lang/Long;)Lcom/virtual/ssv/server/rs/client/entity/Organization;
      90: astore        8
      92: aload         8
      94: ifnull        154
      97: aload         6
      99: aload         8
     101: invokevirtual #121                // Method com/virtual/ssv/server/rs/client/entity/Organization.getEnableAdjustSetting:()Ljava/lang/Integer;
     104: invokevirtual #122                // Method com/virtual/ssv/server/rs/client/entity/VmWorkflow.setEnableAdjustSetting:(Ljava/lang/Integer;)V
     107: aload         8
     109: invokevirtual #39                 // Method com/virtual/ssv/server/rs/client/entity/Organization.getDomainPreName:()Ljava/lang/String;
     112: ifnull        136
     115: aload_1
     116: invokeinterface #3,  1            // InterfaceMethod javax/servlet/http/HttpServletRequest.getSession:()Ljavax/servlet/http/HttpSession;
     121: ldc           #38                 // String domainPreName
     123: aload         8
     125: invokevirtual #39                 // Method com/virtual/ssv/server/rs/client/entity/Organization.getDomainPreName:()Ljava/lang/String;
     128: invokeinterface #40,  3           // InterfaceMethod javax/servlet/http/HttpSession.setAttribute:(Ljava/lang/String;Ljava/lang/Object;)V
     133: goto          169
     136: aload_1
     137: invokeinterface #3,  1            // InterfaceMethod javax/servlet/http/HttpServletRequest.getSession:()Ljavax/servlet/http/HttpSession;
     142: ldc           #38                 // String domainPreName
     144: ldc           #30                 // String
     146: invokeinterface #40,  3           // InterfaceMethod javax/servlet/http/HttpSession.setAttribute:(Ljava/lang/String;Ljava/lang/Object;)V
     151: goto          169
     154: aload_1
     155: invokeinterface #3,  1            // InterfaceMethod javax/servlet/http/HttpServletRequest.getSession:()Ljavax/servlet/http/HttpSession;
     160: ldc           #38                 // String domainPreName
     162: ldc           #30                 // String
     164: invokeinterface #40,  3           // InterfaceMethod javax/servlet/http/HttpSession.setAttribute:(Ljava/lang/String;Ljava/lang/Object;)V
     169: aload_0
     170: aload_2
     171: aload_0
     172: getfield      #31                 // Field gson:Lcom/google/gson/Gson;
     175: aload         6
     177: invokevirtual #33                 // Method com/google/gson/Gson.toJson:(Ljava/lang/Object;)Ljava/lang/String;
     180: invokevirtual #34                 // Method write:(Ljavax/servlet/http/HttpServletResponse;Ljava/lang/String;)V
     183: goto          281
     186: astore        5
     188: aload         5
     190: invokevirtual #108                // Method com/virtual/common/AppException.getErrorCode:()I
     193: bipush        102
     195: if_icmpne     211
     198: aload         4
     200: bipush        102
     202: invokestatic  #109                // Method com/virtual/common/ErrorCodes.getErrorMessage:(I)Ljava/lang/String;
     205: invokevirtual #110                // Method com/virtual/ssv/server/entity/ResultJson.setErrorMsg:(Ljava/lang/String;)V
     208: goto          267
     211: aload         5
     213: invokevirtual #108                // Method com/virtual/common/AppException.getErrorCode:()I
     216: bipush        103
     218: if_icmpne     234
     221: aload         4
     223: bipush        103
     225: invokestatic  #109                // Method com/virtual/common/ErrorCodes.getErrorMessage:(I)Ljava/lang/String;
     228: invokevirtual #110                // Method com/virtual/ssv/server/entity/ResultJson.setErrorMsg:(Ljava/lang/String;)V
     231: goto          267
     234: aload         5
     236: invokevirtual #108                // Method com/virtual/common/AppException.getErrorCode:()I
     239: bipush        11
     241: if_icmpne     257
     244: aload         4
     246: bipush        11
     248: invokestatic  #109                // Method com/virtual/common/ErrorCodes.getErrorMessage:(I)Ljava/lang/String;
     251: invokevirtual #110                // Method com/virtual/ssv/server/entity/ResultJson.setErrorMsg:(Ljava/lang/String;)V
     254: goto          267
     257: aload         4
     259: aload         5
     261: invokevirtual #111                // Method com/virtual/common/AppException.getMessage:()Ljava/lang/String;
     264: invokevirtual #110                // Method com/virtual/ssv/server/entity/ResultJson.setErrorMsg:(Ljava/lang/String;)V
     267: aload_0
     268: aload_2
     269: aload_0
     270: getfield      #46                 // Field filterJson:Lcom/google/gson/Gson;
     273: aload         4
     275: invokevirtual #33                 // Method com/google/gson/Gson.toJson:(Ljava/lang/Object;)Ljava/lang/String;
     278: invokevirtual #34                 // Method write:(Ljavax/servlet/http/HttpServletResponse;Ljava/lang/String;)V
     281: return
    Exception table:
       from    to  target type
           9   183   186   Class com/virtual/common/AppException

  private void revokeVmWorkflow(javax.servlet.http.HttpServletRequest, javax.servlet.http.HttpServletResponse, com.virtual.ssv.server.user.LoginInfo);
    Code:
       0: new           #49                 // class java/util/Date
       3: dup
       4: invokespecial #50                 // Method java/util/Date."<init>":()V
       7: astore        4
       9: new           #51                 // class com/virtual/ssv/server/entity/ResultJson
      12: dup
      13: invokespecial #52                 // Method com/virtual/ssv/server/entity/ResultJson."<init>":()V
      16: astore        5
      18: aload_1
      19: ldc           #123                // String id
      21: invokeinterface #9,  2            // InterfaceMethod javax/servlet/http/HttpServletRequest.getParameter:(Ljava/lang/String;)Ljava/lang/String;
      26: astore        6
      28: aload_1
      29: ldc           #124                // String name
      31: invokeinterface #9,  2            // InterfaceMethod javax/servlet/http/HttpServletRequest.getParameter:(Ljava/lang/String;)Ljava/lang/String;
      36: astore        7
      38: aconst_null
      39: astore        8
      41: aload_1
      42: ldc           #125                // String title
      44: invokeinterface #9,  2            // InterfaceMethod javax/servlet/http/HttpServletRequest.getParameter:(Ljava/lang/String;)Ljava/lang/String;
      49: ldc           #126                // String UTF-8
      51: invokestatic  #127                // Method java/net/URLDecoder.decode:(Ljava/lang/String;Ljava/lang/String;)Ljava/lang/String;
      54: astore        8
      56: goto          74
      59: astore        9
      61: getstatic     #42                 // Field log:Lorg/apache/commons/logging/Log;
      64: aload         9
      66: invokevirtual #129                // Method java/io/UnsupportedEncodingException.getMessage:()Ljava/lang/String;
      69: invokeinterface #43,  2           // InterfaceMethod org/apache/commons/logging/Log.error:(Ljava/lang/Object;)V
      74: aload_1
      75: ldc           #130                // String type
      77: invokeinterface #9,  2            // InterfaceMethod javax/servlet/http/HttpServletRequest.getParameter:(Ljava/lang/String;)Ljava/lang/String;
      82: astore        9
      84: new           #55                 // class com/virtual/ssv/server/rs/client/entity/RsVmWorkflow
      87: dup
      88: invokespecial #131                // Method com/virtual/ssv/server/rs/client/entity/RsVmWorkflow."<init>":()V
      91: astore        10
      93: aload         6
      95: ifnull        108
      98: aload         10
     100: aload         6
     102: invokestatic  #132                // Method java/lang/Long.valueOf:(Ljava/lang/String;)Ljava/lang/Long;
     105: invokevirtual #133                // Method com/virtual/ssv/server/rs/client/entity/RsVmWorkflow.setId:(Ljava/lang/Long;)V
     108: aload         10
     110: aload         7
     112: invokevirtual #134                // Method com/virtual/ssv/server/rs/client/entity/RsVmWorkflow.setDomainName:(Ljava/lang/String;)V
     115: aload         8
     117: ifnonnull     125
     120: aload         7
     122: goto          127
     125: aload         8
     127: astore        8
     129: aload         10
     131: aload         8
     133: invokevirtual #135                // Method com/virtual/ssv/server/rs/client/entity/RsVmWorkflow.setTitle:(Ljava/lang/String;)V
     136: aload_0
     137: getfield      #36                 // Field reqHandle:Lcom/virtual/ssv/server/rs/client/RequestHandle;
     140: aload         10
     142: invokevirtual #136                // Method com/virtual/ssv/server/rs/client/RequestHandle.updateVmWorkflow:(Lcom/virtual/ssv/server/rs/client/entity/RsVmWorkflow;)Lcom/virtual/ssv/server/entity/ResultJson;
     145: astore        5
     147: aload         5
     149: invokevirtual #137                // Method com/virtual/ssv/server/entity/ResultJson.isSuccess:()Z
     152: ifeq          365
     155: new           #49                 // class java/util/Date
     158: dup
     159: invokespecial #50                 // Method java/util/Date."<init>":()V
     162: astore        11
     164: new           #82                 // class com/virtual/ssv/server/rs/client/entity/RsOperateLog
     167: dup
     168: invokespecial #83                 // Method com/virtual/ssv/server/rs/client/entity/RsOperateLog."<init>":()V
     171: astore        12
     173: aload         12
     175: aload_3
     176: invokevirtual #57                 // Method com/virtual/ssv/server/user/LoginInfo.getId:()Ljava/lang/Long;
     179: invokevirtual #84                 // Method com/virtual/ssv/server/rs/client/entity/RsOperateLog.setUserId:(Ljava/lang/Long;)V
     182: aload         12
     184: aload_3
     185: invokevirtual #35                 // Method com/virtual/ssv/server/user/LoginInfo.getOrgId:()Ljava/lang/Long;
     188: invokevirtual #85                 // Method com/virtual/ssv/server/rs/client/entity/RsOperateLog.setOrgId:(Ljava/lang/Long;)V
     191: aload         12
     193: aload_3
     194: invokevirtual #86                 // Method com/virtual/ssv/server/user/LoginInfo.getLoginName:()Ljava/lang/String;
     197: invokevirtual #87                 // Method com/virtual/ssv/server/rs/client/entity/RsOperateLog.setLoginName:(Ljava/lang/String;)V
     200: aload         12
     202: aload_3
     203: invokevirtual #59                 // Method com/virtual/ssv/server/user/LoginInfo.getUserName:()Ljava/lang/String;
     206: invokevirtual #88                 // Method com/virtual/ssv/server/rs/client/entity/RsOperateLog.setUserName:(Ljava/lang/String;)V
     209: aload         12
     211: aload_3
     212: invokevirtual #89                 // Method com/virtual/ssv/server/user/LoginInfo.getLoginIp:()Ljava/lang/String;
     215: invokevirtual #90                 // Method com/virtual/ssv/server/rs/client/entity/RsOperateLog.setAddress:(Ljava/lang/String;)V
     218: aload         12
     220: bipush        30
     222: invokestatic  #92                 // Method java/lang/Integer.valueOf:(I)Ljava/lang/Integer;
     225: invokevirtual #93                 // Method com/virtual/ssv/server/rs/client/entity/RsOperateLog.setCategory:(Ljava/lang/Integer;)V
     228: aload         12
     230: aload         4
     232: invokevirtual #105                // Method com/virtual/ssv/server/rs/client/entity/RsOperateLog.setStartTime:(Ljava/util/Date;)V
     235: aload         12
     237: aload         11
     239: invokevirtual #106                // Method com/virtual/ssv/server/rs/client/entity/RsOperateLog.setEndTime:(Ljava/util/Date;)V
     242: ldc           #138                // String 1
     244: aload         9
     246: invokevirtual #11                 // Method java/lang/String.equals:(Ljava/lang/Object;)Z
     249: ifeq          278
     252: aload         12
     254: aload_0
     255: getfield      #94                 // Field logSm:Lcom/virtual/common/StringManager;
     258: ldc           #139                // String revoke.apply.vm
     260: iconst_1
     261: anewarray     #96                 // class java/lang/Object
     264: dup
     265: iconst_0
     266: aload         8
     268: aastore
     269: invokevirtual #97                 // Method com/virtual/common/StringManager.getString:(Ljava/lang/String;[Ljava/lang/Object;)Ljava/lang/String;
     272: invokevirtual #98                 // Method com/virtual/ssv/server/rs/client/entity/RsOperateLog.setDescription:(Ljava/lang/String;)V
     275: goto          347
     278: ldc           #140                // String 0
     280: aload         9
     282: invokevirtual #11                 // Method java/lang/String.equals:(Ljava/lang/Object;)Z
     285: ifeq          314
     288: aload         12
     290: aload_0
     291: getfield      #94                 // Field logSm:Lcom/virtual/common/StringManager;
     294: ldc           #141                // String revoke.cancel.vm
     296: iconst_1
     297: anewarray     #96                 // class java/lang/Object
     300: dup
     301: iconst_0
     302: aload         8
     304: aastore
     305: invokevirtual #97                 // Method com/virtual/common/StringManager.getString:(Ljava/lang/String;[Ljava/lang/Object;)Ljava/lang/String;
     308: invokevirtual #98                 // Method com/virtual/ssv/server/rs/client/entity/RsOperateLog.setDescription:(Ljava/lang/String;)V
     311: goto          347
     314: ldc           #142                // String 4
     316: aload         9
     318: invokevirtual #11                 // Method java/lang/String.equals:(Ljava/lang/Object;)Z
     321: ifeq          347
     324: aload         12
     326: aload_0
     327: getfield      #94                 // Field logSm:Lcom/virtual/common/StringManager;
     330: ldc           #143                // String revoke.delay.vm
     332: iconst_1
     333: anewarray     #96                 // class java/lang/Object
     336: dup
     337: iconst_0
     338: aload         8
     340: aastore
     341: invokevirtual #97                 // Method com/virtual/common/StringManager.getString:(Ljava/lang/String;[Ljava/lang/Object;)Ljava/lang/String;
     344: invokevirtual #98                 // Method com/virtual/ssv/server/rs/client/entity/RsOperateLog.setDescription:(Ljava/lang/String;)V
     347: aload         12
     349: getstatic     #100                // Field com/virtual/ssv/server/rs/client/entity/RsOperateLog.RESULT_SUCCESS:Ljava/lang/Integer;
     352: invokevirtual #101                // Method com/virtual/ssv/server/rs/client/entity/RsOperateLog.setResult:(Ljava/lang/Integer;)V
     355: aload_0
     356: getfield      #36                 // Field reqHandle:Lcom/virtual/ssv/server/rs/client/RequestHandle;
     359: aload         12
     361: invokevirtual #107                // Method com/virtual/ssv/server/rs/client/RequestHandle.addUserLog:(Lcom/virtual/ssv/server/rs/client/entity/RsOperateLog;)Ljava/lang/Long;
     364: pop
     365: goto          449
     368: astore        6
     370: aload         6
     372: invokevirtual #108                // Method com/virtual/common/AppException.getErrorCode:()I
     375: bipush        102
     377: if_icmpne     393
     380: aload         5
     382: bipush        102
     384: invokestatic  #109                // Method com/virtual/common/ErrorCodes.getErrorMessage:(I)Ljava/lang/String;
     387: invokevirtual #110                // Method com/virtual/ssv/server/entity/ResultJson.setErrorMsg:(Ljava/lang/String;)V
     390: goto          449
     393: aload         6
     395: invokevirtual #108                // Method com/virtual/common/AppException.getErrorCode:()I
     398: bipush        103
     400: if_icmpne     416
     403: aload         5
     405: bipush        103
     407: invokestatic  #109                // Method com/virtual/common/ErrorCodes.getErrorMessage:(I)Ljava/lang/String;
     410: invokevirtual #110                // Method com/virtual/ssv/server/entity/ResultJson.setErrorMsg:(Ljava/lang/String;)V
     413: goto          449
     416: aload         6
     418: invokevirtual #108                // Method com/virtual/common/AppException.getErrorCode:()I
     421: bipush        11
     423: if_icmpne     439
     426: aload         5
     428: bipush        11
     430: invokestatic  #109                // Method com/virtual/common/ErrorCodes.getErrorMessage:(I)Ljava/lang/String;
     433: invokevirtual #110                // Method com/virtual/ssv/server/entity/ResultJson.setErrorMsg:(Ljava/lang/String;)V
     436: goto          449
     439: aload         5
     441: aload         6
     443: invokevirtual #111                // Method com/virtual/common/AppException.getMessage:()Ljava/lang/String;
     446: invokevirtual #110                // Method com/virtual/ssv/server/entity/ResultJson.setErrorMsg:(Ljava/lang/String;)V
     449: aload_0
     450: aload_2
     451: aload_0
     452: getfield      #46                 // Field filterJson:Lcom/google/gson/Gson;
     455: aload         5
     457: invokevirtual #33                 // Method com/google/gson/Gson.toJson:(Ljava/lang/Object;)Ljava/lang/String;
     460: invokevirtual #34                 // Method write:(Ljavax/servlet/http/HttpServletResponse;Ljava/lang/String;)V
     463: return
    Exception table:
       from    to  target type
          41    56    59   Class java/io/UnsupportedEncodingException
          18   365   368   Class com/virtual/common/AppException

  private void getList(javax.servlet.http.HttpServletRequest, javax.servlet.http.HttpServletResponse, com.virtual.ssv.server.user.LoginInfo);
    Code:
       0: new           #144                // class com/virtual/ssv/server/entity/CommonListJson
       3: dup
       4: invokespecial #145                // Method com/virtual/ssv/server/entity/CommonListJson."<init>":()V
       7: astore        4
       9: aload_1
      10: ldc           #130                // String type
      12: invokeinterface #9,  2            // InterfaceMethod javax/servlet/http/HttpServletRequest.getParameter:(Ljava/lang/String;)Ljava/lang/String;
      17: astore        5
      19: aload_0
      20: aload_1
      21: invokevirtual #146                // Method getPagingConfig:(Ljavax/servlet/http/HttpServletRequest;)Lcom/virtual/ssv/server/entity/PagingLoadConfig;
      24: astore        6
      26: aload         6
      28: invokevirtual #147                // Method com/virtual/ssv/server/entity/PagingLoadConfig.getSortField:()Ljava/lang/String;
      31: invokestatic  #80                 // Method org/apache/commons/lang/StringUtils.isEmpty:(Ljava/lang/String;)Z
      34: ifeq          51
      37: aload         6
      39: ldc           #123                // String id
      41: invokevirtual #148                // Method com/virtual/ssv/server/entity/PagingLoadConfig.setSortField:(Ljava/lang/String;)V
      44: aload         6
      46: ldc           #149                // String Desc
      48: invokevirtual #150                // Method com/virtual/ssv/server/entity/PagingLoadConfig.setSortDir:(Ljava/lang/String;)V
      51: aload         6
      53: ldc           #151                // String userId
      55: aload_3
      56: invokevirtual #57                 // Method com/virtual/ssv/server/user/LoginInfo.getId:()Ljava/lang/Long;
      59: invokevirtual #152                // Method com/virtual/ssv/server/entity/PagingLoadConfig.put:(Ljava/lang/Object;Ljava/lang/Object;)Ljava/lang/Object;
      62: pop
      63: aload         6
      65: ldc           #153                // String orgId
      67: aload_3
      68: invokevirtual #35                 // Method com/virtual/ssv/server/user/LoginInfo.getOrgId:()Ljava/lang/Long;
      71: invokevirtual #152                // Method com/virtual/ssv/server/entity/PagingLoadConfig.put:(Ljava/lang/Object;Ljava/lang/Object;)Ljava/lang/Object;
      74: pop
      75: aload_1
      76: ldc           #154                // String status
      78: invokeinterface #9,  2            // InterfaceMethod javax/servlet/http/HttpServletRequest.getParameter:(Ljava/lang/String;)Ljava/lang/String;
      83: astore        7
      85: aload         7
      87: invokestatic  #71                 // Method org/apache/commons/lang/StringUtils.isNotEmpty:(Ljava/lang/String;)Z
      90: ifeq          103
      93: aload         6
      95: ldc           #154                // String status
      97: aload         7
      99: invokevirtual #152                // Method com/virtual/ssv/server/entity/PagingLoadConfig.put:(Ljava/lang/Object;Ljava/lang/Object;)Ljava/lang/Object;
     102: pop
     103: aload         5
     105: invokestatic  #71                 // Method org/apache/commons/lang/StringUtils.isNotEmpty:(Ljava/lang/String;)Z
     108: ifeq          121
     111: aload         6
     113: ldc           #130                // String type
     115: aload         5
     117: invokevirtual #152                // Method com/virtual/ssv/server/entity/PagingLoadConfig.put:(Ljava/lang/Object;Ljava/lang/Object;)Ljava/lang/Object;
     120: pop
     121: aload_0
     122: getfield      #36                 // Field reqHandle:Lcom/virtual/ssv/server/rs/client/RequestHandle;
     125: aload         6
     127: invokevirtual #155                // Method com/virtual/ssv/server/rs/client/RequestHandle.queryUserVmWorkflowCount:(Lcom/virtual/ssv/server/entity/PagingLoadConfig;)Ljava/lang/Integer;
     130: astore        8
     132: aload         8
     134: invokevirtual #156                // Method java/lang/Integer.intValue:()I
     137: ifle          230
     140: aload_0
     141: getfield      #36                 // Field reqHandle:Lcom/virtual/ssv/server/rs/client/RequestHandle;
     144: aload         6
     146: invokevirtual #157                // Method com/virtual/ssv/server/rs/client/RequestHandle.queryUserVmWorkflow:(Lcom/virtual/ssv/server/entity/PagingLoadConfig;)Ljava/util/List;
     149: astore        9
     151: aload         9
     153: invokeinterface #158,  1          // InterfaceMethod java/util/List.iterator:()Ljava/util/Iterator;
     158: astore        10
     160: aload         10
     162: invokeinterface #159,  1          // InterfaceMethod java/util/Iterator.hasNext:()Z
     167: ifeq          220
     170: aload         10
     172: invokeinterface #160,  1          // InterfaceMethod java/util/Iterator.next:()Ljava/lang/Object;
     177: checkcast     #55                 // class com/virtual/ssv/server/rs/client/entity/RsVmWorkflow
     180: astore        11
     182: aload         11
     184: invokevirtual #161                // Method com/virtual/ssv/server/rs/client/entity/RsVmWorkflow.getCreateDate:()Ljava/util/Date;
     187: astore        12
     189: aload         12
     191: ifnull        217
     194: new           #116                // class java/text/SimpleDateFormat
     197: dup
     198: ldc           #162                // String yyyy-MM-dd HH:mm:ss
     200: invokespecial #118                // Method java/text/SimpleDateFormat."<init>":(Ljava/lang/String;)V
     203: astore        13
     205: aload         11
     207: aload         13
     209: aload         12
     211: invokevirtual #119                // Method java/text/SimpleDateFormat.format:(Ljava/util/Date;)Ljava/lang/String;
     214: invokevirtual #163                // Method com/virtual/ssv/server/rs/client/entity/RsVmWorkflow.setCreateDateStr:(Ljava/lang/String;)V
     217: goto          160
     220: aload         4
     222: aload         9
     224: invokevirtual #164                // Method com/virtual/ssv/server/entity/CommonListJson.setRows:(Ljava/util/List;)V
     227: goto          242
     230: aload         4
     232: new           #165                // class java/util/ArrayList
     235: dup
     236: invokespecial #166                // Method java/util/ArrayList."<init>":()V
     239: invokevirtual #164                // Method com/virtual/ssv/server/entity/CommonListJson.setRows:(Ljava/util/List;)V
     242: aload         4
     244: aload         8
     246: invokevirtual #156                // Method java/lang/Integer.intValue:()I
     249: i2l
     250: invokevirtual #167                // Method com/virtual/ssv/server/entity/CommonListJson.setTotal:(J)V
     253: goto          369
     256: astore        6
     258: aload         4
     260: aload_0
     261: getfield      #94                 // Field logSm:Lcom/virtual/common/StringManager;
     264: ldc           #168                // String operError
     266: invokevirtual #169                // Method com/virtual/common/StringManager.getString:(Ljava/lang/String;)Ljava/lang/String;
     269: invokevirtual #170                // Method com/virtual/ssv/server/entity/CommonListJson.setTitle:(Ljava/lang/String;)V
     272: aload         6
     274: invokevirtual #108                // Method com/virtual/common/AppException.getErrorCode:()I
     277: bipush        102
     279: if_icmpne     295
     282: aload         4
     284: bipush        102
     286: invokestatic  #109                // Method com/virtual/common/ErrorCodes.getErrorMessage:(I)Ljava/lang/String;
     289: invokevirtual #171                // Method com/virtual/ssv/server/entity/CommonListJson.setMessage:(Ljava/lang/String;)V
     292: goto          351
     295: aload         6
     297: invokevirtual #108                // Method com/virtual/common/AppException.getErrorCode:()I
     300: bipush        103
     302: if_icmpne     318
     305: aload         4
     307: bipush        103
     309: invokestatic  #109                // Method com/virtual/common/ErrorCodes.getErrorMessage:(I)Ljava/lang/String;
     312: invokevirtual #171                // Method com/virtual/ssv/server/entity/CommonListJson.setMessage:(Ljava/lang/String;)V
     315: goto          351
     318: aload         6
     320: invokevirtual #108                // Method com/virtual/common/AppException.getErrorCode:()I
     323: bipush        11
     325: if_icmpne     341
     328: aload         4
     330: bipush        11
     332: invokestatic  #109                // Method com/virtual/common/ErrorCodes.getErrorMessage:(I)Ljava/lang/String;
     335: invokevirtual #171                // Method com/virtual/ssv/server/entity/CommonListJson.setMessage:(Ljava/lang/String;)V
     338: goto          351
     341: aload         4
     343: aload         6
     345: invokevirtual #111                // Method com/virtual/common/AppException.getMessage:()Ljava/lang/String;
     348: invokevirtual #171                // Method com/virtual/ssv/server/entity/CommonListJson.setMessage:(Ljava/lang/String;)V
     351: aload         4
     353: iconst_0
     354: invokevirtual #172                // Method com/virtual/ssv/server/entity/CommonListJson.setState:(I)V
     357: aload         4
     359: new           #165                // class java/util/ArrayList
     362: dup
     363: invokespecial #166                // Method java/util/ArrayList."<init>":()V
     366: invokevirtual #164                // Method com/virtual/ssv/server/entity/CommonListJson.setRows:(Ljava/util/List;)V
     369: aload_0
     370: aload_2
     371: aload_0
     372: getfield      #31                 // Field gson:Lcom/google/gson/Gson;
     375: aload         4
     377: invokevirtual #33                 // Method com/google/gson/Gson.toJson:(Ljava/lang/Object;)Ljava/lang/String;
     380: invokevirtual #34                 // Method write:(Ljavax/servlet/http/HttpServletResponse;Ljava/lang/String;)V
     383: return
    Exception table:
       from    to  target type
          19   253   256   Class com/virtual/common/AppException

  public void queryApplyVmExtend(javax.servlet.http.HttpServletRequest, javax.servlet.http.HttpServletResponse, com.virtual.ssv.server.user.LoginInfo);
    Code:
       0: new           #51                 // class com/virtual/ssv/server/entity/ResultJson
       3: dup
       4: invokespecial #52                 // Method com/virtual/ssv/server/entity/ResultJson."<init>":()V
       7: astore        4
       9: new           #173                // class com/virtual/ssv/server/rs/client/RequestHandle
      12: dup
      13: aload_0
      14: getfield      #174                // Field httpManager:Lcom/virtual/ssv/server/rs/client/HttpConnectionManager;
      17: invokespecial #175                // Method com/virtual/ssv/server/rs/client/RequestHandle."<init>":(Lcom/virtual/ssv/server/rs/client/HttpConnectionManager;)V
      20: astore        5
      22: aload_3
      23: ifnull        92
      26: aload         5
      28: aload_3
      29: invokevirtual #57                 // Method com/virtual/ssv/server/user/LoginInfo.getId:()Ljava/lang/Long;
      32: invokevirtual #176                // Method com/virtual/ssv/server/rs/client/RequestHandle.isUserExists:(Ljava/lang/Long;)Z
      35: ifeq          92
      38: new           #144                // class com/virtual/ssv/server/entity/CommonListJson
      41: dup
      42: invokespecial #145                // Method com/virtual/ssv/server/entity/CommonListJson."<init>":()V
      45: astore        6
      47: aload         5
      49: invokevirtual #177                // Method com/virtual/ssv/server/rs/client/RequestHandle.queryapplyVmExtend:()Ljava/util/List;
      52: astore        7
      54: aload         6
      56: aload         7
      58: invokeinterface #178,  1          // InterfaceMethod java/util/List.size:()I
      63: i2l
      64: invokevirtual #167                // Method com/virtual/ssv/server/entity/CommonListJson.setTotal:(J)V
      67: aload         6
      69: aload         7
      71: invokevirtual #164                // Method com/virtual/ssv/server/entity/CommonListJson.setRows:(Ljava/util/List;)V
      74: aload_0
      75: getfield      #31                 // Field gson:Lcom/google/gson/Gson;
      78: aload         6
      80: invokevirtual #33                 // Method com/google/gson/Gson.toJson:(Ljava/lang/Object;)Ljava/lang/String;
      83: astore        8
      85: aload_0
      86: aload_2
      87: aload         8
      89: invokevirtual #34                 // Method write:(Ljavax/servlet/http/HttpServletResponse;Ljava/lang/String;)V
      92: goto          198
      95: astore        5
      97: getstatic     #42                 // Field log:Lorg/apache/commons/logging/Log;
     100: aload         5
     102: invokestatic  #179                // Method com/virtual/ssv/server/ServerUtils.logAppException:(Lorg/apache/commons/logging/Log;Lcom/virtual/common/AppException;)V
     105: aload         5
     107: invokevirtual #108                // Method com/virtual/common/AppException.getErrorCode:()I
     110: bipush        102
     112: if_icmpne     128
     115: aload         4
     117: bipush        102
     119: invokestatic  #109                // Method com/virtual/common/ErrorCodes.getErrorMessage:(I)Ljava/lang/String;
     122: invokevirtual #110                // Method com/virtual/ssv/server/entity/ResultJson.setErrorMsg:(Ljava/lang/String;)V
     125: goto          184
     128: aload         5
     130: invokevirtual #108                // Method com/virtual/common/AppException.getErrorCode:()I
     133: bipush        103
     135: if_icmpne     151
     138: aload         4
     140: bipush        103
     142: invokestatic  #109                // Method com/virtual/common/ErrorCodes.getErrorMessage:(I)Ljava/lang/String;
     145: invokevirtual #110                // Method com/virtual/ssv/server/entity/ResultJson.setErrorMsg:(Ljava/lang/String;)V
     148: goto          184
     151: aload         5
     153: invokevirtual #108                // Method com/virtual/common/AppException.getErrorCode:()I
     156: bipush        11
     158: if_icmpne     174
     161: aload         4
     163: bipush        11
     165: invokestatic  #109                // Method com/virtual/common/ErrorCodes.getErrorMessage:(I)Ljava/lang/String;
     168: invokevirtual #110                // Method com/virtual/ssv/server/entity/ResultJson.setErrorMsg:(Ljava/lang/String;)V
     171: goto          184
     174: aload         4
     176: aload         5
     178: invokevirtual #111                // Method com/virtual/common/AppException.getMessage:()Ljava/lang/String;
     181: invokevirtual #110                // Method com/virtual/ssv/server/entity/ResultJson.setErrorMsg:(Ljava/lang/String;)V
     184: aload_0
     185: aload_2
     186: aload_0
     187: getfield      #46                 // Field filterJson:Lcom/google/gson/Gson;
     190: aload         4
     192: invokevirtual #33                 // Method com/google/gson/Gson.toJson:(Ljava/lang/Object;)Ljava/lang/String;
     195: invokevirtual #34                 // Method write:(Ljavax/servlet/http/HttpServletResponse;Ljava/lang/String;)V
     198: return
    Exception table:
       from    to  target type
           9    92    95   Class com/virtual/common/AppException
}
