Compiled from "FileUploadServlet.java"
public class com.virtual.ssv.server.upload.FileUploadServlet extends com.virtual.ssv.server.BaseServlet {
  private static final long serialVersionUID;

  private static org.apache.commons.logging.Log log;

  private static final java.lang.String INIT_PARAM_MAX_FILE_SIZE;

  private static final java.lang.String INIT_PARAM_MAX_REQUEST_SIZE;

  private com.virtual.common.StringManager sm;

  private long maxFileSize;

  private long maxRequestSize;

  public com.virtual.ssv.server.upload.FileUploadServlet();
    Code:
       0: aload_0
       1: invokespecial #1                  // Method com/virtual/ssv/server/BaseServlet."<init>":()V
       4: aload_0
       5: ldc           #2                  // class com/virtual/ssv/server/upload/FileUploadServlet
       7: invokestatic  #3                  // Method com/virtual/common/StringManager.getManager:(Ljava/lang/Class;)Lcom/virtual/common/StringManager;
      10: putfield      #4                  // Field sm:Lcom/virtual/common/StringManager;
      13: aload_0
      14: ldc2_w        #5                  // long -1l
      17: putfield      #7                  // Field maxFileSize:J
      20: aload_0
      21: ldc2_w        #5                  // long -1l
      24: putfield      #8                  // Field maxRequestSize:J
      27: return

  public void init();
    Code:
       0: aload_0
       1: invokespecial #9                  // Method com/virtual/ssv/server/BaseServlet.init:()V
       4: aload_0
       5: ldc           #10                 // String maxFileSize
       7: invokevirtual #11                 // Method getInitParameter:(Ljava/lang/String;)Ljava/lang/String;
      10: astore_1
      11: aload_1
      12: ifnull        23
      15: aload_0
      16: aload_1
      17: invokestatic  #12                 // Method java/lang/Long.parseLong:(Ljava/lang/String;)J
      20: putfield      #7                  // Field maxFileSize:J
      23: aload_0
      24: ldc           #13                 // String maxRequestSize
      26: invokevirtual #11                 // Method getInitParameter:(Ljava/lang/String;)Ljava/lang/String;
      29: astore_1
      30: aload_1
      31: ifnull        42
      34: aload_0
      35: aload_1
      36: invokestatic  #12                 // Method java/lang/Long.parseLong:(Ljava/lang/String;)J
      39: putfield      #8                  // Field maxRequestSize:J
      42: return

  protected void doPost(javax.servlet.http.HttpServletRequest, javax.servlet.http.HttpServletResponse) throws javax.servlet.ServletException, java.io.IOException;
    Code:
       0: getstatic     #14                 // Field log:Lorg/apache/commons/logging/Log;
       3: invokeinterface #15,  1           // InterfaceMethod org/apache/commons/logging/Log.isDebugEnabled:()Z
       8: ifeq          21
      11: getstatic     #14                 // Field log:Lorg/apache/commons/logging/Log;
      14: ldc           #16                 // String Handling file upload request
      16: invokeinterface #17,  2           // InterfaceMethod org/apache/commons/logging/Log.debug:(Ljava/lang/Object;)V
      21: aload_1
      22: invokeinterface #18,  1           // InterfaceMethod javax/servlet/http/HttpServletRequest.getSession:()Ljavax/servlet/http/HttpSession;
      27: astore_3
      28: aload_3
      29: ldc           #19                 // String loginInfo
      31: invokeinterface #20,  2           // InterfaceMethod javax/servlet/http/HttpSession.getAttribute:(Ljava/lang/String;)Ljava/lang/Object;
      36: checkcast     #21                 // class com/virtual/ssv/server/user/LoginInfo
      39: astore        4
      41: aload         4
      43: ifnull        727
      46: aload_1
      47: ldc           #22                 // String imageUrl
      49: invokeinterface #23,  2           // InterfaceMethod javax/servlet/http/HttpServletRequest.getParameter:(Ljava/lang/String;)Ljava/lang/String;
      54: astore        5
      56: aload_1
      57: invokestatic  #24                 // Method org/apache/commons/fileupload/servlet/ServletFileUpload.isMultipartContent:(Ljavax/servlet/http/HttpServletRequest;)Z
      60: ifne          70
      63: aload_0
      64: aload_1
      65: aload_2
      66: invokespecial #25                 // Method com/virtual/ssv/server/BaseServlet.doPost:(Ljavax/servlet/http/HttpServletRequest;Ljavax/servlet/http/HttpServletResponse;)V
      69: return
      70: aload_1
      71: invokeinterface #18,  1           // InterfaceMethod javax/servlet/http/HttpServletRequest.getSession:()Ljavax/servlet/http/HttpSession;
      76: invokestatic  #26                 // Method com/virtual/ssv/server/upload/FileUploadInfo.getInstance:(Ljavax/servlet/http/HttpSession;)Lcom/virtual/ssv/server/upload/FileUploadInfo;
      79: astore        6
      81: new           #27                 // class org/apache/commons/fileupload/disk/DiskFileItemFactory
      84: dup
      85: invokespecial #28                 // Method org/apache/commons/fileupload/disk/DiskFileItemFactory."<init>":()V
      88: astore        7
      90: new           #29                 // class org/apache/commons/fileupload/servlet/ServletFileUpload
      93: dup
      94: aload         7
      96: invokespecial #30                 // Method org/apache/commons/fileupload/servlet/ServletFileUpload."<init>":(Lorg/apache/commons/fileupload/FileItemFactory;)V
      99: astore        8
     101: aload_0
     102: getfield      #7                  // Field maxFileSize:J
     105: lconst_0
     106: lcmp
     107: ifle          119
     110: aload         8
     112: aload_0
     113: getfield      #7                  // Field maxFileSize:J
     116: invokevirtual #31                 // Method org/apache/commons/fileupload/servlet/ServletFileUpload.setFileSizeMax:(J)V
     119: aload_0
     120: getfield      #8                  // Field maxRequestSize:J
     123: lconst_0
     124: lcmp
     125: ifle          137
     128: aload         8
     130: aload_0
     131: getfield      #8                  // Field maxRequestSize:J
     134: invokevirtual #32                 // Method org/apache/commons/fileupload/servlet/ServletFileUpload.setSizeMax:(J)V
     137: aload         8
     139: new           #33                 // class com/virtual/ssv/server/upload/FileUploadServlet$1
     142: dup
     143: aload_0
     144: aload         6
     146: invokespecial #34                 // Method com/virtual/ssv/server/upload/FileUploadServlet$1."<init>":(Lcom/virtual/ssv/server/upload/FileUploadServlet;Lcom/virtual/ssv/server/upload/FileUploadInfo;)V
     149: invokevirtual #35                 // Method org/apache/commons/fileupload/servlet/ServletFileUpload.setProgressListener:(Lorg/apache/commons/fileupload/ProgressListener;)V
     152: aload         8
     154: aload_1
     155: invokevirtual #36                 // Method org/apache/commons/fileupload/servlet/ServletFileUpload.parseRequest:(Ljavax/servlet/http/HttpServletRequest;)Ljava/util/List;
     158: astore        9
     160: aload         9
     162: invokeinterface #37,  1           // InterfaceMethod java/util/List.iterator:()Ljava/util/Iterator;
     167: astore        10
     169: aload         10
     171: invokeinterface #38,  1           // InterfaceMethod java/util/Iterator.hasNext:()Z
     176: ifeq          565
     179: aload         10
     181: invokeinterface #39,  1           // InterfaceMethod java/util/Iterator.next:()Ljava/lang/Object;
     186: checkcast     #40                 // class org/apache/commons/fileupload/FileItem
     189: astore        11
     191: aload         11
     193: invokeinterface #41,  1           // InterfaceMethod org/apache/commons/fileupload/FileItem.isFormField:()Z
     198: ifeq          263
     201: getstatic     #14                 // Field log:Lorg/apache/commons/logging/Log;
     204: invokeinterface #15,  1           // InterfaceMethod org/apache/commons/logging/Log.isDebugEnabled:()Z
     209: ifeq          562
     212: getstatic     #14                 // Field log:Lorg/apache/commons/logging/Log;
     215: new           #42                 // class java/lang/StringBuilder
     218: dup
     219: invokespecial #43                 // Method java/lang/StringBuilder."<init>":()V
     222: ldc           #44                 // String Skip form field:
     224: invokevirtual #45                 // Method java/lang/StringBuilder.append:(Ljava/lang/String;)Ljava/lang/StringBuilder;
     227: aload         11
     229: invokeinterface #46,  1           // InterfaceMethod org/apache/commons/fileupload/FileItem.getName:()Ljava/lang/String;
     234: invokevirtual #45                 // Method java/lang/StringBuilder.append:(Ljava/lang/String;)Ljava/lang/StringBuilder;
     237: ldc           #47                 // String -
     239: invokevirtual #45                 // Method java/lang/StringBuilder.append:(Ljava/lang/String;)Ljava/lang/StringBuilder;
     242: aload         11
     244: invokeinterface #48,  1           // InterfaceMethod org/apache/commons/fileupload/FileItem.getString:()Ljava/lang/String;
     249: invokevirtual #45                 // Method java/lang/StringBuilder.append:(Ljava/lang/String;)Ljava/lang/StringBuilder;
     252: invokevirtual #49                 // Method java/lang/StringBuilder.toString:()Ljava/lang/String;
     255: invokeinterface #17,  2           // InterfaceMethod org/apache/commons/logging/Log.debug:(Ljava/lang/Object;)V
     260: goto          562
     263: aload_1
     264: invokeinterface #18,  1           // InterfaceMethod javax/servlet/http/HttpServletRequest.getSession:()Ljavax/servlet/http/HttpSession;
     269: invokeinterface #50,  1           // InterfaceMethod javax/servlet/http/HttpSession.getServletContext:()Ljavax/servlet/ServletContext;
     274: ldc           #51                 // String /
     276: invokeinterface #52,  2           // InterfaceMethod javax/servlet/ServletContext.getRealPath:(Ljava/lang/String;)Ljava/lang/String;
     281: astore        12
     283: ldc           #53                 // String
     285: astore        13
     287: aload         12
     289: ldc           #51                 // String /
     291: invokevirtual #54                 // Method java/lang/String.endsWith:(Ljava/lang/String;)Z
     294: ifeq          322
     297: new           #42                 // class java/lang/StringBuilder
     300: dup
     301: invokespecial #43                 // Method java/lang/StringBuilder."<init>":()V
     304: aload         12
     306: invokevirtual #45                 // Method java/lang/StringBuilder.append:(Ljava/lang/String;)Ljava/lang/StringBuilder;
     309: ldc           #55                 // String images
     311: invokevirtual #45                 // Method java/lang/StringBuilder.append:(Ljava/lang/String;)Ljava/lang/StringBuilder;
     314: invokevirtual #49                 // Method java/lang/StringBuilder.toString:()Ljava/lang/String;
     317: astore        13
     319: goto          344
     322: new           #42                 // class java/lang/StringBuilder
     325: dup
     326: invokespecial #43                 // Method java/lang/StringBuilder."<init>":()V
     329: aload         12
     331: invokevirtual #45                 // Method java/lang/StringBuilder.append:(Ljava/lang/String;)Ljava/lang/StringBuilder;
     334: ldc           #56                 // String /images
     336: invokevirtual #45                 // Method java/lang/StringBuilder.append:(Ljava/lang/String;)Ljava/lang/StringBuilder;
     339: invokevirtual #49                 // Method java/lang/StringBuilder.toString:()Ljava/lang/String;
     342: astore        13
     344: ldc           #53                 // String
     346: astore        14
     348: aload         5
     350: ifnull        363
     353: ldc           #53                 // String
     355: aload         5
     357: invokevirtual #57                 // Method java/lang/String.equals:(Ljava/lang/Object;)Z
     360: ifeq          408
     363: aload         11
     365: invokeinterface #46,  1           // InterfaceMethod org/apache/commons/fileupload/FileItem.getName:()Ljava/lang/String;
     370: astore        14
     372: new           #42                 // class java/lang/StringBuilder
     375: dup
     376: invokespecial #43                 // Method java/lang/StringBuilder."<init>":()V
     379: invokestatic  #58                 // Method java/util/UUID.randomUUID:()Ljava/util/UUID;
     382: invokevirtual #59                 // Method java/lang/StringBuilder.append:(Ljava/lang/Object;)Ljava/lang/StringBuilder;
     385: aload         14
     387: aload         14
     389: invokevirtual #60                 // Method java/lang/String.length:()I
     392: iconst_4
     393: isub
     394: invokevirtual #61                 // Method java/lang/String.substring:(I)Ljava/lang/String;
     397: invokevirtual #45                 // Method java/lang/StringBuilder.append:(Ljava/lang/String;)Ljava/lang/StringBuilder;
     400: invokevirtual #49                 // Method java/lang/StringBuilder.toString:()Ljava/lang/String;
     403: astore        14
     405: goto          412
     408: aload         5
     410: astore        14
     412: aload_0
     413: getfield      #62                 // Field reqHandle:Lcom/virtual/ssv/server/rs/client/RequestHandle;
     416: aload         4
     418: invokevirtual #63                 // Method com/virtual/ssv/server/user/LoginInfo.getId:()Ljava/lang/Long;
     421: invokevirtual #64                 // Method com/virtual/ssv/server/rs/client/RequestHandle.getUserImageUrl:(Ljava/lang/Long;)Ljava/lang/String;
     424: astore        15
     426: aload         6
     428: aload         11
     430: invokeinterface #65,  1           // InterfaceMethod org/apache/commons/fileupload/FileItem.getFieldName:()Ljava/lang/String;
     435: aload         11
     437: new           #42                 // class java/lang/StringBuilder
     440: dup
     441: invokespecial #43                 // Method java/lang/StringBuilder."<init>":()V
     444: aload         13
     446: invokevirtual #45                 // Method java/lang/StringBuilder.append:(Ljava/lang/String;)Ljava/lang/StringBuilder;
     449: ldc           #51                 // String /
     451: invokevirtual #45                 // Method java/lang/StringBuilder.append:(Ljava/lang/String;)Ljava/lang/StringBuilder;
     454: aload         14
     456: invokevirtual #45                 // Method java/lang/StringBuilder.append:(Ljava/lang/String;)Ljava/lang/StringBuilder;
     459: invokevirtual #49                 // Method java/lang/StringBuilder.toString:()Ljava/lang/String;
     462: invokevirtual #66                 // Method com/virtual/ssv/server/upload/FileUploadInfo.addFile:(Ljava/lang/String;Lorg/apache/commons/fileupload/FileItem;Ljava/lang/String;)V
     465: aload_0
     466: getfield      #62                 // Field reqHandle:Lcom/virtual/ssv/server/rs/client/RequestHandle;
     469: aload         4
     471: invokevirtual #63                 // Method com/virtual/ssv/server/user/LoginInfo.getId:()Ljava/lang/Long;
     474: aload         14
     476: invokevirtual #67                 // Method com/virtual/ssv/server/rs/client/RequestHandle.updateUserImageUrl:(Ljava/lang/Long;Ljava/lang/String;)Lcom/virtual/ssv/server/entity/ResultJson;
     479: pop
     480: aload         15
     482: invokestatic  #68                 // Method org/apache/commons/lang/StringUtils.isNotEmpty:(Ljava/lang/String;)Z
     485: ifeq          537
     488: new           #69                 // class java/io/File
     491: dup
     492: new           #42                 // class java/lang/StringBuilder
     495: dup
     496: invokespecial #43                 // Method java/lang/StringBuilder."<init>":()V
     499: aload         13
     501: invokevirtual #45                 // Method java/lang/StringBuilder.append:(Ljava/lang/String;)Ljava/lang/StringBuilder;
     504: getstatic     #70                 // Field java/io/File.separator:Ljava/lang/String;
     507: invokevirtual #45                 // Method java/lang/StringBuilder.append:(Ljava/lang/String;)Ljava/lang/StringBuilder;
     510: aload         15
     512: invokevirtual #45                 // Method java/lang/StringBuilder.append:(Ljava/lang/String;)Ljava/lang/StringBuilder;
     515: invokevirtual #49                 // Method java/lang/StringBuilder.toString:()Ljava/lang/String;
     518: invokespecial #71                 // Method java/io/File."<init>":(Ljava/lang/String;)V
     521: astore        16
     523: aload         16
     525: invokevirtual #72                 // Method java/io/File.exists:()Z
     528: ifeq          537
     531: aload         16
     533: invokevirtual #73                 // Method java/io/File.delete:()Z
     536: pop
     537: aload_0
     538: aload_2
     539: new           #42                 // class java/lang/StringBuilder
     542: dup
     543: invokespecial #43                 // Method java/lang/StringBuilder."<init>":()V
     546: ldc           #74                 // String images/
     548: invokevirtual #45                 // Method java/lang/StringBuilder.append:(Ljava/lang/String;)Ljava/lang/StringBuilder;
     551: aload         14
     553: invokevirtual #45                 // Method java/lang/StringBuilder.append:(Ljava/lang/String;)Ljava/lang/StringBuilder;
     556: invokevirtual #49                 // Method java/lang/StringBuilder.toString:()Ljava/lang/String;
     559: invokevirtual #75                 // Method write:(Ljavax/servlet/http/HttpServletResponse;Ljava/lang/String;)V
     562: goto          169
     565: getstatic     #14                 // Field log:Lorg/apache/commons/logging/Log;
     568: ldc           #76                 // String Completed
     570: invokeinterface #77,  2           // InterfaceMethod org/apache/commons/logging/Log.info:(Ljava/lang/Object;)V
     575: aload         6
     577: invokevirtual #78                 // Method com/virtual/ssv/server/upload/FileUploadInfo.setCompleted:()V
     580: goto          727
     583: astore        7
     585: getstatic     #14                 // Field log:Lorg/apache/commons/logging/Log;
     588: ldc           #80                 // String Parse upload file request failed
     590: invokeinterface #81,  2           // InterfaceMethod org/apache/commons/logging/Log.warn:(Ljava/lang/Object;)V
     595: getstatic     #14                 // Field log:Lorg/apache/commons/logging/Log;
     598: invokeinterface #15,  1           // InterfaceMethod org/apache/commons/logging/Log.isDebugEnabled:()Z
     603: ifeq          617
     606: getstatic     #14                 // Field log:Lorg/apache/commons/logging/Log;
     609: aconst_null
     610: aload         7
     612: invokeinterface #82,  3           // InterfaceMethod org/apache/commons/logging/Log.debug:(Ljava/lang/Object;Ljava/lang/Throwable;)V
     617: aload         7
     619: instanceof    #83                 // class org/apache/commons/fileupload/FileUploadBase$FileSizeLimitExceededException
     622: ifeq          660
     625: aload         6
     627: aload_0
     628: getfield      #4                  // Field sm:Lcom/virtual/common/StringManager;
     631: ldc           #84                 // String fileupload.fileSizeLimitExceeded
     633: iconst_1
     634: anewarray     #85                 // class java/lang/Object
     637: dup
     638: iconst_0
     639: aload_0
     640: getfield      #7                  // Field maxFileSize:J
     643: ldc2_w        #86                 // long 1048576l
     646: ldiv
     647: invokestatic  #88                 // Method java/lang/Long.valueOf:(J)Ljava/lang/Long;
     650: aastore
     651: invokevirtual #89                 // Method com/virtual/common/StringManager.getString:(Ljava/lang/String;[Ljava/lang/Object;)Ljava/lang/String;
     654: invokevirtual #90                 // Method com/virtual/ssv/server/upload/FileUploadInfo.setError:(Ljava/lang/String;)V
     657: goto          727
     660: aload         7
     662: instanceof    #91                 // class javax/naming/SizeLimitExceededException
     665: ifeq          703
     668: aload         6
     670: aload_0
     671: getfield      #4                  // Field sm:Lcom/virtual/common/StringManager;
     674: ldc           #92                 // String fileupload.requestSizeLimitExceeded
     676: iconst_1
     677: anewarray     #85                 // class java/lang/Object
     680: dup
     681: iconst_0
     682: aload_0
     683: getfield      #8                  // Field maxRequestSize:J
     686: ldc2_w        #86                 // long 1048576l
     689: ldiv
     690: invokestatic  #88                 // Method java/lang/Long.valueOf:(J)Ljava/lang/Long;
     693: aastore
     694: invokevirtual #89                 // Method com/virtual/common/StringManager.getString:(Ljava/lang/String;[Ljava/lang/Object;)Ljava/lang/String;
     697: invokevirtual #90                 // Method com/virtual/ssv/server/upload/FileUploadInfo.setError:(Ljava/lang/String;)V
     700: goto          727
     703: getstatic     #14                 // Field log:Lorg/apache/commons/logging/Log;
     706: ldc           #93                 // String Upload request is interrupted by user
     708: invokeinterface #81,  2           // InterfaceMethod org/apache/commons/logging/Log.warn:(Ljava/lang/Object;)V
     713: aload         6
     715: aload_0
     716: getfield      #4                  // Field sm:Lcom/virtual/common/StringManager;
     719: ldc           #94                 // String fileupload.error
     721: invokevirtual #95                 // Method com/virtual/common/StringManager.getString:(Ljava/lang/String;)Ljava/lang/String;
     724: invokevirtual #90                 // Method com/virtual/ssv/server/upload/FileUploadInfo.setError:(Ljava/lang/String;)V
     727: return
    Exception table:
       from    to  target type
          81   580   583   Class java/lang/Throwable

  static {};
    Code:
       0: ldc           #2                  // class com/virtual/ssv/server/upload/FileUploadServlet
       2: invokestatic  #96                 // Method org/apache/commons/logging/LogFactory.getLog:(Ljava/lang/Class;)Lorg/apache/commons/logging/Log;
       5: putstatic     #14                 // Field log:Lorg/apache/commons/logging/Log;
       8: return
}
