Compiled from "HomeServlet.java"
public class com.virtual.ssv.server.home.HomeServlet extends com.virtual.ssv.server.BaseServlet {
  private static final long serialVersionUID;

  public com.virtual.ssv.server.home.HomeServlet();
    Code:
       0: aload_0
       1: invokespecial #1                  // Method com/virtual/ssv/server/BaseServlet."<init>":()V
       4: return

  protected void doGet(javax.servlet.http.HttpServletRequest, javax.servlet.http.HttpServletResponse) throws javax.servlet.ServletException, java.io.IOException;
    Code:
       0: aload_1
       1: invokeinterface #2,  1            // InterfaceMethod javax/servlet/http/HttpServletRequest.getSession:()Ljavax/servlet/http/HttpSession;
       6: astore_3
       7: aload_3
       8: ldc           #3                  // String loginName
      10: invokeinterface #4,  2            // InterfaceMethod javax/servlet/http/HttpSession.getAttribute:(Ljava/lang/String;)Ljava/lang/Object;
      15: checkcast     #5                  // class java/lang/String
      18: astore        4
      20: aload         4
      22: ifnull        36
      25: aload_2
      26: ldc           #6                  // String index2.jsp
      28: invokeinterface #7,  2            // InterfaceMethod javax/servlet/http/HttpServletResponse.sendRedirect:(Ljava/lang/String;)V
      33: goto          44
      36: aload_2
      37: ldc           #8                  // String login.jsp
      39: invokeinterface #7,  2            // InterfaceMethod javax/servlet/http/HttpServletResponse.sendRedirect:(Ljava/lang/String;)V
      44: return
}
