Compiled from "ApplyDiskServlet.java"
public class com.virtual.ssv.server.applydisk.ApplyDiskServlet extends com.virtual.ssv.server.BaseServlet {
  private static final long serialVersionUID;

  public com.virtual.ssv.server.applydisk.ApplyDiskServlet();
    Code:
       0: aload_0
       1: invokespecial #1                  // Method com/virtual/ssv/server/BaseServlet."<init>":()V
       4: return

  protected void doGet(javax.servlet.http.HttpServletRequest, javax.servlet.http.HttpServletResponse) throws javax.servlet.ServletException, java.io.IOException;
    Code:
       0: aload_1
       1: invokeinterface #2,  1            // InterfaceMethod javax/servlet/http/HttpServletRequest.getSession:()Ljavax/servlet/http/HttpSession;
       6: astore_3
       7: aload_3
       8: ldc           #3                  // String loginInfo
      10: invokeinterface #4,  2            // InterfaceMethod javax/servlet/http/HttpSession.getAttribute:(Ljava/lang/String;)Ljava/lang/Object;
      15: checkcast     #5                  // class com/virtual/ssv/server/user/LoginInfo
      18: astore        4
      20: aload         4
      22: ifnull        164
      25: aload_0
      26: aload_1
      27: aload_2
      28: invokevirtual #6                  // Method checkUserState:(Ljavax/servlet/http/HttpServletRequest;Ljavax/servlet/http/HttpServletResponse;)V
      31: aload_1
      32: ldc           #7                  // String way
      34: invokeinterface #8,  2            // InterfaceMethod javax/servlet/http/HttpServletRequest.getParameter:(Ljava/lang/String;)Ljava/lang/String;
      39: astore        5
      41: ldc           #9                  // String list
      43: aload         5
      45: invokevirtual #10                 // Method java/lang/String.equals:(Ljava/lang/Object;)Z
      48: ifeq          62
      51: aload_0
      52: aload_1
      53: aload_2
      54: aload         4
      56: invokespecial #11                 // Method getList:(Ljavax/servlet/http/HttpServletRequest;Ljavax/servlet/http/HttpServletResponse;Lcom/virtual/ssv/server/user/LoginInfo;)V
      59: goto          164
      62: ldc           #12                 // String apply
      64: aload         5
      66: invokevirtual #10                 // Method java/lang/String.equals:(Ljava/lang/Object;)Z
      69: ifeq          83
      72: aload_0
      73: aload_1
      74: aload_2
      75: aload         4
      77: invokespecial #13                 // Method apply:(Ljavax/servlet/http/HttpServletRequest;Ljavax/servlet/http/HttpServletResponse;Lcom/virtual/ssv/server/user/LoginInfo;)V
      80: goto          164
      83: ldc           #14                 // String delete
      85: aload         5
      87: invokevirtual #10                 // Method java/lang/String.equals:(Ljava/lang/Object;)Z
      90: ifeq          104
      93: aload_0
      94: aload_1
      95: aload_2
      96: aload         4
      98: invokespecial #15                 // Method delete:(Ljavax/servlet/http/HttpServletRequest;Ljavax/servlet/http/HttpServletResponse;Lcom/virtual/ssv/server/user/LoginInfo;)V
     101: goto          164
     104: ldc           #16                 // String loadedToHost
     106: aload         5
     108: invokevirtual #10                 // Method java/lang/String.equals:(Ljava/lang/Object;)Z
     111: ifeq          125
     114: aload_0
     115: aload_1
     116: aload_2
     117: aload         4
     119: invokespecial #17                 // Method addDiskToCloudHost:(Ljavax/servlet/http/HttpServletRequest;Ljavax/servlet/http/HttpServletResponse;Lcom/virtual/ssv/server/user/LoginInfo;)V
     122: goto          164
     125: ldc           #18                 // String unloadFromHost
     127: aload         5
     129: invokevirtual #10                 // Method java/lang/String.equals:(Ljava/lang/Object;)Z
     132: ifeq          146
     135: aload_0
     136: aload_1
     137: aload_2
     138: aload         4
     140: invokespecial #19                 // Method unloadDiskFromCloudHost:(Ljavax/servlet/http/HttpServletRequest;Ljavax/servlet/http/HttpServletResponse;Lcom/virtual/ssv/server/user/LoginInfo;)V
     143: goto          164
     146: ldc           #20                 // String checkNameExist
     148: aload         5
     150: invokevirtual #10                 // Method java/lang/String.equals:(Ljava/lang/Object;)Z
     153: ifeq          164
     156: aload_0
     157: aload_1
     158: aload_2
     159: aload         4
     161: invokespecial #21                 // Method checkNameExist:(Ljavax/servlet/http/HttpServletRequest;Ljavax/servlet/http/HttpServletResponse;Lcom/virtual/ssv/server/user/LoginInfo;)V
     164: return

  private void checkNameExist(javax.servlet.http.HttpServletRequest, javax.servlet.http.HttpServletResponse, com.virtual.ssv.server.user.LoginInfo);
    Code:
       0: aload_1
       1: ldc           #22                 // String name
       3: invokeinterface #8,  2            // InterfaceMethod javax/servlet/http/HttpServletRequest.getParameter:(Ljava/lang/String;)Ljava/lang/String;
       8: astore        4
      10: aload         4
      12: invokestatic  #23                 // Method org/apache/commons/lang/StringUtils.isEmpty:(Ljava/lang/String;)Z
      15: ifeq          19
      18: return
      19: aload_0
      20: getfield      #24                 // Field reqHandle:Lcom/virtual/ssv/server/rs/client/RequestHandle;
      23: aload         4
      25: aload_3
      26: invokevirtual #25                 // Method com/virtual/ssv/server/user/LoginInfo.getId:()Ljava/lang/Long;
      29: invokevirtual #26                 // Method com/virtual/ssv/server/rs/client/RequestHandle.checkDiskNameExist:(Ljava/lang/String;Ljava/lang/Long;)Ljava/lang/String;
      32: astore        5
      34: aload_0
      35: aload_2
      36: aload         5
      38: invokevirtual #27                 // Method write:(Ljavax/servlet/http/HttpServletResponse;Ljava/lang/String;)V
      41: return

  private void unloadDiskFromCloudHost(javax.servlet.http.HttpServletRequest, javax.servlet.http.HttpServletResponse, com.virtual.ssv.server.user.LoginInfo);
    Code:
       0: new           #28                 // class java/util/Date
       3: dup
       4: invokespecial #29                 // Method java/util/Date."<init>":()V
       7: astore        4
       9: new           #30                 // class com/virtual/ssv/server/entity/ResultJson
      12: dup
      13: invokespecial #31                 // Method com/virtual/ssv/server/entity/ResultJson."<init>":()V
      16: astore        5
      18: aload_1
      19: ldc           #32                 // String id
      21: invokeinterface #8,  2            // InterfaceMethod javax/servlet/http/HttpServletRequest.getParameter:(Ljava/lang/String;)Ljava/lang/String;
      26: astore        6
      28: aload         6
      30: invokestatic  #23                 // Method org/apache/commons/lang/StringUtils.isEmpty:(Ljava/lang/String;)Z
      33: ifeq          37
      36: return
      37: aload         6
      39: invokestatic  #33                 // Method java/lang/Long.parseLong:(Ljava/lang/String;)J
      42: invokestatic  #34                 // Method java/lang/Long.valueOf:(J)Ljava/lang/Long;
      45: astore        7
      47: aload_0
      48: getfield      #24                 // Field reqHandle:Lcom/virtual/ssv/server/rs/client/RequestHandle;
      51: aload         7
      53: aload_3
      54: invokevirtual #35                 // Method com/virtual/ssv/server/user/LoginInfo.getOrgId:()Ljava/lang/Long;
      57: invokevirtual #36                 // Method com/virtual/ssv/server/rs/client/RequestHandle.getCloudDiskById:(Ljava/lang/Long;Ljava/lang/Long;)Lcom/virtual/ssv/server/rs/client/entity/ApplyDisk;
      60: astore        8
      62: aload         8
      64: ifnonnull     96
      67: aload         5
      69: aload_0
      70: getfield      #37                 // Field commonSm:Lcom/virtual/common/StringManager;
      73: ldc           #38                 // String cloudDisk.ErrorMsg
      75: invokevirtual #39                 // Method com/virtual/common/StringManager.getString:(Ljava/lang/String;)Ljava/lang/String;
      78: invokevirtual #40                 // Method com/virtual/ssv/server/entity/ResultJson.setErrorMsg:(Ljava/lang/String;)V
      81: aload_0
      82: aload_2
      83: aload_0
      84: getfield      #41                 // Field filterJson:Lcom/google/gson/Gson;
      87: aload         5
      89: invokevirtual #42                 // Method com/google/gson/Gson.toJson:(Ljava/lang/Object;)Ljava/lang/String;
      92: invokevirtual #27                 // Method write:(Ljavax/servlet/http/HttpServletResponse;Ljava/lang/String;)V
      95: return
      96: aload         8
      98: invokevirtual #43                 // Method com/virtual/ssv/server/rs/client/entity/ApplyDisk.getDomainId:()Ljava/lang/Long;
     101: ifnonnull     153
     104: aload         5
     106: aload_0
     107: getfield      #37                 // Field commonSm:Lcom/virtual/common/StringManager;
     110: ldc           #44                 // String unloadFromHost.ErrorMessage
     112: iconst_2
     113: anewarray     #45                 // class java/lang/Object
     116: dup
     117: iconst_0
     118: aload         8
     120: invokevirtual #46                 // Method com/virtual/ssv/server/rs/client/entity/ApplyDisk.getDomainName:()Ljava/lang/String;
     123: aastore
     124: dup
     125: iconst_1
     126: aload         8
     128: invokevirtual #47                 // Method com/virtual/ssv/server/rs/client/entity/ApplyDisk.getName:()Ljava/lang/String;
     131: aastore
     132: invokevirtual #48                 // Method com/virtual/common/StringManager.getString:(Ljava/lang/String;[Ljava/lang/Object;)Ljava/lang/String;
     135: invokevirtual #40                 // Method com/virtual/ssv/server/entity/ResultJson.setErrorMsg:(Ljava/lang/String;)V
     138: aload_0
     139: aload_2
     140: aload_0
     141: getfield      #41                 // Field filterJson:Lcom/google/gson/Gson;
     144: aload         5
     146: invokevirtual #42                 // Method com/google/gson/Gson.toJson:(Ljava/lang/Object;)Ljava/lang/String;
     149: invokevirtual #27                 // Method write:(Ljavax/servlet/http/HttpServletResponse;Ljava/lang/String;)V
     152: return
     153: aload         8
     155: invokevirtual #46                 // Method com/virtual/ssv/server/rs/client/entity/ApplyDisk.getDomainName:()Ljava/lang/String;
     158: ifnonnull     187
     161: aload         5
     163: sipush        1001
     166: invokestatic  #50                 // Method com/virtual/common/ErrorCodes.getErrorMessage:(I)Ljava/lang/String;
     169: invokevirtual #40                 // Method com/virtual/ssv/server/entity/ResultJson.setErrorMsg:(Ljava/lang/String;)V
     172: aload_0
     173: aload_2
     174: aload_0
     175: getfield      #41                 // Field filterJson:Lcom/google/gson/Gson;
     178: aload         5
     180: invokevirtual #42                 // Method com/google/gson/Gson.toJson:(Ljava/lang/Object;)Ljava/lang/String;
     183: invokevirtual #27                 // Method write:(Ljavax/servlet/http/HttpServletResponse;Ljava/lang/String;)V
     186: return
     187: aload_0
     188: getfield      #24                 // Field reqHandle:Lcom/virtual/ssv/server/rs/client/RequestHandle;
     191: aload         7
     193: aload         8
     195: invokevirtual #47                 // Method com/virtual/ssv/server/rs/client/entity/ApplyDisk.getName:()Ljava/lang/String;
     198: aload         8
     200: invokevirtual #46                 // Method com/virtual/ssv/server/rs/client/entity/ApplyDisk.getDomainName:()Ljava/lang/String;
     203: aload_3
     204: invokevirtual #35                 // Method com/virtual/ssv/server/user/LoginInfo.getOrgId:()Ljava/lang/Long;
     207: invokevirtual #51                 // Method com/virtual/ssv/server/rs/client/RequestHandle.unloadDiskFromCloudHost:(Ljava/lang/Long;Ljava/lang/String;Ljava/lang/String;Ljava/lang/Long;)Lcom/virtual/ssv/server/entity/ResultJson;
     210: astore        5
     212: aload         5
     214: invokevirtual #52                 // Method com/virtual/ssv/server/entity/ResultJson.isSuccess:()Z
     217: ifeq          359
     220: new           #28                 // class java/util/Date
     223: dup
     224: invokespecial #29                 // Method java/util/Date."<init>":()V
     227: astore        9
     229: new           #53                 // class com/virtual/ssv/server/rs/client/entity/RsOperateLog
     232: dup
     233: invokespecial #54                 // Method com/virtual/ssv/server/rs/client/entity/RsOperateLog."<init>":()V
     236: astore        10
     238: aload         10
     240: aload_3
     241: invokevirtual #25                 // Method com/virtual/ssv/server/user/LoginInfo.getId:()Ljava/lang/Long;
     244: invokevirtual #55                 // Method com/virtual/ssv/server/rs/client/entity/RsOperateLog.setUserId:(Ljava/lang/Long;)V
     247: aload         10
     249: aload_3
     250: invokevirtual #35                 // Method com/virtual/ssv/server/user/LoginInfo.getOrgId:()Ljava/lang/Long;
     253: invokevirtual #56                 // Method com/virtual/ssv/server/rs/client/entity/RsOperateLog.setOrgId:(Ljava/lang/Long;)V
     256: aload         10
     258: aload_3
     259: invokevirtual #57                 // Method com/virtual/ssv/server/user/LoginInfo.getLoginName:()Ljava/lang/String;
     262: invokevirtual #58                 // Method com/virtual/ssv/server/rs/client/entity/RsOperateLog.setLoginName:(Ljava/lang/String;)V
     265: aload         10
     267: aload_3
     268: invokevirtual #59                 // Method com/virtual/ssv/server/user/LoginInfo.getUserName:()Ljava/lang/String;
     271: invokevirtual #60                 // Method com/virtual/ssv/server/rs/client/entity/RsOperateLog.setUserName:(Ljava/lang/String;)V
     274: aload         10
     276: aload_3
     277: invokevirtual #61                 // Method com/virtual/ssv/server/user/LoginInfo.getLoginIp:()Ljava/lang/String;
     280: invokevirtual #62                 // Method com/virtual/ssv/server/rs/client/entity/RsOperateLog.setAddress:(Ljava/lang/String;)V
     283: aload         10
     285: bipush        30
     287: invokestatic  #64                 // Method java/lang/Integer.valueOf:(I)Ljava/lang/Integer;
     290: invokevirtual #65                 // Method com/virtual/ssv/server/rs/client/entity/RsOperateLog.setCategory:(Ljava/lang/Integer;)V
     293: aload         10
     295: aload_0
     296: getfield      #66                 // Field logSm:Lcom/virtual/common/StringManager;
     299: ldc           #67                 // String cloudDisk.unloadFromHost.operation
     301: iconst_2
     302: anewarray     #45                 // class java/lang/Object
     305: dup
     306: iconst_0
     307: aload         8
     309: invokevirtual #47                 // Method com/virtual/ssv/server/rs/client/entity/ApplyDisk.getName:()Ljava/lang/String;
     312: aastore
     313: dup
     314: iconst_1
     315: aload         8
     317: invokevirtual #46                 // Method com/virtual/ssv/server/rs/client/entity/ApplyDisk.getDomainName:()Ljava/lang/String;
     320: aastore
     321: invokevirtual #48                 // Method com/virtual/common/StringManager.getString:(Ljava/lang/String;[Ljava/lang/Object;)Ljava/lang/String;
     324: invokevirtual #68                 // Method com/virtual/ssv/server/rs/client/entity/RsOperateLog.setDescription:(Ljava/lang/String;)V
     327: aload         10
     329: aload         4
     331: invokevirtual #69                 // Method com/virtual/ssv/server/rs/client/entity/RsOperateLog.setStartTime:(Ljava/util/Date;)V
     334: aload         10
     336: aload         9
     338: invokevirtual #70                 // Method com/virtual/ssv/server/rs/client/entity/RsOperateLog.setEndTime:(Ljava/util/Date;)V
     341: aload         10
     343: getstatic     #71                 // Field com/virtual/ssv/server/rs/client/entity/RsOperateLog.RESULT_SUCCESS:Ljava/lang/Integer;
     346: invokevirtual #72                 // Method com/virtual/ssv/server/rs/client/entity/RsOperateLog.setResult:(Ljava/lang/Integer;)V
     349: aload_0
     350: getfield      #24                 // Field reqHandle:Lcom/virtual/ssv/server/rs/client/RequestHandle;
     353: aload         10
     355: invokevirtual #73                 // Method com/virtual/ssv/server/rs/client/RequestHandle.addUserLog:(Lcom/virtual/ssv/server/rs/client/entity/RsOperateLog;)Ljava/lang/Long;
     358: pop
     359: goto          458
     362: astore        6
     364: aload         6
     366: instanceof    #75                 // class com/virtual/common/AppException
     369: ifeq          458
     372: aload         6
     374: checkcast     #75                 // class com/virtual/common/AppException
     377: astore        7
     379: aload         7
     381: invokevirtual #76                 // Method com/virtual/common/AppException.getErrorCode:()I
     384: bipush        102
     386: if_icmpne     402
     389: aload         5
     391: bipush        102
     393: invokestatic  #50                 // Method com/virtual/common/ErrorCodes.getErrorMessage:(I)Ljava/lang/String;
     396: invokevirtual #40                 // Method com/virtual/ssv/server/entity/ResultJson.setErrorMsg:(Ljava/lang/String;)V
     399: goto          458
     402: aload         7
     404: invokevirtual #76                 // Method com/virtual/common/AppException.getErrorCode:()I
     407: bipush        103
     409: if_icmpne     425
     412: aload         5
     414: bipush        103
     416: invokestatic  #50                 // Method com/virtual/common/ErrorCodes.getErrorMessage:(I)Ljava/lang/String;
     419: invokevirtual #40                 // Method com/virtual/ssv/server/entity/ResultJson.setErrorMsg:(Ljava/lang/String;)V
     422: goto          458
     425: aload         7
     427: invokevirtual #76                 // Method com/virtual/common/AppException.getErrorCode:()I
     430: bipush        11
     432: if_icmpne     448
     435: aload         5
     437: bipush        11
     439: invokestatic  #50                 // Method com/virtual/common/ErrorCodes.getErrorMessage:(I)Ljava/lang/String;
     442: invokevirtual #40                 // Method com/virtual/ssv/server/entity/ResultJson.setErrorMsg:(Ljava/lang/String;)V
     445: goto          458
     448: aload         5
     450: aload         7
     452: invokevirtual #77                 // Method com/virtual/common/AppException.getMessage:()Ljava/lang/String;
     455: invokevirtual #40                 // Method com/virtual/ssv/server/entity/ResultJson.setErrorMsg:(Ljava/lang/String;)V
     458: aload_0
     459: aload_2
     460: aload_0
     461: getfield      #41                 // Field filterJson:Lcom/google/gson/Gson;
     464: aload         5
     466: invokevirtual #42                 // Method com/google/gson/Gson.toJson:(Ljava/lang/Object;)Ljava/lang/String;
     469: invokevirtual #27                 // Method write:(Ljavax/servlet/http/HttpServletResponse;Ljava/lang/String;)V
     472: return
    Exception table:
       from    to  target type
          18    36   362   Class java/lang/Exception
          37    95   362   Class java/lang/Exception
          96   152   362   Class java/lang/Exception
         153   186   362   Class java/lang/Exception
         187   359   362   Class java/lang/Exception

  private void addDiskToCloudHost(javax.servlet.http.HttpServletRequest, javax.servlet.http.HttpServletResponse, com.virtual.ssv.server.user.LoginInfo);
    Code:
       0: new           #28                 // class java/util/Date
       3: dup
       4: invokespecial #29                 // Method java/util/Date."<init>":()V
       7: astore        4
       9: new           #30                 // class com/virtual/ssv/server/entity/ResultJson
      12: dup
      13: invokespecial #31                 // Method com/virtual/ssv/server/entity/ResultJson."<init>":()V
      16: astore        5
      18: aload_1
      19: ldc           #32                 // String id
      21: invokeinterface #8,  2            // InterfaceMethod javax/servlet/http/HttpServletRequest.getParameter:(Ljava/lang/String;)Ljava/lang/String;
      26: astore        6
      28: aload_1
      29: ldc           #78                 // String vmId
      31: invokeinterface #8,  2            // InterfaceMethod javax/servlet/http/HttpServletRequest.getParameter:(Ljava/lang/String;)Ljava/lang/String;
      36: astore        7
      38: aload_1
      39: ldc           #79                 // String vmName
      41: invokeinterface #8,  2            // InterfaceMethod javax/servlet/http/HttpServletRequest.getParameter:(Ljava/lang/String;)Ljava/lang/String;
      46: astore        8
      48: aload         6
      50: invokestatic  #23                 // Method org/apache/commons/lang/StringUtils.isEmpty:(Ljava/lang/String;)Z
      53: ifne          64
      56: aload         7
      58: invokestatic  #23                 // Method org/apache/commons/lang/StringUtils.isEmpty:(Ljava/lang/String;)Z
      61: ifeq          65
      64: return
      65: aload         6
      67: invokestatic  #33                 // Method java/lang/Long.parseLong:(Ljava/lang/String;)J
      70: invokestatic  #34                 // Method java/lang/Long.valueOf:(J)Ljava/lang/Long;
      73: astore        9
      75: aload_0
      76: getfield      #24                 // Field reqHandle:Lcom/virtual/ssv/server/rs/client/RequestHandle;
      79: aload         9
      81: aload_3
      82: invokevirtual #35                 // Method com/virtual/ssv/server/user/LoginInfo.getOrgId:()Ljava/lang/Long;
      85: invokevirtual #36                 // Method com/virtual/ssv/server/rs/client/RequestHandle.getCloudDiskById:(Ljava/lang/Long;Ljava/lang/Long;)Lcom/virtual/ssv/server/rs/client/entity/ApplyDisk;
      88: astore        10
      90: aload         10
      92: ifnonnull     124
      95: aload         5
      97: aload_0
      98: getfield      #37                 // Field commonSm:Lcom/virtual/common/StringManager;
     101: ldc           #38                 // String cloudDisk.ErrorMsg
     103: invokevirtual #39                 // Method com/virtual/common/StringManager.getString:(Ljava/lang/String;)Ljava/lang/String;
     106: invokevirtual #40                 // Method com/virtual/ssv/server/entity/ResultJson.setErrorMsg:(Ljava/lang/String;)V
     109: aload_0
     110: aload_2
     111: aload_0
     112: getfield      #41                 // Field filterJson:Lcom/google/gson/Gson;
     115: aload         5
     117: invokevirtual #42                 // Method com/google/gson/Gson.toJson:(Ljava/lang/Object;)Ljava/lang/String;
     120: invokevirtual #27                 // Method write:(Ljavax/servlet/http/HttpServletResponse;Ljava/lang/String;)V
     123: return
     124: aload         10
     126: invokevirtual #43                 // Method com/virtual/ssv/server/rs/client/entity/ApplyDisk.getDomainId:()Ljava/lang/Long;
     129: ifnull        199
     132: aload         10
     134: invokevirtual #43                 // Method com/virtual/ssv/server/rs/client/entity/ApplyDisk.getDomainId:()Ljava/lang/Long;
     137: invokevirtual #80                 // Method java/lang/Long.longValue:()J
     140: lconst_0
     141: lcmp
     142: iflt          199
     145: aload         5
     147: aload_0
     148: getfield      #37                 // Field commonSm:Lcom/virtual/common/StringManager;
     151: ldc           #81                 // String loadedToHost.ErrorMessage
     153: iconst_3
     154: anewarray     #45                 // class java/lang/Object
     157: dup
     158: iconst_0
     159: aload         8
     161: aastore
     162: dup
     163: iconst_1
     164: aload         10
     166: invokevirtual #47                 // Method com/virtual/ssv/server/rs/client/entity/ApplyDisk.getName:()Ljava/lang/String;
     169: aastore
     170: dup
     171: iconst_2
     172: aload         10
     174: invokevirtual #46                 // Method com/virtual/ssv/server/rs/client/entity/ApplyDisk.getDomainName:()Ljava/lang/String;
     177: aastore
     178: invokevirtual #48                 // Method com/virtual/common/StringManager.getString:(Ljava/lang/String;[Ljava/lang/Object;)Ljava/lang/String;
     181: invokevirtual #40                 // Method com/virtual/ssv/server/entity/ResultJson.setErrorMsg:(Ljava/lang/String;)V
     184: aload_0
     185: aload_2
     186: aload_0
     187: getfield      #41                 // Field filterJson:Lcom/google/gson/Gson;
     190: aload         5
     192: invokevirtual #42                 // Method com/google/gson/Gson.toJson:(Ljava/lang/Object;)Ljava/lang/String;
     195: invokevirtual #27                 // Method write:(Ljavax/servlet/http/HttpServletResponse;Ljava/lang/String;)V
     198: return
     199: new           #82                 // class com/virtual/ssv/server/rs/client/entity/RsDomainForModify$StorageConfig
     202: dup
     203: invokespecial #83                 // Method com/virtual/ssv/server/rs/client/entity/RsDomainForModify$StorageConfig."<init>":()V
     206: astore        11
     208: aload         11
     210: ldc           #84                 // String directsync
     212: invokevirtual #85                 // Method com/virtual/ssv/server/rs/client/entity/RsDomainForModify$StorageConfig.setCacheType:(Ljava/lang/String;)V
     215: aload         11
     217: aload         10
     219: invokevirtual #86                 // Method com/virtual/ssv/server/rs/client/entity/ApplyDisk.getPath:()Ljava/lang/String;
     222: invokevirtual #87                 // Method com/virtual/ssv/server/rs/client/entity/RsDomainForModify$StorageConfig.setPath:(Ljava/lang/String;)V
     225: aload         11
     227: aload         10
     229: invokevirtual #88                 // Method com/virtual/ssv/server/rs/client/entity/ApplyDisk.getCapacity:()Ljava/lang/Integer;
     232: invokevirtual #89                 // Method java/lang/Integer.intValue:()I
     235: i2l
     236: ldc2_w        #90                 // long 1000l
     239: lmul
     240: invokestatic  #34                 // Method java/lang/Long.valueOf:(J)Ljava/lang/Long;
     243: invokevirtual #92                 // Method com/virtual/ssv/server/rs/client/entity/RsDomainForModify$StorageConfig.setSize:(Ljava/lang/Long;)V
     246: aload         11
     248: ldc           #93                 // String Virtio
     250: invokevirtual #94                 // Method com/virtual/ssv/server/rs/client/entity/RsDomainForModify$StorageConfig.setType:(Ljava/lang/String;)V
     253: aload         11
     255: ldc           #95                 // String virtio
     257: invokevirtual #96                 // Method com/virtual/ssv/server/rs/client/entity/RsDomainForModify$StorageConfig.setTargetBus:(Ljava/lang/String;)V
     260: aload_0
     261: getfield      #24                 // Field reqHandle:Lcom/virtual/ssv/server/rs/client/RequestHandle;
     264: aload         11
     266: aload         7
     268: invokestatic  #33                 // Method java/lang/Long.parseLong:(Ljava/lang/String;)J
     271: invokestatic  #34                 // Method java/lang/Long.valueOf:(J)Ljava/lang/Long;
     274: aload         8
     276: aload         9
     278: aload         10
     280: invokevirtual #47                 // Method com/virtual/ssv/server/rs/client/entity/ApplyDisk.getName:()Ljava/lang/String;
     283: aload_3
     284: invokevirtual #35                 // Method com/virtual/ssv/server/user/LoginInfo.getOrgId:()Ljava/lang/Long;
     287: invokevirtual #97                 // Method com/virtual/ssv/server/rs/client/RequestHandle.addDiskToCloudHost:(Lcom/virtual/ssv/server/rs/client/entity/RsDomainForModify$StorageConfig;Ljava/lang/Long;Ljava/lang/String;Ljava/lang/Long;Ljava/lang/String;Ljava/lang/Long;)Lcom/virtual/ssv/server/entity/ResultJson;
     290: astore        5
     292: new           #28                 // class java/util/Date
     295: dup
     296: invokespecial #29                 // Method java/util/Date."<init>":()V
     299: astore        12
     301: new           #53                 // class com/virtual/ssv/server/rs/client/entity/RsOperateLog
     304: dup
     305: invokespecial #54                 // Method com/virtual/ssv/server/rs/client/entity/RsOperateLog."<init>":()V
     308: astore        13
     310: aload         13
     312: aload_3
     313: invokevirtual #25                 // Method com/virtual/ssv/server/user/LoginInfo.getId:()Ljava/lang/Long;
     316: invokevirtual #55                 // Method com/virtual/ssv/server/rs/client/entity/RsOperateLog.setUserId:(Ljava/lang/Long;)V
     319: aload         13
     321: aload_3
     322: invokevirtual #35                 // Method com/virtual/ssv/server/user/LoginInfo.getOrgId:()Ljava/lang/Long;
     325: invokevirtual #56                 // Method com/virtual/ssv/server/rs/client/entity/RsOperateLog.setOrgId:(Ljava/lang/Long;)V
     328: aload         13
     330: aload_3
     331: invokevirtual #57                 // Method com/virtual/ssv/server/user/LoginInfo.getLoginName:()Ljava/lang/String;
     334: invokevirtual #58                 // Method com/virtual/ssv/server/rs/client/entity/RsOperateLog.setLoginName:(Ljava/lang/String;)V
     337: aload         13
     339: aload_3
     340: invokevirtual #59                 // Method com/virtual/ssv/server/user/LoginInfo.getUserName:()Ljava/lang/String;
     343: invokevirtual #60                 // Method com/virtual/ssv/server/rs/client/entity/RsOperateLog.setUserName:(Ljava/lang/String;)V
     346: aload         13
     348: aload_3
     349: invokevirtual #61                 // Method com/virtual/ssv/server/user/LoginInfo.getLoginIp:()Ljava/lang/String;
     352: invokevirtual #62                 // Method com/virtual/ssv/server/rs/client/entity/RsOperateLog.setAddress:(Ljava/lang/String;)V
     355: aload         13
     357: bipush        30
     359: invokestatic  #64                 // Method java/lang/Integer.valueOf:(I)Ljava/lang/Integer;
     362: invokevirtual #65                 // Method com/virtual/ssv/server/rs/client/entity/RsOperateLog.setCategory:(Ljava/lang/Integer;)V
     365: aload         13
     367: aload_0
     368: getfield      #66                 // Field logSm:Lcom/virtual/common/StringManager;
     371: ldc           #98                 // String cloudDisk.addToHost.operation
     373: iconst_2
     374: anewarray     #45                 // class java/lang/Object
     377: dup
     378: iconst_0
     379: aload         10
     381: invokevirtual #47                 // Method com/virtual/ssv/server/rs/client/entity/ApplyDisk.getName:()Ljava/lang/String;
     384: aastore
     385: dup
     386: iconst_1
     387: aload         8
     389: aastore
     390: invokevirtual #48                 // Method com/virtual/common/StringManager.getString:(Ljava/lang/String;[Ljava/lang/Object;)Ljava/lang/String;
     393: invokevirtual #68                 // Method com/virtual/ssv/server/rs/client/entity/RsOperateLog.setDescription:(Ljava/lang/String;)V
     396: aload         13
     398: aload         4
     400: invokevirtual #69                 // Method com/virtual/ssv/server/rs/client/entity/RsOperateLog.setStartTime:(Ljava/util/Date;)V
     403: aload         13
     405: aload         12
     407: invokevirtual #70                 // Method com/virtual/ssv/server/rs/client/entity/RsOperateLog.setEndTime:(Ljava/util/Date;)V
     410: aload         5
     412: invokevirtual #52                 // Method com/virtual/ssv/server/entity/ResultJson.isSuccess:()Z
     415: ifeq          429
     418: aload         13
     420: getstatic     #71                 // Field com/virtual/ssv/server/rs/client/entity/RsOperateLog.RESULT_SUCCESS:Ljava/lang/Integer;
     423: invokevirtual #72                 // Method com/virtual/ssv/server/rs/client/entity/RsOperateLog.setResult:(Ljava/lang/Integer;)V
     426: goto          447
     429: aload         13
     431: getstatic     #99                 // Field com/virtual/ssv/server/rs/client/entity/RsOperateLog.RESULT_FAILURE:Ljava/lang/Integer;
     434: invokevirtual #72                 // Method com/virtual/ssv/server/rs/client/entity/RsOperateLog.setResult:(Ljava/lang/Integer;)V
     437: aload         13
     439: aload         5
     441: invokevirtual #100                // Method com/virtual/ssv/server/entity/ResultJson.getFailtureReson:()Ljava/lang/String;
     444: invokevirtual #101                // Method com/virtual/ssv/server/rs/client/entity/RsOperateLog.setFailureReason:(Ljava/lang/String;)V
     447: aload_0
     448: getfield      #24                 // Field reqHandle:Lcom/virtual/ssv/server/rs/client/RequestHandle;
     451: aload         13
     453: invokevirtual #73                 // Method com/virtual/ssv/server/rs/client/RequestHandle.addUserLog:(Lcom/virtual/ssv/server/rs/client/entity/RsOperateLog;)Ljava/lang/Long;
     456: pop
     457: goto          541
     460: astore        6
     462: aload         6
     464: invokevirtual #76                 // Method com/virtual/common/AppException.getErrorCode:()I
     467: bipush        102
     469: if_icmpne     485
     472: aload         5
     474: bipush        102
     476: invokestatic  #50                 // Method com/virtual/common/ErrorCodes.getErrorMessage:(I)Ljava/lang/String;
     479: invokevirtual #40                 // Method com/virtual/ssv/server/entity/ResultJson.setErrorMsg:(Ljava/lang/String;)V
     482: goto          541
     485: aload         6
     487: invokevirtual #76                 // Method com/virtual/common/AppException.getErrorCode:()I
     490: bipush        103
     492: if_icmpne     508
     495: aload         5
     497: bipush        103
     499: invokestatic  #50                 // Method com/virtual/common/ErrorCodes.getErrorMessage:(I)Ljava/lang/String;
     502: invokevirtual #40                 // Method com/virtual/ssv/server/entity/ResultJson.setErrorMsg:(Ljava/lang/String;)V
     505: goto          541
     508: aload         6
     510: invokevirtual #76                 // Method com/virtual/common/AppException.getErrorCode:()I
     513: bipush        11
     515: if_icmpne     531
     518: aload         5
     520: bipush        11
     522: invokestatic  #50                 // Method com/virtual/common/ErrorCodes.getErrorMessage:(I)Ljava/lang/String;
     525: invokevirtual #40                 // Method com/virtual/ssv/server/entity/ResultJson.setErrorMsg:(Ljava/lang/String;)V
     528: goto          541
     531: aload         5
     533: aload         6
     535: invokevirtual #77                 // Method com/virtual/common/AppException.getMessage:()Ljava/lang/String;
     538: invokevirtual #40                 // Method com/virtual/ssv/server/entity/ResultJson.setErrorMsg:(Ljava/lang/String;)V
     541: aload_0
     542: aload_2
     543: aload_0
     544: getfield      #41                 // Field filterJson:Lcom/google/gson/Gson;
     547: aload         5
     549: invokevirtual #42                 // Method com/google/gson/Gson.toJson:(Ljava/lang/Object;)Ljava/lang/String;
     552: invokevirtual #27                 // Method write:(Ljavax/servlet/http/HttpServletResponse;Ljava/lang/String;)V
     555: return
    Exception table:
       from    to  target type
          18    64   460   Class com/virtual/common/AppException
          65   123   460   Class com/virtual/common/AppException
         124   198   460   Class com/virtual/common/AppException
         199   457   460   Class com/virtual/common/AppException

  private void delete(javax.servlet.http.HttpServletRequest, javax.servlet.http.HttpServletResponse, com.virtual.ssv.server.user.LoginInfo);
    Code:
       0: new           #28                 // class java/util/Date
       3: dup
       4: invokespecial #29                 // Method java/util/Date."<init>":()V
       7: astore        4
       9: new           #30                 // class com/virtual/ssv/server/entity/ResultJson
      12: dup
      13: invokespecial #31                 // Method com/virtual/ssv/server/entity/ResultJson."<init>":()V
      16: astore        5
      18: aload_1
      19: ldc           #32                 // String id
      21: invokeinterface #8,  2            // InterfaceMethod javax/servlet/http/HttpServletRequest.getParameter:(Ljava/lang/String;)Ljava/lang/String;
      26: astore        6
      28: aload_1
      29: ldc           #22                 // String name
      31: invokeinterface #8,  2            // InterfaceMethod javax/servlet/http/HttpServletRequest.getParameter:(Ljava/lang/String;)Ljava/lang/String;
      36: astore        7
      38: aload         6
      40: invokestatic  #23                 // Method org/apache/commons/lang/StringUtils.isEmpty:(Ljava/lang/String;)Z
      43: ifne          54
      46: aload         7
      48: invokestatic  #23                 // Method org/apache/commons/lang/StringUtils.isEmpty:(Ljava/lang/String;)Z
      51: ifeq          55
      54: return
      55: aload_0
      56: getfield      #24                 // Field reqHandle:Lcom/virtual/ssv/server/rs/client/RequestHandle;
      59: aload         6
      61: invokestatic  #33                 // Method java/lang/Long.parseLong:(Ljava/lang/String;)J
      64: invokestatic  #34                 // Method java/lang/Long.valueOf:(J)Ljava/lang/Long;
      67: aload         7
      69: invokevirtual #102                // Method com/virtual/ssv/server/rs/client/RequestHandle.deleteCloudDisk:(Ljava/lang/Long;Ljava/lang/String;)Lcom/virtual/ssv/server/entity/ResultJson;
      72: astore        5
      74: new           #28                 // class java/util/Date
      77: dup
      78: invokespecial #29                 // Method java/util/Date."<init>":()V
      81: astore        8
      83: new           #53                 // class com/virtual/ssv/server/rs/client/entity/RsOperateLog
      86: dup
      87: invokespecial #54                 // Method com/virtual/ssv/server/rs/client/entity/RsOperateLog."<init>":()V
      90: astore        9
      92: aload         9
      94: aload_3
      95: invokevirtual #25                 // Method com/virtual/ssv/server/user/LoginInfo.getId:()Ljava/lang/Long;
      98: invokevirtual #55                 // Method com/virtual/ssv/server/rs/client/entity/RsOperateLog.setUserId:(Ljava/lang/Long;)V
     101: aload         9
     103: aload_3
     104: invokevirtual #35                 // Method com/virtual/ssv/server/user/LoginInfo.getOrgId:()Ljava/lang/Long;
     107: invokevirtual #56                 // Method com/virtual/ssv/server/rs/client/entity/RsOperateLog.setOrgId:(Ljava/lang/Long;)V
     110: aload         9
     112: aload_3
     113: invokevirtual #57                 // Method com/virtual/ssv/server/user/LoginInfo.getLoginName:()Ljava/lang/String;
     116: invokevirtual #58                 // Method com/virtual/ssv/server/rs/client/entity/RsOperateLog.setLoginName:(Ljava/lang/String;)V
     119: aload         9
     121: aload_3
     122: invokevirtual #59                 // Method com/virtual/ssv/server/user/LoginInfo.getUserName:()Ljava/lang/String;
     125: invokevirtual #60                 // Method com/virtual/ssv/server/rs/client/entity/RsOperateLog.setUserName:(Ljava/lang/String;)V
     128: aload         9
     130: aload_3
     131: invokevirtual #61                 // Method com/virtual/ssv/server/user/LoginInfo.getLoginIp:()Ljava/lang/String;
     134: invokevirtual #62                 // Method com/virtual/ssv/server/rs/client/entity/RsOperateLog.setAddress:(Ljava/lang/String;)V
     137: aload         9
     139: bipush        30
     141: invokestatic  #64                 // Method java/lang/Integer.valueOf:(I)Ljava/lang/Integer;
     144: invokevirtual #65                 // Method com/virtual/ssv/server/rs/client/entity/RsOperateLog.setCategory:(Ljava/lang/Integer;)V
     147: aload         9
     149: aload_0
     150: getfield      #66                 // Field logSm:Lcom/virtual/common/StringManager;
     153: ldc           #103                // String cloudDisk.delete.operation
     155: iconst_1
     156: anewarray     #45                 // class java/lang/Object
     159: dup
     160: iconst_0
     161: aload         7
     163: aastore
     164: invokevirtual #48                 // Method com/virtual/common/StringManager.getString:(Ljava/lang/String;[Ljava/lang/Object;)Ljava/lang/String;
     167: invokevirtual #68                 // Method com/virtual/ssv/server/rs/client/entity/RsOperateLog.setDescription:(Ljava/lang/String;)V
     170: aload         9
     172: aload         4
     174: invokevirtual #69                 // Method com/virtual/ssv/server/rs/client/entity/RsOperateLog.setStartTime:(Ljava/util/Date;)V
     177: aload         9
     179: aload         8
     181: invokevirtual #70                 // Method com/virtual/ssv/server/rs/client/entity/RsOperateLog.setEndTime:(Ljava/util/Date;)V
     184: aload         5
     186: invokevirtual #52                 // Method com/virtual/ssv/server/entity/ResultJson.isSuccess:()Z
     189: ifeq          203
     192: aload         9
     194: getstatic     #71                 // Field com/virtual/ssv/server/rs/client/entity/RsOperateLog.RESULT_SUCCESS:Ljava/lang/Integer;
     197: invokevirtual #72                 // Method com/virtual/ssv/server/rs/client/entity/RsOperateLog.setResult:(Ljava/lang/Integer;)V
     200: goto          221
     203: aload         9
     205: getstatic     #99                 // Field com/virtual/ssv/server/rs/client/entity/RsOperateLog.RESULT_FAILURE:Ljava/lang/Integer;
     208: invokevirtual #72                 // Method com/virtual/ssv/server/rs/client/entity/RsOperateLog.setResult:(Ljava/lang/Integer;)V
     211: aload         9
     213: aload         5
     215: invokevirtual #100                // Method com/virtual/ssv/server/entity/ResultJson.getFailtureReson:()Ljava/lang/String;
     218: invokevirtual #101                // Method com/virtual/ssv/server/rs/client/entity/RsOperateLog.setFailureReason:(Ljava/lang/String;)V
     221: aload_0
     222: getfield      #24                 // Field reqHandle:Lcom/virtual/ssv/server/rs/client/RequestHandle;
     225: aload         9
     227: invokevirtual #73                 // Method com/virtual/ssv/server/rs/client/RequestHandle.addUserLog:(Lcom/virtual/ssv/server/rs/client/entity/RsOperateLog;)Ljava/lang/Long;
     230: pop
     231: goto          315
     234: astore        6
     236: aload         6
     238: invokevirtual #76                 // Method com/virtual/common/AppException.getErrorCode:()I
     241: bipush        102
     243: if_icmpne     259
     246: aload         5
     248: bipush        102
     250: invokestatic  #50                 // Method com/virtual/common/ErrorCodes.getErrorMessage:(I)Ljava/lang/String;
     253: invokevirtual #40                 // Method com/virtual/ssv/server/entity/ResultJson.setErrorMsg:(Ljava/lang/String;)V
     256: goto          315
     259: aload         6
     261: invokevirtual #76                 // Method com/virtual/common/AppException.getErrorCode:()I
     264: bipush        103
     266: if_icmpne     282
     269: aload         5
     271: bipush        103
     273: invokestatic  #50                 // Method com/virtual/common/ErrorCodes.getErrorMessage:(I)Ljava/lang/String;
     276: invokevirtual #40                 // Method com/virtual/ssv/server/entity/ResultJson.setErrorMsg:(Ljava/lang/String;)V
     279: goto          315
     282: aload         6
     284: invokevirtual #76                 // Method com/virtual/common/AppException.getErrorCode:()I
     287: bipush        11
     289: if_icmpne     305
     292: aload         5
     294: bipush        11
     296: invokestatic  #50                 // Method com/virtual/common/ErrorCodes.getErrorMessage:(I)Ljava/lang/String;
     299: invokevirtual #40                 // Method com/virtual/ssv/server/entity/ResultJson.setErrorMsg:(Ljava/lang/String;)V
     302: goto          315
     305: aload         5
     307: aload         6
     309: invokevirtual #77                 // Method com/virtual/common/AppException.getMessage:()Ljava/lang/String;
     312: invokevirtual #40                 // Method com/virtual/ssv/server/entity/ResultJson.setErrorMsg:(Ljava/lang/String;)V
     315: aload_0
     316: aload_2
     317: aload_0
     318: getfield      #41                 // Field filterJson:Lcom/google/gson/Gson;
     321: aload         5
     323: invokevirtual #42                 // Method com/google/gson/Gson.toJson:(Ljava/lang/Object;)Ljava/lang/String;
     326: invokevirtual #27                 // Method write:(Ljavax/servlet/http/HttpServletResponse;Ljava/lang/String;)V
     329: return
    Exception table:
       from    to  target type
          18    54   234   Class com/virtual/common/AppException
          55   231   234   Class com/virtual/common/AppException

  private void apply(javax.servlet.http.HttpServletRequest, javax.servlet.http.HttpServletResponse, com.virtual.ssv.server.user.LoginInfo);
    Code:
       0: new           #28                 // class java/util/Date
       3: dup
       4: invokespecial #29                 // Method java/util/Date."<init>":()V
       7: astore        4
       9: new           #30                 // class com/virtual/ssv/server/entity/ResultJson
      12: dup
      13: invokespecial #31                 // Method com/virtual/ssv/server/entity/ResultJson."<init>":()V
      16: astore        5
      18: aload_1
      19: ldc           #22                 // String name
      21: invokeinterface #8,  2            // InterfaceMethod javax/servlet/http/HttpServletRequest.getParameter:(Ljava/lang/String;)Ljava/lang/String;
      26: astore        6
      28: aload_1
      29: ldc           #104                // String capacity
      31: invokeinterface #8,  2            // InterfaceMethod javax/servlet/http/HttpServletRequest.getParameter:(Ljava/lang/String;)Ljava/lang/String;
      36: astore        7
      38: aload         6
      40: invokestatic  #23                 // Method org/apache/commons/lang/StringUtils.isEmpty:(Ljava/lang/String;)Z
      43: ifne          54
      46: aload         7
      48: invokestatic  #23                 // Method org/apache/commons/lang/StringUtils.isEmpty:(Ljava/lang/String;)Z
      51: ifeq          55
      54: return
      55: new           #105                // class com/virtual/ssv/server/rs/client/entity/ApplyDisk
      58: dup
      59: invokespecial #106                // Method com/virtual/ssv/server/rs/client/entity/ApplyDisk."<init>":()V
      62: astore        8
      64: aload         8
      66: aload         7
      68: invokestatic  #107                // Method java/lang/Integer.valueOf:(Ljava/lang/String;)Ljava/lang/Integer;
      71: invokevirtual #108                // Method com/virtual/ssv/server/rs/client/entity/ApplyDisk.setCapacity:(Ljava/lang/Integer;)V
      74: aload         8
      76: aload         6
      78: invokevirtual #109                // Method com/virtual/ssv/server/rs/client/entity/ApplyDisk.setName:(Ljava/lang/String;)V
      81: aload         8
      83: aload_3
      84: invokevirtual #25                 // Method com/virtual/ssv/server/user/LoginInfo.getId:()Ljava/lang/Long;
      87: invokevirtual #110                // Method com/virtual/ssv/server/rs/client/entity/ApplyDisk.setUserId:(Ljava/lang/Long;)V
      90: aload         8
      92: aload_3
      93: invokevirtual #35                 // Method com/virtual/ssv/server/user/LoginInfo.getOrgId:()Ljava/lang/Long;
      96: invokevirtual #111                // Method com/virtual/ssv/server/rs/client/entity/ApplyDisk.setOrgId:(Ljava/lang/Long;)V
      99: aload         8
     101: iconst_0
     102: invokestatic  #64                 // Method java/lang/Integer.valueOf:(I)Ljava/lang/Integer;
     105: invokevirtual #112                // Method com/virtual/ssv/server/rs/client/entity/ApplyDisk.setState:(Ljava/lang/Integer;)V
     108: aload_0
     109: getfield      #24                 // Field reqHandle:Lcom/virtual/ssv/server/rs/client/RequestHandle;
     112: aload         8
     114: invokevirtual #113                // Method com/virtual/ssv/server/rs/client/RequestHandle.addCloudDisk:(Lcom/virtual/ssv/server/rs/client/entity/ApplyDisk;)Lcom/virtual/ssv/server/entity/ResultJson;
     117: astore        5
     119: new           #28                 // class java/util/Date
     122: dup
     123: invokespecial #29                 // Method java/util/Date."<init>":()V
     126: astore        9
     128: new           #53                 // class com/virtual/ssv/server/rs/client/entity/RsOperateLog
     131: dup
     132: invokespecial #54                 // Method com/virtual/ssv/server/rs/client/entity/RsOperateLog."<init>":()V
     135: astore        10
     137: aload         10
     139: aload_3
     140: invokevirtual #25                 // Method com/virtual/ssv/server/user/LoginInfo.getId:()Ljava/lang/Long;
     143: invokevirtual #55                 // Method com/virtual/ssv/server/rs/client/entity/RsOperateLog.setUserId:(Ljava/lang/Long;)V
     146: aload         10
     148: aload_3
     149: invokevirtual #35                 // Method com/virtual/ssv/server/user/LoginInfo.getOrgId:()Ljava/lang/Long;
     152: invokevirtual #56                 // Method com/virtual/ssv/server/rs/client/entity/RsOperateLog.setOrgId:(Ljava/lang/Long;)V
     155: aload         10
     157: aload_3
     158: invokevirtual #57                 // Method com/virtual/ssv/server/user/LoginInfo.getLoginName:()Ljava/lang/String;
     161: invokevirtual #58                 // Method com/virtual/ssv/server/rs/client/entity/RsOperateLog.setLoginName:(Ljava/lang/String;)V
     164: aload         10
     166: aload_3
     167: invokevirtual #59                 // Method com/virtual/ssv/server/user/LoginInfo.getUserName:()Ljava/lang/String;
     170: invokevirtual #60                 // Method com/virtual/ssv/server/rs/client/entity/RsOperateLog.setUserName:(Ljava/lang/String;)V
     173: aload         10
     175: aload_3
     176: invokevirtual #61                 // Method com/virtual/ssv/server/user/LoginInfo.getLoginIp:()Ljava/lang/String;
     179: invokevirtual #62                 // Method com/virtual/ssv/server/rs/client/entity/RsOperateLog.setAddress:(Ljava/lang/String;)V
     182: aload         10
     184: bipush        30
     186: invokestatic  #64                 // Method java/lang/Integer.valueOf:(I)Ljava/lang/Integer;
     189: invokevirtual #65                 // Method com/virtual/ssv/server/rs/client/entity/RsOperateLog.setCategory:(Ljava/lang/Integer;)V
     192: aload         10
     194: aload_0
     195: getfield      #66                 // Field logSm:Lcom/virtual/common/StringManager;
     198: ldc           #114                // String cloudDisk.apply.operation
     200: iconst_1
     201: anewarray     #45                 // class java/lang/Object
     204: dup
     205: iconst_0
     206: aload         6
     208: aastore
     209: invokevirtual #48                 // Method com/virtual/common/StringManager.getString:(Ljava/lang/String;[Ljava/lang/Object;)Ljava/lang/String;
     212: invokevirtual #68                 // Method com/virtual/ssv/server/rs/client/entity/RsOperateLog.setDescription:(Ljava/lang/String;)V
     215: aload         10
     217: aload         4
     219: invokevirtual #69                 // Method com/virtual/ssv/server/rs/client/entity/RsOperateLog.setStartTime:(Ljava/util/Date;)V
     222: aload         10
     224: aload         9
     226: invokevirtual #70                 // Method com/virtual/ssv/server/rs/client/entity/RsOperateLog.setEndTime:(Ljava/util/Date;)V
     229: aload         5
     231: invokevirtual #52                 // Method com/virtual/ssv/server/entity/ResultJson.isSuccess:()Z
     234: ifeq          248
     237: aload         10
     239: getstatic     #71                 // Field com/virtual/ssv/server/rs/client/entity/RsOperateLog.RESULT_SUCCESS:Ljava/lang/Integer;
     242: invokevirtual #72                 // Method com/virtual/ssv/server/rs/client/entity/RsOperateLog.setResult:(Ljava/lang/Integer;)V
     245: goto          266
     248: aload         10
     250: getstatic     #99                 // Field com/virtual/ssv/server/rs/client/entity/RsOperateLog.RESULT_FAILURE:Ljava/lang/Integer;
     253: invokevirtual #72                 // Method com/virtual/ssv/server/rs/client/entity/RsOperateLog.setResult:(Ljava/lang/Integer;)V
     256: aload         10
     258: aload         5
     260: invokevirtual #115                // Method com/virtual/ssv/server/entity/ResultJson.getMessage:()Ljava/lang/String;
     263: invokevirtual #101                // Method com/virtual/ssv/server/rs/client/entity/RsOperateLog.setFailureReason:(Ljava/lang/String;)V
     266: aload_0
     267: getfield      #24                 // Field reqHandle:Lcom/virtual/ssv/server/rs/client/RequestHandle;
     270: aload         10
     272: invokevirtual #73                 // Method com/virtual/ssv/server/rs/client/RequestHandle.addUserLog:(Lcom/virtual/ssv/server/rs/client/entity/RsOperateLog;)Ljava/lang/Long;
     275: pop
     276: goto          360
     279: astore        6
     281: aload         6
     283: invokevirtual #76                 // Method com/virtual/common/AppException.getErrorCode:()I
     286: bipush        102
     288: if_icmpne     304
     291: aload         5
     293: bipush        102
     295: invokestatic  #50                 // Method com/virtual/common/ErrorCodes.getErrorMessage:(I)Ljava/lang/String;
     298: invokevirtual #40                 // Method com/virtual/ssv/server/entity/ResultJson.setErrorMsg:(Ljava/lang/String;)V
     301: goto          360
     304: aload         6
     306: invokevirtual #76                 // Method com/virtual/common/AppException.getErrorCode:()I
     309: bipush        103
     311: if_icmpne     327
     314: aload         5
     316: bipush        103
     318: invokestatic  #50                 // Method com/virtual/common/ErrorCodes.getErrorMessage:(I)Ljava/lang/String;
     321: invokevirtual #40                 // Method com/virtual/ssv/server/entity/ResultJson.setErrorMsg:(Ljava/lang/String;)V
     324: goto          360
     327: aload         6
     329: invokevirtual #76                 // Method com/virtual/common/AppException.getErrorCode:()I
     332: bipush        11
     334: if_icmpne     350
     337: aload         5
     339: bipush        11
     341: invokestatic  #50                 // Method com/virtual/common/ErrorCodes.getErrorMessage:(I)Ljava/lang/String;
     344: invokevirtual #40                 // Method com/virtual/ssv/server/entity/ResultJson.setErrorMsg:(Ljava/lang/String;)V
     347: goto          360
     350: aload         5
     352: aload         6
     354: invokevirtual #77                 // Method com/virtual/common/AppException.getMessage:()Ljava/lang/String;
     357: invokevirtual #40                 // Method com/virtual/ssv/server/entity/ResultJson.setErrorMsg:(Ljava/lang/String;)V
     360: aload_0
     361: aload_2
     362: aload_0
     363: getfield      #41                 // Field filterJson:Lcom/google/gson/Gson;
     366: aload         5
     368: invokevirtual #42                 // Method com/google/gson/Gson.toJson:(Ljava/lang/Object;)Ljava/lang/String;
     371: invokevirtual #27                 // Method write:(Ljavax/servlet/http/HttpServletResponse;Ljava/lang/String;)V
     374: return
    Exception table:
       from    to  target type
          18    54   279   Class com/virtual/common/AppException
          55   276   279   Class com/virtual/common/AppException

  private void getList(javax.servlet.http.HttpServletRequest, javax.servlet.http.HttpServletResponse, com.virtual.ssv.server.user.LoginInfo);
    Code:
       0: aload_0
       1: aload_1
       2: invokevirtual #116                // Method getPagingConfig:(Ljavax/servlet/http/HttpServletRequest;)Lcom/virtual/ssv/server/entity/PagingLoadConfig;
       5: astore        4
       7: aload         4
       9: invokevirtual #117                // Method com/virtual/ssv/server/entity/PagingLoadConfig.getSortField:()Ljava/lang/String;
      12: invokestatic  #23                 // Method org/apache/commons/lang/StringUtils.isEmpty:(Ljava/lang/String;)Z
      15: ifeq          35
      18: aload         4
      20: ldc           #32                 // String id
      22: invokevirtual #118                // Method com/virtual/ssv/server/entity/PagingLoadConfig.setSortField:(Ljava/lang/String;)V
      25: aload         4
      27: ldc           #119                // String Desc
      29: invokevirtual #120                // Method com/virtual/ssv/server/entity/PagingLoadConfig.setSortDir:(Ljava/lang/String;)V
      32: goto          59
      35: aload         4
      37: invokevirtual #117                // Method com/virtual/ssv/server/entity/PagingLoadConfig.getSortField:()Ljava/lang/String;
      40: astore        5
      42: ldc           #22                 // String name
      44: aload         5
      46: invokevirtual #10                 // Method java/lang/String.equals:(Ljava/lang/Object;)Z
      49: ifeq          59
      52: aload         4
      54: ldc           #22                 // String name
      56: invokevirtual #118                // Method com/virtual/ssv/server/entity/PagingLoadConfig.setSortField:(Ljava/lang/String;)V
      59: new           #121                // class com/virtual/ssv/server/entity/CommonListJson
      62: dup
      63: invokespecial #122                // Method com/virtual/ssv/server/entity/CommonListJson."<init>":()V
      66: astore        5
      68: aload_0
      69: getfield      #24                 // Field reqHandle:Lcom/virtual/ssv/server/rs/client/RequestHandle;
      72: aload         4
      74: aload_3
      75: invokevirtual #25                 // Method com/virtual/ssv/server/user/LoginInfo.getId:()Ljava/lang/Long;
      78: aload_3
      79: invokevirtual #35                 // Method com/virtual/ssv/server/user/LoginInfo.getOrgId:()Ljava/lang/Long;
      82: aconst_null
      83: invokevirtual #123                // Method com/virtual/ssv/server/rs/client/RequestHandle.getCloudDiskList:(Lcom/virtual/ssv/server/entity/PagingLoadConfig;Ljava/lang/Long;Ljava/lang/Long;Ljava/lang/Long;)Lcom/virtual/ssv/server/entity/CommonListJson;
      86: astore        5
      88: goto          204
      91: astore        6
      93: aload         5
      95: aload_0
      96: getfield      #66                 // Field logSm:Lcom/virtual/common/StringManager;
      99: ldc           #124                // String operError
     101: invokevirtual #39                 // Method com/virtual/common/StringManager.getString:(Ljava/lang/String;)Ljava/lang/String;
     104: invokevirtual #125                // Method com/virtual/ssv/server/entity/CommonListJson.setTitle:(Ljava/lang/String;)V
     107: aload         6
     109: invokevirtual #76                 // Method com/virtual/common/AppException.getErrorCode:()I
     112: bipush        102
     114: if_icmpne     130
     117: aload         5
     119: bipush        102
     121: invokestatic  #50                 // Method com/virtual/common/ErrorCodes.getErrorMessage:(I)Ljava/lang/String;
     124: invokevirtual #126                // Method com/virtual/ssv/server/entity/CommonListJson.setMessage:(Ljava/lang/String;)V
     127: goto          186
     130: aload         6
     132: invokevirtual #76                 // Method com/virtual/common/AppException.getErrorCode:()I
     135: bipush        103
     137: if_icmpne     153
     140: aload         5
     142: bipush        103
     144: invokestatic  #50                 // Method com/virtual/common/ErrorCodes.getErrorMessage:(I)Ljava/lang/String;
     147: invokevirtual #126                // Method com/virtual/ssv/server/entity/CommonListJson.setMessage:(Ljava/lang/String;)V
     150: goto          186
     153: aload         6
     155: invokevirtual #76                 // Method com/virtual/common/AppException.getErrorCode:()I
     158: bipush        11
     160: if_icmpne     176
     163: aload         5
     165: bipush        11
     167: invokestatic  #50                 // Method com/virtual/common/ErrorCodes.getErrorMessage:(I)Ljava/lang/String;
     170: invokevirtual #126                // Method com/virtual/ssv/server/entity/CommonListJson.setMessage:(Ljava/lang/String;)V
     173: goto          186
     176: aload         5
     178: aload         6
     180: invokevirtual #77                 // Method com/virtual/common/AppException.getMessage:()Ljava/lang/String;
     183: invokevirtual #126                // Method com/virtual/ssv/server/entity/CommonListJson.setMessage:(Ljava/lang/String;)V
     186: aload         5
     188: iconst_0
     189: invokevirtual #127                // Method com/virtual/ssv/server/entity/CommonListJson.setState:(I)V
     192: aload         5
     194: new           #128                // class java/util/ArrayList
     197: dup
     198: invokespecial #129                // Method java/util/ArrayList."<init>":()V
     201: invokevirtual #130                // Method com/virtual/ssv/server/entity/CommonListJson.setRows:(Ljava/util/List;)V
     204: aload_0
     205: aload_2
     206: aload_0
     207: getfield      #131                // Field gson:Lcom/google/gson/Gson;
     210: aload         5
     212: invokevirtual #42                 // Method com/google/gson/Gson.toJson:(Ljava/lang/Object;)Ljava/lang/String;
     215: invokevirtual #27                 // Method write:(Ljavax/servlet/http/HttpServletResponse;Ljava/lang/String;)V
     218: return
    Exception table:
       from    to  target type
          68    88    91   Class com/virtual/common/AppException
}
