Compiled from "SessionFilter.java"
public class com.virtual.ssv.server.SessionFilter implements javax.servlet.Filter {
  protected static org.apache.commons.logging.Log log;

  protected com.virtual.ssv.server.rs.client.RequestHandle reqHandle;

  public com.virtual.ssv.server.SessionFilter();
    Code:
       0: aload_0
       1: invokespecial #1                  // Method java/lang/Object."<init>":()V
       4: aload_0
       5: aconst_null
       6: putfield      #2                  // Field reqHandle:Lcom/virtual/ssv/server/rs/client/RequestHandle;
       9: return

  public void destroy();
    Code:
       0: return

  public void doFilter(javax.servlet.ServletRequest, javax.servlet.ServletResponse, javax.servlet.FilterChain) throws java.io.IOException, javax.servlet.ServletException;
    Code:
       0: aload_1
       1: checkcast     #3                  // class javax/servlet/http/HttpServletRequest
       4: astore        4
       6: aload_2
       7: checkcast     #4                  // class javax/servlet/http/HttpServletResponse
      10: astore        5
      12: aload         4
      14: invokeinterface #5,  1            // InterfaceMethod javax/servlet/http/HttpServletRequest.getSession:()Ljavax/servlet/http/HttpSession;
      19: astore        6
      21: aload         6
      23: ldc           #6                  // String loginInfo
      25: invokeinterface #7,  2            // InterfaceMethod javax/servlet/http/HttpSession.getAttribute:(Ljava/lang/String;)Ljava/lang/Object;
      30: checkcast     #8                  // class com/virtual/ssv/server/user/LoginInfo
      33: astore        7
      35: aload         4
      37: ldc           #9                  // String x-requested-with
      39: invokeinterface #10,  2           // InterfaceMethod javax/servlet/http/HttpServletRequest.getHeader:(Ljava/lang/String;)Ljava/lang/String;
      44: ifnull        96
      47: aload         4
      49: ldc           #9                  // String x-requested-with
      51: invokeinterface #10,  2           // InterfaceMethod javax/servlet/http/HttpServletRequest.getHeader:(Ljava/lang/String;)Ljava/lang/String;
      56: ldc           #11                 // String XMLHttpRequest
      58: invokevirtual #12                 // Method java/lang/String.equalsIgnoreCase:(Ljava/lang/String;)Z
      61: ifeq          96
      64: aload         7
      66: ifnonnull     83
      69: aload         5
      71: ldc           #13                 // String session
      73: ldc           #14                 // String timeout
      75: invokeinterface #15,  3           // InterfaceMethod javax/servlet/http/HttpServletResponse.setHeader:(Ljava/lang/String;Ljava/lang/String;)V
      80: goto          178
      83: aload_3
      84: aload         4
      86: aload         5
      88: invokeinterface #16,  3           // InterfaceMethod javax/servlet/FilterChain.doFilter:(Ljavax/servlet/ServletRequest;Ljavax/servlet/ServletResponse;)V
      93: goto          178
      96: aload         7
      98: ifnull        112
     101: aload_3
     102: aload_1
     103: aload_2
     104: invokeinterface #16,  3           // InterfaceMethod javax/servlet/FilterChain.doFilter:(Ljavax/servlet/ServletRequest;Ljavax/servlet/ServletResponse;)V
     109: goto          178
     112: aconst_null
     113: astore        8
     115: aload         5
     117: ldc           #17                 // String UTF-8
     119: invokeinterface #18,  2           // InterfaceMethod javax/servlet/http/HttpServletResponse.setCharacterEncoding:(Ljava/lang/String;)V
     124: aload_2
     125: invokeinterface #19,  1           // InterfaceMethod javax/servlet/ServletResponse.getWriter:()Ljava/io/PrintWriter;
     130: astore        8
     132: aload         8
     134: ldc           #20                 // String invalid session
     136: invokevirtual #21                 // Method java/io/PrintWriter.println:(Ljava/lang/String;)V
     139: aload         8
     141: invokevirtual #22                 // Method java/io/PrintWriter.close:()V
     144: goto          178
     147: astore        9
     149: getstatic     #24                 // Field log:Lorg/apache/commons/logging/Log;
     152: aconst_null
     153: aload         9
     155: invokeinterface #25,  3           // InterfaceMethod org/apache/commons/logging/Log.error:(Ljava/lang/Object;Ljava/lang/Throwable;)V
     160: aload         8
     162: invokevirtual #22                 // Method java/io/PrintWriter.close:()V
     165: goto          178
     168: astore        10
     170: aload         8
     172: invokevirtual #22                 // Method java/io/PrintWriter.close:()V
     175: aload         10
     177: athrow
     178: return
    Exception table:
       from    to  target type
         124   139   147   Class java/io/IOException
         124   139   168   any
         147   160   168   any
         168   170   168   any

  public void init(javax.servlet.FilterConfig) throws javax.servlet.ServletException;
    Code:
       0: return

  static {};
    Code:
       0: ldc           #26                 // class com/virtual/ssv/server/SessionFilter
       2: invokestatic  #27                 // Method org/apache/commons/logging/LogFactory.getLog:(Ljava/lang/Class;)Lorg/apache/commons/logging/Log;
       5: putstatic     #24                 // Field log:Lorg/apache/commons/logging/Log;
       8: return
}
