Compiled from "WorkflowServlet.java"
public class com.virtual.ssv.server.workflow.WorkflowServlet extends com.virtual.ssv.server.BaseServlet {
  private static final long serialVersionUID;

  public com.virtual.ssv.server.workflow.WorkflowServlet();
    Code:
       0: aload_0
       1: invokespecial #1                  // Method com/virtual/ssv/server/BaseServlet."<init>":()V
       4: return

  protected void doGet(javax.servlet.http.HttpServletRequest, javax.servlet.http.HttpServletResponse) throws javax.servlet.ServletException, java.io.IOException;
    Code:
       0: aload_0
       1: aload_1
       2: aload_2
       3: invokevirtual #2                  // Method doPost:(Ljavax/servlet/http/HttpServletRequest;Ljavax/servlet/http/HttpServletResponse;)V
       6: return

  protected void doPost(javax.servlet.http.HttpServletRequest, javax.servlet.http.HttpServletResponse) throws javax.servlet.ServletException, java.io.IOException;
    Code:
       0: aload_1
       1: invokeinterface #3,  1            // InterfaceMethod javax/servlet/http/HttpServletRequest.getSession:()Ljavax/servlet/http/HttpSession;
       6: astore_3
       7: aload_3
       8: ldc           #4                  // String loginInfo
      10: invokeinterface #5,  2            // InterfaceMethod javax/servlet/http/HttpSession.getAttribute:(Ljava/lang/String;)Ljava/lang/Object;
      15: checkcast     #6                  // class com/virtual/ssv/server/user/LoginInfo
      18: astore        4
      20: aload         4
      22: ifnull        122
      25: aload_0
      26: aload_1
      27: aload_2
      28: invokevirtual #7                  // Method checkUserState:(Ljavax/servlet/http/HttpServletRequest;Ljavax/servlet/http/HttpServletResponse;)V
      31: aload_1
      32: ldc           #8                  // String way
      34: invokeinterface #9,  2            // InterfaceMethod javax/servlet/http/HttpServletRequest.getParameter:(Ljava/lang/String;)Ljava/lang/String;
      39: astore        5
      41: ldc           #10                 // String queryApprovalRecord
      43: aload         5
      45: invokevirtual #11                 // Method java/lang/String.equals:(Ljava/lang/Object;)Z
      48: ifeq          62
      51: aload_0
      52: aload_1
      53: aload_2
      54: aload         4
      56: invokespecial #12                 // Method queryApprovalRecords:(Ljavax/servlet/http/HttpServletRequest;Ljavax/servlet/http/HttpServletResponse;Lcom/virtual/ssv/server/user/LoginInfo;)V
      59: goto          122
      62: ldc           #13                 // String queryStepRecord
      64: aload         5
      66: invokevirtual #11                 // Method java/lang/String.equals:(Ljava/lang/Object;)Z
      69: ifeq          83
      72: aload_0
      73: aload_1
      74: aload_2
      75: aload         4
      77: invokespecial #14                 // Method queryStepRecord:(Ljavax/servlet/http/HttpServletRequest;Ljavax/servlet/http/HttpServletResponse;Lcom/virtual/ssv/server/user/LoginInfo;)V
      80: goto          122
      83: ldc           #15                 // String reminderSign
      85: aload         5
      87: invokevirtual #11                 // Method java/lang/String.equals:(Ljava/lang/Object;)Z
      90: ifeq          104
      93: aload_0
      94: aload_1
      95: aload_2
      96: aload         4
      98: invokespecial #16                 // Method reminderSign:(Ljavax/servlet/http/HttpServletRequest;Ljavax/servlet/http/HttpServletResponse;Lcom/virtual/ssv/server/user/LoginInfo;)V
     101: goto          122
     104: ldc           #17                 // String workflowDetail
     106: aload         5
     108: invokevirtual #11                 // Method java/lang/String.equals:(Ljava/lang/Object;)Z
     111: ifeq          122
     114: aload_0
     115: aload_1
     116: aload_2
     117: aload         4
     119: invokespecial #18                 // Method queryWorkflowDetail:(Ljavax/servlet/http/HttpServletRequest;Ljavax/servlet/http/HttpServletResponse;Lcom/virtual/ssv/server/user/LoginInfo;)V
     122: return

  private void queryWorkflowDetail(javax.servlet.http.HttpServletRequest, javax.servlet.http.HttpServletResponse, com.virtual.ssv.server.user.LoginInfo);
    Code:
       0: aload_1
       1: ldc           #19                 // String applyRecordId
       3: invokeinterface #9,  2            // InterfaceMethod javax/servlet/http/HttpServletRequest.getParameter:(Ljava/lang/String;)Ljava/lang/String;
       8: astore        4
      10: aload_1
      11: ldc           #20                 // String workflowId
      13: invokeinterface #9,  2            // InterfaceMethod javax/servlet/http/HttpServletRequest.getParameter:(Ljava/lang/String;)Ljava/lang/String;
      18: astore        5
      20: aload         4
      22: invokestatic  #21                 // Method java/lang/Long.parseLong:(Ljava/lang/String;)J
      25: invokestatic  #22                 // Method java/lang/Long.valueOf:(J)Ljava/lang/Long;
      28: astore        6
      30: aload         5
      32: invokestatic  #21                 // Method java/lang/Long.parseLong:(Ljava/lang/String;)J
      35: invokestatic  #22                 // Method java/lang/Long.valueOf:(J)Ljava/lang/Long;
      38: astore        7
      40: lconst_1
      41: aload         7
      43: invokevirtual #23                 // Method java/lang/Long.longValue:()J
      46: lcmp
      47: ifne          130
      50: aload_0
      51: getfield      #24                 // Field reqHandle:Lcom/virtual/ssv/server/rs/client/RequestHandle;
      54: aload         6
      56: invokevirtual #25                 // Method com/virtual/ssv/server/rs/client/RequestHandle.getVmWorkflow:(Ljava/lang/Long;)Lcom/virtual/ssv/server/rs/client/entity/VmWorkflow;
      59: astore        8
      61: aload         8
      63: invokevirtual #26                 // Method com/virtual/ssv/server/rs/client/entity/VmWorkflow.getExpireDate:()Ljava/util/Date;
      66: astore        9
      68: aload         9
      70: ifnull        96
      73: new           #27                 // class java/text/SimpleDateFormat
      76: dup
      77: ldc           #28                 // String yyyy-MM-dd
      79: invokespecial #29                 // Method java/text/SimpleDateFormat."<init>":(Ljava/lang/String;)V
      82: astore        10
      84: aload         8
      86: aload         10
      88: aload         9
      90: invokevirtual #30                 // Method java/text/SimpleDateFormat.format:(Ljava/util/Date;)Ljava/lang/String;
      93: invokevirtual #31                 // Method com/virtual/ssv/server/rs/client/entity/VmWorkflow.setExpireDateStr:(Ljava/lang/String;)V
      96: new           #32                 // class com/virtual/ssv/server/rs/client/entity/RpcResult
      99: dup
     100: aload         8
     102: invokespecial #33                 // Method com/virtual/ssv/server/rs/client/entity/RpcResult."<init>":(Ljava/lang/Object;)V
     105: astore        10
     107: aload_0
     108: aload         10
     110: invokespecial #34                 // Method checkResult:(Lcom/virtual/ssv/server/rs/client/entity/RpcResult;)V
     113: aload_0
     114: aload_2
     115: aload_0
     116: getfield      #35                 // Field gson:Lcom/google/gson/Gson;
     119: aload         10
     121: invokevirtual #36                 // Method com/google/gson/Gson.toJson:(Ljava/lang/Object;)Ljava/lang/String;
     124: invokevirtual #37                 // Method write:(Ljavax/servlet/http/HttpServletResponse;Ljava/lang/String;)V
     127: goto          260
     130: ldc2_w        #38                 // long 2l
     133: aload         7
     135: invokevirtual #23                 // Method java/lang/Long.longValue:()J
     138: lcmp
     139: ifne          191
     142: aload_0
     143: getfield      #24                 // Field reqHandle:Lcom/virtual/ssv/server/rs/client/RequestHandle;
     146: aload         6
     148: aload_3
     149: invokevirtual #40                 // Method com/virtual/ssv/server/user/LoginInfo.getOrgId:()Ljava/lang/Long;
     152: invokevirtual #41                 // Method com/virtual/ssv/server/rs/client/RequestHandle.getCloudDiskById:(Ljava/lang/Long;Ljava/lang/Long;)Lcom/virtual/ssv/server/rs/client/entity/ApplyDisk;
     155: astore        8
     157: new           #32                 // class com/virtual/ssv/server/rs/client/entity/RpcResult
     160: dup
     161: aload         8
     163: invokespecial #33                 // Method com/virtual/ssv/server/rs/client/entity/RpcResult."<init>":(Ljava/lang/Object;)V
     166: astore        9
     168: aload_0
     169: aload         9
     171: invokespecial #34                 // Method checkResult:(Lcom/virtual/ssv/server/rs/client/entity/RpcResult;)V
     174: aload_0
     175: aload_2
     176: aload_0
     177: getfield      #35                 // Field gson:Lcom/google/gson/Gson;
     180: aload         9
     182: invokevirtual #36                 // Method com/google/gson/Gson.toJson:(Ljava/lang/Object;)Ljava/lang/String;
     185: invokevirtual #37                 // Method write:(Ljavax/servlet/http/HttpServletResponse;Ljava/lang/String;)V
     188: goto          260
     191: ldc2_w        #42                 // long 3l
     194: aload         7
     196: invokevirtual #23                 // Method java/lang/Long.longValue:()J
     199: lcmp
     200: ifne          206
     203: goto          260
     206: ldc2_w        #44                 // long 4l
     209: aload         7
     211: invokevirtual #23                 // Method java/lang/Long.longValue:()J
     214: lcmp
     215: ifne          260
     218: aload_0
     219: getfield      #24                 // Field reqHandle:Lcom/virtual/ssv/server/rs/client/RequestHandle;
     222: aload         6
     224: invokevirtual #46                 // Method com/virtual/ssv/server/rs/client/RequestHandle.queryCloudBackUpStrategyWorkFlowById:(Ljava/lang/Long;)Lcom/virtual/ssv/server/rs/client/entity/RsCloudBackUpStrategyWorkFlow;
     227: astore        8
     229: new           #32                 // class com/virtual/ssv/server/rs/client/entity/RpcResult
     232: dup
     233: aload         8
     235: invokespecial #33                 // Method com/virtual/ssv/server/rs/client/entity/RpcResult."<init>":(Ljava/lang/Object;)V
     238: astore        9
     240: aload_0
     241: aload         9
     243: invokespecial #34                 // Method checkResult:(Lcom/virtual/ssv/server/rs/client/entity/RpcResult;)V
     246: aload_0
     247: aload_2
     248: aload_0
     249: getfield      #35                 // Field gson:Lcom/google/gson/Gson;
     252: aload         9
     254: invokevirtual #36                 // Method com/google/gson/Gson.toJson:(Ljava/lang/Object;)Ljava/lang/String;
     257: invokevirtual #37                 // Method write:(Ljavax/servlet/http/HttpServletResponse;Ljava/lang/String;)V
     260: return

  private void checkResult(com.virtual.ssv.server.rs.client.entity.RpcResult<?>);
    Code:
       0: aload_1
       1: invokevirtual #47                 // Method com/virtual/ssv/server/rs/client/entity/RpcResult.getData:()Ljava/lang/Object;
       4: ifnonnull     29
       7: aload_1
       8: iconst_1
       9: invokevirtual #49                 // Method com/virtual/ssv/server/rs/client/entity/RpcResult.setState:(I)V
      12: aload_1
      13: sipush        400
      16: invokevirtual #51                 // Method com/virtual/ssv/server/rs/client/entity/RpcResult.setErrorCode:(I)V
      19: aload_1
      20: sipush        400
      23: invokestatic  #52                 // Method com/virtual/common/ErrorCodes.getErrorMessage:(I)Ljava/lang/String;
      26: invokevirtual #53                 // Method com/virtual/ssv/server/rs/client/entity/RpcResult.setFailureMessage:(Ljava/lang/String;)V
      29: return

  private void queryStepRecord(javax.servlet.http.HttpServletRequest, javax.servlet.http.HttpServletResponse, com.virtual.ssv.server.user.LoginInfo);
    Code:
       0: new           #54                 // class com/virtual/ssv/server/entity/CommonListJson
       3: dup
       4: invokespecial #55                 // Method com/virtual/ssv/server/entity/CommonListJson."<init>":()V
       7: astore        4
       9: aload_1
      10: ldc           #19                 // String applyRecordId
      12: invokeinterface #9,  2            // InterfaceMethod javax/servlet/http/HttpServletRequest.getParameter:(Ljava/lang/String;)Ljava/lang/String;
      17: astore        5
      19: aload_1
      20: ldc           #20                 // String workflowId
      22: invokeinterface #9,  2            // InterfaceMethod javax/servlet/http/HttpServletRequest.getParameter:(Ljava/lang/String;)Ljava/lang/String;
      27: astore        6
      29: aconst_null
      30: astore        7
      32: aload_0
      33: getfield      #24                 // Field reqHandle:Lcom/virtual/ssv/server/rs/client/RequestHandle;
      36: aload         6
      38: aload         5
      40: invokevirtual #56                 // Method com/virtual/ssv/server/rs/client/RequestHandle.queryApprovalRecord:(Ljava/lang/String;Ljava/lang/String;)Ljava/util/List;
      43: astore        8
      45: aload         8
      47: ifnull        76
      50: aload         8
      52: invokeinterface #57,  1           // InterfaceMethod java/util/List.size:()I
      57: ifle          76
      60: aload         8
      62: iconst_0
      63: invokeinterface #58,  2           // InterfaceMethod java/util/List.get:(I)Ljava/lang/Object;
      68: checkcast     #59                 // class com/virtual/ssv/server/rs/client/entity/RsApprovalRecord
      71: invokevirtual #60                 // Method com/virtual/ssv/server/rs/client/entity/RsApprovalRecord.getVersion:()Ljava/lang/Integer;
      74: astore        7
      76: aload_0
      77: getfield      #24                 // Field reqHandle:Lcom/virtual/ssv/server/rs/client/RequestHandle;
      80: aload         6
      82: aload         7
      84: invokevirtual #61                 // Method com/virtual/ssv/server/rs/client/RequestHandle.queryStepRecord:(Ljava/lang/String;Ljava/lang/Integer;)Ljava/util/List;
      87: astore        9
      89: aload         9
      91: ifnull        678
      94: ldc2_w        #62                 // long -1l
      97: lstore        10
      99: new           #64                 // class java/util/HashMap
     102: dup
     103: invokespecial #65                 // Method java/util/HashMap."<init>":()V
     106: astore        12
     108: iconst_1
     109: istore        13
     111: aload         8
     113: ifnull        269
     116: aload         8
     118: invokeinterface #66,  1           // InterfaceMethod java/util/List.iterator:()Ljava/util/Iterator;
     123: astore        14
     125: aload         14
     127: invokeinterface #67,  1           // InterfaceMethod java/util/Iterator.hasNext:()Z
     132: ifeq          269
     135: aload         14
     137: invokeinterface #68,  1           // InterfaceMethod java/util/Iterator.next:()Ljava/lang/Object;
     142: checkcast     #59                 // class com/virtual/ssv/server/rs/client/entity/RsApprovalRecord
     145: astore        15
     147: aload         12
     149: aload         15
     151: invokevirtual #69                 // Method com/virtual/ssv/server/rs/client/entity/RsApprovalRecord.getWorkflowStepId:()Ljava/lang/Long;
     154: invokeinterface #70,  2           // InterfaceMethod java/util/Map.get:(Ljava/lang/Object;)Ljava/lang/Object;
     159: checkcast     #71                 // class java/util/List
     162: astore        16
     164: aload         16
     166: ifnonnull     193
     169: new           #72                 // class java/util/ArrayList
     172: dup
     173: invokespecial #73                 // Method java/util/ArrayList."<init>":()V
     176: astore        16
     178: aload         12
     180: aload         15
     182: invokevirtual #69                 // Method com/virtual/ssv/server/rs/client/entity/RsApprovalRecord.getWorkflowStepId:()Ljava/lang/Long;
     185: aload         16
     187: invokeinterface #74,  3           // InterfaceMethod java/util/Map.put:(Ljava/lang/Object;Ljava/lang/Object;)Ljava/lang/Object;
     192: pop
     193: aload         16
     195: aload         15
     197: invokeinterface #75,  2           // InterfaceMethod java/util/List.add:(Ljava/lang/Object;)Z
     202: pop
     203: aload         15
     205: invokevirtual #76                 // Method com/virtual/ssv/server/rs/client/entity/RsApprovalRecord.getStatus:()Ljava/lang/Integer;
     208: ifnull        266
     211: aload         15
     213: invokevirtual #76                 // Method com/virtual/ssv/server/rs/client/entity/RsApprovalRecord.getStatus:()Ljava/lang/Integer;
     216: invokevirtual #77                 // Method java/lang/Integer.intValue:()I
     219: iconst_1
     220: if_icmpne     266
     223: aload         15
     225: invokevirtual #78                 // Method com/virtual/ssv/server/rs/client/entity/RsApprovalRecord.getHandleResult:()Ljava/lang/Integer;
     228: ifnull        266
     231: aload         15
     233: invokevirtual #78                 // Method com/virtual/ssv/server/rs/client/entity/RsApprovalRecord.getHandleResult:()Ljava/lang/Integer;
     236: invokevirtual #77                 // Method java/lang/Integer.intValue:()I
     239: ifeq          266
     242: lload         10
     244: aload         15
     246: invokevirtual #69                 // Method com/virtual/ssv/server/rs/client/entity/RsApprovalRecord.getWorkflowStepId:()Ljava/lang/Long;
     249: invokevirtual #23                 // Method java/lang/Long.longValue:()J
     252: lcmp
     253: ifge          266
     256: aload         15
     258: invokevirtual #69                 // Method com/virtual/ssv/server/rs/client/entity/RsApprovalRecord.getWorkflowStepId:()Ljava/lang/Long;
     261: invokevirtual #23                 // Method java/lang/Long.longValue:()J
     264: lstore        10
     266: goto          125
     269: iconst_1
     270: istore        14
     272: aload         9
     274: invokeinterface #66,  1           // InterfaceMethod java/util/List.iterator:()Ljava/util/Iterator;
     279: astore        15
     281: aload         15
     283: invokeinterface #67,  1           // InterfaceMethod java/util/Iterator.hasNext:()Z
     288: ifeq          429
     291: aload         15
     293: invokeinterface #68,  1           // InterfaceMethod java/util/Iterator.next:()Ljava/lang/Object;
     298: checkcast     #79                 // class com/virtual/ssv/server/rs/client/entity/RsWorkflowStep
     301: astore        16
     303: aload         12
     305: aload         16
     307: invokevirtual #80                 // Method com/virtual/ssv/server/rs/client/entity/RsWorkflowStep.getId:()Ljava/lang/Long;
     310: invokeinterface #70,  2           // InterfaceMethod java/util/Map.get:(Ljava/lang/Object;)Ljava/lang/Object;
     315: checkcast     #71                 // class java/util/List
     318: astore        17
     320: aload         17
     322: ifnull        410
     325: iconst_0
     326: istore        14
     328: aload         17
     330: invokeinterface #66,  1           // InterfaceMethod java/util/List.iterator:()Ljava/util/Iterator;
     335: astore        18
     337: aload         18
     339: invokeinterface #67,  1           // InterfaceMethod java/util/Iterator.hasNext:()Z
     344: ifeq          407
     347: aload         18
     349: invokeinterface #68,  1           // InterfaceMethod java/util/Iterator.next:()Ljava/lang/Object;
     354: checkcast     #59                 // class com/virtual/ssv/server/rs/client/entity/RsApprovalRecord
     357: astore        19
     359: aload         19
     361: invokevirtual #76                 // Method com/virtual/ssv/server/rs/client/entity/RsApprovalRecord.getStatus:()Ljava/lang/Integer;
     364: ifnull        404
     367: aload         19
     369: invokevirtual #76                 // Method com/virtual/ssv/server/rs/client/entity/RsApprovalRecord.getStatus:()Ljava/lang/Integer;
     372: invokevirtual #77                 // Method java/lang/Integer.intValue:()I
     375: iconst_1
     376: if_icmpne     404
     379: aload         19
     381: invokevirtual #78                 // Method com/virtual/ssv/server/rs/client/entity/RsApprovalRecord.getHandleResult:()Ljava/lang/Integer;
     384: ifnull        398
     387: aload         19
     389: invokevirtual #78                 // Method com/virtual/ssv/server/rs/client/entity/RsApprovalRecord.getHandleResult:()Ljava/lang/Integer;
     392: invokevirtual #77                 // Method java/lang/Integer.intValue:()I
     395: ifne          404
     398: iconst_0
     399: istore        13
     401: goto          407
     404: goto          337
     407: goto          413
     410: iconst_0
     411: istore        13
     413: aload         16
     415: iload         13
     417: invokestatic  #81                 // Method java/lang/Boolean.valueOf:(Z)Ljava/lang/Boolean;
     420: invokevirtual #82                 // Method com/virtual/ssv/server/rs/client/entity/RsWorkflowStep.setIsHandle:(Ljava/lang/Boolean;)V
     423: iconst_1
     424: istore        13
     426: goto          281
     429: iload         14
     431: ifeq          654
     434: new           #72                 // class java/util/ArrayList
     437: dup
     438: invokespecial #73                 // Method java/util/ArrayList."<init>":()V
     441: astore        9
     443: aconst_null
     444: astore        15
     446: aload         12
     448: invokeinterface #83,  1           // InterfaceMethod java/util/Map.entrySet:()Ljava/util/Set;
     453: invokeinterface #84,  1           // InterfaceMethod java/util/Set.iterator:()Ljava/util/Iterator;
     458: astore        16
     460: aload         16
     462: invokeinterface #67,  1           // InterfaceMethod java/util/Iterator.hasNext:()Z
     467: ifeq          654
     470: aload         16
     472: invokeinterface #68,  1           // InterfaceMethod java/util/Iterator.next:()Ljava/lang/Object;
     477: checkcast     #85                 // class java/util/Map$Entry
     480: astore        17
     482: aload         17
     484: invokeinterface #86,  1           // InterfaceMethod java/util/Map$Entry.getValue:()Ljava/lang/Object;
     489: checkcast     #71                 // class java/util/List
     492: astore        18
     494: new           #79                 // class com/virtual/ssv/server/rs/client/entity/RsWorkflowStep
     497: dup
     498: invokespecial #87                 // Method com/virtual/ssv/server/rs/client/entity/RsWorkflowStep."<init>":()V
     501: astore        15
     503: aload         15
     505: aload         18
     507: iconst_0
     508: invokeinterface #58,  2           // InterfaceMethod java/util/List.get:(I)Ljava/lang/Object;
     513: checkcast     #59                 // class com/virtual/ssv/server/rs/client/entity/RsApprovalRecord
     516: invokevirtual #69                 // Method com/virtual/ssv/server/rs/client/entity/RsApprovalRecord.getWorkflowStepId:()Ljava/lang/Long;
     519: invokevirtual #88                 // Method com/virtual/ssv/server/rs/client/entity/RsWorkflowStep.setId:(Ljava/lang/Long;)V
     522: aload         15
     524: aload         18
     526: iconst_0
     527: invokeinterface #58,  2           // InterfaceMethod java/util/List.get:(I)Ljava/lang/Object;
     532: checkcast     #59                 // class com/virtual/ssv/server/rs/client/entity/RsApprovalRecord
     535: invokevirtual #89                 // Method com/virtual/ssv/server/rs/client/entity/RsApprovalRecord.getApprovalType:()Ljava/lang/Integer;
     538: invokevirtual #90                 // Method com/virtual/ssv/server/rs/client/entity/RsWorkflowStep.setType:(Ljava/lang/Integer;)V
     541: aload         15
     543: aload         18
     545: iconst_0
     546: invokeinterface #58,  2           // InterfaceMethod java/util/List.get:(I)Ljava/lang/Object;
     551: checkcast     #59                 // class com/virtual/ssv/server/rs/client/entity/RsApprovalRecord
     554: invokevirtual #91                 // Method com/virtual/ssv/server/rs/client/entity/RsApprovalRecord.getWorkflowId:()Ljava/lang/Long;
     557: invokevirtual #92                 // Method com/virtual/ssv/server/rs/client/entity/RsWorkflowStep.setWorkflowId:(Ljava/lang/Long;)V
     560: aload         18
     562: invokeinterface #66,  1           // InterfaceMethod java/util/List.iterator:()Ljava/util/Iterator;
     567: astore        19
     569: aload         19
     571: invokeinterface #67,  1           // InterfaceMethod java/util/Iterator.hasNext:()Z
     576: ifeq          628
     579: aload         19
     581: invokeinterface #68,  1           // InterfaceMethod java/util/Iterator.next:()Ljava/lang/Object;
     586: checkcast     #59                 // class com/virtual/ssv/server/rs/client/entity/RsApprovalRecord
     589: astore        20
     591: aload         20
     593: invokevirtual #76                 // Method com/virtual/ssv/server/rs/client/entity/RsApprovalRecord.getStatus:()Ljava/lang/Integer;
     596: ifnull        625
     599: aload         20
     601: invokevirtual #76                 // Method com/virtual/ssv/server/rs/client/entity/RsApprovalRecord.getStatus:()Ljava/lang/Integer;
     604: invokevirtual #77                 // Method java/lang/Integer.intValue:()I
     607: iconst_1
     608: if_icmpne     625
     611: aload         20
     613: invokevirtual #78                 // Method com/virtual/ssv/server/rs/client/entity/RsApprovalRecord.getHandleResult:()Ljava/lang/Integer;
     616: ifnonnull     625
     619: iconst_0
     620: istore        13
     622: goto          628
     625: goto          569
     628: aload         15
     630: iload         13
     632: invokestatic  #81                 // Method java/lang/Boolean.valueOf:(Z)Ljava/lang/Boolean;
     635: invokevirtual #82                 // Method com/virtual/ssv/server/rs/client/entity/RsWorkflowStep.setIsHandle:(Ljava/lang/Boolean;)V
     638: aload         9
     640: aload         15
     642: invokeinterface #75,  2           // InterfaceMethod java/util/List.add:(Ljava/lang/Object;)Z
     647: pop
     648: iconst_1
     649: istore        13
     651: goto          460
     654: new           #93                 // class com/virtual/ssv/server/workflow/WorkflowServlet$1
     657: dup
     658: aload_0
     659: invokespecial #94                 // Method com/virtual/ssv/server/workflow/WorkflowServlet$1."<init>":(Lcom/virtual/ssv/server/workflow/WorkflowServlet;)V
     662: astore        15
     664: aload         9
     666: aload         15
     668: invokestatic  #95                 // Method java/util/Collections.sort:(Ljava/util/List;Ljava/util/Comparator;)V
     671: aload         4
     673: aload         9
     675: invokevirtual #96                 // Method com/virtual/ssv/server/entity/CommonListJson.setRows:(Ljava/util/List;)V
     678: goto          794
     681: astore        5
     683: aload         4
     685: aload_0
     686: getfield      #98                 // Field logSm:Lcom/virtual/common/StringManager;
     689: ldc           #99                 // String operError
     691: invokevirtual #100                // Method com/virtual/common/StringManager.getString:(Ljava/lang/String;)Ljava/lang/String;
     694: invokevirtual #101                // Method com/virtual/ssv/server/entity/CommonListJson.setTitle:(Ljava/lang/String;)V
     697: aload         5
     699: invokevirtual #102                // Method com/virtual/common/AppException.getErrorCode:()I
     702: bipush        102
     704: if_icmpne     720
     707: aload         4
     709: bipush        102
     711: invokestatic  #52                 // Method com/virtual/common/ErrorCodes.getErrorMessage:(I)Ljava/lang/String;
     714: invokevirtual #103                // Method com/virtual/ssv/server/entity/CommonListJson.setMessage:(Ljava/lang/String;)V
     717: goto          776
     720: aload         5
     722: invokevirtual #102                // Method com/virtual/common/AppException.getErrorCode:()I
     725: bipush        103
     727: if_icmpne     743
     730: aload         4
     732: bipush        103
     734: invokestatic  #52                 // Method com/virtual/common/ErrorCodes.getErrorMessage:(I)Ljava/lang/String;
     737: invokevirtual #103                // Method com/virtual/ssv/server/entity/CommonListJson.setMessage:(Ljava/lang/String;)V
     740: goto          776
     743: aload         5
     745: invokevirtual #102                // Method com/virtual/common/AppException.getErrorCode:()I
     748: bipush        11
     750: if_icmpne     766
     753: aload         4
     755: bipush        11
     757: invokestatic  #52                 // Method com/virtual/common/ErrorCodes.getErrorMessage:(I)Ljava/lang/String;
     760: invokevirtual #103                // Method com/virtual/ssv/server/entity/CommonListJson.setMessage:(Ljava/lang/String;)V
     763: goto          776
     766: aload         4
     768: aload         5
     770: invokevirtual #104                // Method com/virtual/common/AppException.getMessage:()Ljava/lang/String;
     773: invokevirtual #103                // Method com/virtual/ssv/server/entity/CommonListJson.setMessage:(Ljava/lang/String;)V
     776: aload         4
     778: iconst_0
     779: invokevirtual #105                // Method com/virtual/ssv/server/entity/CommonListJson.setState:(I)V
     782: aload         4
     784: new           #72                 // class java/util/ArrayList
     787: dup
     788: invokespecial #73                 // Method java/util/ArrayList."<init>":()V
     791: invokevirtual #96                 // Method com/virtual/ssv/server/entity/CommonListJson.setRows:(Ljava/util/List;)V
     794: aload_0
     795: aload_2
     796: aload_0
     797: getfield      #35                 // Field gson:Lcom/google/gson/Gson;
     800: aload         4
     802: invokevirtual #36                 // Method com/google/gson/Gson.toJson:(Ljava/lang/Object;)Ljava/lang/String;
     805: invokevirtual #37                 // Method write:(Ljavax/servlet/http/HttpServletResponse;Ljava/lang/String;)V
     808: return
    Exception table:
       from    to  target type
           9   678   681   Class com/virtual/common/AppException

  private void queryApprovalRecords(javax.servlet.http.HttpServletRequest, javax.servlet.http.HttpServletResponse, com.virtual.ssv.server.user.LoginInfo);
    Code:
       0: new           #54                 // class com/virtual/ssv/server/entity/CommonListJson
       3: dup
       4: invokespecial #55                 // Method com/virtual/ssv/server/entity/CommonListJson."<init>":()V
       7: astore        4
       9: aload_1
      10: ldc           #19                 // String applyRecordId
      12: invokeinterface #9,  2            // InterfaceMethod javax/servlet/http/HttpServletRequest.getParameter:(Ljava/lang/String;)Ljava/lang/String;
      17: astore        5
      19: aload_1
      20: ldc           #20                 // String workflowId
      22: invokeinterface #9,  2            // InterfaceMethod javax/servlet/http/HttpServletRequest.getParameter:(Ljava/lang/String;)Ljava/lang/String;
      27: astore        6
      29: aload_0
      30: getfield      #24                 // Field reqHandle:Lcom/virtual/ssv/server/rs/client/RequestHandle;
      33: aload         6
      35: aload         5
      37: invokevirtual #56                 // Method com/virtual/ssv/server/rs/client/RequestHandle.queryApprovalRecord:(Ljava/lang/String;Ljava/lang/String;)Ljava/util/List;
      40: astore        7
      42: aload         4
      44: aload         7
      46: invokevirtual #96                 // Method com/virtual/ssv/server/entity/CommonListJson.setRows:(Ljava/util/List;)V
      49: goto          165
      52: astore        5
      54: aload         4
      56: aload_0
      57: getfield      #98                 // Field logSm:Lcom/virtual/common/StringManager;
      60: ldc           #99                 // String operError
      62: invokevirtual #100                // Method com/virtual/common/StringManager.getString:(Ljava/lang/String;)Ljava/lang/String;
      65: invokevirtual #101                // Method com/virtual/ssv/server/entity/CommonListJson.setTitle:(Ljava/lang/String;)V
      68: aload         5
      70: invokevirtual #102                // Method com/virtual/common/AppException.getErrorCode:()I
      73: bipush        102
      75: if_icmpne     91
      78: aload         4
      80: bipush        102
      82: invokestatic  #52                 // Method com/virtual/common/ErrorCodes.getErrorMessage:(I)Ljava/lang/String;
      85: invokevirtual #103                // Method com/virtual/ssv/server/entity/CommonListJson.setMessage:(Ljava/lang/String;)V
      88: goto          147
      91: aload         5
      93: invokevirtual #102                // Method com/virtual/common/AppException.getErrorCode:()I
      96: bipush        103
      98: if_icmpne     114
     101: aload         4
     103: bipush        103
     105: invokestatic  #52                 // Method com/virtual/common/ErrorCodes.getErrorMessage:(I)Ljava/lang/String;
     108: invokevirtual #103                // Method com/virtual/ssv/server/entity/CommonListJson.setMessage:(Ljava/lang/String;)V
     111: goto          147
     114: aload         5
     116: invokevirtual #102                // Method com/virtual/common/AppException.getErrorCode:()I
     119: bipush        11
     121: if_icmpne     137
     124: aload         4
     126: bipush        11
     128: invokestatic  #52                 // Method com/virtual/common/ErrorCodes.getErrorMessage:(I)Ljava/lang/String;
     131: invokevirtual #103                // Method com/virtual/ssv/server/entity/CommonListJson.setMessage:(Ljava/lang/String;)V
     134: goto          147
     137: aload         4
     139: aload         5
     141: invokevirtual #104                // Method com/virtual/common/AppException.getMessage:()Ljava/lang/String;
     144: invokevirtual #103                // Method com/virtual/ssv/server/entity/CommonListJson.setMessage:(Ljava/lang/String;)V
     147: aload         4
     149: iconst_0
     150: invokevirtual #105                // Method com/virtual/ssv/server/entity/CommonListJson.setState:(I)V
     153: aload         4
     155: new           #72                 // class java/util/ArrayList
     158: dup
     159: invokespecial #73                 // Method java/util/ArrayList."<init>":()V
     162: invokevirtual #96                 // Method com/virtual/ssv/server/entity/CommonListJson.setRows:(Ljava/util/List;)V
     165: aload_0
     166: aload_2
     167: aload_0
     168: getfield      #35                 // Field gson:Lcom/google/gson/Gson;
     171: aload         4
     173: invokevirtual #36                 // Method com/google/gson/Gson.toJson:(Ljava/lang/Object;)Ljava/lang/String;
     176: invokevirtual #37                 // Method write:(Ljavax/servlet/http/HttpServletResponse;Ljava/lang/String;)V
     179: return
    Exception table:
       from    to  target type
           9    49    52   Class com/virtual/common/AppException

  private void reminderSign(javax.servlet.http.HttpServletRequest, javax.servlet.http.HttpServletResponse, com.virtual.ssv.server.user.LoginInfo);
    Code:
       0: aload_1
       1: ldc           #19                 // String applyRecordId
       3: invokeinterface #9,  2            // InterfaceMethod javax/servlet/http/HttpServletRequest.getParameter:(Ljava/lang/String;)Ljava/lang/String;
       8: astore        4
      10: aload_1
      11: ldc           #20                 // String workflowId
      13: invokeinterface #9,  2            // InterfaceMethod javax/servlet/http/HttpServletRequest.getParameter:(Ljava/lang/String;)Ljava/lang/String;
      18: astore        5
      20: new           #106                // class java/util/Date
      23: dup
      24: invokespecial #107                // Method java/util/Date."<init>":()V
      27: astore        6
      29: new           #108                // class com/virtual/ssv/server/entity/ResultJson
      32: dup
      33: invokespecial #109                // Method com/virtual/ssv/server/entity/ResultJson."<init>":()V
      36: astore        7
      38: aload         4
      40: invokestatic  #110                // Method org/apache/commons/lang/StringUtils.isBlank:(Ljava/lang/String;)Z
      43: ifne          54
      46: aload         5
      48: invokestatic  #110                // Method org/apache/commons/lang/StringUtils.isBlank:(Ljava/lang/String;)Z
      51: ifeq          55
      54: return
      55: aload_1
      56: ldc           #111                // String name
      58: invokeinterface #9,  2            // InterfaceMethod javax/servlet/http/HttpServletRequest.getParameter:(Ljava/lang/String;)Ljava/lang/String;
      63: astore        8
      65: aload_0
      66: getfield      #24                 // Field reqHandle:Lcom/virtual/ssv/server/rs/client/RequestHandle;
      69: aload         5
      71: invokestatic  #21                 // Method java/lang/Long.parseLong:(Ljava/lang/String;)J
      74: invokestatic  #22                 // Method java/lang/Long.valueOf:(J)Ljava/lang/Long;
      77: aload         4
      79: invokestatic  #21                 // Method java/lang/Long.parseLong:(Ljava/lang/String;)J
      82: invokestatic  #22                 // Method java/lang/Long.valueOf:(J)Ljava/lang/Long;
      85: invokevirtual #112                // Method com/virtual/ssv/server/rs/client/RequestHandle.reminderSign:(Ljava/lang/Long;Ljava/lang/Long;)Lcom/virtual/ssv/server/entity/ResultJson;
      88: astore        7
      90: new           #106                // class java/util/Date
      93: dup
      94: invokespecial #107                // Method java/util/Date."<init>":()V
      97: astore        9
      99: new           #113                // class com/virtual/ssv/server/rs/client/entity/RsOperateLog
     102: dup
     103: invokespecial #114                // Method com/virtual/ssv/server/rs/client/entity/RsOperateLog."<init>":()V
     106: astore        10
     108: aload         10
     110: aload_3
     111: invokevirtual #115                // Method com/virtual/ssv/server/user/LoginInfo.getId:()Ljava/lang/Long;
     114: invokevirtual #116                // Method com/virtual/ssv/server/rs/client/entity/RsOperateLog.setUserId:(Ljava/lang/Long;)V
     117: aload         10
     119: aload_3
     120: invokevirtual #40                 // Method com/virtual/ssv/server/user/LoginInfo.getOrgId:()Ljava/lang/Long;
     123: invokevirtual #117                // Method com/virtual/ssv/server/rs/client/entity/RsOperateLog.setOrgId:(Ljava/lang/Long;)V
     126: aload         10
     128: aload_3
     129: invokevirtual #118                // Method com/virtual/ssv/server/user/LoginInfo.getLoginName:()Ljava/lang/String;
     132: invokevirtual #119                // Method com/virtual/ssv/server/rs/client/entity/RsOperateLog.setLoginName:(Ljava/lang/String;)V
     135: aload         10
     137: aload_3
     138: invokevirtual #120                // Method com/virtual/ssv/server/user/LoginInfo.getUserName:()Ljava/lang/String;
     141: invokevirtual #121                // Method com/virtual/ssv/server/rs/client/entity/RsOperateLog.setUserName:(Ljava/lang/String;)V
     144: aload         10
     146: aload_3
     147: invokevirtual #122                // Method com/virtual/ssv/server/user/LoginInfo.getLoginIp:()Ljava/lang/String;
     150: invokevirtual #123                // Method com/virtual/ssv/server/rs/client/entity/RsOperateLog.setAddress:(Ljava/lang/String;)V
     153: aload         10
     155: bipush        30
     157: invokestatic  #125                // Method java/lang/Integer.valueOf:(I)Ljava/lang/Integer;
     160: invokevirtual #126                // Method com/virtual/ssv/server/rs/client/entity/RsOperateLog.setCategory:(Ljava/lang/Integer;)V
     163: aload         10
     165: aload_0
     166: getfield      #98                 // Field logSm:Lcom/virtual/common/StringManager;
     169: ldc           #127                // String reminder.sign
     171: iconst_1
     172: anewarray     #128                // class java/lang/Object
     175: dup
     176: iconst_0
     177: aload         8
     179: aastore
     180: invokevirtual #129                // Method com/virtual/common/StringManager.getString:(Ljava/lang/String;[Ljava/lang/Object;)Ljava/lang/String;
     183: invokevirtual #130                // Method com/virtual/ssv/server/rs/client/entity/RsOperateLog.setDescription:(Ljava/lang/String;)V
     186: aload         10
     188: aload         6
     190: invokevirtual #131                // Method com/virtual/ssv/server/rs/client/entity/RsOperateLog.setStartTime:(Ljava/util/Date;)V
     193: aload         10
     195: aload         9
     197: invokevirtual #132                // Method com/virtual/ssv/server/rs/client/entity/RsOperateLog.setEndTime:(Ljava/util/Date;)V
     200: aload         7
     202: invokevirtual #133                // Method com/virtual/ssv/server/entity/ResultJson.isSuccess:()Z
     205: ifeq          219
     208: aload         10
     210: getstatic     #134                // Field com/virtual/ssv/server/rs/client/entity/RsOperateLog.RESULT_SUCCESS:Ljava/lang/Integer;
     213: invokevirtual #135                // Method com/virtual/ssv/server/rs/client/entity/RsOperateLog.setResult:(Ljava/lang/Integer;)V
     216: goto          237
     219: aload         10
     221: getstatic     #136                // Field com/virtual/ssv/server/rs/client/entity/RsOperateLog.RESULT_FAILURE:Ljava/lang/Integer;
     224: invokevirtual #135                // Method com/virtual/ssv/server/rs/client/entity/RsOperateLog.setResult:(Ljava/lang/Integer;)V
     227: aload         10
     229: aload         7
     231: invokevirtual #137                // Method com/virtual/ssv/server/entity/ResultJson.getMessage:()Ljava/lang/String;
     234: invokevirtual #138                // Method com/virtual/ssv/server/rs/client/entity/RsOperateLog.setFailureReason:(Ljava/lang/String;)V
     237: aload_0
     238: getfield      #24                 // Field reqHandle:Lcom/virtual/ssv/server/rs/client/RequestHandle;
     241: aload         10
     243: invokevirtual #139                // Method com/virtual/ssv/server/rs/client/RequestHandle.addUserLog:(Lcom/virtual/ssv/server/rs/client/entity/RsOperateLog;)Ljava/lang/Long;
     246: pop
     247: goto          331
     250: astore        8
     252: aload         8
     254: invokevirtual #102                // Method com/virtual/common/AppException.getErrorCode:()I
     257: bipush        102
     259: if_icmpne     275
     262: aload         7
     264: bipush        102
     266: invokestatic  #52                 // Method com/virtual/common/ErrorCodes.getErrorMessage:(I)Ljava/lang/String;
     269: invokevirtual #140                // Method com/virtual/ssv/server/entity/ResultJson.setErrorMsg:(Ljava/lang/String;)V
     272: goto          331
     275: aload         8
     277: invokevirtual #102                // Method com/virtual/common/AppException.getErrorCode:()I
     280: bipush        103
     282: if_icmpne     298
     285: aload         7
     287: bipush        103
     289: invokestatic  #52                 // Method com/virtual/common/ErrorCodes.getErrorMessage:(I)Ljava/lang/String;
     292: invokevirtual #140                // Method com/virtual/ssv/server/entity/ResultJson.setErrorMsg:(Ljava/lang/String;)V
     295: goto          331
     298: aload         8
     300: invokevirtual #102                // Method com/virtual/common/AppException.getErrorCode:()I
     303: bipush        11
     305: if_icmpne     321
     308: aload         7
     310: bipush        11
     312: invokestatic  #52                 // Method com/virtual/common/ErrorCodes.getErrorMessage:(I)Ljava/lang/String;
     315: invokevirtual #140                // Method com/virtual/ssv/server/entity/ResultJson.setErrorMsg:(Ljava/lang/String;)V
     318: goto          331
     321: aload         7
     323: aload         8
     325: invokevirtual #104                // Method com/virtual/common/AppException.getMessage:()Ljava/lang/String;
     328: invokevirtual #140                // Method com/virtual/ssv/server/entity/ResultJson.setErrorMsg:(Ljava/lang/String;)V
     331: aload_0
     332: aload_2
     333: aload_0
     334: getfield      #141                // Field filterJson:Lcom/google/gson/Gson;
     337: aload         7
     339: invokevirtual #36                 // Method com/google/gson/Gson.toJson:(Ljava/lang/Object;)Ljava/lang/String;
     342: invokevirtual #37                 // Method write:(Ljavax/servlet/http/HttpServletResponse;Ljava/lang/String;)V
     345: return
    Exception table:
       from    to  target type
          38    54   250   Class com/virtual/common/AppException
          55   247   250   Class com/virtual/common/AppException
}
