Compiled from "BackupServlet.java"
public class com.virtual.ssv.server.backup.BackupServlet extends com.virtual.ssv.server.BaseServlet {
  private static final long serialVersionUID;

  public com.virtual.ssv.server.backup.BackupServlet();
    Code:
       0: aload_0
       1: invokespecial #1                  // Method com/virtual/ssv/server/BaseServlet."<init>":()V
       4: return

  protected void doGet(javax.servlet.http.HttpServletRequest, javax.servlet.http.HttpServletResponse) throws javax.servlet.ServletException, java.io.IOException;
    Code:
       0: aload_1
       1: invokeinterface #2,  1            // InterfaceMethod javax/servlet/http/HttpServletRequest.getSession:()Ljavax/servlet/http/HttpSession;
       6: astore_3
       7: aload_3
       8: ldc           #3                  // String loginInfo
      10: invokeinterface #4,  2            // InterfaceMethod javax/servlet/http/HttpSession.getAttribute:(Ljava/lang/String;)Ljava/lang/Object;
      15: checkcast     #5                  // class com/virtual/ssv/server/user/LoginInfo
      18: astore        4
      20: aload         4
      22: ifnull        370
      25: aload_0
      26: aload_1
      27: aload_2
      28: invokevirtual #6                  // Method checkUserState:(Ljavax/servlet/http/HttpServletRequest;Ljavax/servlet/http/HttpServletResponse;)V
      31: aload_1
      32: ldc           #7                  // String way
      34: invokeinterface #8,  2            // InterfaceMethod javax/servlet/http/HttpServletRequest.getParameter:(Ljava/lang/String;)Ljava/lang/String;
      39: astore        5
      41: ldc           #9                  // String list
      43: aload         5
      45: invokevirtual #10                 // Method java/lang/String.equals:(Ljava/lang/Object;)Z
      48: ifeq          62
      51: aload_0
      52: aload_1
      53: aload_2
      54: aload         4
      56: invokespecial #11                 // Method getBackupList:(Ljavax/servlet/http/HttpServletRequest;Ljavax/servlet/http/HttpServletResponse;Lcom/virtual/ssv/server/user/LoginInfo;)V
      59: goto          370
      62: ldc           #12                 // String restore
      64: aload         5
      66: invokevirtual #10                 // Method java/lang/String.equals:(Ljava/lang/Object;)Z
      69: ifeq          83
      72: aload_0
      73: aload_1
      74: aload_2
      75: aload         4
      77: invokespecial #13                 // Method restore:(Ljavax/servlet/http/HttpServletRequest;Ljavax/servlet/http/HttpServletResponse;Lcom/virtual/ssv/server/user/LoginInfo;)V
      80: goto          370
      83: ldc           #14                 // String delete
      85: aload         5
      87: invokevirtual #10                 // Method java/lang/String.equals:(Ljava/lang/Object;)Z
      90: ifeq          104
      93: aload_0
      94: aload_1
      95: aload_2
      96: aload         4
      98: invokespecial #15                 // Method delete:(Ljavax/servlet/http/HttpServletRequest;Ljavax/servlet/http/HttpServletResponse;Lcom/virtual/ssv/server/user/LoginInfo;)V
     101: goto          370
     104: ldc           #16                 // String listStrategy
     106: aload         5
     108: invokevirtual #10                 // Method java/lang/String.equals:(Ljava/lang/Object;)Z
     111: ifeq          125
     114: aload_0
     115: aload_1
     116: aload_2
     117: aload         4
     119: invokespecial #17                 // Method getBackupStrategyList:(Ljavax/servlet/http/HttpServletRequest;Ljavax/servlet/http/HttpServletResponse;Lcom/virtual/ssv/server/user/LoginInfo;)V
     122: goto          370
     125: ldc           #18                 // String applyStrategy
     127: aload         5
     129: invokevirtual #10                 // Method java/lang/String.equals:(Ljava/lang/Object;)Z
     132: ifeq          146
     135: aload_0
     136: aload_1
     137: aload_2
     138: aload         4
     140: invokespecial #19                 // Method applyBackupStrategy:(Ljavax/servlet/http/HttpServletRequest;Ljavax/servlet/http/HttpServletResponse;Lcom/virtual/ssv/server/user/LoginInfo;)V
     143: goto          370
     146: ldc           #20                 // String startStrategy
     148: aload         5
     150: invokevirtual #10                 // Method java/lang/String.equals:(Ljava/lang/Object;)Z
     153: ifeq          169
     156: aload_0
     157: aload_1
     158: aload_2
     159: ldc           #21                 // String start
     161: aload         4
     163: invokespecial #22                 // Method handle:(Ljavax/servlet/http/HttpServletRequest;Ljavax/servlet/http/HttpServletResponse;Ljava/lang/String;Lcom/virtual/ssv/server/user/LoginInfo;)V
     166: goto          370
     169: ldc           #23                 // String stopStrategy
     171: aload         5
     173: invokevirtual #10                 // Method java/lang/String.equals:(Ljava/lang/Object;)Z
     176: ifeq          192
     179: aload_0
     180: aload_1
     181: aload_2
     182: ldc           #24                 // String stop
     184: aload         4
     186: invokespecial #22                 // Method handle:(Ljavax/servlet/http/HttpServletRequest;Ljavax/servlet/http/HttpServletResponse;Ljava/lang/String;Lcom/virtual/ssv/server/user/LoginInfo;)V
     189: goto          370
     192: ldc           #25                 // String modifyStrategy
     194: aload         5
     196: invokevirtual #10                 // Method java/lang/String.equals:(Ljava/lang/Object;)Z
     199: ifeq          205
     202: goto          370
     205: ldc           #26                 // String deleStrategy
     207: aload         5
     209: invokevirtual #10                 // Method java/lang/String.equals:(Ljava/lang/Object;)Z
     212: ifeq          226
     215: aload_0
     216: aload_1
     217: aload_2
     218: aload         4
     220: invokespecial #27                 // Method deleteStrategy:(Ljavax/servlet/http/HttpServletRequest;Ljavax/servlet/http/HttpServletResponse;Lcom/virtual/ssv/server/user/LoginInfo;)V
     223: goto          370
     226: ldc           #28                 // String listStrategyVm
     228: aload         5
     230: invokevirtual #10                 // Method java/lang/String.equals:(Ljava/lang/Object;)Z
     233: ifeq          247
     236: aload_0
     237: aload_1
     238: aload_2
     239: aload         4
     241: invokespecial #29                 // Method getBackupStrategyVmList:(Ljavax/servlet/http/HttpServletRequest;Ljavax/servlet/http/HttpServletResponse;Lcom/virtual/ssv/server/user/LoginInfo;)V
     244: goto          370
     247: ldc           #30                 // String listStrategyHistory
     249: aload         5
     251: invokevirtual #10                 // Method java/lang/String.equals:(Ljava/lang/Object;)Z
     254: ifeq          268
     257: aload_0
     258: aload_1
     259: aload_2
     260: aload         4
     262: invokespecial #31                 // Method getBackupStrategyWorkFlow:(Ljavax/servlet/http/HttpServletRequest;Ljavax/servlet/http/HttpServletResponse;Lcom/virtual/ssv/server/user/LoginInfo;)V
     265: goto          370
     268: ldc           #32                 // String revokeStrategyHistory
     270: aload         5
     272: invokevirtual #10                 // Method java/lang/String.equals:(Ljava/lang/Object;)Z
     275: ifeq          289
     278: aload_0
     279: aload_1
     280: aload_2
     281: aload         4
     283: invokespecial #33                 // Method revokeStrategyWorkFlow:(Ljavax/servlet/http/HttpServletRequest;Ljavax/servlet/http/HttpServletResponse;Lcom/virtual/ssv/server/user/LoginInfo;)V
     286: goto          370
     289: ldc           #34                 // String checkStrategyReName
     291: aload         5
     293: invokevirtual #10                 // Method java/lang/String.equals:(Ljava/lang/Object;)Z
     296: ifeq          310
     299: aload_0
     300: aload_1
     301: aload_2
     302: aload         4
     304: invokespecial #35                 // Method checkStrategyReName:(Ljavax/servlet/http/HttpServletRequest;Ljavax/servlet/http/HttpServletResponse;Lcom/virtual/ssv/server/user/LoginInfo;)V
     307: goto          370
     310: ldc           #36                 // String queryStrategyInfo
     312: aload         5
     314: invokevirtual #10                 // Method java/lang/String.equals:(Ljava/lang/Object;)Z
     317: ifeq          331
     320: aload_0
     321: aload_1
     322: aload_2
     323: aload         4
     325: invokespecial #37                 // Method getBackupStrategyInfo:(Ljavax/servlet/http/HttpServletRequest;Ljavax/servlet/http/HttpServletResponse;Lcom/virtual/ssv/server/user/LoginInfo;)V
     328: goto          370
     331: ldc           #38                 // String queryStrategyWorkFlowInfo
     333: aload         5
     335: invokevirtual #10                 // Method java/lang/String.equals:(Ljava/lang/Object;)Z
     338: ifeq          352
     341: aload_0
     342: aload_1
     343: aload_2
     344: aload         4
     346: invokespecial #39                 // Method getBackupStrategyWorkFlowInfo:(Ljavax/servlet/http/HttpServletRequest;Ljavax/servlet/http/HttpServletResponse;Lcom/virtual/ssv/server/user/LoginInfo;)V
     349: goto          370
     352: ldc           #40                 // String queryStrategyVmList
     354: aload         5
     356: invokevirtual #10                 // Method java/lang/String.equals:(Ljava/lang/Object;)Z
     359: ifeq          370
     362: aload_0
     363: aload_1
     364: aload_2
     365: aload         4
     367: invokespecial #41                 // Method queryStrategyVmList:(Ljavax/servlet/http/HttpServletRequest;Ljavax/servlet/http/HttpServletResponse;Lcom/virtual/ssv/server/user/LoginInfo;)V
     370: return

  private void delete(javax.servlet.http.HttpServletRequest, javax.servlet.http.HttpServletResponse, com.virtual.ssv.server.user.LoginInfo);
    Code:
       0: new           #42                 // class java/util/Date
       3: dup
       4: invokespecial #43                 // Method java/util/Date."<init>":()V
       7: astore        4
       9: new           #44                 // class com/virtual/ssv/server/entity/ResultJson
      12: dup
      13: invokespecial #45                 // Method com/virtual/ssv/server/entity/ResultJson."<init>":()V
      16: astore        5
      18: aload_1
      19: ldc           #46                 // String id
      21: invokeinterface #8,  2            // InterfaceMethod javax/servlet/http/HttpServletRequest.getParameter:(Ljava/lang/String;)Ljava/lang/String;
      26: astore        6
      28: aload_1
      29: ldc           #47                 // String domainName
      31: invokeinterface #8,  2            // InterfaceMethod javax/servlet/http/HttpServletRequest.getParameter:(Ljava/lang/String;)Ljava/lang/String;
      36: astore        7
      38: aload_1
      39: ldc           #48                 // String name
      41: invokeinterface #8,  2            // InterfaceMethod javax/servlet/http/HttpServletRequest.getParameter:(Ljava/lang/String;)Ljava/lang/String;
      46: astore        8
      48: aload         6
      50: invokestatic  #49                 // Method org/apache/commons/lang/StringUtils.isNotEmpty:(Ljava/lang/String;)Z
      53: ifeq          236
      56: aload_0
      57: getfield      #50                 // Field reqHandle:Lcom/virtual/ssv/server/rs/client/RequestHandle;
      60: aload         6
      62: invokestatic  #51                 // Method java/lang/Long.valueOf:(Ljava/lang/String;)Ljava/lang/Long;
      65: aload         7
      67: aload         8
      69: invokevirtual #52                 // Method com/virtual/ssv/server/rs/client/RequestHandle.deleteBackupHistory:(Ljava/lang/Long;Ljava/lang/String;Ljava/lang/String;)Lcom/virtual/ssv/server/entity/ResultJson;
      72: astore        5
      74: new           #42                 // class java/util/Date
      77: dup
      78: invokespecial #43                 // Method java/util/Date."<init>":()V
      81: astore        9
      83: new           #53                 // class com/virtual/ssv/server/rs/client/entity/RsOperateLog
      86: dup
      87: invokespecial #54                 // Method com/virtual/ssv/server/rs/client/entity/RsOperateLog."<init>":()V
      90: astore        10
      92: aload         10
      94: aload_3
      95: invokevirtual #55                 // Method com/virtual/ssv/server/user/LoginInfo.getId:()Ljava/lang/Long;
      98: invokevirtual #56                 // Method com/virtual/ssv/server/rs/client/entity/RsOperateLog.setUserId:(Ljava/lang/Long;)V
     101: aload         10
     103: aload_3
     104: invokevirtual #57                 // Method com/virtual/ssv/server/user/LoginInfo.getOrgId:()Ljava/lang/Long;
     107: invokevirtual #58                 // Method com/virtual/ssv/server/rs/client/entity/RsOperateLog.setOrgId:(Ljava/lang/Long;)V
     110: aload         10
     112: aload_3
     113: invokevirtual #59                 // Method com/virtual/ssv/server/user/LoginInfo.getLoginName:()Ljava/lang/String;
     116: invokevirtual #60                 // Method com/virtual/ssv/server/rs/client/entity/RsOperateLog.setLoginName:(Ljava/lang/String;)V
     119: aload         10
     121: aload_3
     122: invokevirtual #61                 // Method com/virtual/ssv/server/user/LoginInfo.getUserName:()Ljava/lang/String;
     125: invokevirtual #62                 // Method com/virtual/ssv/server/rs/client/entity/RsOperateLog.setUserName:(Ljava/lang/String;)V
     128: aload         10
     130: aload_3
     131: invokevirtual #63                 // Method com/virtual/ssv/server/user/LoginInfo.getLoginIp:()Ljava/lang/String;
     134: invokevirtual #64                 // Method com/virtual/ssv/server/rs/client/entity/RsOperateLog.setAddress:(Ljava/lang/String;)V
     137: aload         10
     139: bipush        10
     141: invokestatic  #66                 // Method java/lang/Integer.valueOf:(I)Ljava/lang/Integer;
     144: invokevirtual #67                 // Method com/virtual/ssv/server/rs/client/entity/RsOperateLog.setCategory:(Ljava/lang/Integer;)V
     147: aload         10
     149: aload_0
     150: getfield      #68                 // Field logSm:Lcom/virtual/common/StringManager;
     153: ldc           #69                 // String domainBackup.delete.task
     155: iconst_2
     156: anewarray     #70                 // class java/lang/Object
     159: dup
     160: iconst_0
     161: aload         7
     163: aastore
     164: dup
     165: iconst_1
     166: aload         8
     168: aastore
     169: invokevirtual #71                 // Method com/virtual/common/StringManager.getString:(Ljava/lang/String;[Ljava/lang/Object;)Ljava/lang/String;
     172: invokevirtual #72                 // Method com/virtual/ssv/server/rs/client/entity/RsOperateLog.setDescription:(Ljava/lang/String;)V
     175: aload         10
     177: aload         4
     179: invokevirtual #73                 // Method com/virtual/ssv/server/rs/client/entity/RsOperateLog.setStartTime:(Ljava/util/Date;)V
     182: aload         10
     184: aload         9
     186: invokevirtual #74                 // Method com/virtual/ssv/server/rs/client/entity/RsOperateLog.setEndTime:(Ljava/util/Date;)V
     189: aload         5
     191: invokevirtual #75                 // Method com/virtual/ssv/server/entity/ResultJson.isSuccess:()Z
     194: ifeq          208
     197: aload         10
     199: getstatic     #76                 // Field com/virtual/ssv/server/rs/client/entity/RsOperateLog.RESULT_SUCCESS:Ljava/lang/Integer;
     202: invokevirtual #77                 // Method com/virtual/ssv/server/rs/client/entity/RsOperateLog.setResult:(Ljava/lang/Integer;)V
     205: goto          226
     208: aload         10
     210: getstatic     #78                 // Field com/virtual/ssv/server/rs/client/entity/RsOperateLog.RESULT_FAILURE:Ljava/lang/Integer;
     213: invokevirtual #77                 // Method com/virtual/ssv/server/rs/client/entity/RsOperateLog.setResult:(Ljava/lang/Integer;)V
     216: aload         10
     218: aload         5
     220: invokevirtual #79                 // Method com/virtual/ssv/server/entity/ResultJson.getMessage:()Ljava/lang/String;
     223: invokevirtual #80                 // Method com/virtual/ssv/server/rs/client/entity/RsOperateLog.setFailureReason:(Ljava/lang/String;)V
     226: aload_0
     227: getfield      #50                 // Field reqHandle:Lcom/virtual/ssv/server/rs/client/RequestHandle;
     230: aload         10
     232: invokevirtual #81                 // Method com/virtual/ssv/server/rs/client/RequestHandle.addUserLog:(Lcom/virtual/ssv/server/rs/client/entity/RsOperateLog;)Ljava/lang/Long;
     235: pop
     236: goto          320
     239: astore        6
     241: aload         6
     243: invokevirtual #83                 // Method com/virtual/common/AppException.getErrorCode:()I
     246: bipush        102
     248: if_icmpne     264
     251: aload         5
     253: bipush        102
     255: invokestatic  #85                 // Method com/virtual/common/ErrorCodes.getErrorMessage:(I)Ljava/lang/String;
     258: invokevirtual #86                 // Method com/virtual/ssv/server/entity/ResultJson.setErrorMsg:(Ljava/lang/String;)V
     261: goto          320
     264: aload         6
     266: invokevirtual #83                 // Method com/virtual/common/AppException.getErrorCode:()I
     269: bipush        103
     271: if_icmpne     287
     274: aload         5
     276: bipush        103
     278: invokestatic  #85                 // Method com/virtual/common/ErrorCodes.getErrorMessage:(I)Ljava/lang/String;
     281: invokevirtual #86                 // Method com/virtual/ssv/server/entity/ResultJson.setErrorMsg:(Ljava/lang/String;)V
     284: goto          320
     287: aload         6
     289: invokevirtual #83                 // Method com/virtual/common/AppException.getErrorCode:()I
     292: bipush        11
     294: if_icmpne     310
     297: aload         5
     299: bipush        11
     301: invokestatic  #85                 // Method com/virtual/common/ErrorCodes.getErrorMessage:(I)Ljava/lang/String;
     304: invokevirtual #86                 // Method com/virtual/ssv/server/entity/ResultJson.setErrorMsg:(Ljava/lang/String;)V
     307: goto          320
     310: aload         5
     312: aload         6
     314: invokevirtual #87                 // Method com/virtual/common/AppException.getMessage:()Ljava/lang/String;
     317: invokevirtual #86                 // Method com/virtual/ssv/server/entity/ResultJson.setErrorMsg:(Ljava/lang/String;)V
     320: aload_0
     321: aload_2
     322: aload_0
     323: getfield      #88                 // Field filterJson:Lcom/google/gson/Gson;
     326: aload         5
     328: invokevirtual #89                 // Method com/google/gson/Gson.toJson:(Ljava/lang/Object;)Ljava/lang/String;
     331: invokevirtual #90                 // Method write:(Ljavax/servlet/http/HttpServletResponse;Ljava/lang/String;)V
     334: return
    Exception table:
       from    to  target type
          18   236   239   Class com/virtual/common/AppException

  private void restore(javax.servlet.http.HttpServletRequest, javax.servlet.http.HttpServletResponse, com.virtual.ssv.server.user.LoginInfo);
    Code:
       0: new           #42                 // class java/util/Date
       3: dup
       4: invokespecial #43                 // Method java/util/Date."<init>":()V
       7: astore        4
       9: new           #44                 // class com/virtual/ssv/server/entity/ResultJson
      12: dup
      13: invokespecial #45                 // Method com/virtual/ssv/server/entity/ResultJson."<init>":()V
      16: astore        5
      18: aload_1
      19: ldc           #46                 // String id
      21: invokeinterface #8,  2            // InterfaceMethod javax/servlet/http/HttpServletRequest.getParameter:(Ljava/lang/String;)Ljava/lang/String;
      26: astore        6
      28: aload_1
      29: ldc           #91                 // String domainId
      31: invokeinterface #8,  2            // InterfaceMethod javax/servlet/http/HttpServletRequest.getParameter:(Ljava/lang/String;)Ljava/lang/String;
      36: astore        7
      38: aload_1
      39: ldc           #47                 // String domainName
      41: invokeinterface #8,  2            // InterfaceMethod javax/servlet/http/HttpServletRequest.getParameter:(Ljava/lang/String;)Ljava/lang/String;
      46: astore        8
      48: aload_1
      49: ldc           #48                 // String name
      51: invokeinterface #8,  2            // InterfaceMethod javax/servlet/http/HttpServletRequest.getParameter:(Ljava/lang/String;)Ljava/lang/String;
      56: astore        9
      58: aload         6
      60: ifnull        68
      63: aload         7
      65: ifnonnull     69
      68: return
      69: aload_0
      70: getfield      #50                 // Field reqHandle:Lcom/virtual/ssv/server/rs/client/RequestHandle;
      73: aload         6
      75: invokestatic  #92                 // Method java/lang/Long.parseLong:(Ljava/lang/String;)J
      78: invokestatic  #93                 // Method java/lang/Long.valueOf:(J)Ljava/lang/Long;
      81: aload         7
      83: invokestatic  #92                 // Method java/lang/Long.parseLong:(Ljava/lang/String;)J
      86: invokestatic  #93                 // Method java/lang/Long.valueOf:(J)Ljava/lang/Long;
      89: aload         8
      91: aload_3
      92: invokevirtual #63                 // Method com/virtual/ssv/server/user/LoginInfo.getLoginIp:()Ljava/lang/String;
      95: invokevirtual #94                 // Method com/virtual/ssv/server/rs/client/RequestHandle.restore:(Ljava/lang/Long;Ljava/lang/Long;Ljava/lang/String;Ljava/lang/String;)Lcom/virtual/ssv/server/entity/ResultJson;
      98: astore        5
     100: aload         5
     102: invokevirtual #75                 // Method com/virtual/ssv/server/entity/ResultJson.isSuccess:()Z
     105: ifeq          270
     108: new           #42                 // class java/util/Date
     111: dup
     112: invokespecial #43                 // Method java/util/Date."<init>":()V
     115: astore        10
     117: new           #53                 // class com/virtual/ssv/server/rs/client/entity/RsOperateLog
     120: dup
     121: invokespecial #54                 // Method com/virtual/ssv/server/rs/client/entity/RsOperateLog."<init>":()V
     124: astore        11
     126: aload         11
     128: aload_3
     129: invokevirtual #55                 // Method com/virtual/ssv/server/user/LoginInfo.getId:()Ljava/lang/Long;
     132: invokevirtual #56                 // Method com/virtual/ssv/server/rs/client/entity/RsOperateLog.setUserId:(Ljava/lang/Long;)V
     135: aload         11
     137: aload_3
     138: invokevirtual #57                 // Method com/virtual/ssv/server/user/LoginInfo.getOrgId:()Ljava/lang/Long;
     141: invokevirtual #58                 // Method com/virtual/ssv/server/rs/client/entity/RsOperateLog.setOrgId:(Ljava/lang/Long;)V
     144: aload         11
     146: aload_3
     147: invokevirtual #59                 // Method com/virtual/ssv/server/user/LoginInfo.getLoginName:()Ljava/lang/String;
     150: invokevirtual #60                 // Method com/virtual/ssv/server/rs/client/entity/RsOperateLog.setLoginName:(Ljava/lang/String;)V
     153: aload         11
     155: aload_3
     156: invokevirtual #61                 // Method com/virtual/ssv/server/user/LoginInfo.getUserName:()Ljava/lang/String;
     159: invokevirtual #62                 // Method com/virtual/ssv/server/rs/client/entity/RsOperateLog.setUserName:(Ljava/lang/String;)V
     162: aload         11
     164: aload_3
     165: invokevirtual #63                 // Method com/virtual/ssv/server/user/LoginInfo.getLoginIp:()Ljava/lang/String;
     168: invokevirtual #64                 // Method com/virtual/ssv/server/rs/client/entity/RsOperateLog.setAddress:(Ljava/lang/String;)V
     171: aload         11
     173: bipush        10
     175: invokestatic  #66                 // Method java/lang/Integer.valueOf:(I)Ljava/lang/Integer;
     178: invokevirtual #67                 // Method com/virtual/ssv/server/rs/client/entity/RsOperateLog.setCategory:(Ljava/lang/Integer;)V
     181: aload         11
     183: aload_0
     184: getfield      #68                 // Field logSm:Lcom/virtual/common/StringManager;
     187: ldc           #95                 // String domainBackup.restore.task
     189: iconst_2
     190: anewarray     #70                 // class java/lang/Object
     193: dup
     194: iconst_0
     195: aload         8
     197: aastore
     198: dup
     199: iconst_1
     200: aload         9
     202: aastore
     203: invokevirtual #71                 // Method com/virtual/common/StringManager.getString:(Ljava/lang/String;[Ljava/lang/Object;)Ljava/lang/String;
     206: invokevirtual #72                 // Method com/virtual/ssv/server/rs/client/entity/RsOperateLog.setDescription:(Ljava/lang/String;)V
     209: aload         11
     211: aload         4
     213: invokevirtual #73                 // Method com/virtual/ssv/server/rs/client/entity/RsOperateLog.setStartTime:(Ljava/util/Date;)V
     216: aload         11
     218: aload         10
     220: invokevirtual #74                 // Method com/virtual/ssv/server/rs/client/entity/RsOperateLog.setEndTime:(Ljava/util/Date;)V
     223: aload         5
     225: invokevirtual #75                 // Method com/virtual/ssv/server/entity/ResultJson.isSuccess:()Z
     228: ifeq          242
     231: aload         11
     233: getstatic     #76                 // Field com/virtual/ssv/server/rs/client/entity/RsOperateLog.RESULT_SUCCESS:Ljava/lang/Integer;
     236: invokevirtual #77                 // Method com/virtual/ssv/server/rs/client/entity/RsOperateLog.setResult:(Ljava/lang/Integer;)V
     239: goto          260
     242: aload         11
     244: getstatic     #78                 // Field com/virtual/ssv/server/rs/client/entity/RsOperateLog.RESULT_FAILURE:Ljava/lang/Integer;
     247: invokevirtual #77                 // Method com/virtual/ssv/server/rs/client/entity/RsOperateLog.setResult:(Ljava/lang/Integer;)V
     250: aload         11
     252: aload         5
     254: invokevirtual #96                 // Method com/virtual/ssv/server/entity/ResultJson.getFailtureReson:()Ljava/lang/String;
     257: invokevirtual #80                 // Method com/virtual/ssv/server/rs/client/entity/RsOperateLog.setFailureReason:(Ljava/lang/String;)V
     260: aload_0
     261: getfield      #50                 // Field reqHandle:Lcom/virtual/ssv/server/rs/client/RequestHandle;
     264: aload         11
     266: invokevirtual #81                 // Method com/virtual/ssv/server/rs/client/RequestHandle.addUserLog:(Lcom/virtual/ssv/server/rs/client/entity/RsOperateLog;)Ljava/lang/Long;
     269: pop
     270: goto          354
     273: astore        6
     275: aload         6
     277: invokevirtual #83                 // Method com/virtual/common/AppException.getErrorCode:()I
     280: bipush        102
     282: if_icmpne     298
     285: aload         5
     287: bipush        102
     289: invokestatic  #85                 // Method com/virtual/common/ErrorCodes.getErrorMessage:(I)Ljava/lang/String;
     292: invokevirtual #86                 // Method com/virtual/ssv/server/entity/ResultJson.setErrorMsg:(Ljava/lang/String;)V
     295: goto          354
     298: aload         6
     300: invokevirtual #83                 // Method com/virtual/common/AppException.getErrorCode:()I
     303: bipush        103
     305: if_icmpne     321
     308: aload         5
     310: bipush        103
     312: invokestatic  #85                 // Method com/virtual/common/ErrorCodes.getErrorMessage:(I)Ljava/lang/String;
     315: invokevirtual #86                 // Method com/virtual/ssv/server/entity/ResultJson.setErrorMsg:(Ljava/lang/String;)V
     318: goto          354
     321: aload         6
     323: invokevirtual #83                 // Method com/virtual/common/AppException.getErrorCode:()I
     326: bipush        11
     328: if_icmpne     344
     331: aload         5
     333: bipush        11
     335: invokestatic  #85                 // Method com/virtual/common/ErrorCodes.getErrorMessage:(I)Ljava/lang/String;
     338: invokevirtual #86                 // Method com/virtual/ssv/server/entity/ResultJson.setErrorMsg:(Ljava/lang/String;)V
     341: goto          354
     344: aload         5
     346: aload         6
     348: invokevirtual #87                 // Method com/virtual/common/AppException.getMessage:()Ljava/lang/String;
     351: invokevirtual #86                 // Method com/virtual/ssv/server/entity/ResultJson.setErrorMsg:(Ljava/lang/String;)V
     354: aload_0
     355: aload_2
     356: aload_0
     357: getfield      #88                 // Field filterJson:Lcom/google/gson/Gson;
     360: aload         5
     362: invokevirtual #89                 // Method com/google/gson/Gson.toJson:(Ljava/lang/Object;)Ljava/lang/String;
     365: invokevirtual #90                 // Method write:(Ljavax/servlet/http/HttpServletResponse;Ljava/lang/String;)V
     368: return
    Exception table:
       from    to  target type
          18    68   273   Class com/virtual/common/AppException
          69   270   273   Class com/virtual/common/AppException

  private void getBackupList(javax.servlet.http.HttpServletRequest, javax.servlet.http.HttpServletResponse, com.virtual.ssv.server.user.LoginInfo);
    Code:
       0: aload_3
       1: invokevirtual #55                 // Method com/virtual/ssv/server/user/LoginInfo.getId:()Ljava/lang/Long;
       4: astore        4
       6: aload_1
       7: ldc           #97                 // String vmId
       9: invokeinterface #8,  2            // InterfaceMethod javax/servlet/http/HttpServletRequest.getParameter:(Ljava/lang/String;)Ljava/lang/String;
      14: astore        5
      16: aload         5
      18: ifnull        52
      21: ldc           #98                 // String [1-9]\\d*
      23: astore        6
      25: aload         6
      27: invokestatic  #99                 // Method java/util/regex/Pattern.compile:(Ljava/lang/String;)Ljava/util/regex/Pattern;
      30: astore        7
      32: aload         7
      34: aload         5
      36: invokevirtual #100                // Method java/util/regex/Pattern.matcher:(Ljava/lang/CharSequence;)Ljava/util/regex/Matcher;
      39: astore        8
      41: aload         8
      43: invokevirtual #101                // Method java/util/regex/Matcher.matches:()Z
      46: ifne          52
      49: aconst_null
      50: astore        5
      52: aload_1
      53: ldc           #102                // String domainTitle
      55: invokeinterface #8,  2            // InterfaceMethod javax/servlet/http/HttpServletRequest.getParameter:(Ljava/lang/String;)Ljava/lang/String;
      60: astore        6
      62: new           #103                // class com/virtual/ssv/server/entity/CommonListJson
      65: dup
      66: invokespecial #104                // Method com/virtual/ssv/server/entity/CommonListJson."<init>":()V
      69: astore        7
      71: aload_0
      72: aload_1
      73: invokevirtual #105                // Method getPagingConfig:(Ljavax/servlet/http/HttpServletRequest;)Lcom/virtual/ssv/server/entity/PagingLoadConfig;
      76: astore        8
      78: aload         8
      80: invokevirtual #106                // Method com/virtual/ssv/server/entity/PagingLoadConfig.getSortField:()Ljava/lang/String;
      83: invokestatic  #107                // Method org/apache/commons/lang/StringUtils.isEmpty:(Ljava/lang/String;)Z
      86: ifeq          106
      89: aload         8
      91: ldc           #46                 // String id
      93: invokevirtual #108                // Method com/virtual/ssv/server/entity/PagingLoadConfig.setSortField:(Ljava/lang/String;)V
      96: aload         8
      98: ldc           #109                // String Desc
     100: invokevirtual #110                // Method com/virtual/ssv/server/entity/PagingLoadConfig.setSortDir:(Ljava/lang/String;)V
     103: goto          130
     106: aload         8
     108: invokevirtual #106                // Method com/virtual/ssv/server/entity/PagingLoadConfig.getSortField:()Ljava/lang/String;
     111: astore        9
     113: ldc           #48                 // String name
     115: aload         9
     117: invokevirtual #10                 // Method java/lang/String.equals:(Ljava/lang/Object;)Z
     120: ifeq          130
     123: aload         8
     125: ldc           #48                 // String name
     127: invokevirtual #108                // Method com/virtual/ssv/server/entity/PagingLoadConfig.setSortField:(Ljava/lang/String;)V
     130: aload_0
     131: getfield      #50                 // Field reqHandle:Lcom/virtual/ssv/server/rs/client/RequestHandle;
     134: aload         8
     136: aload         4
     138: aload         5
     140: aload         6
     142: invokevirtual #111                // Method com/virtual/ssv/server/rs/client/RequestHandle.getBackupList:(Lcom/virtual/ssv/server/entity/PagingLoadConfig;Ljava/lang/Long;Ljava/lang/String;Ljava/lang/String;)Lcom/virtual/ssv/server/entity/CommonListJson;
     145: astore        7
     147: aload_0
     148: aload_2
     149: aload_0
     150: getfield      #112                // Field gson:Lcom/google/gson/Gson;
     153: aload         7
     155: invokevirtual #89                 // Method com/google/gson/Gson.toJson:(Ljava/lang/Object;)Ljava/lang/String;
     158: invokevirtual #90                 // Method write:(Ljavax/servlet/http/HttpServletResponse;Ljava/lang/String;)V
     161: goto          277
     164: astore        9
     166: aload         7
     168: aload_0
     169: getfield      #68                 // Field logSm:Lcom/virtual/common/StringManager;
     172: ldc           #113                // String operError
     174: invokevirtual #114                // Method com/virtual/common/StringManager.getString:(Ljava/lang/String;)Ljava/lang/String;
     177: invokevirtual #115                // Method com/virtual/ssv/server/entity/CommonListJson.setTitle:(Ljava/lang/String;)V
     180: aload         9
     182: invokevirtual #83                 // Method com/virtual/common/AppException.getErrorCode:()I
     185: bipush        102
     187: if_icmpne     203
     190: aload         7
     192: bipush        102
     194: invokestatic  #85                 // Method com/virtual/common/ErrorCodes.getErrorMessage:(I)Ljava/lang/String;
     197: invokevirtual #116                // Method com/virtual/ssv/server/entity/CommonListJson.setMessage:(Ljava/lang/String;)V
     200: goto          259
     203: aload         9
     205: invokevirtual #83                 // Method com/virtual/common/AppException.getErrorCode:()I
     208: bipush        103
     210: if_icmpne     226
     213: aload         7
     215: bipush        103
     217: invokestatic  #85                 // Method com/virtual/common/ErrorCodes.getErrorMessage:(I)Ljava/lang/String;
     220: invokevirtual #116                // Method com/virtual/ssv/server/entity/CommonListJson.setMessage:(Ljava/lang/String;)V
     223: goto          259
     226: aload         9
     228: invokevirtual #83                 // Method com/virtual/common/AppException.getErrorCode:()I
     231: bipush        11
     233: if_icmpne     249
     236: aload         7
     238: bipush        11
     240: invokestatic  #85                 // Method com/virtual/common/ErrorCodes.getErrorMessage:(I)Ljava/lang/String;
     243: invokevirtual #116                // Method com/virtual/ssv/server/entity/CommonListJson.setMessage:(Ljava/lang/String;)V
     246: goto          259
     249: aload         7
     251: aload         9
     253: invokevirtual #87                 // Method com/virtual/common/AppException.getMessage:()Ljava/lang/String;
     256: invokevirtual #116                // Method com/virtual/ssv/server/entity/CommonListJson.setMessage:(Ljava/lang/String;)V
     259: aload         7
     261: iconst_0
     262: invokevirtual #117                // Method com/virtual/ssv/server/entity/CommonListJson.setState:(I)V
     265: aload         7
     267: new           #118                // class java/util/ArrayList
     270: dup
     271: invokespecial #119                // Method java/util/ArrayList."<init>":()V
     274: invokevirtual #120                // Method com/virtual/ssv/server/entity/CommonListJson.setRows:(Ljava/util/List;)V
     277: aload_0
     278: aload_2
     279: aload_0
     280: getfield      #112                // Field gson:Lcom/google/gson/Gson;
     283: aload         7
     285: invokevirtual #89                 // Method com/google/gson/Gson.toJson:(Ljava/lang/Object;)Ljava/lang/String;
     288: invokevirtual #90                 // Method write:(Ljavax/servlet/http/HttpServletResponse;Ljava/lang/String;)V
     291: return
    Exception table:
       from    to  target type
         130   161   164   Class com/virtual/common/AppException

  private void getBackupStrategyList(javax.servlet.http.HttpServletRequest, javax.servlet.http.HttpServletResponse, com.virtual.ssv.server.user.LoginInfo);
    Code:
       0: aload_3
       1: invokevirtual #55                 // Method com/virtual/ssv/server/user/LoginInfo.getId:()Ljava/lang/Long;
       4: astore        4
       6: aload_3
       7: invokevirtual #57                 // Method com/virtual/ssv/server/user/LoginInfo.getOrgId:()Ljava/lang/Long;
      10: astore        5
      12: new           #103                // class com/virtual/ssv/server/entity/CommonListJson
      15: dup
      16: invokespecial #104                // Method com/virtual/ssv/server/entity/CommonListJson."<init>":()V
      19: astore        6
      21: aload_0
      22: aload_1
      23: invokevirtual #105                // Method getPagingConfig:(Ljavax/servlet/http/HttpServletRequest;)Lcom/virtual/ssv/server/entity/PagingLoadConfig;
      26: astore        7
      28: aload         7
      30: invokevirtual #106                // Method com/virtual/ssv/server/entity/PagingLoadConfig.getSortField:()Ljava/lang/String;
      33: invokestatic  #107                // Method org/apache/commons/lang/StringUtils.isEmpty:(Ljava/lang/String;)Z
      36: ifeq          56
      39: aload         7
      41: ldc           #46                 // String id
      43: invokevirtual #108                // Method com/virtual/ssv/server/entity/PagingLoadConfig.setSortField:(Ljava/lang/String;)V
      46: aload         7
      48: ldc           #109                // String Desc
      50: invokevirtual #110                // Method com/virtual/ssv/server/entity/PagingLoadConfig.setSortDir:(Ljava/lang/String;)V
      53: goto          80
      56: aload         7
      58: invokevirtual #106                // Method com/virtual/ssv/server/entity/PagingLoadConfig.getSortField:()Ljava/lang/String;
      61: astore        8
      63: ldc           #48                 // String name
      65: aload         8
      67: invokevirtual #10                 // Method java/lang/String.equals:(Ljava/lang/Object;)Z
      70: ifeq          80
      73: aload         7
      75: ldc           #48                 // String name
      77: invokevirtual #108                // Method com/virtual/ssv/server/entity/PagingLoadConfig.setSortField:(Ljava/lang/String;)V
      80: aload_1
      81: ldc           #121                // String strategyId
      83: invokeinterface #8,  2            // InterfaceMethod javax/servlet/http/HttpServletRequest.getParameter:(Ljava/lang/String;)Ljava/lang/String;
      88: astore        8
      90: aload_0
      91: getfield      #50                 // Field reqHandle:Lcom/virtual/ssv/server/rs/client/RequestHandle;
      94: aload         7
      96: aload         4
      98: aload         5
     100: aload         8
     102: invokevirtual #122                // Method com/virtual/ssv/server/rs/client/RequestHandle.getBackupStrategyList:(Lcom/virtual/ssv/server/entity/PagingLoadConfig;Ljava/lang/Long;Ljava/lang/Long;Ljava/lang/String;)Lcom/virtual/ssv/server/entity/CommonListJson;
     105: astore        6
     107: aload_0
     108: aload_2
     109: aload_0
     110: getfield      #112                // Field gson:Lcom/google/gson/Gson;
     113: aload         6
     115: invokevirtual #89                 // Method com/google/gson/Gson.toJson:(Ljava/lang/Object;)Ljava/lang/String;
     118: invokevirtual #90                 // Method write:(Ljavax/servlet/http/HttpServletResponse;Ljava/lang/String;)V
     121: goto          237
     124: astore        8
     126: aload         6
     128: aload_0
     129: getfield      #68                 // Field logSm:Lcom/virtual/common/StringManager;
     132: ldc           #113                // String operError
     134: invokevirtual #114                // Method com/virtual/common/StringManager.getString:(Ljava/lang/String;)Ljava/lang/String;
     137: invokevirtual #115                // Method com/virtual/ssv/server/entity/CommonListJson.setTitle:(Ljava/lang/String;)V
     140: aload         8
     142: invokevirtual #83                 // Method com/virtual/common/AppException.getErrorCode:()I
     145: bipush        102
     147: if_icmpne     163
     150: aload         6
     152: bipush        102
     154: invokestatic  #85                 // Method com/virtual/common/ErrorCodes.getErrorMessage:(I)Ljava/lang/String;
     157: invokevirtual #116                // Method com/virtual/ssv/server/entity/CommonListJson.setMessage:(Ljava/lang/String;)V
     160: goto          219
     163: aload         8
     165: invokevirtual #83                 // Method com/virtual/common/AppException.getErrorCode:()I
     168: bipush        103
     170: if_icmpne     186
     173: aload         6
     175: bipush        103
     177: invokestatic  #85                 // Method com/virtual/common/ErrorCodes.getErrorMessage:(I)Ljava/lang/String;
     180: invokevirtual #116                // Method com/virtual/ssv/server/entity/CommonListJson.setMessage:(Ljava/lang/String;)V
     183: goto          219
     186: aload         8
     188: invokevirtual #83                 // Method com/virtual/common/AppException.getErrorCode:()I
     191: bipush        11
     193: if_icmpne     209
     196: aload         6
     198: bipush        11
     200: invokestatic  #85                 // Method com/virtual/common/ErrorCodes.getErrorMessage:(I)Ljava/lang/String;
     203: invokevirtual #116                // Method com/virtual/ssv/server/entity/CommonListJson.setMessage:(Ljava/lang/String;)V
     206: goto          219
     209: aload         6
     211: aload         8
     213: invokevirtual #87                 // Method com/virtual/common/AppException.getMessage:()Ljava/lang/String;
     216: invokevirtual #116                // Method com/virtual/ssv/server/entity/CommonListJson.setMessage:(Ljava/lang/String;)V
     219: aload         6
     221: iconst_0
     222: invokevirtual #117                // Method com/virtual/ssv/server/entity/CommonListJson.setState:(I)V
     225: aload         6
     227: new           #118                // class java/util/ArrayList
     230: dup
     231: invokespecial #119                // Method java/util/ArrayList."<init>":()V
     234: invokevirtual #120                // Method com/virtual/ssv/server/entity/CommonListJson.setRows:(Ljava/util/List;)V
     237: aload_0
     238: aload_2
     239: aload_0
     240: getfield      #112                // Field gson:Lcom/google/gson/Gson;
     243: aload         6
     245: invokevirtual #89                 // Method com/google/gson/Gson.toJson:(Ljava/lang/Object;)Ljava/lang/String;
     248: invokevirtual #90                 // Method write:(Ljavax/servlet/http/HttpServletResponse;Ljava/lang/String;)V
     251: return
    Exception table:
       from    to  target type
          80   121   124   Class com/virtual/common/AppException

  private void getBackupStrategyInfo(javax.servlet.http.HttpServletRequest, javax.servlet.http.HttpServletResponse, com.virtual.ssv.server.user.LoginInfo);
    Code:
       0: aload_1
       1: ldc           #121                // String strategyId
       3: invokeinterface #8,  2            // InterfaceMethod javax/servlet/http/HttpServletRequest.getParameter:(Ljava/lang/String;)Ljava/lang/String;
       8: astore        4
      10: aload         4
      12: ifnull        64
      15: aconst_null
      16: astore        5
      18: aload_0
      19: getfield      #50                 // Field reqHandle:Lcom/virtual/ssv/server/rs/client/RequestHandle;
      22: aload         4
      24: invokestatic  #92                 // Method java/lang/Long.parseLong:(Ljava/lang/String;)J
      27: invokestatic  #93                 // Method java/lang/Long.valueOf:(J)Ljava/lang/Long;
      30: invokevirtual #123                // Method com/virtual/ssv/server/rs/client/RequestHandle.queryStrategyInfo:(Ljava/lang/Long;)Lcom/virtual/ssv/server/rs/client/entity/RsCloudBackUpStrategy;
      33: astore        5
      35: goto          50
      38: astore        6
      40: getstatic     #125                // Field log:Lorg/apache/commons/logging/Log;
      43: aload         6
      45: invokeinterface #126,  2          // InterfaceMethod org/apache/commons/logging/Log.error:(Ljava/lang/Object;)V
      50: aload_0
      51: aload_2
      52: aload_0
      53: getfield      #112                // Field gson:Lcom/google/gson/Gson;
      56: aload         5
      58: invokevirtual #89                 // Method com/google/gson/Gson.toJson:(Ljava/lang/Object;)Ljava/lang/String;
      61: invokevirtual #90                 // Method write:(Ljavax/servlet/http/HttpServletResponse;Ljava/lang/String;)V
      64: return
    Exception table:
       from    to  target type
          18    35    38   Class java/lang/Exception

  private void getBackupStrategyWorkFlowInfo(javax.servlet.http.HttpServletRequest, javax.servlet.http.HttpServletResponse, com.virtual.ssv.server.user.LoginInfo);
    Code:
       0: aload_1
       1: ldc           #121                // String strategyId
       3: invokeinterface #8,  2            // InterfaceMethod javax/servlet/http/HttpServletRequest.getParameter:(Ljava/lang/String;)Ljava/lang/String;
       8: astore        4
      10: aload         4
      12: ifnull        73
      15: aconst_null
      16: astore        5
      18: aload_0
      19: getfield      #50                 // Field reqHandle:Lcom/virtual/ssv/server/rs/client/RequestHandle;
      22: aload         4
      24: invokestatic  #92                 // Method java/lang/Long.parseLong:(Ljava/lang/String;)J
      27: invokestatic  #93                 // Method java/lang/Long.valueOf:(J)Ljava/lang/Long;
      30: aconst_null
      31: aload_3
      32: invokevirtual #55                 // Method com/virtual/ssv/server/user/LoginInfo.getId:()Ljava/lang/Long;
      35: aload_3
      36: invokevirtual #57                 // Method com/virtual/ssv/server/user/LoginInfo.getOrgId:()Ljava/lang/Long;
      39: invokevirtual #127                // Method com/virtual/ssv/server/rs/client/RequestHandle.queryCloudBackUpStrategyWorkFlow:(Ljava/lang/Long;Ljava/lang/String;Ljava/lang/Long;Ljava/lang/Long;)Lcom/virtual/ssv/server/rs/client/entity/RsCloudBackUpStrategyWorkFlow;
      42: astore        5
      44: goto          59
      47: astore        6
      49: getstatic     #125                // Field log:Lorg/apache/commons/logging/Log;
      52: aload         6
      54: invokeinterface #126,  2          // InterfaceMethod org/apache/commons/logging/Log.error:(Ljava/lang/Object;)V
      59: aload_0
      60: aload_2
      61: aload_0
      62: getfield      #112                // Field gson:Lcom/google/gson/Gson;
      65: aload         5
      67: invokevirtual #89                 // Method com/google/gson/Gson.toJson:(Ljava/lang/Object;)Ljava/lang/String;
      70: invokevirtual #90                 // Method write:(Ljavax/servlet/http/HttpServletResponse;Ljava/lang/String;)V
      73: return
    Exception table:
       from    to  target type
          18    44    47   Class java/lang/Exception

  private void getBackupStrategyVmList(javax.servlet.http.HttpServletRequest, javax.servlet.http.HttpServletResponse, com.virtual.ssv.server.user.LoginInfo);
    Code:
       0: return

  private void getBackupStrategyWorkFlow(javax.servlet.http.HttpServletRequest, javax.servlet.http.HttpServletResponse, com.virtual.ssv.server.user.LoginInfo);
    Code:
       0: aload_3
       1: invokevirtual #55                 // Method com/virtual/ssv/server/user/LoginInfo.getId:()Ljava/lang/Long;
       4: astore        4
       6: aload_3
       7: invokevirtual #57                 // Method com/virtual/ssv/server/user/LoginInfo.getOrgId:()Ljava/lang/Long;
      10: astore        5
      12: new           #103                // class com/virtual/ssv/server/entity/CommonListJson
      15: dup
      16: invokespecial #104                // Method com/virtual/ssv/server/entity/CommonListJson."<init>":()V
      19: astore        6
      21: aload_0
      22: aload_1
      23: invokevirtual #105                // Method getPagingConfig:(Ljavax/servlet/http/HttpServletRequest;)Lcom/virtual/ssv/server/entity/PagingLoadConfig;
      26: astore        7
      28: aload         7
      30: invokevirtual #106                // Method com/virtual/ssv/server/entity/PagingLoadConfig.getSortField:()Ljava/lang/String;
      33: invokestatic  #107                // Method org/apache/commons/lang/StringUtils.isEmpty:(Ljava/lang/String;)Z
      36: ifeq          56
      39: aload         7
      41: ldc           #46                 // String id
      43: invokevirtual #108                // Method com/virtual/ssv/server/entity/PagingLoadConfig.setSortField:(Ljava/lang/String;)V
      46: aload         7
      48: ldc           #109                // String Desc
      50: invokevirtual #110                // Method com/virtual/ssv/server/entity/PagingLoadConfig.setSortDir:(Ljava/lang/String;)V
      53: goto          80
      56: aload         7
      58: invokevirtual #106                // Method com/virtual/ssv/server/entity/PagingLoadConfig.getSortField:()Ljava/lang/String;
      61: astore        8
      63: ldc           #48                 // String name
      65: aload         8
      67: invokevirtual #10                 // Method java/lang/String.equals:(Ljava/lang/Object;)Z
      70: ifeq          80
      73: aload         7
      75: ldc           #48                 // String name
      77: invokevirtual #108                // Method com/virtual/ssv/server/entity/PagingLoadConfig.setSortField:(Ljava/lang/String;)V
      80: aload_1
      81: ldc           #128                // String type
      83: invokeinterface #8,  2            // InterfaceMethod javax/servlet/http/HttpServletRequest.getParameter:(Ljava/lang/String;)Ljava/lang/String;
      88: astore        8
      90: aload_0
      91: getfield      #50                 // Field reqHandle:Lcom/virtual/ssv/server/rs/client/RequestHandle;
      94: aload         7
      96: aload         4
      98: aload         5
     100: aload         8
     102: invokevirtual #129                // Method com/virtual/ssv/server/rs/client/RequestHandle.getBackupStrategyWorkFlow:(Lcom/virtual/ssv/server/entity/PagingLoadConfig;Ljava/lang/Long;Ljava/lang/Long;Ljava/lang/String;)Lcom/virtual/ssv/server/entity/CommonListJson;
     105: astore        6
     107: aload_0
     108: aload_2
     109: aload_0
     110: getfield      #112                // Field gson:Lcom/google/gson/Gson;
     113: aload         6
     115: invokevirtual #89                 // Method com/google/gson/Gson.toJson:(Ljava/lang/Object;)Ljava/lang/String;
     118: invokevirtual #90                 // Method write:(Ljavax/servlet/http/HttpServletResponse;Ljava/lang/String;)V
     121: goto          237
     124: astore        8
     126: aload         6
     128: aload_0
     129: getfield      #68                 // Field logSm:Lcom/virtual/common/StringManager;
     132: ldc           #113                // String operError
     134: invokevirtual #114                // Method com/virtual/common/StringManager.getString:(Ljava/lang/String;)Ljava/lang/String;
     137: invokevirtual #115                // Method com/virtual/ssv/server/entity/CommonListJson.setTitle:(Ljava/lang/String;)V
     140: aload         8
     142: invokevirtual #83                 // Method com/virtual/common/AppException.getErrorCode:()I
     145: bipush        102
     147: if_icmpne     163
     150: aload         6
     152: bipush        102
     154: invokestatic  #85                 // Method com/virtual/common/ErrorCodes.getErrorMessage:(I)Ljava/lang/String;
     157: invokevirtual #116                // Method com/virtual/ssv/server/entity/CommonListJson.setMessage:(Ljava/lang/String;)V
     160: goto          219
     163: aload         8
     165: invokevirtual #83                 // Method com/virtual/common/AppException.getErrorCode:()I
     168: bipush        103
     170: if_icmpne     186
     173: aload         6
     175: bipush        103
     177: invokestatic  #85                 // Method com/virtual/common/ErrorCodes.getErrorMessage:(I)Ljava/lang/String;
     180: invokevirtual #116                // Method com/virtual/ssv/server/entity/CommonListJson.setMessage:(Ljava/lang/String;)V
     183: goto          219
     186: aload         8
     188: invokevirtual #83                 // Method com/virtual/common/AppException.getErrorCode:()I
     191: bipush        11
     193: if_icmpne     209
     196: aload         6
     198: bipush        11
     200: invokestatic  #85                 // Method com/virtual/common/ErrorCodes.getErrorMessage:(I)Ljava/lang/String;
     203: invokevirtual #116                // Method com/virtual/ssv/server/entity/CommonListJson.setMessage:(Ljava/lang/String;)V
     206: goto          219
     209: aload         6
     211: aload         8
     213: invokevirtual #87                 // Method com/virtual/common/AppException.getMessage:()Ljava/lang/String;
     216: invokevirtual #116                // Method com/virtual/ssv/server/entity/CommonListJson.setMessage:(Ljava/lang/String;)V
     219: aload         6
     221: iconst_0
     222: invokevirtual #117                // Method com/virtual/ssv/server/entity/CommonListJson.setState:(I)V
     225: aload         6
     227: new           #118                // class java/util/ArrayList
     230: dup
     231: invokespecial #119                // Method java/util/ArrayList."<init>":()V
     234: invokevirtual #120                // Method com/virtual/ssv/server/entity/CommonListJson.setRows:(Ljava/util/List;)V
     237: aload_0
     238: aload_2
     239: aload_0
     240: getfield      #112                // Field gson:Lcom/google/gson/Gson;
     243: aload         6
     245: invokevirtual #89                 // Method com/google/gson/Gson.toJson:(Ljava/lang/Object;)Ljava/lang/String;
     248: invokevirtual #90                 // Method write:(Ljavax/servlet/http/HttpServletResponse;Ljava/lang/String;)V
     251: return
    Exception table:
       from    to  target type
          80   121   124   Class com/virtual/common/AppException

  private void applyBackupStrategy(javax.servlet.http.HttpServletRequest, javax.servlet.http.HttpServletResponse, com.virtual.ssv.server.user.LoginInfo);
    Code:
       0: new           #44                 // class com/virtual/ssv/server/entity/ResultJson
       3: dup
       4: invokespecial #45                 // Method com/virtual/ssv/server/entity/ResultJson."<init>":()V
       7: astore        4
       9: new           #42                 // class java/util/Date
      12: dup
      13: invokespecial #43                 // Method java/util/Date."<init>":()V
      16: astore        5
      18: aconst_null
      19: astore        6
      21: aload_1
      22: ldc           #130                // String xml
      24: invokeinterface #8,  2            // InterfaceMethod javax/servlet/http/HttpServletRequest.getParameter:(Ljava/lang/String;)Ljava/lang/String;
      29: ldc           #131                // String UTF-8
      31: invokestatic  #132                // Method java/net/URLDecoder.decode:(Ljava/lang/String;Ljava/lang/String;)Ljava/lang/String;
      34: astore        7
      36: aload         7
      38: ifnull        363
      41: aload         7
      43: ldc           #133                // String column
      45: ldc           #134                // String COLUMN_
      47: invokestatic  #135                // Method org/apache/commons/lang/StringUtils.replace:(Ljava/lang/String;Ljava/lang/String;Ljava/lang/String;)Ljava/lang/String;
      50: astore        8
      52: aload         8
      54: ldc           #136                // class com/virtual/ssv/server/rs/client/entity/RsCloudBackUpStrategyWorkFlow
      56: invokestatic  #137                // Method com/virtual/common/FuncUtil.convertXmlToObject:(Ljava/lang/String;Ljava/lang/Class;)Ljava/lang/Object;
      59: checkcast     #136                // class com/virtual/ssv/server/rs/client/entity/RsCloudBackUpStrategyWorkFlow
      62: astore        6
      64: aload         6
      66: iconst_1
      67: invokestatic  #66                 // Method java/lang/Integer.valueOf:(I)Ljava/lang/Integer;
      70: invokevirtual #138                // Method com/virtual/ssv/server/rs/client/entity/RsCloudBackUpStrategyWorkFlow.setType:(Ljava/lang/Integer;)V
      73: aload         6
      75: aload_3
      76: invokevirtual #57                 // Method com/virtual/ssv/server/user/LoginInfo.getOrgId:()Ljava/lang/Long;
      79: invokevirtual #139                // Method com/virtual/ssv/server/rs/client/entity/RsCloudBackUpStrategyWorkFlow.setOrgId:(Ljava/lang/Long;)V
      82: aload         6
      84: invokevirtual #140                // Method com/virtual/ssv/server/rs/client/entity/RsCloudBackUpStrategyWorkFlow.getStrategyId:()Ljava/lang/Long;
      87: astore        9
      89: aload         6
      91: invokevirtual #141                // Method com/virtual/ssv/server/rs/client/entity/RsCloudBackUpStrategyWorkFlow.getName:()Ljava/lang/String;
      94: astore        10
      96: aload_0
      97: getfield      #50                 // Field reqHandle:Lcom/virtual/ssv/server/rs/client/RequestHandle;
     100: aload         9
     102: aload         10
     104: aload_3
     105: invokevirtual #55                 // Method com/virtual/ssv/server/user/LoginInfo.getId:()Ljava/lang/Long;
     108: aload_3
     109: invokevirtual #57                 // Method com/virtual/ssv/server/user/LoginInfo.getOrgId:()Ljava/lang/Long;
     112: invokevirtual #127                // Method com/virtual/ssv/server/rs/client/RequestHandle.queryCloudBackUpStrategyWorkFlow:(Ljava/lang/Long;Ljava/lang/String;Ljava/lang/Long;Ljava/lang/Long;)Lcom/virtual/ssv/server/rs/client/entity/RsCloudBackUpStrategyWorkFlow;
     115: astore        11
     117: aload         11
     119: ifnull        133
     122: new           #82                 // class com/virtual/common/AppException
     125: dup
     126: sipush        1003
     129: invokespecial #142                // Method com/virtual/common/AppException."<init>":(I)V
     132: athrow
     133: aload         6
     135: aload_3
     136: invokevirtual #55                 // Method com/virtual/ssv/server/user/LoginInfo.getId:()Ljava/lang/Long;
     139: invokevirtual #143                // Method com/virtual/ssv/server/rs/client/entity/RsCloudBackUpStrategyWorkFlow.setUserId:(Ljava/lang/Long;)V
     142: aload         6
     144: aload_3
     145: invokevirtual #57                 // Method com/virtual/ssv/server/user/LoginInfo.getOrgId:()Ljava/lang/Long;
     148: invokevirtual #139                // Method com/virtual/ssv/server/rs/client/entity/RsCloudBackUpStrategyWorkFlow.setOrgId:(Ljava/lang/Long;)V
     151: aload         6
     153: aload         5
     155: invokevirtual #144                // Method com/virtual/ssv/server/rs/client/entity/RsCloudBackUpStrategyWorkFlow.setCreateDate:(Ljava/util/Date;)V
     158: aload_0
     159: getfield      #50                 // Field reqHandle:Lcom/virtual/ssv/server/rs/client/RequestHandle;
     162: aload         6
     164: invokevirtual #145                // Method com/virtual/ssv/server/rs/client/RequestHandle.addCloudBackupStrategyWorkflow:(Lcom/virtual/ssv/server/rs/client/entity/RsCloudBackUpStrategyWorkFlow;)Lcom/virtual/ssv/server/entity/ResultJson;
     167: astore        4
     169: new           #42                 // class java/util/Date
     172: dup
     173: invokespecial #43                 // Method java/util/Date."<init>":()V
     176: astore        12
     178: new           #53                 // class com/virtual/ssv/server/rs/client/entity/RsOperateLog
     181: dup
     182: invokespecial #54                 // Method com/virtual/ssv/server/rs/client/entity/RsOperateLog."<init>":()V
     185: astore        13
     187: aload         13
     189: aload_3
     190: invokevirtual #55                 // Method com/virtual/ssv/server/user/LoginInfo.getId:()Ljava/lang/Long;
     193: invokevirtual #56                 // Method com/virtual/ssv/server/rs/client/entity/RsOperateLog.setUserId:(Ljava/lang/Long;)V
     196: aload         13
     198: aload_3
     199: invokevirtual #57                 // Method com/virtual/ssv/server/user/LoginInfo.getOrgId:()Ljava/lang/Long;
     202: invokevirtual #58                 // Method com/virtual/ssv/server/rs/client/entity/RsOperateLog.setOrgId:(Ljava/lang/Long;)V
     205: aload         13
     207: aload_3
     208: invokevirtual #59                 // Method com/virtual/ssv/server/user/LoginInfo.getLoginName:()Ljava/lang/String;
     211: invokevirtual #60                 // Method com/virtual/ssv/server/rs/client/entity/RsOperateLog.setLoginName:(Ljava/lang/String;)V
     214: aload         13
     216: aload_3
     217: invokevirtual #61                 // Method com/virtual/ssv/server/user/LoginInfo.getUserName:()Ljava/lang/String;
     220: invokevirtual #62                 // Method com/virtual/ssv/server/rs/client/entity/RsOperateLog.setUserName:(Ljava/lang/String;)V
     223: aload         13
     225: aload_3
     226: invokevirtual #63                 // Method com/virtual/ssv/server/user/LoginInfo.getLoginIp:()Ljava/lang/String;
     229: invokevirtual #64                 // Method com/virtual/ssv/server/rs/client/entity/RsOperateLog.setAddress:(Ljava/lang/String;)V
     232: aload         13
     234: bipush        30
     236: invokestatic  #66                 // Method java/lang/Integer.valueOf:(I)Ljava/lang/Integer;
     239: invokevirtual #67                 // Method com/virtual/ssv/server/rs/client/entity/RsOperateLog.setCategory:(Ljava/lang/Integer;)V
     242: aload         9
     244: ifnonnull     276
     247: aload         13
     249: aload_0
     250: getfield      #68                 // Field logSm:Lcom/virtual/common/StringManager;
     253: ldc           #146                // String apply.cloudBackupStrategy
     255: iconst_1
     256: anewarray     #70                 // class java/lang/Object
     259: dup
     260: iconst_0
     261: aload         6
     263: invokevirtual #141                // Method com/virtual/ssv/server/rs/client/entity/RsCloudBackUpStrategyWorkFlow.getName:()Ljava/lang/String;
     266: aastore
     267: invokevirtual #71                 // Method com/virtual/common/StringManager.getString:(Ljava/lang/String;[Ljava/lang/Object;)Ljava/lang/String;
     270: invokevirtual #72                 // Method com/virtual/ssv/server/rs/client/entity/RsOperateLog.setDescription:(Ljava/lang/String;)V
     273: goto          302
     276: aload         13
     278: aload_0
     279: getfield      #68                 // Field logSm:Lcom/virtual/common/StringManager;
     282: ldc           #147                // String modify.cloudBackupStrategy
     284: iconst_1
     285: anewarray     #70                 // class java/lang/Object
     288: dup
     289: iconst_0
     290: aload         6
     292: invokevirtual #141                // Method com/virtual/ssv/server/rs/client/entity/RsCloudBackUpStrategyWorkFlow.getName:()Ljava/lang/String;
     295: aastore
     296: invokevirtual #71                 // Method com/virtual/common/StringManager.getString:(Ljava/lang/String;[Ljava/lang/Object;)Ljava/lang/String;
     299: invokevirtual #72                 // Method com/virtual/ssv/server/rs/client/entity/RsOperateLog.setDescription:(Ljava/lang/String;)V
     302: aload         4
     304: invokevirtual #75                 // Method com/virtual/ssv/server/entity/ResultJson.isSuccess:()Z
     307: ifeq          321
     310: aload         13
     312: getstatic     #76                 // Field com/virtual/ssv/server/rs/client/entity/RsOperateLog.RESULT_SUCCESS:Ljava/lang/Integer;
     315: invokevirtual #77                 // Method com/virtual/ssv/server/rs/client/entity/RsOperateLog.setResult:(Ljava/lang/Integer;)V
     318: goto          339
     321: aload         13
     323: getstatic     #78                 // Field com/virtual/ssv/server/rs/client/entity/RsOperateLog.RESULT_FAILURE:Ljava/lang/Integer;
     326: invokevirtual #77                 // Method com/virtual/ssv/server/rs/client/entity/RsOperateLog.setResult:(Ljava/lang/Integer;)V
     329: aload         13
     331: aload         4
     333: invokevirtual #79                 // Method com/virtual/ssv/server/entity/ResultJson.getMessage:()Ljava/lang/String;
     336: invokevirtual #80                 // Method com/virtual/ssv/server/rs/client/entity/RsOperateLog.setFailureReason:(Ljava/lang/String;)V
     339: aload         13
     341: aload         5
     343: invokevirtual #73                 // Method com/virtual/ssv/server/rs/client/entity/RsOperateLog.setStartTime:(Ljava/util/Date;)V
     346: aload         13
     348: aload         12
     350: invokevirtual #74                 // Method com/virtual/ssv/server/rs/client/entity/RsOperateLog.setEndTime:(Ljava/util/Date;)V
     353: aload_0
     354: getfield      #50                 // Field reqHandle:Lcom/virtual/ssv/server/rs/client/RequestHandle;
     357: aload         13
     359: invokevirtual #81                 // Method com/virtual/ssv/server/rs/client/RequestHandle.addUserLog:(Lcom/virtual/ssv/server/rs/client/entity/RsOperateLog;)Ljava/lang/Long;
     362: pop
     363: goto          487
     366: astore        5
     368: aload         5
     370: invokevirtual #83                 // Method com/virtual/common/AppException.getErrorCode:()I
     373: bipush        102
     375: if_icmpne     391
     378: aload         4
     380: bipush        102
     382: invokestatic  #85                 // Method com/virtual/common/ErrorCodes.getErrorMessage:(I)Ljava/lang/String;
     385: invokevirtual #86                 // Method com/virtual/ssv/server/entity/ResultJson.setErrorMsg:(Ljava/lang/String;)V
     388: goto          472
     391: aload         5
     393: invokevirtual #83                 // Method com/virtual/common/AppException.getErrorCode:()I
     396: bipush        103
     398: if_icmpne     414
     401: aload         4
     403: bipush        103
     405: invokestatic  #85                 // Method com/virtual/common/ErrorCodes.getErrorMessage:(I)Ljava/lang/String;
     408: invokevirtual #86                 // Method com/virtual/ssv/server/entity/ResultJson.setErrorMsg:(Ljava/lang/String;)V
     411: goto          472
     414: aload         5
     416: invokevirtual #83                 // Method com/virtual/common/AppException.getErrorCode:()I
     419: bipush        11
     421: if_icmpne     437
     424: aload         4
     426: bipush        11
     428: invokestatic  #85                 // Method com/virtual/common/ErrorCodes.getErrorMessage:(I)Ljava/lang/String;
     431: invokevirtual #86                 // Method com/virtual/ssv/server/entity/ResultJson.setErrorMsg:(Ljava/lang/String;)V
     434: goto          472
     437: aload         5
     439: invokevirtual #83                 // Method com/virtual/common/AppException.getErrorCode:()I
     442: sipush        1003
     445: if_icmpne     462
     448: aload         4
     450: sipush        1003
     453: invokestatic  #85                 // Method com/virtual/common/ErrorCodes.getErrorMessage:(I)Ljava/lang/String;
     456: invokevirtual #86                 // Method com/virtual/ssv/server/entity/ResultJson.setErrorMsg:(Ljava/lang/String;)V
     459: goto          472
     462: aload         4
     464: aload         5
     466: invokevirtual #87                 // Method com/virtual/common/AppException.getMessage:()Ljava/lang/String;
     469: invokevirtual #86                 // Method com/virtual/ssv/server/entity/ResultJson.setErrorMsg:(Ljava/lang/String;)V
     472: goto          487
     475: astore        5
     477: aload         4
     479: aload         5
     481: invokevirtual #149                // Method java/io/UnsupportedEncodingException.getMessage:()Ljava/lang/String;
     484: invokevirtual #86                 // Method com/virtual/ssv/server/entity/ResultJson.setErrorMsg:(Ljava/lang/String;)V
     487: aload_0
     488: aload_2
     489: aload_0
     490: getfield      #88                 // Field filterJson:Lcom/google/gson/Gson;
     493: aload         4
     495: invokevirtual #89                 // Method com/google/gson/Gson.toJson:(Ljava/lang/Object;)Ljava/lang/String;
     498: invokevirtual #90                 // Method write:(Ljavax/servlet/http/HttpServletResponse;Ljava/lang/String;)V
     501: return
    Exception table:
       from    to  target type
           9   363   366   Class com/virtual/common/AppException
           9   363   475   Class java/io/UnsupportedEncodingException

  public void init();
    Code:
       0: aload_0
       1: invokespecial #150                // Method com/virtual/ssv/server/BaseServlet.init:()V
       4: return

  private void handle(javax.servlet.http.HttpServletRequest, javax.servlet.http.HttpServletResponse, java.lang.String, com.virtual.ssv.server.user.LoginInfo);
    Code:
       0: new           #42                 // class java/util/Date
       3: dup
       4: invokespecial #43                 // Method java/util/Date."<init>":()V
       7: astore        5
       9: new           #44                 // class com/virtual/ssv/server/entity/ResultJson
      12: dup
      13: invokespecial #45                 // Method com/virtual/ssv/server/entity/ResultJson."<init>":()V
      16: astore        6
      18: aload_1
      19: ldc           #121                // String strategyId
      21: invokeinterface #8,  2            // InterfaceMethod javax/servlet/http/HttpServletRequest.getParameter:(Ljava/lang/String;)Ljava/lang/String;
      26: astore        7
      28: aload_1
      29: ldc           #151                // String strategyName
      31: invokeinterface #8,  2            // InterfaceMethod javax/servlet/http/HttpServletRequest.getParameter:(Ljava/lang/String;)Ljava/lang/String;
      36: astore        8
      38: aload_0
      39: getfield      #50                 // Field reqHandle:Lcom/virtual/ssv/server/rs/client/RequestHandle;
      42: aload         7
      44: invokestatic  #92                 // Method java/lang/Long.parseLong:(Ljava/lang/String;)J
      47: invokestatic  #93                 // Method java/lang/Long.valueOf:(J)Ljava/lang/Long;
      50: aload         8
      52: aload_3
      53: invokevirtual #152                // Method com/virtual/ssv/server/rs/client/RequestHandle.operateStrategy:(Ljava/lang/Long;Ljava/lang/String;Ljava/lang/String;)Lcom/virtual/ssv/server/entity/ResultJson;
      56: astore        6
      58: new           #42                 // class java/util/Date
      61: dup
      62: invokespecial #43                 // Method java/util/Date."<init>":()V
      65: astore        9
      67: new           #53                 // class com/virtual/ssv/server/rs/client/entity/RsOperateLog
      70: dup
      71: invokespecial #54                 // Method com/virtual/ssv/server/rs/client/entity/RsOperateLog."<init>":()V
      74: astore        10
      76: aload         10
      78: aload         4
      80: invokevirtual #55                 // Method com/virtual/ssv/server/user/LoginInfo.getId:()Ljava/lang/Long;
      83: invokevirtual #56                 // Method com/virtual/ssv/server/rs/client/entity/RsOperateLog.setUserId:(Ljava/lang/Long;)V
      86: aload         10
      88: aload         4
      90: invokevirtual #57                 // Method com/virtual/ssv/server/user/LoginInfo.getOrgId:()Ljava/lang/Long;
      93: invokevirtual #58                 // Method com/virtual/ssv/server/rs/client/entity/RsOperateLog.setOrgId:(Ljava/lang/Long;)V
      96: aload         10
      98: aload         4
     100: invokevirtual #59                 // Method com/virtual/ssv/server/user/LoginInfo.getLoginName:()Ljava/lang/String;
     103: invokevirtual #60                 // Method com/virtual/ssv/server/rs/client/entity/RsOperateLog.setLoginName:(Ljava/lang/String;)V
     106: aload         10
     108: aload         4
     110: invokevirtual #61                 // Method com/virtual/ssv/server/user/LoginInfo.getUserName:()Ljava/lang/String;
     113: invokevirtual #62                 // Method com/virtual/ssv/server/rs/client/entity/RsOperateLog.setUserName:(Ljava/lang/String;)V
     116: aload         10
     118: aload         4
     120: invokevirtual #63                 // Method com/virtual/ssv/server/user/LoginInfo.getLoginIp:()Ljava/lang/String;
     123: invokevirtual #64                 // Method com/virtual/ssv/server/rs/client/entity/RsOperateLog.setAddress:(Ljava/lang/String;)V
     126: aload         10
     128: iconst_1
     129: invokestatic  #66                 // Method java/lang/Integer.valueOf:(I)Ljava/lang/Integer;
     132: invokevirtual #67                 // Method com/virtual/ssv/server/rs/client/entity/RsOperateLog.setCategory:(Ljava/lang/Integer;)V
     135: aload         10
     137: aload_0
     138: getfield      #68                 // Field logSm:Lcom/virtual/common/StringManager;
     141: new           #153                // class java/lang/StringBuilder
     144: dup
     145: invokespecial #154                // Method java/lang/StringBuilder."<init>":()V
     148: aload_3
     149: invokevirtual #155                // Method java/lang/StringBuilder.append:(Ljava/lang/String;)Ljava/lang/StringBuilder;
     152: ldc           #156                // String .backupstrategy.operation
     154: invokevirtual #155                // Method java/lang/StringBuilder.append:(Ljava/lang/String;)Ljava/lang/StringBuilder;
     157: invokevirtual #157                // Method java/lang/StringBuilder.toString:()Ljava/lang/String;
     160: iconst_1
     161: anewarray     #70                 // class java/lang/Object
     164: dup
     165: iconst_0
     166: aload         8
     168: aastore
     169: invokevirtual #71                 // Method com/virtual/common/StringManager.getString:(Ljava/lang/String;[Ljava/lang/Object;)Ljava/lang/String;
     172: invokevirtual #72                 // Method com/virtual/ssv/server/rs/client/entity/RsOperateLog.setDescription:(Ljava/lang/String;)V
     175: aload         10
     177: aload         5
     179: invokevirtual #73                 // Method com/virtual/ssv/server/rs/client/entity/RsOperateLog.setStartTime:(Ljava/util/Date;)V
     182: aload         10
     184: aload         9
     186: invokevirtual #74                 // Method com/virtual/ssv/server/rs/client/entity/RsOperateLog.setEndTime:(Ljava/util/Date;)V
     189: aload         6
     191: invokevirtual #158                // Method com/virtual/ssv/server/entity/ResultJson.getState:()I
     194: iconst_1
     195: if_icmpne     209
     198: aload         10
     200: getstatic     #76                 // Field com/virtual/ssv/server/rs/client/entity/RsOperateLog.RESULT_SUCCESS:Ljava/lang/Integer;
     203: invokevirtual #77                 // Method com/virtual/ssv/server/rs/client/entity/RsOperateLog.setResult:(Ljava/lang/Integer;)V
     206: goto          227
     209: aload         10
     211: getstatic     #78                 // Field com/virtual/ssv/server/rs/client/entity/RsOperateLog.RESULT_FAILURE:Ljava/lang/Integer;
     214: invokevirtual #77                 // Method com/virtual/ssv/server/rs/client/entity/RsOperateLog.setResult:(Ljava/lang/Integer;)V
     217: aload         10
     219: aload         6
     221: invokevirtual #79                 // Method com/virtual/ssv/server/entity/ResultJson.getMessage:()Ljava/lang/String;
     224: invokevirtual #80                 // Method com/virtual/ssv/server/rs/client/entity/RsOperateLog.setFailureReason:(Ljava/lang/String;)V
     227: aload_0
     228: getfield      #50                 // Field reqHandle:Lcom/virtual/ssv/server/rs/client/RequestHandle;
     231: aload         10
     233: invokevirtual #81                 // Method com/virtual/ssv/server/rs/client/RequestHandle.addUserLog:(Lcom/virtual/ssv/server/rs/client/entity/RsOperateLog;)Ljava/lang/Long;
     236: pop
     237: aload_0
     238: getfield      #88                 // Field filterJson:Lcom/google/gson/Gson;
     241: aload         6
     243: invokevirtual #89                 // Method com/google/gson/Gson.toJson:(Ljava/lang/Object;)Ljava/lang/String;
     246: astore        11
     248: aload_0
     249: aload_2
     250: aload         11
     252: invokevirtual #90                 // Method write:(Ljavax/servlet/http/HttpServletResponse;Ljava/lang/String;)V
     255: goto          353
     258: astore        7
     260: aload         7
     262: invokevirtual #83                 // Method com/virtual/common/AppException.getErrorCode:()I
     265: bipush        102
     267: if_icmpne     283
     270: aload         6
     272: bipush        102
     274: invokestatic  #85                 // Method com/virtual/common/ErrorCodes.getErrorMessage:(I)Ljava/lang/String;
     277: invokevirtual #86                 // Method com/virtual/ssv/server/entity/ResultJson.setErrorMsg:(Ljava/lang/String;)V
     280: goto          339
     283: aload         7
     285: invokevirtual #83                 // Method com/virtual/common/AppException.getErrorCode:()I
     288: bipush        103
     290: if_icmpne     306
     293: aload         6
     295: bipush        103
     297: invokestatic  #85                 // Method com/virtual/common/ErrorCodes.getErrorMessage:(I)Ljava/lang/String;
     300: invokevirtual #86                 // Method com/virtual/ssv/server/entity/ResultJson.setErrorMsg:(Ljava/lang/String;)V
     303: goto          339
     306: aload         7
     308: invokevirtual #83                 // Method com/virtual/common/AppException.getErrorCode:()I
     311: bipush        11
     313: if_icmpne     329
     316: aload         6
     318: bipush        11
     320: invokestatic  #85                 // Method com/virtual/common/ErrorCodes.getErrorMessage:(I)Ljava/lang/String;
     323: invokevirtual #86                 // Method com/virtual/ssv/server/entity/ResultJson.setErrorMsg:(Ljava/lang/String;)V
     326: goto          339
     329: aload         6
     331: aload         7
     333: invokevirtual #87                 // Method com/virtual/common/AppException.getMessage:()Ljava/lang/String;
     336: invokevirtual #86                 // Method com/virtual/ssv/server/entity/ResultJson.setErrorMsg:(Ljava/lang/String;)V
     339: aload_0
     340: aload_2
     341: aload_0
     342: getfield      #88                 // Field filterJson:Lcom/google/gson/Gson;
     345: aload         6
     347: invokevirtual #89                 // Method com/google/gson/Gson.toJson:(Ljava/lang/Object;)Ljava/lang/String;
     350: invokevirtual #90                 // Method write:(Ljavax/servlet/http/HttpServletResponse;Ljava/lang/String;)V
     353: return
    Exception table:
       from    to  target type
          18   255   258   Class com/virtual/common/AppException

  private void deleteStrategy(javax.servlet.http.HttpServletRequest, javax.servlet.http.HttpServletResponse, com.virtual.ssv.server.user.LoginInfo);
    Code:
       0: new           #42                 // class java/util/Date
       3: dup
       4: invokespecial #43                 // Method java/util/Date."<init>":()V
       7: astore        4
       9: new           #44                 // class com/virtual/ssv/server/entity/ResultJson
      12: dup
      13: invokespecial #45                 // Method com/virtual/ssv/server/entity/ResultJson."<init>":()V
      16: astore        5
      18: aload_1
      19: ldc           #121                // String strategyId
      21: invokeinterface #8,  2            // InterfaceMethod javax/servlet/http/HttpServletRequest.getParameter:(Ljava/lang/String;)Ljava/lang/String;
      26: astore        6
      28: aload_1
      29: ldc           #151                // String strategyName
      31: invokeinterface #8,  2            // InterfaceMethod javax/servlet/http/HttpServletRequest.getParameter:(Ljava/lang/String;)Ljava/lang/String;
      36: astore        7
      38: aload         6
      40: invokestatic  #107                // Method org/apache/commons/lang/StringUtils.isEmpty:(Ljava/lang/String;)Z
      43: ifne          54
      46: aload         7
      48: invokestatic  #107                // Method org/apache/commons/lang/StringUtils.isEmpty:(Ljava/lang/String;)Z
      51: ifeq          55
      54: return
      55: aload_0
      56: getfield      #50                 // Field reqHandle:Lcom/virtual/ssv/server/rs/client/RequestHandle;
      59: aload         6
      61: invokestatic  #92                 // Method java/lang/Long.parseLong:(Ljava/lang/String;)J
      64: invokestatic  #93                 // Method java/lang/Long.valueOf:(J)Ljava/lang/Long;
      67: aload         7
      69: invokevirtual #159                // Method com/virtual/ssv/server/rs/client/RequestHandle.deleteCloudBackupStrategy:(Ljava/lang/Long;Ljava/lang/String;)Lcom/virtual/ssv/server/entity/ResultJson;
      72: astore        5
      74: new           #42                 // class java/util/Date
      77: dup
      78: invokespecial #43                 // Method java/util/Date."<init>":()V
      81: astore        8
      83: new           #53                 // class com/virtual/ssv/server/rs/client/entity/RsOperateLog
      86: dup
      87: invokespecial #54                 // Method com/virtual/ssv/server/rs/client/entity/RsOperateLog."<init>":()V
      90: astore        9
      92: aload         9
      94: aload_3
      95: invokevirtual #55                 // Method com/virtual/ssv/server/user/LoginInfo.getId:()Ljava/lang/Long;
      98: invokevirtual #56                 // Method com/virtual/ssv/server/rs/client/entity/RsOperateLog.setUserId:(Ljava/lang/Long;)V
     101: aload         9
     103: aload_3
     104: invokevirtual #57                 // Method com/virtual/ssv/server/user/LoginInfo.getOrgId:()Ljava/lang/Long;
     107: invokevirtual #58                 // Method com/virtual/ssv/server/rs/client/entity/RsOperateLog.setOrgId:(Ljava/lang/Long;)V
     110: aload         9
     112: aload_3
     113: invokevirtual #59                 // Method com/virtual/ssv/server/user/LoginInfo.getLoginName:()Ljava/lang/String;
     116: invokevirtual #60                 // Method com/virtual/ssv/server/rs/client/entity/RsOperateLog.setLoginName:(Ljava/lang/String;)V
     119: aload         9
     121: aload_3
     122: invokevirtual #61                 // Method com/virtual/ssv/server/user/LoginInfo.getUserName:()Ljava/lang/String;
     125: invokevirtual #62                 // Method com/virtual/ssv/server/rs/client/entity/RsOperateLog.setUserName:(Ljava/lang/String;)V
     128: aload         9
     130: aload_3
     131: invokevirtual #63                 // Method com/virtual/ssv/server/user/LoginInfo.getLoginIp:()Ljava/lang/String;
     134: invokevirtual #64                 // Method com/virtual/ssv/server/rs/client/entity/RsOperateLog.setAddress:(Ljava/lang/String;)V
     137: aload         9
     139: bipush        30
     141: invokestatic  #66                 // Method java/lang/Integer.valueOf:(I)Ljava/lang/Integer;
     144: invokevirtual #67                 // Method com/virtual/ssv/server/rs/client/entity/RsOperateLog.setCategory:(Ljava/lang/Integer;)V
     147: aload         9
     149: aload_0
     150: getfield      #68                 // Field logSm:Lcom/virtual/common/StringManager;
     153: ldc           #160                // String cloudBackupStrategy.delete.operation
     155: iconst_1
     156: anewarray     #70                 // class java/lang/Object
     159: dup
     160: iconst_0
     161: aload         7
     163: aastore
     164: invokevirtual #71                 // Method com/virtual/common/StringManager.getString:(Ljava/lang/String;[Ljava/lang/Object;)Ljava/lang/String;
     167: invokevirtual #72                 // Method com/virtual/ssv/server/rs/client/entity/RsOperateLog.setDescription:(Ljava/lang/String;)V
     170: aload         9
     172: aload         4
     174: invokevirtual #73                 // Method com/virtual/ssv/server/rs/client/entity/RsOperateLog.setStartTime:(Ljava/util/Date;)V
     177: aload         9
     179: aload         8
     181: invokevirtual #74                 // Method com/virtual/ssv/server/rs/client/entity/RsOperateLog.setEndTime:(Ljava/util/Date;)V
     184: aload         5
     186: invokevirtual #75                 // Method com/virtual/ssv/server/entity/ResultJson.isSuccess:()Z
     189: ifeq          203
     192: aload         9
     194: getstatic     #76                 // Field com/virtual/ssv/server/rs/client/entity/RsOperateLog.RESULT_SUCCESS:Ljava/lang/Integer;
     197: invokevirtual #77                 // Method com/virtual/ssv/server/rs/client/entity/RsOperateLog.setResult:(Ljava/lang/Integer;)V
     200: goto          221
     203: aload         9
     205: getstatic     #78                 // Field com/virtual/ssv/server/rs/client/entity/RsOperateLog.RESULT_FAILURE:Ljava/lang/Integer;
     208: invokevirtual #77                 // Method com/virtual/ssv/server/rs/client/entity/RsOperateLog.setResult:(Ljava/lang/Integer;)V
     211: aload         9
     213: aload         5
     215: invokevirtual #96                 // Method com/virtual/ssv/server/entity/ResultJson.getFailtureReson:()Ljava/lang/String;
     218: invokevirtual #80                 // Method com/virtual/ssv/server/rs/client/entity/RsOperateLog.setFailureReason:(Ljava/lang/String;)V
     221: aload_0
     222: getfield      #50                 // Field reqHandle:Lcom/virtual/ssv/server/rs/client/RequestHandle;
     225: aload         9
     227: invokevirtual #81                 // Method com/virtual/ssv/server/rs/client/RequestHandle.addUserLog:(Lcom/virtual/ssv/server/rs/client/entity/RsOperateLog;)Ljava/lang/Long;
     230: pop
     231: goto          315
     234: astore        6
     236: aload         6
     238: invokevirtual #83                 // Method com/virtual/common/AppException.getErrorCode:()I
     241: bipush        102
     243: if_icmpne     259
     246: aload         5
     248: bipush        102
     250: invokestatic  #85                 // Method com/virtual/common/ErrorCodes.getErrorMessage:(I)Ljava/lang/String;
     253: invokevirtual #86                 // Method com/virtual/ssv/server/entity/ResultJson.setErrorMsg:(Ljava/lang/String;)V
     256: goto          315
     259: aload         6
     261: invokevirtual #83                 // Method com/virtual/common/AppException.getErrorCode:()I
     264: bipush        103
     266: if_icmpne     282
     269: aload         5
     271: bipush        103
     273: invokestatic  #85                 // Method com/virtual/common/ErrorCodes.getErrorMessage:(I)Ljava/lang/String;
     276: invokevirtual #86                 // Method com/virtual/ssv/server/entity/ResultJson.setErrorMsg:(Ljava/lang/String;)V
     279: goto          315
     282: aload         6
     284: invokevirtual #83                 // Method com/virtual/common/AppException.getErrorCode:()I
     287: bipush        11
     289: if_icmpne     305
     292: aload         5
     294: bipush        11
     296: invokestatic  #85                 // Method com/virtual/common/ErrorCodes.getErrorMessage:(I)Ljava/lang/String;
     299: invokevirtual #86                 // Method com/virtual/ssv/server/entity/ResultJson.setErrorMsg:(Ljava/lang/String;)V
     302: goto          315
     305: aload         5
     307: aload         6
     309: invokevirtual #87                 // Method com/virtual/common/AppException.getMessage:()Ljava/lang/String;
     312: invokevirtual #86                 // Method com/virtual/ssv/server/entity/ResultJson.setErrorMsg:(Ljava/lang/String;)V
     315: aload_0
     316: aload_2
     317: aload_0
     318: getfield      #88                 // Field filterJson:Lcom/google/gson/Gson;
     321: aload         5
     323: invokevirtual #89                 // Method com/google/gson/Gson.toJson:(Ljava/lang/Object;)Ljava/lang/String;
     326: invokevirtual #90                 // Method write:(Ljavax/servlet/http/HttpServletResponse;Ljava/lang/String;)V
     329: return
    Exception table:
       from    to  target type
          18    54   234   Class com/virtual/common/AppException
          55   231   234   Class com/virtual/common/AppException

  private void revokeStrategyWorkFlow(javax.servlet.http.HttpServletRequest, javax.servlet.http.HttpServletResponse, com.virtual.ssv.server.user.LoginInfo);
    Code:
       0: new           #42                 // class java/util/Date
       3: dup
       4: invokespecial #43                 // Method java/util/Date."<init>":()V
       7: astore        4
       9: new           #44                 // class com/virtual/ssv/server/entity/ResultJson
      12: dup
      13: invokespecial #45                 // Method com/virtual/ssv/server/entity/ResultJson."<init>":()V
      16: astore        5
      18: aload_1
      19: ldc           #161                // String strategyIds
      21: invokeinterface #8,  2            // InterfaceMethod javax/servlet/http/HttpServletRequest.getParameter:(Ljava/lang/String;)Ljava/lang/String;
      26: astore        6
      28: aload_1
      29: ldc           #48                 // String name
      31: invokeinterface #8,  2            // InterfaceMethod javax/servlet/http/HttpServletRequest.getParameter:(Ljava/lang/String;)Ljava/lang/String;
      36: astore        7
      38: aload         6
      40: invokestatic  #107                // Method org/apache/commons/lang/StringUtils.isEmpty:(Ljava/lang/String;)Z
      43: ifeq          47
      46: return
      47: aload_0
      48: getfield      #50                 // Field reqHandle:Lcom/virtual/ssv/server/rs/client/RequestHandle;
      51: aload         6
      53: invokestatic  #51                 // Method java/lang/Long.valueOf:(Ljava/lang/String;)Ljava/lang/Long;
      56: aload         7
      58: invokevirtual #162                // Method com/virtual/ssv/server/rs/client/RequestHandle.revokeCloudBackupStrategyWorkFlow:(Ljava/lang/Long;Ljava/lang/String;)Lcom/virtual/ssv/server/entity/ResultJson;
      61: astore        5
      63: new           #42                 // class java/util/Date
      66: dup
      67: invokespecial #43                 // Method java/util/Date."<init>":()V
      70: astore        8
      72: new           #53                 // class com/virtual/ssv/server/rs/client/entity/RsOperateLog
      75: dup
      76: invokespecial #54                 // Method com/virtual/ssv/server/rs/client/entity/RsOperateLog."<init>":()V
      79: astore        9
      81: aload         9
      83: aload_3
      84: invokevirtual #55                 // Method com/virtual/ssv/server/user/LoginInfo.getId:()Ljava/lang/Long;
      87: invokevirtual #56                 // Method com/virtual/ssv/server/rs/client/entity/RsOperateLog.setUserId:(Ljava/lang/Long;)V
      90: aload         9
      92: aload_3
      93: invokevirtual #57                 // Method com/virtual/ssv/server/user/LoginInfo.getOrgId:()Ljava/lang/Long;
      96: invokevirtual #58                 // Method com/virtual/ssv/server/rs/client/entity/RsOperateLog.setOrgId:(Ljava/lang/Long;)V
      99: aload         9
     101: aload_3
     102: invokevirtual #59                 // Method com/virtual/ssv/server/user/LoginInfo.getLoginName:()Ljava/lang/String;
     105: invokevirtual #60                 // Method com/virtual/ssv/server/rs/client/entity/RsOperateLog.setLoginName:(Ljava/lang/String;)V
     108: aload         9
     110: aload_3
     111: invokevirtual #61                 // Method com/virtual/ssv/server/user/LoginInfo.getUserName:()Ljava/lang/String;
     114: invokevirtual #62                 // Method com/virtual/ssv/server/rs/client/entity/RsOperateLog.setUserName:(Ljava/lang/String;)V
     117: aload         9
     119: aload_3
     120: invokevirtual #63                 // Method com/virtual/ssv/server/user/LoginInfo.getLoginIp:()Ljava/lang/String;
     123: invokevirtual #64                 // Method com/virtual/ssv/server/rs/client/entity/RsOperateLog.setAddress:(Ljava/lang/String;)V
     126: aload         9
     128: bipush        30
     130: invokestatic  #66                 // Method java/lang/Integer.valueOf:(I)Ljava/lang/Integer;
     133: invokevirtual #67                 // Method com/virtual/ssv/server/rs/client/entity/RsOperateLog.setCategory:(Ljava/lang/Integer;)V
     136: aload         9
     138: aload_0
     139: getfield      #68                 // Field logSm:Lcom/virtual/common/StringManager;
     142: ldc           #163                // String cloudBackupStrategyWorkFlow.revoke.operation
     144: iconst_1
     145: anewarray     #70                 // class java/lang/Object
     148: dup
     149: iconst_0
     150: aload         7
     152: aastore
     153: invokevirtual #71                 // Method com/virtual/common/StringManager.getString:(Ljava/lang/String;[Ljava/lang/Object;)Ljava/lang/String;
     156: invokevirtual #72                 // Method com/virtual/ssv/server/rs/client/entity/RsOperateLog.setDescription:(Ljava/lang/String;)V
     159: aload         9
     161: aload         4
     163: invokevirtual #73                 // Method com/virtual/ssv/server/rs/client/entity/RsOperateLog.setStartTime:(Ljava/util/Date;)V
     166: aload         9
     168: aload         8
     170: invokevirtual #74                 // Method com/virtual/ssv/server/rs/client/entity/RsOperateLog.setEndTime:(Ljava/util/Date;)V
     173: aload         5
     175: invokevirtual #75                 // Method com/virtual/ssv/server/entity/ResultJson.isSuccess:()Z
     178: ifeq          192
     181: aload         9
     183: getstatic     #76                 // Field com/virtual/ssv/server/rs/client/entity/RsOperateLog.RESULT_SUCCESS:Ljava/lang/Integer;
     186: invokevirtual #77                 // Method com/virtual/ssv/server/rs/client/entity/RsOperateLog.setResult:(Ljava/lang/Integer;)V
     189: goto          210
     192: aload         9
     194: getstatic     #78                 // Field com/virtual/ssv/server/rs/client/entity/RsOperateLog.RESULT_FAILURE:Ljava/lang/Integer;
     197: invokevirtual #77                 // Method com/virtual/ssv/server/rs/client/entity/RsOperateLog.setResult:(Ljava/lang/Integer;)V
     200: aload         9
     202: aload         5
     204: invokevirtual #96                 // Method com/virtual/ssv/server/entity/ResultJson.getFailtureReson:()Ljava/lang/String;
     207: invokevirtual #80                 // Method com/virtual/ssv/server/rs/client/entity/RsOperateLog.setFailureReason:(Ljava/lang/String;)V
     210: aload_0
     211: getfield      #50                 // Field reqHandle:Lcom/virtual/ssv/server/rs/client/RequestHandle;
     214: aload         9
     216: invokevirtual #81                 // Method com/virtual/ssv/server/rs/client/RequestHandle.addUserLog:(Lcom/virtual/ssv/server/rs/client/entity/RsOperateLog;)Ljava/lang/Long;
     219: pop
     220: goto          304
     223: astore        6
     225: aload         6
     227: invokevirtual #83                 // Method com/virtual/common/AppException.getErrorCode:()I
     230: bipush        102
     232: if_icmpne     248
     235: aload         5
     237: bipush        102
     239: invokestatic  #85                 // Method com/virtual/common/ErrorCodes.getErrorMessage:(I)Ljava/lang/String;
     242: invokevirtual #86                 // Method com/virtual/ssv/server/entity/ResultJson.setErrorMsg:(Ljava/lang/String;)V
     245: goto          304
     248: aload         6
     250: invokevirtual #83                 // Method com/virtual/common/AppException.getErrorCode:()I
     253: bipush        103
     255: if_icmpne     271
     258: aload         5
     260: bipush        103
     262: invokestatic  #85                 // Method com/virtual/common/ErrorCodes.getErrorMessage:(I)Ljava/lang/String;
     265: invokevirtual #86                 // Method com/virtual/ssv/server/entity/ResultJson.setErrorMsg:(Ljava/lang/String;)V
     268: goto          304
     271: aload         6
     273: invokevirtual #83                 // Method com/virtual/common/AppException.getErrorCode:()I
     276: bipush        11
     278: if_icmpne     294
     281: aload         5
     283: bipush        11
     285: invokestatic  #85                 // Method com/virtual/common/ErrorCodes.getErrorMessage:(I)Ljava/lang/String;
     288: invokevirtual #86                 // Method com/virtual/ssv/server/entity/ResultJson.setErrorMsg:(Ljava/lang/String;)V
     291: goto          304
     294: aload         5
     296: aload         6
     298: invokevirtual #87                 // Method com/virtual/common/AppException.getMessage:()Ljava/lang/String;
     301: invokevirtual #86                 // Method com/virtual/ssv/server/entity/ResultJson.setErrorMsg:(Ljava/lang/String;)V
     304: aload_0
     305: aload_2
     306: aload_0
     307: getfield      #88                 // Field filterJson:Lcom/google/gson/Gson;
     310: aload         5
     312: invokevirtual #89                 // Method com/google/gson/Gson.toJson:(Ljava/lang/Object;)Ljava/lang/String;
     315: invokevirtual #90                 // Method write:(Ljavax/servlet/http/HttpServletResponse;Ljava/lang/String;)V
     318: return
    Exception table:
       from    to  target type
          18    46   223   Class com/virtual/common/AppException
          47   220   223   Class com/virtual/common/AppException

  private void checkStrategyReName(javax.servlet.http.HttpServletRequest, javax.servlet.http.HttpServletResponse, com.virtual.ssv.server.user.LoginInfo);
    Code:
       0: ldc           #164                // String
       2: astore        4
       4: aload_1
       5: ldc           #151                // String strategyName
       7: invokeinterface #8,  2            // InterfaceMethod javax/servlet/http/HttpServletRequest.getParameter:(Ljava/lang/String;)Ljava/lang/String;
      12: astore        5
      14: aload_1
      15: ldc           #46                 // String id
      17: invokeinterface #8,  2            // InterfaceMethod javax/servlet/http/HttpServletRequest.getParameter:(Ljava/lang/String;)Ljava/lang/String;
      22: astore        6
      24: aload         5
      26: ifnull        43
      29: aload_0
      30: getfield      #50                 // Field reqHandle:Lcom/virtual/ssv/server/rs/client/RequestHandle;
      33: aload         5
      35: aload         6
      37: aload_3
      38: invokevirtual #165                // Method com/virtual/ssv/server/rs/client/RequestHandle.checkBackupStrategyName:(Ljava/lang/String;Ljava/lang/String;Lcom/virtual/ssv/server/user/LoginInfo;)Ljava/lang/String;
      41: astore        4
      43: goto          58
      46: astore        5
      48: getstatic     #125                // Field log:Lorg/apache/commons/logging/Log;
      51: aload         5
      53: invokeinterface #126,  2          // InterfaceMethod org/apache/commons/logging/Log.error:(Ljava/lang/Object;)V
      58: aload_0
      59: aload_2
      60: aload_0
      61: getfield      #88                 // Field filterJson:Lcom/google/gson/Gson;
      64: aload         4
      66: invokevirtual #89                 // Method com/google/gson/Gson.toJson:(Ljava/lang/Object;)Ljava/lang/String;
      69: invokevirtual #90                 // Method write:(Ljavax/servlet/http/HttpServletResponse;Ljava/lang/String;)V
      72: return
    Exception table:
       from    to  target type
           4    43    46   Class java/lang/Exception

  private void queryStrategyVmList(javax.servlet.http.HttpServletRequest, javax.servlet.http.HttpServletResponse, com.virtual.ssv.server.user.LoginInfo);
    Code:
       0: new           #103                // class com/virtual/ssv/server/entity/CommonListJson
       3: dup
       4: invokespecial #104                // Method com/virtual/ssv/server/entity/CommonListJson."<init>":()V
       7: astore        4
       9: aload_1
      10: ldc           #166                // String cloud
      12: invokeinterface #8,  2            // InterfaceMethod javax/servlet/http/HttpServletRequest.getParameter:(Ljava/lang/String;)Ljava/lang/String;
      17: astore        5
      19: aload_1
      20: ldc           #167                // String title
      22: invokeinterface #8,  2            // InterfaceMethod javax/servlet/http/HttpServletRequest.getParameter:(Ljava/lang/String;)Ljava/lang/String;
      27: astore        6
      29: aload_1
      30: ldc           #121                // String strategyId
      32: invokeinterface #8,  2            // InterfaceMethod javax/servlet/http/HttpServletRequest.getParameter:(Ljava/lang/String;)Ljava/lang/String;
      37: astore        7
      39: aload         6
      41: ifnull        63
      44: aload         6
      46: invokestatic  #49                 // Method org/apache/commons/lang/StringUtils.isNotEmpty:(Ljava/lang/String;)Z
      49: ifeq          63
      52: aload         6
      54: ldc           #168                // String *
      56: ldc           #169                // String %
      58: invokevirtual #170                // Method java/lang/String.replace:(Ljava/lang/CharSequence;Ljava/lang/CharSequence;)Ljava/lang/String;
      61: astore        6
      63: aload_0
      64: getfield      #50                 // Field reqHandle:Lcom/virtual/ssv/server/rs/client/RequestHandle;
      67: aload_3
      68: aload         6
      70: aconst_null
      71: invokevirtual #171                // Method com/virtual/ssv/server/rs/client/RequestHandle.queryVmCount:(Lcom/virtual/ssv/server/user/LoginInfo;Ljava/lang/String;Ljava/lang/String;)Ljava/lang/Integer;
      74: astore        8
      76: aload_0
      77: getfield      #50                 // Field reqHandle:Lcom/virtual/ssv/server/rs/client/RequestHandle;
      80: aload_3
      81: iconst_0
      82: iconst_0
      83: aload         6
      85: aload         5
      87: invokevirtual #172                // Method com/virtual/ssv/server/rs/client/RequestHandle.queryVmList:(Lcom/virtual/ssv/server/user/LoginInfo;IILjava/lang/String;Ljava/lang/String;)Ljava/util/List;
      90: astore        9
      92: aload_0
      93: getfield      #50                 // Field reqHandle:Lcom/virtual/ssv/server/rs/client/RequestHandle;
      96: aconst_null
      97: aload_3
      98: invokevirtual #55                 // Method com/virtual/ssv/server/user/LoginInfo.getId:()Ljava/lang/Long;
     101: aload_3
     102: invokevirtual #57                 // Method com/virtual/ssv/server/user/LoginInfo.getOrgId:()Ljava/lang/Long;
     105: aload         7
     107: invokevirtual #173                // Method com/virtual/ssv/server/rs/client/RequestHandle.queryVmBindByWorkFlow:(Lcom/virtual/ssv/server/entity/PagingLoadConfig;Ljava/lang/Long;Ljava/lang/Long;Ljava/lang/String;)Ljava/util/List;
     110: astore        10
     112: new           #118                // class java/util/ArrayList
     115: dup
     116: invokespecial #119                // Method java/util/ArrayList."<init>":()V
     119: astore        11
     121: aload         10
     123: ifnull        173
     126: aload         10
     128: invokeinterface #174,  1          // InterfaceMethod java/util/List.iterator:()Ljava/util/Iterator;
     133: astore        12
     135: aload         12
     137: invokeinterface #175,  1          // InterfaceMethod java/util/Iterator.hasNext:()Z
     142: ifeq          173
     145: aload         12
     147: invokeinterface #176,  1          // InterfaceMethod java/util/Iterator.next:()Ljava/lang/Object;
     152: checkcast     #177                // class com/virtual/ssv/server/rs/client/entity/RsStrategyWorkFlowVM
     155: astore        13
     157: aload         11
     159: aload         13
     161: invokevirtual #178                // Method com/virtual/ssv/server/rs/client/entity/RsStrategyWorkFlowVM.getDomainId:()Ljava/lang/Long;
     164: invokeinterface #179,  2          // InterfaceMethod java/util/List.add:(Ljava/lang/Object;)Z
     169: pop
     170: goto          135
     173: aload_0
     174: getfield      #50                 // Field reqHandle:Lcom/virtual/ssv/server/rs/client/RequestHandle;
     177: aconst_null
     178: aload_3
     179: invokevirtual #55                 // Method com/virtual/ssv/server/user/LoginInfo.getId:()Ljava/lang/Long;
     182: aload_3
     183: invokevirtual #57                 // Method com/virtual/ssv/server/user/LoginInfo.getOrgId:()Ljava/lang/Long;
     186: aload         7
     188: invokevirtual #180                // Method com/virtual/ssv/server/rs/client/RequestHandle.queryVmBindByStrategy:(Lcom/virtual/ssv/server/entity/PagingLoadConfig;Ljava/lang/Long;Ljava/lang/Long;Ljava/lang/String;)Ljava/util/List;
     191: astore        12
     193: new           #118                // class java/util/ArrayList
     196: dup
     197: invokespecial #119                // Method java/util/ArrayList."<init>":()V
     200: astore        13
     202: aload         12
     204: ifnull        254
     207: aload         12
     209: invokeinterface #174,  1          // InterfaceMethod java/util/List.iterator:()Ljava/util/Iterator;
     214: astore        14
     216: aload         14
     218: invokeinterface #175,  1          // InterfaceMethod java/util/Iterator.hasNext:()Z
     223: ifeq          254
     226: aload         14
     228: invokeinterface #176,  1          // InterfaceMethod java/util/Iterator.next:()Ljava/lang/Object;
     233: checkcast     #181                // class com/virtual/ssv/server/rs/client/entity/RsStrategyVM
     236: astore        15
     238: aload         13
     240: aload         15
     242: invokevirtual #182                // Method com/virtual/ssv/server/rs/client/entity/RsStrategyVM.getDomainId:()Ljava/lang/Long;
     245: invokeinterface #179,  2          // InterfaceMethod java/util/List.add:(Ljava/lang/Object;)Z
     250: pop
     251: goto          216
     254: aload         9
     256: invokeinterface #174,  1          // InterfaceMethod java/util/List.iterator:()Ljava/util/Iterator;
     261: astore        14
     263: aload         14
     265: invokeinterface #175,  1          // InterfaceMethod java/util/Iterator.hasNext:()Z
     270: ifeq          420
     273: aload         14
     275: invokeinterface #176,  1          // InterfaceMethod java/util/Iterator.next:()Ljava/lang/Object;
     280: checkcast     #183                // class com/virtual/ssv/server/rs/client/entity/RsDomain
     283: astore        15
     285: aload         15
     287: invokevirtual #184                // Method com/virtual/ssv/server/rs/client/entity/RsDomain.getType:()Ljava/lang/Integer;
     290: invokevirtual #185                // Method java/lang/Integer.intValue:()I
     293: iconst_1
     294: if_icmpne     307
     297: aload         14
     299: invokeinterface #186,  1          // InterfaceMethod java/util/Iterator.remove:()V
     304: goto          263
     307: aload         15
     309: invokevirtual #187                // Method com/virtual/ssv/server/rs/client/entity/RsDomain.getStatus:()Ljava/lang/Integer;
     312: invokevirtual #185                // Method java/lang/Integer.intValue:()I
     315: iconst_1
     316: if_icmpne     329
     319: aload         14
     321: invokeinterface #186,  1          // InterfaceMethod java/util/Iterator.remove:()V
     326: goto          263
     329: aload         15
     331: invokevirtual #188                // Method com/virtual/ssv/server/rs/client/entity/RsDomain.getAssignMode:()I
     334: iconst_2
     335: if_icmpne     348
     338: aload         14
     340: invokeinterface #186,  1          // InterfaceMethod java/util/Iterator.remove:()V
     345: goto          263
     348: aload         11
     350: aload         15
     352: invokevirtual #189                // Method com/virtual/ssv/server/rs/client/entity/RsDomain.getId:()Ljava/lang/Long;
     355: invokeinterface #190,  2          // InterfaceMethod java/util/List.contains:(Ljava/lang/Object;)Z
     360: ifeq          373
     363: aload         14
     365: invokeinterface #186,  1          // InterfaceMethod java/util/Iterator.remove:()V
     370: goto          263
     373: aload         13
     375: aload         15
     377: invokevirtual #189                // Method com/virtual/ssv/server/rs/client/entity/RsDomain.getId:()Ljava/lang/Long;
     380: invokeinterface #190,  2          // InterfaceMethod java/util/List.contains:(Ljava/lang/Object;)Z
     385: ifeq          395
     388: aload         14
     390: invokeinterface #186,  1          // InterfaceMethod java/util/Iterator.remove:()V
     395: aload         15
     397: invokevirtual #191                // Method com/virtual/ssv/server/rs/client/entity/RsDomain.getProtectModel:()Ljava/lang/Integer;
     400: invokevirtual #185                // Method java/lang/Integer.intValue:()I
     403: iconst_1
     404: if_icmpne     417
     407: aload         14
     409: invokeinterface #186,  1          // InterfaceMethod java/util/Iterator.remove:()V
     414: goto          263
     417: goto          263
     420: aload         4
     422: aload         8
     424: invokevirtual #185                // Method java/lang/Integer.intValue:()I
     427: i2l
     428: invokevirtual #192                // Method com/virtual/ssv/server/entity/CommonListJson.setTotal:(J)V
     431: aload         4
     433: aload         9
     435: invokevirtual #120                // Method com/virtual/ssv/server/entity/CommonListJson.setRows:(Ljava/util/List;)V
     438: aload         5
     440: invokestatic  #49                 // Method org/apache/commons/lang/StringUtils.isNotEmpty:(Ljava/lang/String;)Z
     443: ifeq          461
     446: aload_0
     447: aload_2
     448: aload_0
     449: getfield      #112                // Field gson:Lcom/google/gson/Gson;
     452: aload         9
     454: invokevirtual #89                 // Method com/google/gson/Gson.toJson:(Ljava/lang/Object;)Ljava/lang/String;
     457: invokevirtual #90                 // Method write:(Ljavax/servlet/http/HttpServletResponse;Ljava/lang/String;)V
     460: return
     461: goto          577
     464: astore        5
     466: aload         4
     468: aload_0
     469: getfield      #68                 // Field logSm:Lcom/virtual/common/StringManager;
     472: ldc           #113                // String operError
     474: invokevirtual #114                // Method com/virtual/common/StringManager.getString:(Ljava/lang/String;)Ljava/lang/String;
     477: invokevirtual #115                // Method com/virtual/ssv/server/entity/CommonListJson.setTitle:(Ljava/lang/String;)V
     480: aload         5
     482: invokevirtual #83                 // Method com/virtual/common/AppException.getErrorCode:()I
     485: bipush        102
     487: if_icmpne     503
     490: aload         4
     492: bipush        102
     494: invokestatic  #85                 // Method com/virtual/common/ErrorCodes.getErrorMessage:(I)Ljava/lang/String;
     497: invokevirtual #116                // Method com/virtual/ssv/server/entity/CommonListJson.setMessage:(Ljava/lang/String;)V
     500: goto          559
     503: aload         5
     505: invokevirtual #83                 // Method com/virtual/common/AppException.getErrorCode:()I
     508: bipush        103
     510: if_icmpne     526
     513: aload         4
     515: bipush        103
     517: invokestatic  #85                 // Method com/virtual/common/ErrorCodes.getErrorMessage:(I)Ljava/lang/String;
     520: invokevirtual #116                // Method com/virtual/ssv/server/entity/CommonListJson.setMessage:(Ljava/lang/String;)V
     523: goto          559
     526: aload         5
     528: invokevirtual #83                 // Method com/virtual/common/AppException.getErrorCode:()I
     531: bipush        11
     533: if_icmpne     549
     536: aload         4
     538: bipush        11
     540: invokestatic  #85                 // Method com/virtual/common/ErrorCodes.getErrorMessage:(I)Ljava/lang/String;
     543: invokevirtual #116                // Method com/virtual/ssv/server/entity/CommonListJson.setMessage:(Ljava/lang/String;)V
     546: goto          559
     549: aload         4
     551: aload         5
     553: invokevirtual #87                 // Method com/virtual/common/AppException.getMessage:()Ljava/lang/String;
     556: invokevirtual #116                // Method com/virtual/ssv/server/entity/CommonListJson.setMessage:(Ljava/lang/String;)V
     559: aload         4
     561: iconst_0
     562: invokevirtual #117                // Method com/virtual/ssv/server/entity/CommonListJson.setState:(I)V
     565: aload         4
     567: new           #118                // class java/util/ArrayList
     570: dup
     571: invokespecial #119                // Method java/util/ArrayList."<init>":()V
     574: invokevirtual #120                // Method com/virtual/ssv/server/entity/CommonListJson.setRows:(Ljava/util/List;)V
     577: aload_0
     578: aload_2
     579: aload_0
     580: getfield      #112                // Field gson:Lcom/google/gson/Gson;
     583: aload         4
     585: invokevirtual #89                 // Method com/google/gson/Gson.toJson:(Ljava/lang/Object;)Ljava/lang/String;
     588: invokevirtual #90                 // Method write:(Ljavax/servlet/http/HttpServletResponse;Ljava/lang/String;)V
     591: return
    Exception table:
       from    to  target type
           9   460   464   Class com/virtual/common/AppException
}
