Compiled from "WorkOrderServlet.java"
public class com.virtual.ssv.server.workorder.WorkOrderServlet extends com.virtual.ssv.server.BaseServlet {
  private static final long serialVersionUID;

  public void init();
    Code:
       0: aload_0
       1: invokespecial #1                  // Method com/virtual/ssv/server/BaseServlet.init:()V
       4: return

  public com.virtual.ssv.server.workorder.WorkOrderServlet();
    Code:
       0: aload_0
       1: invokespecial #2                  // Method com/virtual/ssv/server/BaseServlet."<init>":()V
       4: return

  protected void doGet(javax.servlet.http.HttpServletRequest, javax.servlet.http.HttpServletResponse) throws javax.servlet.ServletException, java.io.IOException;
    Code:
       0: aload_1
       1: invokeinterface #3,  1            // InterfaceMethod javax/servlet/http/HttpServletRequest.getSession:()Ljavax/servlet/http/HttpSession;
       6: astore_3
       7: aload_3
       8: ldc           #4                  // String loginInfo
      10: invokeinterface #5,  2            // InterfaceMethod javax/servlet/http/HttpSession.getAttribute:(Ljava/lang/String;)Ljava/lang/Object;
      15: checkcast     #6                  // class com/virtual/ssv/server/user/LoginInfo
      18: astore        4
      20: aload         4
      22: ifnull        135
      25: aload_0
      26: aload_1
      27: aload_2
      28: invokevirtual #7                  // Method checkUserState:(Ljavax/servlet/http/HttpServletRequest;Ljavax/servlet/http/HttpServletResponse;)V
      31: aload_1
      32: ldc           #8                  // String way
      34: invokeinterface #9,  2            // InterfaceMethod javax/servlet/http/HttpServletRequest.getParameter:(Ljava/lang/String;)Ljava/lang/String;
      39: astore        5
      41: ldc           #10                 // String list
      43: aload         5
      45: invokevirtual #11                 // Method java/lang/String.equals:(Ljava/lang/Object;)Z
      48: ifeq          62
      51: aload_0
      52: aload_1
      53: aload_2
      54: aload         4
      56: invokespecial #12                 // Method getList:(Ljavax/servlet/http/HttpServletRequest;Ljavax/servlet/http/HttpServletResponse;Lcom/virtual/ssv/server/user/LoginInfo;)V
      59: goto          135
      62: ldc           #13                 // String apply
      64: aload         5
      66: invokevirtual #11                 // Method java/lang/String.equals:(Ljava/lang/Object;)Z
      69: ifeq          83
      72: aload_0
      73: aload_1
      74: aload_2
      75: aload         4
      77: invokespecial #14                 // Method applyWorkOrder:(Ljavax/servlet/http/HttpServletRequest;Ljavax/servlet/http/HttpServletResponse;Lcom/virtual/ssv/server/user/LoginInfo;)V
      80: goto          135
      83: ldc           #15                 // String stop
      85: aload         5
      87: invokevirtual #11                 // Method java/lang/String.equals:(Ljava/lang/Object;)Z
      90: ifeq          104
      93: aload_0
      94: aload_1
      95: aload_2
      96: aload         4
      98: invokespecial #16                 // Method stopWorkOrder:(Ljavax/servlet/http/HttpServletRequest;Ljavax/servlet/http/HttpServletResponse;Lcom/virtual/ssv/server/user/LoginInfo;)V
     101: goto          135
     104: ldc           #17                 // String delete
     106: aload         5
     108: invokevirtual #11                 // Method java/lang/String.equals:(Ljava/lang/Object;)Z
     111: ifeq          125
     114: aload_0
     115: aload_1
     116: aload_2
     117: aload         4
     119: invokespecial #18                 // Method deleteWorkOrder:(Ljavax/servlet/http/HttpServletRequest;Ljavax/servlet/http/HttpServletResponse;Lcom/virtual/ssv/server/user/LoginInfo;)V
     122: goto          135
     125: ldc           #19                 // String getDetail
     127: aload         5
     129: invokevirtual #11                 // Method java/lang/String.equals:(Ljava/lang/Object;)Z
     132: ifeq          135
     135: return

  private void deleteWorkOrder(javax.servlet.http.HttpServletRequest, javax.servlet.http.HttpServletResponse, com.virtual.ssv.server.user.LoginInfo);
    Code:
       0: new           #20                 // class com/virtual/ssv/server/entity/ResultJson
       3: dup
       4: invokespecial #21                 // Method com/virtual/ssv/server/entity/ResultJson."<init>":()V
       7: astore        4
       9: new           #22                 // class java/util/Date
      12: dup
      13: invokespecial #23                 // Method java/util/Date."<init>":()V
      16: astore        5
      18: aload_1
      19: ldc           #24                 // String id
      21: invokeinterface #9,  2            // InterfaceMethod javax/servlet/http/HttpServletRequest.getParameter:(Ljava/lang/String;)Ljava/lang/String;
      26: astore        6
      28: aload_0
      29: getfield      #25                 // Field reqHandle:Lcom/virtual/ssv/server/rs/client/RequestHandle;
      32: aload         6
      34: invokevirtual #26                 // Method com/virtual/ssv/server/rs/client/RequestHandle.getWorkOrderById:(Ljava/lang/String;)Lcom/virtual/ssv/server/rs/client/entity/CloudWorkOrder;
      37: astore        7
      39: ldc           #27                 // String
      41: astore        8
      43: aconst_null
      44: aload         7
      46: if_acmpeq     70
      49: aload_0
      50: getfield      #25                 // Field reqHandle:Lcom/virtual/ssv/server/rs/client/RequestHandle;
      53: aload         7
      55: invokevirtual #28                 // Method com/virtual/ssv/server/rs/client/RequestHandle.deleteWorkOrderById:(Lcom/virtual/ssv/server/rs/client/entity/CloudWorkOrder;)Lcom/virtual/ssv/server/entity/ResultJson;
      58: astore        4
      60: aload         7
      62: invokevirtual #29                 // Method com/virtual/ssv/server/rs/client/entity/CloudWorkOrder.getTitle:()Ljava/lang/String;
      65: astore        8
      67: goto          84
      70: aload         4
      72: aload_0
      73: getfield      #30                 // Field logSm:Lcom/virtual/common/StringManager;
      76: ldc           #31                 // String workOrderServlet.noexist
      78: invokevirtual #32                 // Method com/virtual/common/StringManager.getString:(Ljava/lang/String;)Ljava/lang/String;
      81: invokevirtual #33                 // Method com/virtual/ssv/server/entity/ResultJson.setErrorMsg:(Ljava/lang/String;)V
      84: new           #22                 // class java/util/Date
      87: dup
      88: invokespecial #23                 // Method java/util/Date."<init>":()V
      91: astore        9
      93: aload_0
      94: aload_3
      95: aload         5
      97: ldc           #34                 // String workOrderServlet.delete
      99: aload         8
     101: aload         4
     103: aload         9
     105: invokespecial #35                 // Method logOpe:(Lcom/virtual/ssv/server/user/LoginInfo;Ljava/util/Date;Ljava/lang/String;Ljava/lang/String;Lcom/virtual/ssv/server/entity/ResultJson;Ljava/util/Date;)V
     108: aload_0
     109: aload_2
     110: aload_0
     111: getfield      #36                 // Field filterJson:Lcom/google/gson/Gson;
     114: aload         4
     116: invokevirtual #37                 // Method com/google/gson/Gson.toJson:(Ljava/lang/Object;)Ljava/lang/String;
     119: invokevirtual #38                 // Method write:(Ljavax/servlet/http/HttpServletResponse;Ljava/lang/String;)V
     122: goto          206
     125: astore        5
     127: aload         5
     129: invokevirtual #40                 // Method com/virtual/common/AppException.getErrorCode:()I
     132: bipush        102
     134: if_icmpne     150
     137: aload         4
     139: bipush        102
     141: invokestatic  #42                 // Method com/virtual/common/ErrorCodes.getErrorMessage:(I)Ljava/lang/String;
     144: invokevirtual #33                 // Method com/virtual/ssv/server/entity/ResultJson.setErrorMsg:(Ljava/lang/String;)V
     147: goto          206
     150: aload         5
     152: invokevirtual #40                 // Method com/virtual/common/AppException.getErrorCode:()I
     155: bipush        103
     157: if_icmpne     173
     160: aload         4
     162: bipush        103
     164: invokestatic  #42                 // Method com/virtual/common/ErrorCodes.getErrorMessage:(I)Ljava/lang/String;
     167: invokevirtual #33                 // Method com/virtual/ssv/server/entity/ResultJson.setErrorMsg:(Ljava/lang/String;)V
     170: goto          206
     173: aload         5
     175: invokevirtual #40                 // Method com/virtual/common/AppException.getErrorCode:()I
     178: bipush        11
     180: if_icmpne     196
     183: aload         4
     185: bipush        11
     187: invokestatic  #42                 // Method com/virtual/common/ErrorCodes.getErrorMessage:(I)Ljava/lang/String;
     190: invokevirtual #33                 // Method com/virtual/ssv/server/entity/ResultJson.setErrorMsg:(Ljava/lang/String;)V
     193: goto          206
     196: aload         4
     198: aload         5
     200: invokevirtual #43                 // Method com/virtual/common/AppException.getMessage:()Ljava/lang/String;
     203: invokevirtual #33                 // Method com/virtual/ssv/server/entity/ResultJson.setErrorMsg:(Ljava/lang/String;)V
     206: aload_0
     207: aload_2
     208: aload_0
     209: getfield      #36                 // Field filterJson:Lcom/google/gson/Gson;
     212: aload         4
     214: invokevirtual #37                 // Method com/google/gson/Gson.toJson:(Ljava/lang/Object;)Ljava/lang/String;
     217: invokevirtual #38                 // Method write:(Ljavax/servlet/http/HttpServletResponse;Ljava/lang/String;)V
     220: return
    Exception table:
       from    to  target type
           9   122   125   Class com/virtual/common/AppException

  private void stopWorkOrder(javax.servlet.http.HttpServletRequest, javax.servlet.http.HttpServletResponse, com.virtual.ssv.server.user.LoginInfo);
    Code:
       0: new           #20                 // class com/virtual/ssv/server/entity/ResultJson
       3: dup
       4: invokespecial #21                 // Method com/virtual/ssv/server/entity/ResultJson."<init>":()V
       7: astore        4
       9: new           #22                 // class java/util/Date
      12: dup
      13: invokespecial #23                 // Method java/util/Date."<init>":()V
      16: astore        5
      18: aload_1
      19: ldc           #24                 // String id
      21: invokeinterface #9,  2            // InterfaceMethod javax/servlet/http/HttpServletRequest.getParameter:(Ljava/lang/String;)Ljava/lang/String;
      26: astore        6
      28: ldc           #27                 // String
      30: astore        7
      32: aload_0
      33: getfield      #25                 // Field reqHandle:Lcom/virtual/ssv/server/rs/client/RequestHandle;
      36: aload         6
      38: invokevirtual #26                 // Method com/virtual/ssv/server/rs/client/RequestHandle.getWorkOrderById:(Ljava/lang/String;)Lcom/virtual/ssv/server/rs/client/entity/CloudWorkOrder;
      41: astore        8
      43: aconst_null
      44: aload         8
      46: if_acmpeq     70
      49: aload_0
      50: getfield      #25                 // Field reqHandle:Lcom/virtual/ssv/server/rs/client/RequestHandle;
      53: aload         8
      55: invokevirtual #44                 // Method com/virtual/ssv/server/rs/client/RequestHandle.stopWorkOrderById:(Lcom/virtual/ssv/server/rs/client/entity/CloudWorkOrder;)Lcom/virtual/ssv/server/entity/ResultJson;
      58: astore        4
      60: aload         8
      62: invokevirtual #29                 // Method com/virtual/ssv/server/rs/client/entity/CloudWorkOrder.getTitle:()Ljava/lang/String;
      65: astore        7
      67: goto          84
      70: aload         4
      72: aload_0
      73: getfield      #30                 // Field logSm:Lcom/virtual/common/StringManager;
      76: ldc           #31                 // String workOrderServlet.noexist
      78: invokevirtual #32                 // Method com/virtual/common/StringManager.getString:(Ljava/lang/String;)Ljava/lang/String;
      81: invokevirtual #33                 // Method com/virtual/ssv/server/entity/ResultJson.setErrorMsg:(Ljava/lang/String;)V
      84: new           #22                 // class java/util/Date
      87: dup
      88: invokespecial #23                 // Method java/util/Date."<init>":()V
      91: astore        9
      93: aload_0
      94: aload_3
      95: aload         5
      97: ldc           #45                 // String workOrderServlet.stop
      99: aload         7
     101: aload         4
     103: aload         9
     105: invokespecial #35                 // Method logOpe:(Lcom/virtual/ssv/server/user/LoginInfo;Ljava/util/Date;Ljava/lang/String;Ljava/lang/String;Lcom/virtual/ssv/server/entity/ResultJson;Ljava/util/Date;)V
     108: goto          192
     111: astore        5
     113: aload         5
     115: invokevirtual #40                 // Method com/virtual/common/AppException.getErrorCode:()I
     118: bipush        102
     120: if_icmpne     136
     123: aload         4
     125: bipush        102
     127: invokestatic  #42                 // Method com/virtual/common/ErrorCodes.getErrorMessage:(I)Ljava/lang/String;
     130: invokevirtual #33                 // Method com/virtual/ssv/server/entity/ResultJson.setErrorMsg:(Ljava/lang/String;)V
     133: goto          192
     136: aload         5
     138: invokevirtual #40                 // Method com/virtual/common/AppException.getErrorCode:()I
     141: bipush        103
     143: if_icmpne     159
     146: aload         4
     148: bipush        103
     150: invokestatic  #42                 // Method com/virtual/common/ErrorCodes.getErrorMessage:(I)Ljava/lang/String;
     153: invokevirtual #33                 // Method com/virtual/ssv/server/entity/ResultJson.setErrorMsg:(Ljava/lang/String;)V
     156: goto          192
     159: aload         5
     161: invokevirtual #40                 // Method com/virtual/common/AppException.getErrorCode:()I
     164: bipush        11
     166: if_icmpne     182
     169: aload         4
     171: bipush        11
     173: invokestatic  #42                 // Method com/virtual/common/ErrorCodes.getErrorMessage:(I)Ljava/lang/String;
     176: invokevirtual #33                 // Method com/virtual/ssv/server/entity/ResultJson.setErrorMsg:(Ljava/lang/String;)V
     179: goto          192
     182: aload         4
     184: aload         5
     186: invokevirtual #43                 // Method com/virtual/common/AppException.getMessage:()Ljava/lang/String;
     189: invokevirtual #33                 // Method com/virtual/ssv/server/entity/ResultJson.setErrorMsg:(Ljava/lang/String;)V
     192: aload_0
     193: aload_2
     194: aload_0
     195: getfield      #36                 // Field filterJson:Lcom/google/gson/Gson;
     198: aload         4
     200: invokevirtual #37                 // Method com/google/gson/Gson.toJson:(Ljava/lang/Object;)Ljava/lang/String;
     203: invokevirtual #38                 // Method write:(Ljavax/servlet/http/HttpServletResponse;Ljava/lang/String;)V
     206: return
    Exception table:
       from    to  target type
           9   108   111   Class com/virtual/common/AppException

  private void applyWorkOrder(javax.servlet.http.HttpServletRequest, javax.servlet.http.HttpServletResponse, com.virtual.ssv.server.user.LoginInfo);
    Code:
       0: new           #20                 // class com/virtual/ssv/server/entity/ResultJson
       3: dup
       4: invokespecial #21                 // Method com/virtual/ssv/server/entity/ResultJson."<init>":()V
       7: astore        4
       9: new           #22                 // class java/util/Date
      12: dup
      13: invokespecial #23                 // Method java/util/Date."<init>":()V
      16: astore        5
      18: ldc           #27                 // String
      20: astore        6
      22: ldc           #27                 // String
      24: astore        7
      26: aload_1
      27: ldc           #46                 // String content
      29: invokeinterface #9,  2            // InterfaceMethod javax/servlet/http/HttpServletRequest.getParameter:(Ljava/lang/String;)Ljava/lang/String;
      34: ldc           #47                 // String UTF-8
      36: invokestatic  #48                 // Method java/net/URLDecoder.decode:(Ljava/lang/String;Ljava/lang/String;)Ljava/lang/String;
      39: astore        6
      41: aload_1
      42: ldc           #49                 // String title
      44: invokeinterface #9,  2            // InterfaceMethod javax/servlet/http/HttpServletRequest.getParameter:(Ljava/lang/String;)Ljava/lang/String;
      49: ldc           #47                 // String UTF-8
      51: invokestatic  #48                 // Method java/net/URLDecoder.decode:(Ljava/lang/String;Ljava/lang/String;)Ljava/lang/String;
      54: astore        7
      56: goto          61
      59: astore        8
      61: new           #51                 // class com/virtual/ssv/server/rs/client/entity/CloudWorkOrder
      64: dup
      65: invokespecial #52                 // Method com/virtual/ssv/server/rs/client/entity/CloudWorkOrder."<init>":()V
      68: astore        8
      70: aload         8
      72: aload_3
      73: invokevirtual #53                 // Method com/virtual/ssv/server/user/LoginInfo.getId:()Ljava/lang/Long;
      76: invokevirtual #54                 // Method com/virtual/ssv/server/rs/client/entity/CloudWorkOrder.setFromUserId:(Ljava/lang/Long;)V
      79: aload         8
      81: aload         5
      83: invokevirtual #55                 // Method com/virtual/ssv/server/rs/client/entity/CloudWorkOrder.setCreateTime:(Ljava/util/Date;)V
      86: aload         8
      88: aload         6
      90: invokevirtual #56                 // Method com/virtual/ssv/server/rs/client/entity/CloudWorkOrder.setContent:(Ljava/lang/String;)V
      93: aload         8
      95: aload         7
      97: invokevirtual #57                 // Method com/virtual/ssv/server/rs/client/entity/CloudWorkOrder.setTitle:(Ljava/lang/String;)V
     100: aload         8
     102: iconst_1
     103: invokestatic  #58                 // Method java/lang/Integer.valueOf:(I)Ljava/lang/Integer;
     106: invokevirtual #59                 // Method com/virtual/ssv/server/rs/client/entity/CloudWorkOrder.setStatus:(Ljava/lang/Integer;)V
     109: aload         8
     111: aload_3
     112: invokevirtual #60                 // Method com/virtual/ssv/server/user/LoginInfo.getOrgId:()Ljava/lang/Long;
     115: invokevirtual #61                 // Method com/virtual/ssv/server/rs/client/entity/CloudWorkOrder.setOrgId:(Ljava/lang/Long;)V
     118: aload_0
     119: getfield      #25                 // Field reqHandle:Lcom/virtual/ssv/server/rs/client/RequestHandle;
     122: aload         8
     124: invokevirtual #62                 // Method com/virtual/ssv/server/rs/client/RequestHandle.applyWorkOrder:(Lcom/virtual/ssv/server/rs/client/entity/CloudWorkOrder;)Lcom/virtual/ssv/server/entity/ResultJson;
     127: astore        4
     129: new           #22                 // class java/util/Date
     132: dup
     133: invokespecial #23                 // Method java/util/Date."<init>":()V
     136: astore        9
     138: aload_0
     139: aload_3
     140: aload         5
     142: ldc           #63                 // String workOrderServlet.apply
     144: aload         7
     146: aload         4
     148: aload         9
     150: invokespecial #35                 // Method logOpe:(Lcom/virtual/ssv/server/user/LoginInfo;Ljava/util/Date;Ljava/lang/String;Ljava/lang/String;Lcom/virtual/ssv/server/entity/ResultJson;Ljava/util/Date;)V
     153: goto          237
     156: astore        5
     158: aload         5
     160: invokevirtual #40                 // Method com/virtual/common/AppException.getErrorCode:()I
     163: bipush        102
     165: if_icmpne     181
     168: aload         4
     170: bipush        102
     172: invokestatic  #42                 // Method com/virtual/common/ErrorCodes.getErrorMessage:(I)Ljava/lang/String;
     175: invokevirtual #33                 // Method com/virtual/ssv/server/entity/ResultJson.setErrorMsg:(Ljava/lang/String;)V
     178: goto          237
     181: aload         5
     183: invokevirtual #40                 // Method com/virtual/common/AppException.getErrorCode:()I
     186: bipush        103
     188: if_icmpne     204
     191: aload         4
     193: bipush        103
     195: invokestatic  #42                 // Method com/virtual/common/ErrorCodes.getErrorMessage:(I)Ljava/lang/String;
     198: invokevirtual #33                 // Method com/virtual/ssv/server/entity/ResultJson.setErrorMsg:(Ljava/lang/String;)V
     201: goto          237
     204: aload         5
     206: invokevirtual #40                 // Method com/virtual/common/AppException.getErrorCode:()I
     209: bipush        11
     211: if_icmpne     227
     214: aload         4
     216: bipush        11
     218: invokestatic  #42                 // Method com/virtual/common/ErrorCodes.getErrorMessage:(I)Ljava/lang/String;
     221: invokevirtual #33                 // Method com/virtual/ssv/server/entity/ResultJson.setErrorMsg:(Ljava/lang/String;)V
     224: goto          237
     227: aload         4
     229: aload         5
     231: invokevirtual #43                 // Method com/virtual/common/AppException.getMessage:()Ljava/lang/String;
     234: invokevirtual #33                 // Method com/virtual/ssv/server/entity/ResultJson.setErrorMsg:(Ljava/lang/String;)V
     237: aload_0
     238: aload_2
     239: aload_0
     240: getfield      #36                 // Field filterJson:Lcom/google/gson/Gson;
     243: aload         4
     245: invokevirtual #37                 // Method com/google/gson/Gson.toJson:(Ljava/lang/Object;)Ljava/lang/String;
     248: invokevirtual #38                 // Method write:(Ljavax/servlet/http/HttpServletResponse;Ljava/lang/String;)V
     251: return
    Exception table:
       from    to  target type
          26    56    59   Class java/io/UnsupportedEncodingException
           9   153   156   Class com/virtual/common/AppException

  private void logOpe(com.virtual.ssv.server.user.LoginInfo, java.util.Date, java.lang.String, java.lang.String, com.virtual.ssv.server.entity.ResultJson, java.util.Date);
    Code:
       0: new           #64                 // class com/virtual/ssv/server/rs/client/entity/RsOperateLog
       3: dup
       4: invokespecial #65                 // Method com/virtual/ssv/server/rs/client/entity/RsOperateLog."<init>":()V
       7: astore        7
       9: aload         7
      11: aload_1
      12: invokevirtual #53                 // Method com/virtual/ssv/server/user/LoginInfo.getId:()Ljava/lang/Long;
      15: invokevirtual #66                 // Method com/virtual/ssv/server/rs/client/entity/RsOperateLog.setUserId:(Ljava/lang/Long;)V
      18: aload         7
      20: aload_1
      21: invokevirtual #60                 // Method com/virtual/ssv/server/user/LoginInfo.getOrgId:()Ljava/lang/Long;
      24: invokevirtual #67                 // Method com/virtual/ssv/server/rs/client/entity/RsOperateLog.setOrgId:(Ljava/lang/Long;)V
      27: aload         7
      29: aload_1
      30: invokevirtual #68                 // Method com/virtual/ssv/server/user/LoginInfo.getLoginName:()Ljava/lang/String;
      33: invokevirtual #69                 // Method com/virtual/ssv/server/rs/client/entity/RsOperateLog.setLoginName:(Ljava/lang/String;)V
      36: aload         7
      38: aload_1
      39: invokevirtual #70                 // Method com/virtual/ssv/server/user/LoginInfo.getUserName:()Ljava/lang/String;
      42: invokevirtual #71                 // Method com/virtual/ssv/server/rs/client/entity/RsOperateLog.setUserName:(Ljava/lang/String;)V
      45: aload         7
      47: aload_1
      48: invokevirtual #72                 // Method com/virtual/ssv/server/user/LoginInfo.getLoginIp:()Ljava/lang/String;
      51: invokevirtual #73                 // Method com/virtual/ssv/server/rs/client/entity/RsOperateLog.setAddress:(Ljava/lang/String;)V
      54: aload         7
      56: bipush        30
      58: invokestatic  #58                 // Method java/lang/Integer.valueOf:(I)Ljava/lang/Integer;
      61: invokevirtual #75                 // Method com/virtual/ssv/server/rs/client/entity/RsOperateLog.setCategory:(Ljava/lang/Integer;)V
      64: aload         7
      66: aload_2
      67: invokevirtual #76                 // Method com/virtual/ssv/server/rs/client/entity/RsOperateLog.setStartTime:(Ljava/util/Date;)V
      70: aload         7
      72: aload         6
      74: invokevirtual #77                 // Method com/virtual/ssv/server/rs/client/entity/RsOperateLog.setEndTime:(Ljava/util/Date;)V
      77: aload         7
      79: aload_0
      80: getfield      #30                 // Field logSm:Lcom/virtual/common/StringManager;
      83: aload_3
      84: iconst_1
      85: anewarray     #78                 // class java/lang/Object
      88: dup
      89: iconst_0
      90: aload         4
      92: aastore
      93: invokevirtual #79                 // Method com/virtual/common/StringManager.getString:(Ljava/lang/String;[Ljava/lang/Object;)Ljava/lang/String;
      96: invokevirtual #80                 // Method com/virtual/ssv/server/rs/client/entity/RsOperateLog.setDescription:(Ljava/lang/String;)V
      99: aload         5
     101: invokevirtual #81                 // Method com/virtual/ssv/server/entity/ResultJson.getState:()I
     104: iconst_1
     105: if_icmpne     119
     108: aload         7
     110: getstatic     #82                 // Field com/virtual/ssv/server/rs/client/entity/RsOperateLog.RESULT_SUCCESS:Ljava/lang/Integer;
     113: invokevirtual #83                 // Method com/virtual/ssv/server/rs/client/entity/RsOperateLog.setResult:(Ljava/lang/Integer;)V
     116: goto          137
     119: aload         7
     121: getstatic     #84                 // Field com/virtual/ssv/server/rs/client/entity/RsOperateLog.RESULT_FAILURE:Ljava/lang/Integer;
     124: invokevirtual #83                 // Method com/virtual/ssv/server/rs/client/entity/RsOperateLog.setResult:(Ljava/lang/Integer;)V
     127: aload         7
     129: aload         5
     131: invokevirtual #85                 // Method com/virtual/ssv/server/entity/ResultJson.getMessage:()Ljava/lang/String;
     134: invokevirtual #86                 // Method com/virtual/ssv/server/rs/client/entity/RsOperateLog.setFailureReason:(Ljava/lang/String;)V
     137: aload_0
     138: getfield      #25                 // Field reqHandle:Lcom/virtual/ssv/server/rs/client/RequestHandle;
     141: aload         7
     143: invokevirtual #87                 // Method com/virtual/ssv/server/rs/client/RequestHandle.addUserLog:(Lcom/virtual/ssv/server/rs/client/entity/RsOperateLog;)Ljava/lang/Long;
     146: pop
     147: return

  private void getList(javax.servlet.http.HttpServletRequest, javax.servlet.http.HttpServletResponse, com.virtual.ssv.server.user.LoginInfo);
    Code:
       0: new           #88                 // class com/virtual/ssv/server/entity/CommonListJson
       3: dup
       4: invokespecial #89                 // Method com/virtual/ssv/server/entity/CommonListJson."<init>":()V
       7: astore        4
       9: aload_0
      10: aload_1
      11: invokevirtual #90                 // Method getPagingConfig:(Ljavax/servlet/http/HttpServletRequest;)Lcom/virtual/ssv/server/entity/PagingLoadConfig;
      14: astore        5
      16: aload         5
      18: invokevirtual #91                 // Method com/virtual/ssv/server/entity/PagingLoadConfig.getSortField:()Ljava/lang/String;
      21: invokestatic  #92                 // Method org/apache/commons/lang/StringUtils.isEmpty:(Ljava/lang/String;)Z
      24: ifeq          41
      27: aload         5
      29: ldc           #24                 // String id
      31: invokevirtual #93                 // Method com/virtual/ssv/server/entity/PagingLoadConfig.setSortField:(Ljava/lang/String;)V
      34: aload         5
      36: ldc           #94                 // String Desc
      38: invokevirtual #95                 // Method com/virtual/ssv/server/entity/PagingLoadConfig.setSortDir:(Ljava/lang/String;)V
      41: aload         5
      43: ldc           #96                 // String userId
      45: aload_3
      46: invokevirtual #53                 // Method com/virtual/ssv/server/user/LoginInfo.getId:()Ljava/lang/Long;
      49: invokevirtual #97                 // Method com/virtual/ssv/server/entity/PagingLoadConfig.put:(Ljava/lang/Object;Ljava/lang/Object;)Ljava/lang/Object;
      52: pop
      53: aload         5
      55: ldc           #98                 // String orgId
      57: aload_3
      58: invokevirtual #60                 // Method com/virtual/ssv/server/user/LoginInfo.getOrgId:()Ljava/lang/Long;
      61: invokevirtual #97                 // Method com/virtual/ssv/server/entity/PagingLoadConfig.put:(Ljava/lang/Object;Ljava/lang/Object;)Ljava/lang/Object;
      64: pop
      65: aload_1
      66: ldc           #99                 // String status
      68: invokeinterface #9,  2            // InterfaceMethod javax/servlet/http/HttpServletRequest.getParameter:(Ljava/lang/String;)Ljava/lang/String;
      73: astore        6
      75: aload         6
      77: invokestatic  #100                // Method org/apache/commons/lang/StringUtils.isNotEmpty:(Ljava/lang/String;)Z
      80: ifeq          93
      83: aload         5
      85: ldc           #99                 // String status
      87: aload         6
      89: invokevirtual #97                 // Method com/virtual/ssv/server/entity/PagingLoadConfig.put:(Ljava/lang/Object;Ljava/lang/Object;)Ljava/lang/Object;
      92: pop
      93: aload_0
      94: getfield      #25                 // Field reqHandle:Lcom/virtual/ssv/server/rs/client/RequestHandle;
      97: aload         5
      99: invokevirtual #101                // Method com/virtual/ssv/server/rs/client/RequestHandle.queryUserWorkOrderCount:(Lcom/virtual/ssv/server/entity/PagingLoadConfig;)Ljava/lang/Integer;
     102: astore        7
     104: aload         7
     106: invokevirtual #102                // Method java/lang/Integer.intValue:()I
     109: ifle          202
     112: aload_0
     113: getfield      #25                 // Field reqHandle:Lcom/virtual/ssv/server/rs/client/RequestHandle;
     116: aload         5
     118: invokevirtual #103                // Method com/virtual/ssv/server/rs/client/RequestHandle.queryUserWorkOrder:(Lcom/virtual/ssv/server/entity/PagingLoadConfig;)Ljava/util/List;
     121: astore        8
     123: aload         8
     125: invokeinterface #104,  1          // InterfaceMethod java/util/List.iterator:()Ljava/util/Iterator;
     130: astore        9
     132: aload         9
     134: invokeinterface #105,  1          // InterfaceMethod java/util/Iterator.hasNext:()Z
     139: ifeq          192
     142: aload         9
     144: invokeinterface #106,  1          // InterfaceMethod java/util/Iterator.next:()Ljava/lang/Object;
     149: checkcast     #51                 // class com/virtual/ssv/server/rs/client/entity/CloudWorkOrder
     152: astore        10
     154: aload         10
     156: invokevirtual #107                // Method com/virtual/ssv/server/rs/client/entity/CloudWorkOrder.getCreateTime:()Ljava/util/Date;
     159: astore        11
     161: aload         11
     163: ifnull        189
     166: new           #108                // class java/text/SimpleDateFormat
     169: dup
     170: ldc           #109                // String yyyy-MM-dd HH:mm:ss
     172: invokespecial #110                // Method java/text/SimpleDateFormat."<init>":(Ljava/lang/String;)V
     175: astore        12
     177: aload         10
     179: aload         12
     181: aload         11
     183: invokevirtual #111                // Method java/text/SimpleDateFormat.format:(Ljava/util/Date;)Ljava/lang/String;
     186: invokevirtual #112                // Method com/virtual/ssv/server/rs/client/entity/CloudWorkOrder.setCreateTimeStr:(Ljava/lang/String;)V
     189: goto          132
     192: aload         4
     194: aload         8
     196: invokevirtual #113                // Method com/virtual/ssv/server/entity/CommonListJson.setRows:(Ljava/util/List;)V
     199: goto          214
     202: aload         4
     204: new           #114                // class java/util/ArrayList
     207: dup
     208: invokespecial #115                // Method java/util/ArrayList."<init>":()V
     211: invokevirtual #113                // Method com/virtual/ssv/server/entity/CommonListJson.setRows:(Ljava/util/List;)V
     214: aload         4
     216: aload         7
     218: invokevirtual #102                // Method java/lang/Integer.intValue:()I
     221: i2l
     222: invokevirtual #116                // Method com/virtual/ssv/server/entity/CommonListJson.setTotal:(J)V
     225: goto          341
     228: astore        5
     230: aload         4
     232: aload_0
     233: getfield      #30                 // Field logSm:Lcom/virtual/common/StringManager;
     236: ldc           #117                // String operError
     238: invokevirtual #32                 // Method com/virtual/common/StringManager.getString:(Ljava/lang/String;)Ljava/lang/String;
     241: invokevirtual #118                // Method com/virtual/ssv/server/entity/CommonListJson.setTitle:(Ljava/lang/String;)V
     244: aload         5
     246: invokevirtual #40                 // Method com/virtual/common/AppException.getErrorCode:()I
     249: bipush        102
     251: if_icmpne     267
     254: aload         4
     256: bipush        102
     258: invokestatic  #42                 // Method com/virtual/common/ErrorCodes.getErrorMessage:(I)Ljava/lang/String;
     261: invokevirtual #119                // Method com/virtual/ssv/server/entity/CommonListJson.setMessage:(Ljava/lang/String;)V
     264: goto          323
     267: aload         5
     269: invokevirtual #40                 // Method com/virtual/common/AppException.getErrorCode:()I
     272: bipush        103
     274: if_icmpne     290
     277: aload         4
     279: bipush        103
     281: invokestatic  #42                 // Method com/virtual/common/ErrorCodes.getErrorMessage:(I)Ljava/lang/String;
     284: invokevirtual #119                // Method com/virtual/ssv/server/entity/CommonListJson.setMessage:(Ljava/lang/String;)V
     287: goto          323
     290: aload         5
     292: invokevirtual #40                 // Method com/virtual/common/AppException.getErrorCode:()I
     295: bipush        11
     297: if_icmpne     313
     300: aload         4
     302: bipush        11
     304: invokestatic  #42                 // Method com/virtual/common/ErrorCodes.getErrorMessage:(I)Ljava/lang/String;
     307: invokevirtual #119                // Method com/virtual/ssv/server/entity/CommonListJson.setMessage:(Ljava/lang/String;)V
     310: goto          323
     313: aload         4
     315: aload         5
     317: invokevirtual #43                 // Method com/virtual/common/AppException.getMessage:()Ljava/lang/String;
     320: invokevirtual #119                // Method com/virtual/ssv/server/entity/CommonListJson.setMessage:(Ljava/lang/String;)V
     323: aload         4
     325: iconst_0
     326: invokevirtual #120                // Method com/virtual/ssv/server/entity/CommonListJson.setState:(I)V
     329: aload         4
     331: new           #114                // class java/util/ArrayList
     334: dup
     335: invokespecial #115                // Method java/util/ArrayList."<init>":()V
     338: invokevirtual #113                // Method com/virtual/ssv/server/entity/CommonListJson.setRows:(Ljava/util/List;)V
     341: aload_0
     342: aload_2
     343: aload_0
     344: getfield      #121                // Field gson:Lcom/google/gson/Gson;
     347: aload         4
     349: invokevirtual #37                 // Method com/google/gson/Gson.toJson:(Ljava/lang/Object;)Ljava/lang/String;
     352: invokevirtual #38                 // Method write:(Ljavax/servlet/http/HttpServletResponse;Ljava/lang/String;)V
     355: return
    Exception table:
       from    to  target type
           9   225   228   Class com/virtual/common/AppException
}
