Compiled from "LoginServlet.java"
public class com.virtual.ssv.server.user.LoginServlet extends com.virtual.ssv.server.BaseServlet {
  private static final long serialVersionUID;

  private static com.virtual.common.StringManager strMng;

  static java.lang.String ATTR_LOGIN_SERVLET_IN_CONTEXT;

  private boolean checkPasswordAttack;

  private java.lang.String ATTR_LOGIN_FAILED_COUNT;

  private java.lang.String ATTR_SAVE_SYSTEM_CONFIG_COUNT;

  private java.lang.String ATTR_LAST_SAVE_SYSTEM_CONFIG_TIME;

  private java.lang.String ATTR_LAST_LOGIN_FAILED_TIME;

  private int maxFailCount;

  private int maxConfigFailCount;

  private int lockTime;

  private com.virtual.ssv.server.user.OnlineUsers onlineUsers;

  public void init();
    Code:
       0: aload_0
       1: invokespecial #2                  // Method com/virtual/ssv/server/BaseServlet.init:()V
       4: aload_0
       5: ldc           #3                  // String checkPasswordAttack
       7: invokevirtual #4                  // Method getInitParameter:(Ljava/lang/String;)Ljava/lang/String;
      10: astore_1
      11: aload_1
      12: ifnull        23
      15: aload_0
      16: aload_1
      17: invokestatic  #5                  // Method java/lang/Boolean.parseBoolean:(Ljava/lang/String;)Z
      20: putfield      #6                  // Field checkPasswordAttack:Z
      23: aload_0
      24: ldc           #7                  // String maxFailCount
      26: invokevirtual #4                  // Method getInitParameter:(Ljava/lang/String;)Ljava/lang/String;
      29: astore_1
      30: aload_1
      31: ifnull        42
      34: aload_0
      35: aload_1
      36: invokestatic  #8                  // Method java/lang/Integer.parseInt:(Ljava/lang/String;)I
      39: putfield      #9                  // Field maxFailCount:I
      42: aload_0
      43: ldc           #10                 // String lockTime
      45: invokevirtual #4                  // Method getInitParameter:(Ljava/lang/String;)Ljava/lang/String;
      48: astore_1
      49: aload_1
      50: ifnull        61
      53: aload_0
      54: aload_1
      55: invokestatic  #8                  // Method java/lang/Integer.parseInt:(Ljava/lang/String;)I
      58: putfield      #11                 // Field lockTime:I
      61: aload_0
      62: invokevirtual #12                 // Method getServletContext:()Ljavax/servlet/ServletContext;
      65: getstatic     #13                 // Field ATTR_LOGIN_SERVLET_IN_CONTEXT:Ljava/lang/String;
      68: aload_0
      69: invokeinterface #14,  3           // InterfaceMethod javax/servlet/ServletContext.setAttribute:(Ljava/lang/String;Ljava/lang/Object;)V
      74: aload_0
      75: aload_0
      76: invokevirtual #12                 // Method getServletContext:()Ljavax/servlet/ServletContext;
      79: invokestatic  #15                 // Method com/virtual/ssv/server/user/OnlineUsers.getInstance:(Ljavax/servlet/ServletContext;)Lcom/virtual/ssv/server/user/OnlineUsers;
      82: putfield      #16                 // Field onlineUsers:Lcom/virtual/ssv/server/user/OnlineUsers;
      85: return

  public com.virtual.ssv.server.user.LoginServlet();
    Code:
       0: aload_0
       1: invokespecial #17                 // Method com/virtual/ssv/server/BaseServlet."<init>":()V
       4: aload_0
       5: iconst_1
       6: putfield      #6                  // Field checkPasswordAttack:Z
       9: aload_0
      10: ldc           #18                 // String LOGIN_FAILED_COUNT
      12: putfield      #19                 // Field ATTR_LOGIN_FAILED_COUNT:Ljava/lang/String;
      15: aload_0
      16: ldc           #20                 // String SAVE_SYSTEM_CONFIG
      18: putfield      #21                 // Field ATTR_SAVE_SYSTEM_CONFIG_COUNT:Ljava/lang/String;
      21: aload_0
      22: ldc           #22                 // String LAST_SAVE_SYSTEM_TIME
      24: putfield      #23                 // Field ATTR_LAST_SAVE_SYSTEM_CONFIG_TIME:Ljava/lang/String;
      27: aload_0
      28: ldc           #24                 // String LAST_LOGIN_FAILED_TIME
      30: putfield      #25                 // Field ATTR_LAST_LOGIN_FAILED_TIME:Ljava/lang/String;
      33: aload_0
      34: iconst_5
      35: putfield      #9                  // Field maxFailCount:I
      38: aload_0
      39: iconst_3
      40: putfield      #26                 // Field maxConfigFailCount:I
      43: aload_0
      44: iconst_1
      45: putfield      #11                 // Field lockTime:I
      48: aload_0
      49: aconst_null
      50: putfield      #16                 // Field onlineUsers:Lcom/virtual/ssv/server/user/OnlineUsers;
      53: return

  protected void doGet(javax.servlet.http.HttpServletRequest, javax.servlet.http.HttpServletResponse) throws javax.servlet.ServletException, java.io.IOException;
    Code:
       0: aload_0
       1: aload_1
       2: invokespecial #27                 // Method checkAndSaveHttpChanges:(Ljavax/servlet/http/HttpServletRequest;)V
       5: aload_1
       6: ldc           #28                 // String way
       8: invokeinterface #29,  2           // InterfaceMethod javax/servlet/http/HttpServletRequest.getParameter:(Ljava/lang/String;)Ljava/lang/String;
      13: astore_3
      14: ldc           #30                 // String login
      16: aload_3
      17: invokevirtual #31                 // Method java/lang/String.equals:(Ljava/lang/Object;)Z
      20: ifeq          32
      23: aload_0
      24: aload_1
      25: aload_2
      26: invokespecial #32                 // Method doLogin:(Ljavax/servlet/http/HttpServletRequest;Ljavax/servlet/http/HttpServletResponse;)V
      29: goto          375
      32: ldc           #33                 // String logout
      34: aload_3
      35: invokevirtual #31                 // Method java/lang/String.equals:(Ljava/lang/Object;)Z
      38: ifeq          50
      41: aload_0
      42: aload_1
      43: aload_2
      44: invokevirtual #34                 // Method doLogout:(Ljavax/servlet/http/HttpServletRequest;Ljavax/servlet/http/HttpServletResponse;)V
      47: goto          375
      50: ldc           #35                 // String forgetPassword
      52: aload_3
      53: invokevirtual #31                 // Method java/lang/String.equals:(Ljava/lang/Object;)Z
      56: ifeq          68
      59: aload_0
      60: aload_1
      61: aload_2
      62: invokespecial #36                 // Method forgetPassword:(Ljavax/servlet/http/HttpServletRequest;Ljavax/servlet/http/HttpServletResponse;)V
      65: goto          375
      68: ldc           #37                 // String register
      70: aload_3
      71: invokevirtual #31                 // Method java/lang/String.equals:(Ljava/lang/Object;)Z
      74: ifeq          86
      77: aload_0
      78: aload_1
      79: aload_2
      80: invokespecial #38                 // Method register:(Ljavax/servlet/http/HttpServletRequest;Ljavax/servlet/http/HttpServletResponse;)V
      83: goto          375
      86: ldc           #39                 // String getSsvConfig
      88: aload_3
      89: invokevirtual #31                 // Method java/lang/String.equals:(Ljava/lang/Object;)Z
      92: ifeq          104
      95: aload_0
      96: aload_1
      97: aload_2
      98: invokespecial #40                 // Method getSsvConfig:(Ljavax/servlet/http/HttpServletRequest;Ljavax/servlet/http/HttpServletResponse;)V
     101: goto          375
     104: ldc           #41                 // String saveSsvConfig
     106: aload_3
     107: invokevirtual #31                 // Method java/lang/String.equals:(Ljava/lang/Object;)Z
     110: ifeq          122
     113: aload_0
     114: aload_1
     115: aload_2
     116: invokespecial #42                 // Method saveSsvConfig:(Ljavax/servlet/http/HttpServletRequest;Ljavax/servlet/http/HttpServletResponse;)V
     119: goto          375
     122: ldc           #43                 // String getUIConfig
     124: aload_3
     125: invokevirtual #31                 // Method java/lang/String.equals:(Ljava/lang/Object;)Z
     128: ifeq          140
     131: aload_0
     132: aload_1
     133: aload_2
     134: invokespecial #44                 // Method getUIConfig:(Ljavax/servlet/http/HttpServletRequest;Ljavax/servlet/http/HttpServletResponse;)V
     137: goto          375
     140: ldc           #45                 // String getCopyrightFrom
     142: aload_3
     143: invokevirtual #31                 // Method java/lang/String.equals:(Ljava/lang/Object;)Z
     146: ifeq          158
     149: aload_0
     150: aload_1
     151: aload_2
     152: invokespecial #46                 // Method getCopyrightFrom:(Ljavax/servlet/http/HttpServletRequest;Ljavax/servlet/http/HttpServletResponse;)V
     155: goto          375
     158: ldc           #47                 // String checkRenameAndemail
     160: aload_3
     161: invokevirtual #31                 // Method java/lang/String.equals:(Ljava/lang/Object;)Z
     164: ifeq          176
     167: aload_0
     168: aload_1
     169: aload_2
     170: invokespecial #48                 // Method checkRenameAndemail:(Ljavax/servlet/http/HttpServletRequest;Ljavax/servlet/http/HttpServletResponse;)V
     173: goto          375
     176: aload_1
     177: invokeinterface #49,  1           // InterfaceMethod javax/servlet/http/HttpServletRequest.getSession:()Ljavax/servlet/http/HttpSession;
     182: astore        4
     184: aload         4
     186: ldc           #50                 // String loginInfo
     188: invokeinterface #51,  2           // InterfaceMethod javax/servlet/http/HttpSession.getAttribute:(Ljava/lang/String;)Ljava/lang/Object;
     193: checkcast     #52                 // class com/virtual/ssv/server/user/LoginInfo
     196: astore        5
     198: aload         5
     200: ifnull        367
     203: aload_0
     204: aload_1
     205: aload_2
     206: invokevirtual #53                 // Method checkUserState:(Ljavax/servlet/http/HttpServletRequest;Ljavax/servlet/http/HttpServletResponse;)V
     209: ldc           #54                 // String getUser
     211: aload_3
     212: invokevirtual #31                 // Method java/lang/String.equals:(Ljava/lang/Object;)Z
     215: ifeq          229
     218: aload_0
     219: aload_1
     220: aload_2
     221: aload         5
     223: invokespecial #55                 // Method getUser:(Ljavax/servlet/http/HttpServletRequest;Ljavax/servlet/http/HttpServletResponse;Lcom/virtual/ssv/server/user/LoginInfo;)V
     226: goto          375
     229: ldc           #56                 // String editUser
     231: aload_3
     232: invokevirtual #31                 // Method java/lang/String.equals:(Ljava/lang/Object;)Z
     235: ifeq          249
     238: aload_0
     239: aload_1
     240: aload_2
     241: aload         5
     243: invokespecial #57                 // Method editUser:(Ljavax/servlet/http/HttpServletRequest;Ljavax/servlet/http/HttpServletResponse;Lcom/virtual/ssv/server/user/LoginInfo;)V
     246: goto          375
     249: ldc           #58                 // String saveUserSetting
     251: aload_3
     252: invokevirtual #31                 // Method java/lang/String.equals:(Ljava/lang/Object;)Z
     255: ifeq          269
     258: aload_0
     259: aload_1
     260: aload_2
     261: aload         5
     263: invokespecial #59                 // Method saveUserSetting:(Ljavax/servlet/http/HttpServletRequest;Ljavax/servlet/http/HttpServletResponse;Lcom/virtual/ssv/server/user/LoginInfo;)V
     266: goto          375
     269: ldc           #60                 // String getUserSetting
     271: aload_3
     272: invokevirtual #31                 // Method java/lang/String.equals:(Ljava/lang/Object;)Z
     275: ifeq          289
     278: aload_0
     279: aload_1
     280: aload_2
     281: aload         5
     283: invokespecial #61                 // Method getUserSetting:(Ljavax/servlet/http/HttpServletRequest;Ljavax/servlet/http/HttpServletResponse;Lcom/virtual/ssv/server/user/LoginInfo;)V
     286: goto          375
     289: ldc           #62                 // String saveOtherUserSetting
     291: aload_3
     292: invokevirtual #31                 // Method java/lang/String.equals:(Ljava/lang/Object;)Z
     295: ifeq          309
     298: aload_0
     299: aload_1
     300: aload_2
     301: aload         5
     303: invokespecial #63                 // Method saveOtherUserSetting:(Ljavax/servlet/http/HttpServletRequest;Ljavax/servlet/http/HttpServletResponse;Lcom/virtual/ssv/server/user/LoginInfo;)V
     306: goto          375
     309: ldc           #64                 // String saveTheme
     311: aload_3
     312: invokevirtual #31                 // Method java/lang/String.equals:(Ljava/lang/Object;)Z
     315: ifeq          329
     318: aload_0
     319: aload_1
     320: aload_2
     321: aload         5
     323: invokespecial #65                 // Method saveTheme:(Ljavax/servlet/http/HttpServletRequest;Ljavax/servlet/http/HttpServletResponse;Lcom/virtual/ssv/server/user/LoginInfo;)V
     326: goto          375
     329: ldc           #66                 // String isOldPassword
     331: aload_3
     332: invokevirtual #31                 // Method java/lang/String.equals:(Ljava/lang/Object;)Z
     335: ifeq          349
     338: aload_0
     339: aload_1
     340: aload_2
     341: aload         5
     343: invokespecial #67                 // Method isOldPassword:(Ljavax/servlet/http/HttpServletRequest;Ljavax/servlet/http/HttpServletResponse;Lcom/virtual/ssv/server/user/LoginInfo;)V
     346: goto          375
     349: ldc           #68                 // String test
     351: aload_3
     352: invokevirtual #31                 // Method java/lang/String.equals:(Ljava/lang/Object;)Z
     355: ifeq          375
     358: aload_0
     359: aload_1
     360: aload_2
     361: invokespecial #69                 // Method test:(Ljavax/servlet/http/HttpServletRequest;Ljavax/servlet/http/HttpServletResponse;)V
     364: goto          375
     367: aload_2
     368: ldc           #70                 // String login.jsp
     370: invokeinterface #71,  2           // InterfaceMethod javax/servlet/http/HttpServletResponse.sendRedirect:(Ljava/lang/String;)V
     375: return

  private void checkRenameAndemail(javax.servlet.http.HttpServletRequest, javax.servlet.http.HttpServletResponse);
    Code:
       0: new           #72                 // class com/virtual/ssv/server/entity/ResultJson
       3: dup
       4: invokespecial #73                 // Method com/virtual/ssv/server/entity/ResultJson."<init>":()V
       7: astore_3
       8: aload_1
       9: ldc           #74                 // String name
      11: invokeinterface #29,  2           // InterfaceMethod javax/servlet/http/HttpServletRequest.getParameter:(Ljava/lang/String;)Ljava/lang/String;
      16: astore        4
      18: aload_1
      19: ldc           #75                 // String email
      21: invokeinterface #29,  2           // InterfaceMethod javax/servlet/http/HttpServletRequest.getParameter:(Ljava/lang/String;)Ljava/lang/String;
      26: astore        5
      28: aload         4
      30: ldc           #76                 // String UTF-8
      32: invokestatic  #77                 // Method java/net/URLDecoder.decode:(Ljava/lang/String;Ljava/lang/String;)Ljava/lang/String;
      35: astore        4
      37: aload         5
      39: ldc           #76                 // String UTF-8
      41: invokestatic  #77                 // Method java/net/URLDecoder.decode:(Ljava/lang/String;Ljava/lang/String;)Ljava/lang/String;
      44: astore        5
      46: goto          61
      49: astore        6
      51: getstatic     #79                 // Field log:Lorg/apache/commons/logging/Log;
      54: aload         6
      56: invokeinterface #80,  2           // InterfaceMethod org/apache/commons/logging/Log.error:(Ljava/lang/Object;)V
      61: aload_0
      62: getfield      #1                  // Field reqHandle:Lcom/virtual/ssv/server/rs/client/RequestHandle;
      65: aload         4
      67: invokevirtual #81                 // Method com/virtual/ssv/server/rs/client/RequestHandle.checkRegisterUser:(Ljava/lang/String;)Z
      70: istore        6
      72: iload         6
      74: ifeq          97
      77: aload_3
      78: ldc           #83                 // String 22
      80: invokevirtual #84                 // Method com/virtual/ssv/server/entity/ResultJson.setErrorMsg:(Ljava/lang/String;)V
      83: aload_0
      84: aload_2
      85: aload_0
      86: getfield      #85                 // Field filterJson:Lcom/google/gson/Gson;
      89: aload_3
      90: invokevirtual #86                 // Method com/google/gson/Gson.toJson:(Ljava/lang/Object;)Ljava/lang/String;
      93: invokevirtual #87                 // Method write:(Ljavax/servlet/http/HttpServletResponse;Ljava/lang/String;)V
      96: return
      97: aload_0
      98: getfield      #1                  // Field reqHandle:Lcom/virtual/ssv/server/rs/client/RequestHandle;
     101: aload         5
     103: invokevirtual #88                 // Method com/virtual/ssv/server/rs/client/RequestHandle.checkEmail:(Ljava/lang/String;)Z
     106: istore        7
     108: iload         7
     110: ifeq          133
     113: aload_3
     114: ldc           #89                 // String 23
     116: invokevirtual #84                 // Method com/virtual/ssv/server/entity/ResultJson.setErrorMsg:(Ljava/lang/String;)V
     119: aload_0
     120: aload_2
     121: aload_0
     122: getfield      #85                 // Field filterJson:Lcom/google/gson/Gson;
     125: aload_3
     126: invokevirtual #86                 // Method com/google/gson/Gson.toJson:(Ljava/lang/Object;)Ljava/lang/String;
     129: invokevirtual #87                 // Method write:(Ljavax/servlet/http/HttpServletResponse;Ljava/lang/String;)V
     132: return
     133: aload_3
     134: ldc           #90                 // String ok
     136: invokevirtual #91                 // Method com/virtual/ssv/server/entity/ResultJson.setSuccessMsg:(Ljava/lang/String;)V
     139: aload_0
     140: aload_2
     141: aload_0
     142: getfield      #85                 // Field filterJson:Lcom/google/gson/Gson;
     145: aload_3
     146: invokevirtual #86                 // Method com/google/gson/Gson.toJson:(Ljava/lang/Object;)Ljava/lang/String;
     149: invokevirtual #87                 // Method write:(Ljavax/servlet/http/HttpServletResponse;Ljava/lang/String;)V
     152: return
    Exception table:
       from    to  target type
          28    46    49   Class java/io/UnsupportedEncodingException

  private void getUIConfig(javax.servlet.http.HttpServletRequest, javax.servlet.http.HttpServletResponse);
    Code:
       0: new           #92                 // class com/virtual/ssv/server/rs/client/UIConfig
       3: dup
       4: invokespecial #93                 // Method com/virtual/ssv/server/rs/client/UIConfig."<init>":()V
       7: astore_3
       8: new           #94                 // class java/util/ArrayList
      11: dup
      12: invokespecial #95                 // Method java/util/ArrayList."<init>":()V
      15: astore        4
      17: aload_0
      18: getfield      #1                  // Field reqHandle:Lcom/virtual/ssv/server/rs/client/RequestHandle;
      21: invokevirtual #96                 // Method com/virtual/ssv/server/rs/client/RequestHandle.querySysParameter:()Ljava/util/List;
      24: astore        4
      26: ldc           #98                 // String UNIS
      28: invokestatic  #99                 // Method com/virtual/common/FuncUtil.versionFromPath:(Ljava/lang/String;)Z
      31: istore        5
      33: ldc           #100                // String UniCloud
      35: invokestatic  #99                 // Method com/virtual/common/FuncUtil.versionFromPath:(Ljava/lang/String;)Z
      38: istore        6
      40: aconst_null
      41: astore        7
      43: aconst_null
      44: astore        8
      46: aconst_null
      47: astore        9
      49: aconst_null
      50: astore        10
      52: aconst_null
      53: astore        11
      55: aconst_null
      56: astore        12
      58: aconst_null
      59: astore        13
      61: aconst_null
      62: astore        14
      64: aload         4
      66: ifnull        293
      69: aload         4
      71: invokeinterface #101,  1          // InterfaceMethod java/util/List.iterator:()Ljava/util/Iterator;
      76: astore        15
      78: aload         15
      80: invokeinterface #102,  1          // InterfaceMethod java/util/Iterator.hasNext:()Z
      85: ifeq          293
      88: aload         15
      90: invokeinterface #103,  1          // InterfaceMethod java/util/Iterator.next:()Ljava/lang/Object;
      95: checkcast     #104                // class com/virtual/ssv/server/rs/client/entity/RsParameter
      98: astore        16
     100: aload         16
     102: ifnull        78
     105: aload         16
     107: invokevirtual #105                // Method com/virtual/ssv/server/rs/client/entity/RsParameter.getName:()Ljava/lang/String;
     110: ifnull        78
     113: aload         16
     115: invokevirtual #106                // Method com/virtual/ssv/server/rs/client/entity/RsParameter.getValue:()Ljava/lang/String;
     118: ifnonnull     124
     121: goto          78
     124: aload         16
     126: invokevirtual #105                // Method com/virtual/ssv/server/rs/client/entity/RsParameter.getName:()Ljava/lang/String;
     129: astore        17
     131: ldc           #107                // String ssv.copyright.info
     133: aload         17
     135: invokevirtual #31                 // Method java/lang/String.equals:(Ljava/lang/Object;)Z
     138: ifeq          148
     141: aload         16
     143: invokevirtual #106                // Method com/virtual/ssv/server/rs/client/entity/RsParameter.getValue:()Ljava/lang/String;
     146: astore        10
     148: aload         16
     150: invokevirtual #106                // Method com/virtual/ssv/server/rs/client/entity/RsParameter.getValue:()Ljava/lang/String;
     153: invokevirtual #108                // Method java/lang/String.trim:()Ljava/lang/String;
     156: astore        18
     158: aload         17
     160: invokestatic  #109                // Method org/apache/commons/lang/StringUtils.isNotEmpty:(Ljava/lang/String;)Z
     163: ifeq          290
     166: aload         18
     168: invokestatic  #109                // Method org/apache/commons/lang/StringUtils.isNotEmpty:(Ljava/lang/String;)Z
     171: ifeq          290
     174: ldc           #110                // String ssv.system.name
     176: aload         17
     178: invokevirtual #31                 // Method java/lang/String.equals:(Ljava/lang/Object;)Z
     181: ifeq          191
     184: aload         18
     186: astore        8
     188: goto          290
     191: ldc           #111                // String ssv.system.logo
     193: aload         17
     195: invokevirtual #31                 // Method java/lang/String.equals:(Ljava/lang/Object;)Z
     198: ifeq          208
     201: aload         18
     203: astore        7
     205: goto          290
     208: ldc           #112                // String ssv.vendor.logo
     210: aload         17
     212: invokevirtual #31                 // Method java/lang/String.equals:(Ljava/lang/Object;)Z
     215: ifeq          225
     218: aload         18
     220: astore        9
     222: goto          290
     225: ldc           #113                // String ssv.system.logo.height
     227: aload         17
     229: invokevirtual #31                 // Method java/lang/String.equals:(Ljava/lang/Object;)Z
     232: ifeq          242
     235: aload         18
     237: astore        14
     239: goto          290
     242: ldc           #114                // String ssv.system.logo.width
     244: aload         17
     246: invokevirtual #31                 // Method java/lang/String.equals:(Ljava/lang/Object;)Z
     249: ifeq          259
     252: aload         18
     254: astore        13
     256: goto          290
     259: ldc           #115                // String ssv.vendor.logo.width
     261: aload         17
     263: invokevirtual #31                 // Method java/lang/String.equals:(Ljava/lang/Object;)Z
     266: ifeq          276
     269: aload         18
     271: astore        11
     273: goto          290
     276: ldc           #116                // String ssv.vendor.logo.height
     278: aload         17
     280: invokevirtual #31                 // Method java/lang/String.equals:(Ljava/lang/Object;)Z
     283: ifeq          290
     286: aload         18
     288: astore        12
     290: goto          78
     293: aload         7
     295: ifnull        315
     298: aload         7
     300: invokestatic  #109                // Method org/apache/commons/lang/StringUtils.isNotEmpty:(Ljava/lang/String;)Z
     303: ifeq          315
     306: aload_3
     307: aload         7
     309: invokevirtual #117                // Method com/virtual/ssv/server/rs/client/UIConfig.setSystemLogo:(Ljava/lang/String;)V
     312: goto          349
     315: iload         5
     317: ifeq          327
     320: ldc           #118                // String ./icons/default/caslogo_unis.png
     322: astore        7
     324: goto          343
     327: iload         6
     329: ifeq          339
     332: ldc           #119                // String ./icons/default/caslogo_unicloud.png
     334: astore        7
     336: goto          343
     339: ldc           #120                // String ./icons/default/caslogo.png
     341: astore        7
     343: aload_3
     344: aload         7
     346: invokevirtual #117                // Method com/virtual/ssv/server/rs/client/UIConfig.setSystemLogo:(Ljava/lang/String;)V
     349: aload         8
     351: ifnull        371
     354: aload         8
     356: invokestatic  #109                // Method org/apache/commons/lang/StringUtils.isNotEmpty:(Ljava/lang/String;)Z
     359: ifeq          371
     362: aload_3
     363: aload         8
     365: invokevirtual #121                // Method com/virtual/ssv/server/rs/client/UIConfig.setSystemName:(Ljava/lang/String;)V
     368: goto          423
     371: iload         5
     373: ifeq          389
     376: getstatic     #122                // Field strMng:Lcom/virtual/common/StringManager;
     379: ldc           #123                // String unisCloudConsole
     381: invokevirtual #124                // Method com/virtual/common/StringManager.getString:(Ljava/lang/String;)Ljava/lang/String;
     384: astore        8
     386: goto          417
     389: iload         6
     391: ifeq          407
     394: getstatic     #122                // Field strMng:Lcom/virtual/common/StringManager;
     397: ldc           #125                // String uniCloudConsole
     399: invokevirtual #124                // Method com/virtual/common/StringManager.getString:(Ljava/lang/String;)Ljava/lang/String;
     402: astore        8
     404: goto          417
     407: getstatic     #122                // Field strMng:Lcom/virtual/common/StringManager;
     410: ldc           #126                // String cloudConsole
     412: invokevirtual #124                // Method com/virtual/common/StringManager.getString:(Ljava/lang/String;)Ljava/lang/String;
     415: astore        8
     417: aload_3
     418: aload         8
     420: invokevirtual #121                // Method com/virtual/ssv/server/rs/client/UIConfig.setSystemName:(Ljava/lang/String;)V
     423: aload         9
     425: ifnull        445
     428: aload         9
     430: invokestatic  #109                // Method org/apache/commons/lang/StringUtils.isNotEmpty:(Ljava/lang/String;)Z
     433: ifeq          445
     436: aload_3
     437: aload         9
     439: invokevirtual #127                // Method com/virtual/ssv/server/rs/client/UIConfig.setCopyrightLogo:(Ljava/lang/String;)V
     442: goto          479
     445: iload         5
     447: ifeq          457
     450: ldc           #128                // String ./icons/default/unis.svg
     452: astore        9
     454: goto          473
     457: iload         6
     459: ifeq          469
     462: ldc           #129                // String ./icons/default/unicloud.png
     464: astore        9
     466: goto          473
     469: ldc           #130                // String ./icons/default/h3c.png
     471: astore        9
     473: aload_3
     474: aload         9
     476: invokevirtual #127                // Method com/virtual/ssv/server/rs/client/UIConfig.setCopyrightLogo:(Ljava/lang/String;)V
     479: invokestatic  #131                // Method java/util/Calendar.getInstance:()Ljava/util/Calendar;
     482: iconst_1
     483: invokevirtual #133                // Method java/util/Calendar.get:(I)I
     486: invokestatic  #134                // Method java/lang/Integer.toString:(I)Ljava/lang/String;
     489: astore        15
     491: aload         10
     493: ifnull        513
     496: aload         10
     498: invokestatic  #109                // Method org/apache/commons/lang/StringUtils.isNotEmpty:(Ljava/lang/String;)Z
     501: ifeq          513
     504: aload_3
     505: aload         10
     507: invokevirtual #135                // Method com/virtual/ssv/server/rs/client/UIConfig.setCopyrightName:(Ljava/lang/String;)V
     510: goto          592
     513: iload         5
     515: ifeq          540
     518: getstatic     #122                // Field strMng:Lcom/virtual/common/StringManager;
     521: ldc           #136                // String copyright_unis
     523: iconst_1
     524: anewarray     #137                // class java/lang/Object
     527: dup
     528: iconst_0
     529: aload         15
     531: aastore
     532: invokevirtual #138                // Method com/virtual/common/StringManager.getString:(Ljava/lang/String;[Ljava/lang/Object;)Ljava/lang/String;
     535: astore        10
     537: goto          586
     540: iload         6
     542: ifeq          567
     545: getstatic     #122                // Field strMng:Lcom/virtual/common/StringManager;
     548: ldc           #139                // String copyright_uniCloud
     550: iconst_1
     551: anewarray     #137                // class java/lang/Object
     554: dup
     555: iconst_0
     556: aload         15
     558: aastore
     559: invokevirtual #138                // Method com/virtual/common/StringManager.getString:(Ljava/lang/String;[Ljava/lang/Object;)Ljava/lang/String;
     562: astore        10
     564: goto          586
     567: getstatic     #122                // Field strMng:Lcom/virtual/common/StringManager;
     570: ldc           #140                // String copyright
     572: iconst_1
     573: anewarray     #137                // class java/lang/Object
     576: dup
     577: iconst_0
     578: aload         15
     580: aastore
     581: invokevirtual #138                // Method com/virtual/common/StringManager.getString:(Ljava/lang/String;[Ljava/lang/Object;)Ljava/lang/String;
     584: astore        10
     586: aload_3
     587: aload         10
     589: invokevirtual #135                // Method com/virtual/ssv/server/rs/client/UIConfig.setCopyrightName:(Ljava/lang/String;)V
     592: aload         12
     594: invokestatic  #109                // Method org/apache/commons/lang/StringUtils.isNotEmpty:(Ljava/lang/String;)Z
     597: ifeq          606
     600: aload_3
     601: aload         12
     603: invokevirtual #141                // Method com/virtual/ssv/server/rs/client/UIConfig.setCopyrightLogoHeight:(Ljava/lang/String;)V
     606: aload         11
     608: invokestatic  #109                // Method org/apache/commons/lang/StringUtils.isNotEmpty:(Ljava/lang/String;)Z
     611: ifeq          620
     614: aload_3
     615: aload         11
     617: invokevirtual #142                // Method com/virtual/ssv/server/rs/client/UIConfig.setCopyrightLogoWidth:(Ljava/lang/String;)V
     620: aload         13
     622: invokestatic  #109                // Method org/apache/commons/lang/StringUtils.isNotEmpty:(Ljava/lang/String;)Z
     625: ifeq          634
     628: aload_3
     629: aload         13
     631: invokevirtual #143                // Method com/virtual/ssv/server/rs/client/UIConfig.setSystemLogoWidth:(Ljava/lang/String;)V
     634: aload         14
     636: invokestatic  #109                // Method org/apache/commons/lang/StringUtils.isNotEmpty:(Ljava/lang/String;)Z
     639: ifeq          648
     642: aload_3
     643: aload         14
     645: invokevirtual #144                // Method com/virtual/ssv/server/rs/client/UIConfig.setSystemLogoHeight:(Ljava/lang/String;)V
     648: aload_0
     649: aload_2
     650: aload_0
     651: getfield      #145                // Field gson:Lcom/google/gson/Gson;
     654: aload_3
     655: invokevirtual #86                 // Method com/google/gson/Gson.toJson:(Ljava/lang/Object;)Ljava/lang/String;
     658: invokevirtual #87                 // Method write:(Ljavax/servlet/http/HttpServletResponse;Ljava/lang/String;)V
     661: goto          676
     664: astore        5
     666: getstatic     #79                 // Field log:Lorg/apache/commons/logging/Log;
     669: aload         5
     671: invokeinterface #80,  2           // InterfaceMethod org/apache/commons/logging/Log.error:(Ljava/lang/Object;)V
     676: return
    Exception table:
       from    to  target type
          17   661   664   Class java/lang/Exception

  private void getCopyrightFrom(javax.servlet.http.HttpServletRequest, javax.servlet.http.HttpServletResponse);
    Code:
       0: new           #104                // class com/virtual/ssv/server/rs/client/entity/RsParameter
       3: dup
       4: invokespecial #147                // Method com/virtual/ssv/server/rs/client/entity/RsParameter."<init>":()V
       7: astore_3
       8: ldc           #98                 // String UNIS
      10: invokestatic  #99                 // Method com/virtual/common/FuncUtil.versionFromPath:(Ljava/lang/String;)Z
      13: istore        4
      15: ldc           #100                // String UniCloud
      17: invokestatic  #99                 // Method com/virtual/common/FuncUtil.versionFromPath:(Ljava/lang/String;)Z
      20: istore        5
      22: iload         4
      24: ifeq          33
      27: aload_3
      28: ldc           #98                 // String UNIS
      30: invokevirtual #148                // Method com/virtual/ssv/server/rs/client/entity/RsParameter.setValue:(Ljava/lang/String;)V
      33: iload         5
      35: ifeq          44
      38: aload_3
      39: ldc           #100                // String UniCloud
      41: invokevirtual #148                // Method com/virtual/ssv/server/rs/client/entity/RsParameter.setValue:(Ljava/lang/String;)V
      44: aload_0
      45: aload_2
      46: aload_0
      47: getfield      #145                // Field gson:Lcom/google/gson/Gson;
      50: aload_3
      51: invokevirtual #86                 // Method com/google/gson/Gson.toJson:(Ljava/lang/Object;)Ljava/lang/String;
      54: invokevirtual #87                 // Method write:(Ljavax/servlet/http/HttpServletResponse;Ljava/lang/String;)V
      57: goto          72
      60: astore        4
      62: getstatic     #79                 // Field log:Lorg/apache/commons/logging/Log;
      65: aload         4
      67: invokeinterface #80,  2           // InterfaceMethod org/apache/commons/logging/Log.error:(Ljava/lang/Object;)V
      72: return
    Exception table:
       from    to  target type
           8    57    60   Class java/lang/Exception

  private void saveSsvConfig(javax.servlet.http.HttpServletRequest, javax.servlet.http.HttpServletResponse);
    Code:
       0: new           #72                 // class com/virtual/ssv/server/entity/ResultJson
       3: dup
       4: invokespecial #73                 // Method com/virtual/ssv/server/entity/ResultJson."<init>":()V
       7: astore_3
       8: aload_1
       9: ldc           #149                // String casIp
      11: invokeinterface #29,  2           // InterfaceMethod javax/servlet/http/HttpServletRequest.getParameter:(Ljava/lang/String;)Ljava/lang/String;
      16: astore        4
      18: aload_1
      19: ldc           #150                // String loginName
      21: invokeinterface #29,  2           // InterfaceMethod javax/servlet/http/HttpServletRequest.getParameter:(Ljava/lang/String;)Ljava/lang/String;
      26: astore        5
      28: aload_1
      29: ldc           #151                // String password
      31: invokeinterface #29,  2           // InterfaceMethod javax/servlet/http/HttpServletRequest.getParameter:(Ljava/lang/String;)Ljava/lang/String;
      36: astore        6
      38: aload         4
      40: invokestatic  #152                // Method org/apache/commons/lang/StringUtils.isEmpty:(Ljava/lang/String;)Z
      43: ifne          62
      46: aload         5
      48: invokestatic  #152                // Method org/apache/commons/lang/StringUtils.isEmpty:(Ljava/lang/String;)Z
      51: ifne          62
      54: aload         6
      56: invokestatic  #152                // Method org/apache/commons/lang/StringUtils.isEmpty:(Ljava/lang/String;)Z
      59: ifeq          63
      62: return
      63: aload_1
      64: invokeinterface #49,  1           // InterfaceMethod javax/servlet/http/HttpServletRequest.getSession:()Ljavax/servlet/http/HttpSession;
      69: astore        7
      71: invokestatic  #153                // Method java/lang/System.currentTimeMillis:()J
      74: lstore        8
      76: aload_0
      77: getfield      #6                  // Field checkPasswordAttack:Z
      80: ifeq          275
      83: aload         7
      85: aload_0
      86: getfield      #21                 // Field ATTR_SAVE_SYSTEM_CONFIG_COUNT:Ljava/lang/String;
      89: invokeinterface #51,  2           // InterfaceMethod javax/servlet/http/HttpSession.getAttribute:(Ljava/lang/String;)Ljava/lang/Object;
      94: checkcast     #154                // class java/lang/Integer
      97: astore        10
      99: aload         7
     101: aload_0
     102: getfield      #23                 // Field ATTR_LAST_SAVE_SYSTEM_CONFIG_TIME:Ljava/lang/String;
     105: invokeinterface #51,  2           // InterfaceMethod javax/servlet/http/HttpSession.getAttribute:(Ljava/lang/String;)Ljava/lang/Object;
     110: checkcast     #155                // class java/lang/Long
     113: astore        11
     115: aload         10
     117: ifnull        275
     120: aload         11
     122: ifnull        275
     125: aload         10
     127: invokevirtual #156                // Method java/lang/Integer.intValue:()I
     130: iconst_1
     131: iadd
     132: aload_0
     133: getfield      #26                 // Field maxConfigFailCount:I
     136: if_icmple     275
     139: lload         8
     141: aload         11
     143: invokevirtual #157                // Method java/lang/Long.longValue:()J
     146: lsub
     147: invokestatic  #158                // Method java/lang/Math.abs:(J)J
     150: aload_0
     151: getfield      #11                 // Field lockTime:I
     154: i2l
     155: ldc2_w        #159                // long 60000l
     158: lmul
     159: lcmp
     160: ifge          275
     163: aload         10
     165: invokevirtual #156                // Method java/lang/Integer.intValue:()I
     168: ldc           #161                // int 2147483647
     170: if_icmpge     195
     173: aload         10
     175: astore        12
     177: aload         10
     179: invokevirtual #156                // Method java/lang/Integer.intValue:()I
     182: iconst_1
     183: iadd
     184: invokestatic  #162                // Method java/lang/Integer.valueOf:(I)Ljava/lang/Integer;
     187: dup
     188: astore        10
     190: astore        13
     192: aload         12
     194: pop
     195: aload         7
     197: aload_0
     198: getfield      #21                 // Field ATTR_SAVE_SYSTEM_CONFIG_COUNT:Ljava/lang/String;
     201: aload         10
     203: invokeinterface #163,  3          // InterfaceMethod javax/servlet/http/HttpSession.setAttribute:(Ljava/lang/String;Ljava/lang/Object;)V
     208: aload         7
     210: aload_0
     211: getfield      #23                 // Field ATTR_LAST_SAVE_SYSTEM_CONFIG_TIME:Ljava/lang/String;
     214: lload         8
     216: invokestatic  #164                // Method java/lang/Long.valueOf:(J)Ljava/lang/Long;
     219: invokeinterface #163,  3          // InterfaceMethod javax/servlet/http/HttpSession.setAttribute:(Ljava/lang/String;Ljava/lang/Object;)V
     224: aload_3
     225: aload_0
     226: getfield      #165                // Field logSm:Lcom/virtual/common/StringManager;
     229: ldc           #166                // String save.system.Fail
     231: iconst_2
     232: anewarray     #137                // class java/lang/Object
     235: dup
     236: iconst_0
     237: aload_0
     238: getfield      #26                 // Field maxConfigFailCount:I
     241: invokestatic  #162                // Method java/lang/Integer.valueOf:(I)Ljava/lang/Integer;
     244: aastore
     245: dup
     246: iconst_1
     247: aload_0
     248: getfield      #11                 // Field lockTime:I
     251: invokestatic  #162                // Method java/lang/Integer.valueOf:(I)Ljava/lang/Integer;
     254: aastore
     255: invokevirtual #138                // Method com/virtual/common/StringManager.getString:(Ljava/lang/String;[Ljava/lang/Object;)Ljava/lang/String;
     258: invokevirtual #84                 // Method com/virtual/ssv/server/entity/ResultJson.setErrorMsg:(Ljava/lang/String;)V
     261: aload_0
     262: aload_2
     263: aload_0
     264: getfield      #85                 // Field filterJson:Lcom/google/gson/Gson;
     267: aload_3
     268: invokevirtual #86                 // Method com/google/gson/Gson.toJson:(Ljava/lang/Object;)Ljava/lang/String;
     271: invokevirtual #87                 // Method write:(Ljavax/servlet/http/HttpServletResponse;Ljava/lang/String;)V
     274: return
     275: new           #167                // class com/virtual/ssv/server/rs/client/LoginConfig
     278: dup
     279: invokespecial #168                // Method com/virtual/ssv/server/rs/client/LoginConfig."<init>":()V
     282: astore        10
     284: aload         10
     286: aload         4
     288: invokevirtual #169                // Method com/virtual/ssv/server/rs/client/LoginConfig.setHost:(Ljava/lang/String;)V
     291: aload         10
     293: aload         5
     295: invokevirtual #170                // Method com/virtual/ssv/server/rs/client/LoginConfig.setUserName:(Ljava/lang/String;)V
     298: aload         10
     300: aload         6
     302: invokevirtual #171                // Method com/virtual/ssv/server/rs/client/LoginConfig.setPassword:(Ljava/lang/String;)V
     305: aload_0
     306: getfield      #1                  // Field reqHandle:Lcom/virtual/ssv/server/rs/client/RequestHandle;
     309: aload         10
     311: invokevirtual #172                // Method com/virtual/ssv/server/rs/client/RequestHandle.checkConfig:(Lcom/virtual/ssv/server/rs/client/LoginConfig;)Z
     314: istore        11
     316: iload         11
     318: ifeq          334
     321: aload_0
     322: getfield      #1                  // Field reqHandle:Lcom/virtual/ssv/server/rs/client/RequestHandle;
     325: aload         10
     327: invokevirtual #173                // Method com/virtual/ssv/server/rs/client/RequestHandle.saveSsvConfig:(Lcom/virtual/ssv/server/rs/client/LoginConfig;)Lcom/virtual/ssv/server/entity/ResultJson;
     330: astore_3
     331: goto          343
     334: aload_3
     335: bipush        103
     337: invokestatic  #174                // Method com/virtual/common/ErrorCodes.getErrorMessage:(I)Ljava/lang/String;
     340: invokevirtual #84                 // Method com/virtual/ssv/server/entity/ResultJson.setErrorMsg:(Ljava/lang/String;)V
     343: goto          354
     346: astore        11
     348: aload         11
     350: aload_3
     351: invokestatic  #175                // Method com/virtual/ssv/server/ServerUtils.handleException:(Ljava/lang/Exception;Lcom/virtual/ssv/server/entity/ResultJson;)V
     354: aload_0
     355: getfield      #6                  // Field checkPasswordAttack:Z
     358: ifeq          474
     361: aload_3
     362: invokevirtual #176                // Method com/virtual/ssv/server/entity/ResultJson.getState:()I
     365: ifne          452
     368: aload         7
     370: aload_0
     371: getfield      #21                 // Field ATTR_SAVE_SYSTEM_CONFIG_COUNT:Ljava/lang/String;
     374: invokeinterface #51,  2           // InterfaceMethod javax/servlet/http/HttpSession.getAttribute:(Ljava/lang/String;)Ljava/lang/Object;
     379: checkcast     #154                // class java/lang/Integer
     382: astore        11
     384: aload         11
     386: ifnonnull     398
     389: iconst_1
     390: invokestatic  #162                // Method java/lang/Integer.valueOf:(I)Ljava/lang/Integer;
     393: astore        11
     395: goto          420
     398: aload         11
     400: astore        12
     402: aload         11
     404: invokevirtual #156                // Method java/lang/Integer.intValue:()I
     407: iconst_1
     408: iadd
     409: invokestatic  #162                // Method java/lang/Integer.valueOf:(I)Ljava/lang/Integer;
     412: dup
     413: astore        11
     415: astore        13
     417: aload         12
     419: pop
     420: aload         7
     422: aload_0
     423: getfield      #21                 // Field ATTR_SAVE_SYSTEM_CONFIG_COUNT:Ljava/lang/String;
     426: aload         11
     428: invokeinterface #163,  3          // InterfaceMethod javax/servlet/http/HttpSession.setAttribute:(Ljava/lang/String;Ljava/lang/Object;)V
     433: aload         7
     435: aload_0
     436: getfield      #23                 // Field ATTR_LAST_SAVE_SYSTEM_CONFIG_TIME:Ljava/lang/String;
     439: lload         8
     441: invokestatic  #164                // Method java/lang/Long.valueOf:(J)Ljava/lang/Long;
     444: invokeinterface #163,  3          // InterfaceMethod javax/servlet/http/HttpSession.setAttribute:(Ljava/lang/String;Ljava/lang/Object;)V
     449: goto          474
     452: aload         7
     454: aload_0
     455: getfield      #21                 // Field ATTR_SAVE_SYSTEM_CONFIG_COUNT:Ljava/lang/String;
     458: invokeinterface #177,  2          // InterfaceMethod javax/servlet/http/HttpSession.removeAttribute:(Ljava/lang/String;)V
     463: aload         7
     465: aload_0
     466: getfield      #23                 // Field ATTR_LAST_SAVE_SYSTEM_CONFIG_TIME:Ljava/lang/String;
     469: invokeinterface #177,  2          // InterfaceMethod javax/servlet/http/HttpSession.removeAttribute:(Ljava/lang/String;)V
     474: aload_0
     475: aload_2
     476: aload_0
     477: getfield      #85                 // Field filterJson:Lcom/google/gson/Gson;
     480: aload_3
     481: invokevirtual #86                 // Method com/google/gson/Gson.toJson:(Ljava/lang/Object;)Ljava/lang/String;
     484: invokevirtual #87                 // Method write:(Ljavax/servlet/http/HttpServletResponse;Ljava/lang/String;)V
     487: return
    Exception table:
       from    to  target type
         305   343   346   Class java/lang/Exception

  private void getSsvConfig(javax.servlet.http.HttpServletRequest, javax.servlet.http.HttpServletResponse);
    Code:
       0: new           #72                 // class com/virtual/ssv/server/entity/ResultJson
       3: dup
       4: invokespecial #73                 // Method com/virtual/ssv/server/entity/ResultJson."<init>":()V
       7: astore_3
       8: new           #167                // class com/virtual/ssv/server/rs/client/LoginConfig
      11: dup
      12: invokespecial #168                // Method com/virtual/ssv/server/rs/client/LoginConfig."<init>":()V
      15: astore        4
      17: aload_0
      18: getfield      #1                  // Field reqHandle:Lcom/virtual/ssv/server/rs/client/RequestHandle;
      21: invokevirtual #178                // Method com/virtual/ssv/server/rs/client/RequestHandle.getSsvConfig:()Lcom/virtual/ssv/server/rs/client/LoginConfig;
      24: astore        4
      26: goto          37
      29: astore        5
      31: aload         5
      33: aload_3
      34: invokestatic  #175                // Method com/virtual/ssv/server/ServerUtils.handleException:(Ljava/lang/Exception;Lcom/virtual/ssv/server/entity/ResultJson;)V
      37: aload_0
      38: aload_2
      39: aload_0
      40: getfield      #145                // Field gson:Lcom/google/gson/Gson;
      43: aload         4
      45: invokevirtual #86                 // Method com/google/gson/Gson.toJson:(Ljava/lang/Object;)Ljava/lang/String;
      48: invokevirtual #87                 // Method write:(Ljavax/servlet/http/HttpServletResponse;Ljava/lang/String;)V
      51: return
    Exception table:
       from    to  target type
          17    26    29   Class java/lang/Exception

  private void forgetPassword(javax.servlet.http.HttpServletRequest, javax.servlet.http.HttpServletResponse);
    Code:
       0: aload_1
       1: ldc           #150                // String loginName
       3: invokeinterface #29,  2           // InterfaceMethod javax/servlet/http/HttpServletRequest.getParameter:(Ljava/lang/String;)Ljava/lang/String;
       8: astore_3
       9: aload_1
      10: ldc           #179                // String mailName
      12: invokeinterface #29,  2           // InterfaceMethod javax/servlet/http/HttpServletRequest.getParameter:(Ljava/lang/String;)Ljava/lang/String;
      17: astore        4
      19: aload_3
      20: invokestatic  #152                // Method org/apache/commons/lang/StringUtils.isEmpty:(Ljava/lang/String;)Z
      23: ifne          34
      26: aload         4
      28: invokestatic  #152                // Method org/apache/commons/lang/StringUtils.isEmpty:(Ljava/lang/String;)Z
      31: ifeq          35
      34: return
      35: new           #72                 // class com/virtual/ssv/server/entity/ResultJson
      38: dup
      39: invokespecial #73                 // Method com/virtual/ssv/server/entity/ResultJson."<init>":()V
      42: astore        5
      44: aload_0
      45: getfield      #1                  // Field reqHandle:Lcom/virtual/ssv/server/rs/client/RequestHandle;
      48: aload_3
      49: aload         4
      51: invokevirtual #180                // Method com/virtual/ssv/server/rs/client/RequestHandle.forgetPassword:(Ljava/lang/String;Ljava/lang/String;)Lcom/virtual/ssv/server/entity/ResultJson;
      54: astore        5
      56: goto          68
      59: astore        6
      61: aload         6
      63: aload         5
      65: invokestatic  #175                // Method com/virtual/ssv/server/ServerUtils.handleException:(Ljava/lang/Exception;Lcom/virtual/ssv/server/entity/ResultJson;)V
      68: aload_0
      69: aload_2
      70: aload_0
      71: getfield      #85                 // Field filterJson:Lcom/google/gson/Gson;
      74: aload         5
      76: invokevirtual #86                 // Method com/google/gson/Gson.toJson:(Ljava/lang/Object;)Ljava/lang/String;
      79: invokevirtual #87                 // Method write:(Ljavax/servlet/http/HttpServletResponse;Ljava/lang/String;)V
      82: return
    Exception table:
       from    to  target type
          44    56    59   Class java/lang/Exception

  private void register(javax.servlet.http.HttpServletRequest, javax.servlet.http.HttpServletResponse);
    Code:
       0: aload_1
       1: ldc           #150                // String loginName
       3: invokeinterface #29,  2           // InterfaceMethod javax/servlet/http/HttpServletRequest.getParameter:(Ljava/lang/String;)Ljava/lang/String;
       8: astore_3
       9: aload_1
      10: ldc           #181                // String pwdName
      12: invokeinterface #29,  2           // InterfaceMethod javax/servlet/http/HttpServletRequest.getParameter:(Ljava/lang/String;)Ljava/lang/String;
      17: astore        4
      19: aload_1
      20: ldc           #179                // String mailName
      22: invokeinterface #29,  2           // InterfaceMethod javax/servlet/http/HttpServletRequest.getParameter:(Ljava/lang/String;)Ljava/lang/String;
      27: astore        5
      29: aload_1
      30: ldc           #182                // String userName
      32: invokeinterface #29,  2           // InterfaceMethod javax/servlet/http/HttpServletRequest.getParameter:(Ljava/lang/String;)Ljava/lang/String;
      37: astore        6
      39: aload_1
      40: ldc           #183                // String sex
      42: invokeinterface #29,  2           // InterfaceMethod javax/servlet/http/HttpServletRequest.getParameter:(Ljava/lang/String;)Ljava/lang/String;
      47: astore        7
      49: aload_1
      50: ldc           #184                // String certificateNumName
      52: invokeinterface #29,  2           // InterfaceMethod javax/servlet/http/HttpServletRequest.getParameter:(Ljava/lang/String;)Ljava/lang/String;
      57: astore        8
      59: aload_1
      60: ldc           #185                // String address
      62: invokeinterface #29,  2           // InterfaceMethod javax/servlet/http/HttpServletRequest.getParameter:(Ljava/lang/String;)Ljava/lang/String;
      67: astore        9
      69: aload_1
      70: ldc           #186                // String department
      72: invokeinterface #29,  2           // InterfaceMethod javax/servlet/http/HttpServletRequest.getParameter:(Ljava/lang/String;)Ljava/lang/String;
      77: astore        10
      79: aload_1
      80: ldc           #187                // String position
      82: invokeinterface #29,  2           // InterfaceMethod javax/servlet/http/HttpServletRequest.getParameter:(Ljava/lang/String;)Ljava/lang/String;
      87: invokevirtual #188                // Method java/lang/String.isEmpty:()Z
      90: ifeq          98
      93: ldc           #189                // String
      95: goto          106
      98: aload_1
      99: ldc           #187                // String position
     101: invokeinterface #29,  2           // InterfaceMethod javax/servlet/http/HttpServletRequest.getParameter:(Ljava/lang/String;)Ljava/lang/String;
     106: astore        11
     108: aload_1
     109: ldc           #190                // String phoneName
     111: invokeinterface #29,  2           // InterfaceMethod javax/servlet/http/HttpServletRequest.getParameter:(Ljava/lang/String;)Ljava/lang/String;
     116: invokevirtual #188                // Method java/lang/String.isEmpty:()Z
     119: ifeq          127
     122: ldc           #189                // String
     124: goto          135
     127: aload_1
     128: ldc           #190                // String phoneName
     130: invokeinterface #29,  2           // InterfaceMethod javax/servlet/http/HttpServletRequest.getParameter:(Ljava/lang/String;)Ljava/lang/String;
     135: astore        12
     137: new           #191                // class com/virtual/ssv/server/rs/client/entity/RsUser
     140: dup
     141: invokespecial #192                // Method com/virtual/ssv/server/rs/client/entity/RsUser."<init>":()V
     144: astore        13
     146: aload         13
     148: aload         9
     150: invokevirtual #193                // Method com/virtual/ssv/server/rs/client/entity/RsUser.setAddress:(Ljava/lang/String;)V
     153: aload         13
     155: aload         8
     157: invokevirtual #194                // Method com/virtual/ssv/server/rs/client/entity/RsUser.setCertification:(Ljava/lang/String;)V
     160: aload         13
     162: aload         5
     164: invokevirtual #195                // Method com/virtual/ssv/server/rs/client/entity/RsUser.setEmail:(Ljava/lang/String;)V
     167: aload         13
     169: aload_3
     170: invokevirtual #196                // Method com/virtual/ssv/server/rs/client/entity/RsUser.setLoginName:(Ljava/lang/String;)V
     173: aload         13
     175: aload         4
     177: invokevirtual #197                // Method com/virtual/ssv/server/rs/client/entity/RsUser.setPassword:(Ljava/lang/String;)V
     180: aload         13
     182: aload         10
     184: invokevirtual #198                // Method com/virtual/ssv/server/rs/client/entity/RsUser.setDept:(Ljava/lang/String;)V
     187: aload         13
     189: aload         12
     191: invokevirtual #199                // Method com/virtual/ssv/server/rs/client/entity/RsUser.setPhone:(Ljava/lang/String;)V
     194: aload         13
     196: aload         11
     198: invokevirtual #200                // Method com/virtual/ssv/server/rs/client/entity/RsUser.setPosition:(Ljava/lang/String;)V
     201: aload         13
     203: aload         7
     205: invokestatic  #201                // Method java/lang/Integer.valueOf:(Ljava/lang/String;)Ljava/lang/Integer;
     208: invokevirtual #202                // Method com/virtual/ssv/server/rs/client/entity/RsUser.setSex:(Ljava/lang/Integer;)V
     211: aload         13
     213: aload         6
     215: invokevirtual #203                // Method com/virtual/ssv/server/rs/client/entity/RsUser.setUserName:(Ljava/lang/String;)V
     218: new           #72                 // class com/virtual/ssv/server/entity/ResultJson
     221: dup
     222: invokespecial #73                 // Method com/virtual/ssv/server/entity/ResultJson."<init>":()V
     225: astore        14
     227: aload_0
     228: getfield      #1                  // Field reqHandle:Lcom/virtual/ssv/server/rs/client/RequestHandle;
     231: aload_3
     232: invokevirtual #81                 // Method com/virtual/ssv/server/rs/client/RequestHandle.checkRegisterUser:(Ljava/lang/String;)Z
     235: istore        15
     237: iload         15
     239: ifeq          270
     242: aload         14
     244: getstatic     #122                // Field strMng:Lcom/virtual/common/StringManager;
     247: ldc           #204                // String errorCode.22
     249: invokevirtual #124                // Method com/virtual/common/StringManager.getString:(Ljava/lang/String;)Ljava/lang/String;
     252: invokevirtual #84                 // Method com/virtual/ssv/server/entity/ResultJson.setErrorMsg:(Ljava/lang/String;)V
     255: aload_0
     256: aload_2
     257: aload_0
     258: getfield      #85                 // Field filterJson:Lcom/google/gson/Gson;
     261: aload         14
     263: invokevirtual #86                 // Method com/google/gson/Gson.toJson:(Ljava/lang/Object;)Ljava/lang/String;
     266: invokevirtual #87                 // Method write:(Ljavax/servlet/http/HttpServletResponse;Ljava/lang/String;)V
     269: return
     270: aload_0
     271: getfield      #1                  // Field reqHandle:Lcom/virtual/ssv/server/rs/client/RequestHandle;
     274: aload         5
     276: invokevirtual #88                 // Method com/virtual/ssv/server/rs/client/RequestHandle.checkEmail:(Ljava/lang/String;)Z
     279: istore        15
     281: iload         15
     283: ifeq          314
     286: aload         14
     288: getstatic     #122                // Field strMng:Lcom/virtual/common/StringManager;
     291: ldc           #205                // String errorCode.23
     293: invokevirtual #124                // Method com/virtual/common/StringManager.getString:(Ljava/lang/String;)Ljava/lang/String;
     296: invokevirtual #84                 // Method com/virtual/ssv/server/entity/ResultJson.setErrorMsg:(Ljava/lang/String;)V
     299: aload_0
     300: aload_2
     301: aload_0
     302: getfield      #85                 // Field filterJson:Lcom/google/gson/Gson;
     305: aload         14
     307: invokevirtual #86                 // Method com/google/gson/Gson.toJson:(Ljava/lang/Object;)Ljava/lang/String;
     310: invokevirtual #87                 // Method write:(Ljavax/servlet/http/HttpServletResponse;Ljava/lang/String;)V
     313: return
     314: aload_0
     315: getfield      #1                  // Field reqHandle:Lcom/virtual/ssv/server/rs/client/RequestHandle;
     318: aload         13
     320: invokevirtual #206                // Method com/virtual/ssv/server/rs/client/RequestHandle.addRegisterUser:(Lcom/virtual/ssv/server/rs/client/entity/RsUser;)Lcom/virtual/ssv/server/entity/ResultJson;
     323: astore        14
     325: goto          337
     328: astore        15
     330: aload         15
     332: aload         14
     334: invokestatic  #175                // Method com/virtual/ssv/server/ServerUtils.handleException:(Ljava/lang/Exception;Lcom/virtual/ssv/server/entity/ResultJson;)V
     337: aload_0
     338: aload_2
     339: aload_0
     340: getfield      #85                 // Field filterJson:Lcom/google/gson/Gson;
     343: aload         14
     345: invokevirtual #86                 // Method com/google/gson/Gson.toJson:(Ljava/lang/Object;)Ljava/lang/String;
     348: invokevirtual #87                 // Method write:(Ljavax/servlet/http/HttpServletResponse;Ljava/lang/String;)V
     351: return
    Exception table:
       from    to  target type
         227   269   328   Class java/lang/Exception
         270   313   328   Class java/lang/Exception
         314   325   328   Class java/lang/Exception

  private void doLogin(javax.servlet.http.HttpServletRequest, javax.servlet.http.HttpServletResponse);
    Code:
       0: new           #207                // class java/util/Date
       3: dup
       4: invokespecial #208                // Method java/util/Date."<init>":()V
       7: astore_3
       8: aload_1
       9: ldc           #150                // String loginName
      11: invokeinterface #29,  2           // InterfaceMethod javax/servlet/http/HttpServletRequest.getParameter:(Ljava/lang/String;)Ljava/lang/String;
      16: astore        4
      18: aload_1
      19: ldc           #151                // String password
      21: invokeinterface #29,  2           // InterfaceMethod javax/servlet/http/HttpServletRequest.getParameter:(Ljava/lang/String;)Ljava/lang/String;
      26: astore        5
      28: aload_1
      29: ldc           #209                // String isEncrypt
      31: invokeinterface #29,  2           // InterfaceMethod javax/servlet/http/HttpServletRequest.getParameter:(Ljava/lang/String;)Ljava/lang/String;
      36: astore        6
      38: aload_1
      39: ldc           #210                // String fastLogin
      41: invokeinterface #29,  2           // InterfaceMethod javax/servlet/http/HttpServletRequest.getParameter:(Ljava/lang/String;)Ljava/lang/String;
      46: astore        7
      48: ldc           #211                // String true
      50: aload         6
      52: invokevirtual #31                 // Method java/lang/String.equals:(Ljava/lang/Object;)Z
      55: ifeq          90
      58: aload         5
      60: ldc           #76                 // String UTF-8
      62: invokestatic  #77                 // Method java/net/URLDecoder.decode:(Ljava/lang/String;Ljava/lang/String;)Ljava/lang/String;
      65: astore        5
      67: goto          83
      70: astore        8
      72: getstatic     #79                 // Field log:Lorg/apache/commons/logging/Log;
      75: aconst_null
      76: aload         8
      78: invokeinterface #212,  3          // InterfaceMethod org/apache/commons/logging/Log.error:(Ljava/lang/Object;Ljava/lang/Throwable;)V
      83: aload         5
      85: invokestatic  #213                // Method com/virtual/common/FuncUtil.decryptData:(Ljava/lang/String;)Ljava/lang/String;
      88: astore        5
      90: aload_1
      91: invokeinterface #49,  1           // InterfaceMethod javax/servlet/http/HttpServletRequest.getSession:()Ljavax/servlet/http/HttpSession;
      96: astore        8
      98: aload_1
      99: invokeinterface #214,  1          // InterfaceMethod javax/servlet/http/HttpServletRequest.getRemoteAddr:()Ljava/lang/String;
     104: astore        9
     106: invokestatic  #153                // Method java/lang/System.currentTimeMillis:()J
     109: lstore        10
     111: new           #215                // class com/google/gson/Gson
     114: dup
     115: invokespecial #216                // Method com/google/gson/Gson."<init>":()V
     118: astore        12
     120: aload_0
     121: getfield      #6                  // Field checkPasswordAttack:Z
     124: ifeq          346
     127: aload         8
     129: aload_0
     130: getfield      #19                 // Field ATTR_LOGIN_FAILED_COUNT:Ljava/lang/String;
     133: invokeinterface #51,  2           // InterfaceMethod javax/servlet/http/HttpSession.getAttribute:(Ljava/lang/String;)Ljava/lang/Object;
     138: checkcast     #154                // class java/lang/Integer
     141: astore        13
     143: aload         8
     145: aload_0
     146: getfield      #25                 // Field ATTR_LAST_LOGIN_FAILED_TIME:Ljava/lang/String;
     149: invokeinterface #51,  2           // InterfaceMethod javax/servlet/http/HttpSession.getAttribute:(Ljava/lang/String;)Ljava/lang/Object;
     154: checkcast     #155                // class java/lang/Long
     157: astore        14
     159: aload         13
     161: ifnull        346
     164: aload         14
     166: ifnull        346
     169: aload         13
     171: invokevirtual #156                // Method java/lang/Integer.intValue:()I
     174: iconst_1
     175: iadd
     176: aload_0
     177: getfield      #9                  // Field maxFailCount:I
     180: if_icmple     346
     183: lload         10
     185: aload         14
     187: invokevirtual #157                // Method java/lang/Long.longValue:()J
     190: lsub
     191: invokestatic  #158                // Method java/lang/Math.abs:(J)J
     194: aload_0
     195: getfield      #11                 // Field lockTime:I
     198: i2l
     199: ldc2_w        #159                // long 60000l
     202: lmul
     203: lcmp
     204: ifge          346
     207: aload         13
     209: invokevirtual #156                // Method java/lang/Integer.intValue:()I
     212: ldc           #161                // int 2147483647
     214: if_icmpge     239
     217: aload         13
     219: astore        15
     221: aload         13
     223: invokevirtual #156                // Method java/lang/Integer.intValue:()I
     226: iconst_1
     227: iadd
     228: invokestatic  #162                // Method java/lang/Integer.valueOf:(I)Ljava/lang/Integer;
     231: dup
     232: astore        13
     234: astore        16
     236: aload         15
     238: pop
     239: aload         8
     241: aload_0
     242: getfield      #19                 // Field ATTR_LOGIN_FAILED_COUNT:Ljava/lang/String;
     245: aload         13
     247: invokeinterface #163,  3          // InterfaceMethod javax/servlet/http/HttpSession.setAttribute:(Ljava/lang/String;Ljava/lang/Object;)V
     252: aload         8
     254: aload_0
     255: getfield      #25                 // Field ATTR_LAST_LOGIN_FAILED_TIME:Ljava/lang/String;
     258: lload         10
     260: invokestatic  #164                // Method java/lang/Long.valueOf:(J)Ljava/lang/Long;
     263: invokeinterface #163,  3          // InterfaceMethod javax/servlet/http/HttpSession.setAttribute:(Ljava/lang/String;Ljava/lang/Object;)V
     268: new           #52                 // class com/virtual/ssv/server/user/LoginInfo
     271: dup
     272: invokespecial #217                // Method com/virtual/ssv/server/user/LoginInfo."<init>":()V
     275: astore        15
     277: aload         15
     279: aload_0
     280: getfield      #165                // Field logSm:Lcom/virtual/common/StringManager;
     283: ldc           #218                // String operError
     285: invokevirtual #124                // Method com/virtual/common/StringManager.getString:(Ljava/lang/String;)Ljava/lang/String;
     288: invokevirtual #219                // Method com/virtual/ssv/server/user/LoginInfo.setErrorTitle:(Ljava/lang/String;)V
     291: aload         15
     293: aload_0
     294: getfield      #165                // Field logSm:Lcom/virtual/common/StringManager;
     297: ldc           #220                // String login.attackFail
     299: iconst_2
     300: anewarray     #137                // class java/lang/Object
     303: dup
     304: iconst_0
     305: aload_0
     306: getfield      #9                  // Field maxFailCount:I
     309: invokestatic  #162                // Method java/lang/Integer.valueOf:(I)Ljava/lang/Integer;
     312: aastore
     313: dup
     314: iconst_1
     315: aload_0
     316: getfield      #11                 // Field lockTime:I
     319: invokestatic  #162                // Method java/lang/Integer.valueOf:(I)Ljava/lang/Integer;
     322: aastore
     323: invokevirtual #138                // Method com/virtual/common/StringManager.getString:(Ljava/lang/String;[Ljava/lang/Object;)Ljava/lang/String;
     326: invokevirtual #221                // Method com/virtual/ssv/server/user/LoginInfo.setLoginFailMessage:(Ljava/lang/String;)V
     329: aload         12
     331: aload         15
     333: invokevirtual #86                 // Method com/google/gson/Gson.toJson:(Ljava/lang/Object;)Ljava/lang/String;
     336: astore        16
     338: aload_0
     339: aload_2
     340: aload         16
     342: invokevirtual #87                 // Method write:(Ljavax/servlet/http/HttpServletResponse;Ljava/lang/String;)V
     345: return
     346: aload_0
     347: aload         4
     349: aload         5
     351: aload         9
     353: invokespecial #222                // Method loginCheck:(Ljava/lang/String;Ljava/lang/String;Ljava/lang/String;)Lcom/virtual/ssv/server/user/LoginInfo;
     356: astore        13
     358: aload_0
     359: getfield      #6                  // Field checkPasswordAttack:Z
     362: ifeq          482
     365: aload         13
     367: invokevirtual #223                // Method com/virtual/ssv/server/user/LoginInfo.getLoginFailMessage:()Ljava/lang/String;
     370: invokestatic  #224                // Method org/apache/commons/lang/StringUtils.isNotBlank:(Ljava/lang/String;)Z
     373: ifeq          460
     376: aload         8
     378: aload_0
     379: getfield      #19                 // Field ATTR_LOGIN_FAILED_COUNT:Ljava/lang/String;
     382: invokeinterface #51,  2           // InterfaceMethod javax/servlet/http/HttpSession.getAttribute:(Ljava/lang/String;)Ljava/lang/Object;
     387: checkcast     #154                // class java/lang/Integer
     390: astore        14
     392: aload         14
     394: ifnonnull     406
     397: iconst_1
     398: invokestatic  #162                // Method java/lang/Integer.valueOf:(I)Ljava/lang/Integer;
     401: astore        14
     403: goto          428
     406: aload         14
     408: astore        15
     410: aload         14
     412: invokevirtual #156                // Method java/lang/Integer.intValue:()I
     415: iconst_1
     416: iadd
     417: invokestatic  #162                // Method java/lang/Integer.valueOf:(I)Ljava/lang/Integer;
     420: dup
     421: astore        14
     423: astore        16
     425: aload         15
     427: pop
     428: aload         8
     430: aload_0
     431: getfield      #19                 // Field ATTR_LOGIN_FAILED_COUNT:Ljava/lang/String;
     434: aload         14
     436: invokeinterface #163,  3          // InterfaceMethod javax/servlet/http/HttpSession.setAttribute:(Ljava/lang/String;Ljava/lang/Object;)V
     441: aload         8
     443: aload_0
     444: getfield      #25                 // Field ATTR_LAST_LOGIN_FAILED_TIME:Ljava/lang/String;
     447: lload         10
     449: invokestatic  #164                // Method java/lang/Long.valueOf:(J)Ljava/lang/Long;
     452: invokeinterface #163,  3          // InterfaceMethod javax/servlet/http/HttpSession.setAttribute:(Ljava/lang/String;Ljava/lang/Object;)V
     457: goto          482
     460: aload         8
     462: aload_0
     463: getfield      #19                 // Field ATTR_LOGIN_FAILED_COUNT:Ljava/lang/String;
     466: invokeinterface #177,  2          // InterfaceMethod javax/servlet/http/HttpSession.removeAttribute:(Ljava/lang/String;)V
     471: aload         8
     473: aload_0
     474: getfield      #25                 // Field ATTR_LAST_LOGIN_FAILED_TIME:Ljava/lang/String;
     477: invokeinterface #177,  2          // InterfaceMethod javax/servlet/http/HttpSession.removeAttribute:(Ljava/lang/String;)V
     482: aload         13
     484: invokevirtual #223                // Method com/virtual/ssv/server/user/LoginInfo.getLoginFailMessage:()Ljava/lang/String;
     487: invokestatic  #225                // Method org/apache/commons/lang/StringUtils.isBlank:(Ljava/lang/String;)Z
     490: ifeq          1014
     493: new           #94                 // class java/util/ArrayList
     496: dup
     497: invokespecial #95                 // Method java/util/ArrayList."<init>":()V
     500: astore        14
     502: aload_0
     503: getfield      #1                  // Field reqHandle:Lcom/virtual/ssv/server/rs/client/RequestHandle;
     506: invokevirtual #96                 // Method com/virtual/ssv/server/rs/client/RequestHandle.querySysParameter:()Ljava/util/List;
     509: astore        14
     511: goto          530
     514: astore        15
     516: aload         13
     518: iconst_0
     519: invokevirtual #226                // Method com/virtual/ssv/server/user/LoginInfo.setOnline:(Z)V
     522: aload_0
     523: aload         13
     525: aload         15
     527: invokespecial #227                // Method handleLoginException:(Lcom/virtual/ssv/server/user/LoginInfo;Ljava/lang/Exception;)V
     530: aload         14
     532: ifnull        948
     535: new           #228                // class java/util/HashMap
     538: dup
     539: invokespecial #229                // Method java/util/HashMap."<init>":()V
     542: astore        15
     544: aload         14
     546: invokeinterface #101,  1          // InterfaceMethod java/util/List.iterator:()Ljava/util/Iterator;
     551: astore        16
     553: aload         16
     555: invokeinterface #102,  1          // InterfaceMethod java/util/Iterator.hasNext:()Z
     560: ifeq          866
     563: aload         16
     565: invokeinterface #103,  1          // InterfaceMethod java/util/Iterator.next:()Ljava/lang/Object;
     570: checkcast     #104                // class com/virtual/ssv/server/rs/client/entity/RsParameter
     573: astore        17
     575: aload         17
     577: ifnull        553
     580: aload         17
     582: invokevirtual #105                // Method com/virtual/ssv/server/rs/client/entity/RsParameter.getName:()Ljava/lang/String;
     585: ifnull        553
     588: aload         17
     590: invokevirtual #106                // Method com/virtual/ssv/server/rs/client/entity/RsParameter.getValue:()Ljava/lang/String;
     593: ifnonnull     599
     596: goto          553
     599: aload         17
     601: invokevirtual #105                // Method com/virtual/ssv/server/rs/client/entity/RsParameter.getName:()Ljava/lang/String;
     604: astore        18
     606: aload         17
     608: invokevirtual #106                // Method com/virtual/ssv/server/rs/client/entity/RsParameter.getValue:()Ljava/lang/String;
     611: invokevirtual #108                // Method java/lang/String.trim:()Ljava/lang/String;
     614: astore        19
     616: aload         18
     618: invokestatic  #109                // Method org/apache/commons/lang/StringUtils.isNotEmpty:(Ljava/lang/String;)Z
     621: ifeq          845
     624: aload         19
     626: invokestatic  #109                // Method org/apache/commons/lang/StringUtils.isNotEmpty:(Ljava/lang/String;)Z
     629: ifeq          845
     632: ldc           #230                // String ssv.isusing.snap
     634: aload         18
     636: invokevirtual #31                 // Method java/lang/String.equals:(Ljava/lang/Object;)Z
     639: ifeq          656
     642: aload         8
     644: ldc           #231                // String snapshotEnabled
     646: aload         19
     648: invokeinterface #163,  3          // InterfaceMethod javax/servlet/http/HttpSession.setAttribute:(Ljava/lang/String;Ljava/lang/Object;)V
     653: goto          845
     656: ldc           #232                // String ssv.vnc
     658: aload         18
     660: invokevirtual #31                 // Method java/lang/String.equals:(Ljava/lang/Object;)Z
     663: ifeq          680
     666: aload         8
     668: ldc           #233                // String vncEnabled
     670: aload         19
     672: invokeinterface #163,  3          // InterfaceMethod javax/servlet/http/HttpSession.setAttribute:(Ljava/lang/String;Ljava/lang/Object;)V
     677: goto          845
     680: ldc           #234                // String ssv.isusing.backup
     682: aload         18
     684: invokevirtual #31                 // Method java/lang/String.equals:(Ljava/lang/Object;)Z
     687: ifeq          704
     690: aload         8
     692: ldc           #235                // String backupEnabled
     694: aload         19
     696: invokeinterface #163,  3          // InterfaceMethod javax/servlet/http/HttpSession.setAttribute:(Ljava/lang/String;Ljava/lang/Object;)V
     701: goto          845
     704: ldc           #236                // String ssv.isusing.disk
     706: aload         18
     708: invokevirtual #31                 // Method java/lang/String.equals:(Ljava/lang/Object;)Z
     711: ifeq          728
     714: aload         8
     716: ldc           #237                // String diskEnabled
     718: aload         19
     720: invokeinterface #163,  3          // InterfaceMethod javax/servlet/http/HttpSession.setAttribute:(Ljava/lang/String;Ljava/lang/Object;)V
     725: goto          845
     728: ldc           #238                // String ssv.isusing.message
     730: aload         18
     732: invokevirtual #31                 // Method java/lang/String.equals:(Ljava/lang/Object;)Z
     735: ifeq          752
     738: aload         8
     740: ldc           #239                // String messageEnabled
     742: aload         19
     744: invokeinterface #163,  3          // InterfaceMethod javax/servlet/http/HttpSession.setAttribute:(Ljava/lang/String;Ljava/lang/Object;)V
     749: goto          845
     752: ldc           #240                // String ssv.isusing.workorder
     754: aload         18
     756: invokevirtual #31                 // Method java/lang/String.equals:(Ljava/lang/Object;)Z
     759: ifeq          776
     762: aload         8
     764: ldc           #241                // String workorderEnabled
     766: aload         19
     768: invokeinterface #163,  3          // InterfaceMethod javax/servlet/http/HttpSession.setAttribute:(Ljava/lang/String;Ljava/lang/Object;)V
     773: goto          845
     776: ldc           #242                // String ssv.isusing.alarm
     778: aload         18
     780: invokevirtual #31                 // Method java/lang/String.equals:(Ljava/lang/Object;)Z
     783: ifeq          800
     786: aload         8
     788: ldc           #243                // String alarmEnabled
     790: aload         19
     792: invokeinterface #163,  3          // InterfaceMethod javax/servlet/http/HttpSession.setAttribute:(Ljava/lang/String;Ljava/lang/Object;)V
     797: goto          845
     800: ldc           #244                // String ssv.isusing.instant.message
     802: aload         18
     804: invokevirtual #31                 // Method java/lang/String.equals:(Ljava/lang/Object;)Z
     807: ifeq          824
     810: aload         8
     812: ldc           #245                // String instantMessageEnabled
     814: aload         19
     816: invokeinterface #163,  3          // InterfaceMethod javax/servlet/http/HttpSession.setAttribute:(Ljava/lang/String;Ljava/lang/Object;)V
     821: goto          845
     824: ldc           #246                // String ssv.isusing.firewall
     826: aload         18
     828: invokevirtual #31                 // Method java/lang/String.equals:(Ljava/lang/Object;)Z
     831: ifeq          845
     834: aload         8
     836: ldc           #247                // String firewallEnable
     838: aload         19
     840: invokeinterface #163,  3          // InterfaceMethod javax/servlet/http/HttpSession.setAttribute:(Ljava/lang/String;Ljava/lang/Object;)V
     845: aload         15
     847: aload         17
     849: invokevirtual #105                // Method com/virtual/ssv/server/rs/client/entity/RsParameter.getName:()Ljava/lang/String;
     852: aload         17
     854: invokevirtual #106                // Method com/virtual/ssv/server/rs/client/entity/RsParameter.getValue:()Ljava/lang/String;
     857: invokeinterface #248,  3          // InterfaceMethod java/util/Map.put:(Ljava/lang/Object;Ljava/lang/Object;)Ljava/lang/Object;
     862: pop
     863: goto          553
     866: aload         13
     868: aload         15
     870: invokevirtual #249                // Method com/virtual/ssv/server/user/LoginInfo.setSsvConf:(Ljava/util/Map;)V
     873: aload         8
     875: ldc           #250                // String hasCVMResource
     877: aload         13
     879: invokevirtual #251                // Method com/virtual/ssv/server/user/LoginInfo.isHasCVMResource:()Z
     882: invokestatic  #252                // Method java/lang/Boolean.valueOf:(Z)Ljava/lang/Boolean;
     885: invokeinterface #163,  3          // InterfaceMethod javax/servlet/http/HttpSession.setAttribute:(Ljava/lang/String;Ljava/lang/Object;)V
     890: aload_0
     891: getfield      #1                  // Field reqHandle:Lcom/virtual/ssv/server/rs/client/RequestHandle;
     894: aload         13
     896: invokevirtual #253                // Method com/virtual/ssv/server/user/LoginInfo.getId:()Ljava/lang/Long;
     899: invokevirtual #254                // Method com/virtual/ssv/server/rs/client/RequestHandle.getUserSetting:(Ljava/lang/Long;)Lcom/virtual/ssv/server/rs/client/entity/UserSetting;
     902: astore        16
     904: aload         16
     906: ifnull        935
     909: aload         16
     911: invokevirtual #255                // Method com/virtual/ssv/server/rs/client/entity/UserSetting.getTheme:()Ljava/lang/String;
     914: ifnull        935
     917: aload         8
     919: ldc_w         #256                // String userTheme
     922: aload         16
     924: invokevirtual #255                // Method com/virtual/ssv/server/rs/client/entity/UserSetting.getTheme:()Ljava/lang/String;
     927: invokeinterface #163,  3          // InterfaceMethod javax/servlet/http/HttpSession.setAttribute:(Ljava/lang/String;Ljava/lang/Object;)V
     932: goto          948
     935: aload         8
     937: ldc_w         #256                // String userTheme
     940: ldc_w         #257                // String black
     943: invokeinterface #163,  3          // InterfaceMethod javax/servlet/http/HttpSession.setAttribute:(Ljava/lang/String;Ljava/lang/Object;)V
     948: aload         8
     950: new           #258                // class java/lang/StringBuilder
     953: dup
     954: invokespecial #259                // Method java/lang/StringBuilder."<init>":()V
     957: aload         13
     959: invokevirtual #260                // Method com/virtual/ssv/server/user/LoginInfo.getIdleTimeout:()J
     962: invokevirtual #261                // Method java/lang/StringBuilder.append:(J)Ljava/lang/StringBuilder;
     965: ldc           #189                // String
     967: invokevirtual #262                // Method java/lang/StringBuilder.append:(Ljava/lang/String;)Ljava/lang/StringBuilder;
     970: invokevirtual #263                // Method java/lang/StringBuilder.toString:()Ljava/lang/String;
     973: invokestatic  #201                // Method java/lang/Integer.valueOf:(Ljava/lang/String;)Ljava/lang/Integer;
     976: invokevirtual #156                // Method java/lang/Integer.intValue:()I
     979: invokeinterface #264,  2          // InterfaceMethod javax/servlet/http/HttpSession.setMaxInactiveInterval:(I)V
     984: aload_0
     985: getfield      #16                 // Field onlineUsers:Lcom/virtual/ssv/server/user/OnlineUsers;
     988: aload         8
     990: aload         13
     992: invokevirtual #265                // Method com/virtual/ssv/server/user/OnlineUsers.addOnlineUser:(Ljavax/servlet/http/HttpSession;Lcom/virtual/ssv/server/user/LoginInfo;)V
     995: aload_0
     996: getfield      #1                  // Field reqHandle:Lcom/virtual/ssv/server/rs/client/RequestHandle;
     999: aload         13
    1001: invokevirtual #253                // Method com/virtual/ssv/server/user/LoginInfo.getId:()Ljava/lang/Long;
    1004: invokevirtual #266                // Method com/virtual/ssv/server/rs/client/RequestHandle.assignDynamicVDesktop:(Ljava/lang/Long;)V
    1007: aload_0
    1008: aload         13
    1010: aload_3
    1011: invokevirtual #267                // Method onLogin:(Lcom/virtual/ssv/server/user/LoginInfo;Ljava/util/Date;)V
    1014: aload         8
    1016: ldc           #150                // String loginName
    1018: aload         4
    1020: invokeinterface #163,  3          // InterfaceMethod javax/servlet/http/HttpSession.setAttribute:(Ljava/lang/String;Ljava/lang/Object;)V
    1025: aload         8
    1027: ldc           #182                // String userName
    1029: aload         13
    1031: invokevirtual #268                // Method com/virtual/ssv/server/user/LoginInfo.getUserName:()Ljava/lang/String;
    1034: invokeinterface #163,  3          // InterfaceMethod javax/servlet/http/HttpSession.setAttribute:(Ljava/lang/String;Ljava/lang/Object;)V
    1039: aload         13
    1041: invokevirtual #269                // Method com/virtual/ssv/server/user/LoginInfo.getImageUrl:()Ljava/lang/String;
    1044: astore        14
    1046: aload         13
    1048: invokevirtual #269                // Method com/virtual/ssv/server/user/LoginInfo.getImageUrl:()Ljava/lang/String;
    1051: invokestatic  #152                // Method org/apache/commons/lang/StringUtils.isEmpty:(Ljava/lang/String;)Z
    1054: ifeq          1062
    1057: getstatic     #270                // Field com/virtual/ssv/server/Constant.DEFAULT_IMAGEURL:Ljava/lang/String;
    1060: astore        14
    1062: aload         8
    1064: ldc_w         #271                // String imageUrl
    1067: aload         14
    1069: invokeinterface #163,  3          // InterfaceMethod javax/servlet/http/HttpSession.setAttribute:(Ljava/lang/String;Ljava/lang/Object;)V
    1074: aload         8
    1076: ldc           #50                 // String loginInfo
    1078: aload         13
    1080: invokeinterface #163,  3          // InterfaceMethod javax/servlet/http/HttpSession.setAttribute:(Ljava/lang/String;Ljava/lang/Object;)V
    1085: aload         13
    1087: getstatic     #122                // Field strMng:Lcom/virtual/common/StringManager;
    1090: ldc_w         #272                // String login_failture
    1093: invokevirtual #124                // Method com/virtual/common/StringManager.getString:(Ljava/lang/String;)Ljava/lang/String;
    1096: invokevirtual #219                // Method com/virtual/ssv/server/user/LoginInfo.setErrorTitle:(Ljava/lang/String;)V
    1099: ldc           #211                // String true
    1101: aload         7
    1103: invokevirtual #31                 // Method java/lang/String.equals:(Ljava/lang/Object;)Z
    1106: ifeq          1159
    1109: aload         13
    1111: invokevirtual #223                // Method com/virtual/ssv/server/user/LoginInfo.getLoginFailMessage:()Ljava/lang/String;
    1114: invokestatic  #225                // Method org/apache/commons/lang/StringUtils.isBlank:(Ljava/lang/String;)Z
    1117: ifeq          1132
    1120: aload_2
    1121: ldc_w         #273                // String index2.jsp
    1124: invokeinterface #71,  2           // InterfaceMethod javax/servlet/http/HttpServletResponse.sendRedirect:(Ljava/lang/String;)V
    1129: goto          1140
    1132: aload_2
    1133: ldc           #70                 // String login.jsp
    1135: invokeinterface #71,  2           // InterfaceMethod javax/servlet/http/HttpServletResponse.sendRedirect:(Ljava/lang/String;)V
    1140: goto          1175
    1143: astore        15
    1145: getstatic     #79                 // Field log:Lorg/apache/commons/logging/Log;
    1148: aconst_null
    1149: aload         15
    1151: invokeinterface #212,  3          // InterfaceMethod org/apache/commons/logging/Log.error:(Ljava/lang/Object;Ljava/lang/Throwable;)V
    1156: goto          1175
    1159: aload         12
    1161: aload         13
    1163: invokevirtual #86                 // Method com/google/gson/Gson.toJson:(Ljava/lang/Object;)Ljava/lang/String;
    1166: astore        15
    1168: aload_0
    1169: aload_2
    1170: aload         15
    1172: invokevirtual #87                 // Method write:(Ljavax/servlet/http/HttpServletResponse;Ljava/lang/String;)V
    1175: return
    Exception table:
       from    to  target type
          58    67    70   Class java/io/UnsupportedEncodingException
         502   511   514   Class java/lang/Exception
        1109  1140  1143   Class java/io/IOException

  private void handleLoginException(com.virtual.ssv.server.user.LoginInfo, java.lang.Exception);
    Code:
       0: aload_2
       1: instanceof    #275                // class com/virtual/common/AppException
       4: ifeq          130
       7: aload_2
       8: checkcast     #275                // class com/virtual/common/AppException
      11: astore_3
      12: aload_3
      13: invokevirtual #276                // Method com/virtual/common/AppException.getErrorCode:()I
      16: bipush        102
      18: if_icmpne     44
      21: aload_1
      22: aload_3
      23: invokevirtual #276                // Method com/virtual/common/AppException.getErrorCode:()I
      26: invokestatic  #162                // Method java/lang/Integer.valueOf:(I)Ljava/lang/Integer;
      29: invokevirtual #277                // Method com/virtual/ssv/server/user/LoginInfo.setErrorCode:(Ljava/lang/Integer;)V
      32: aload_1
      33: bipush        102
      35: invokestatic  #174                // Method com/virtual/common/ErrorCodes.getErrorMessage:(I)Ljava/lang/String;
      38: invokevirtual #221                // Method com/virtual/ssv/server/user/LoginInfo.setLoginFailMessage:(Ljava/lang/String;)V
      41: goto          127
      44: aload_3
      45: invokevirtual #276                // Method com/virtual/common/AppException.getErrorCode:()I
      48: bipush        103
      50: if_icmpne     76
      53: aload_1
      54: aload_3
      55: invokevirtual #276                // Method com/virtual/common/AppException.getErrorCode:()I
      58: invokestatic  #162                // Method java/lang/Integer.valueOf:(I)Ljava/lang/Integer;
      61: invokevirtual #277                // Method com/virtual/ssv/server/user/LoginInfo.setErrorCode:(Ljava/lang/Integer;)V
      64: aload_1
      65: bipush        103
      67: invokestatic  #174                // Method com/virtual/common/ErrorCodes.getErrorMessage:(I)Ljava/lang/String;
      70: invokevirtual #221                // Method com/virtual/ssv/server/user/LoginInfo.setLoginFailMessage:(Ljava/lang/String;)V
      73: goto          127
      76: aload_3
      77: invokevirtual #276                // Method com/virtual/common/AppException.getErrorCode:()I
      80: bipush        11
      82: if_icmpne     108
      85: aload_1
      86: aload_3
      87: invokevirtual #276                // Method com/virtual/common/AppException.getErrorCode:()I
      90: invokestatic  #162                // Method java/lang/Integer.valueOf:(I)Ljava/lang/Integer;
      93: invokevirtual #277                // Method com/virtual/ssv/server/user/LoginInfo.setErrorCode:(Ljava/lang/Integer;)V
      96: aload_1
      97: bipush        11
      99: invokestatic  #174                // Method com/virtual/common/ErrorCodes.getErrorMessage:(I)Ljava/lang/String;
     102: invokevirtual #221                // Method com/virtual/ssv/server/user/LoginInfo.setLoginFailMessage:(Ljava/lang/String;)V
     105: goto          127
     108: aload_1
     109: aload_3
     110: invokevirtual #276                // Method com/virtual/common/AppException.getErrorCode:()I
     113: invokestatic  #162                // Method java/lang/Integer.valueOf:(I)Ljava/lang/Integer;
     116: invokevirtual #277                // Method com/virtual/ssv/server/user/LoginInfo.setErrorCode:(Ljava/lang/Integer;)V
     119: aload_1
     120: aload_3
     121: invokevirtual #278                // Method com/virtual/common/AppException.getMessage:()Ljava/lang/String;
     124: invokevirtual #221                // Method com/virtual/ssv/server/user/LoginInfo.setLoginFailMessage:(Ljava/lang/String;)V
     127: goto          148
     130: aload_1
     131: bipush        11
     133: invokestatic  #162                // Method java/lang/Integer.valueOf:(I)Ljava/lang/Integer;
     136: invokevirtual #277                // Method com/virtual/ssv/server/user/LoginInfo.setErrorCode:(Ljava/lang/Integer;)V
     139: aload_1
     140: bipush        11
     142: invokestatic  #174                // Method com/virtual/common/ErrorCodes.getErrorMessage:(I)Ljava/lang/String;
     145: invokevirtual #221                // Method com/virtual/ssv/server/user/LoginInfo.setLoginFailMessage:(Ljava/lang/String;)V
     148: return

  private com.virtual.ssv.server.user.LoginInfo loginCheck(java.lang.String, java.lang.String, java.lang.String);
    Code:
       0: new           #52                 // class com/virtual/ssv/server/user/LoginInfo
       3: dup
       4: invokespecial #217                // Method com/virtual/ssv/server/user/LoginInfo."<init>":()V
       7: astore        4
       9: aload_2
      10: invokestatic  #279                // Method com/virtual/common/FuncUtil.encryptData:(Ljava/lang/String;)Ljava/lang/String;
      13: astore_2
      14: aload_0
      15: getfield      #1                  // Field reqHandle:Lcom/virtual/ssv/server/rs/client/RequestHandle;
      18: aload_1
      19: aload_2
      20: invokevirtual #280                // Method com/virtual/ssv/server/rs/client/RequestHandle.userAuth:(Ljava/lang/String;Ljava/lang/String;)Lcom/virtual/ssv/server/rs/client/entity/RsUser;
      23: astore        5
      25: aload         5
      27: ifnull        205
      30: aload         4
      32: aload         5
      34: invokevirtual #281                // Method com/virtual/ssv/server/rs/client/entity/RsUser.getId:()J
      37: invokestatic  #164                // Method java/lang/Long.valueOf:(J)Ljava/lang/Long;
      40: invokevirtual #282                // Method com/virtual/ssv/server/user/LoginInfo.setId:(Ljava/lang/Long;)V
      43: aload         4
      45: aload         5
      47: invokevirtual #283                // Method com/virtual/ssv/server/rs/client/entity/RsUser.getLoginName:()Ljava/lang/String;
      50: invokevirtual #284                // Method com/virtual/ssv/server/user/LoginInfo.setLoginName:(Ljava/lang/String;)V
      53: aload         4
      55: aload_3
      56: invokevirtual #285                // Method com/virtual/ssv/server/user/LoginInfo.setLoginIp:(Ljava/lang/String;)V
      59: aload         4
      61: aload         5
      63: invokevirtual #286                // Method com/virtual/ssv/server/rs/client/entity/RsUser.getUserName:()Ljava/lang/String;
      66: invokevirtual #287                // Method com/virtual/ssv/server/user/LoginInfo.setUserName:(Ljava/lang/String;)V
      69: aload         4
      71: new           #207                // class java/util/Date
      74: dup
      75: invokespecial #208                // Method java/util/Date."<init>":()V
      78: invokevirtual #288                // Method com/virtual/ssv/server/user/LoginInfo.setLoginTime:(Ljava/util/Date;)V
      81: aload         4
      83: iconst_1
      84: invokevirtual #226                // Method com/virtual/ssv/server/user/LoginInfo.setOnline:(Z)V
      87: aload         4
      89: aload         5
      91: invokevirtual #289                // Method com/virtual/ssv/server/rs/client/entity/RsUser.getOrgId:()Ljava/lang/Long;
      94: invokevirtual #290                // Method com/virtual/ssv/server/user/LoginInfo.setOrgId:(Ljava/lang/Long;)V
      97: aload         4
      99: aload         5
     101: invokevirtual #291                // Method com/virtual/ssv/server/rs/client/entity/RsUser.getUserGroupId:()J
     104: invokevirtual #292                // Method com/virtual/ssv/server/user/LoginInfo.setUserGroupId:(J)V
     107: aload         4
     109: aload         5
     111: invokevirtual #293                // Method com/virtual/ssv/server/rs/client/entity/RsUser.isHasCVMResource:()Z
     114: invokevirtual #294                // Method com/virtual/ssv/server/user/LoginInfo.setHasCVMResource:(Z)V
     117: aload         5
     119: invokevirtual #295                // Method com/virtual/ssv/server/rs/client/entity/RsUser.getImageUrl:()Ljava/lang/String;
     122: invokestatic  #109                // Method org/apache/commons/lang/StringUtils.isNotEmpty:(Ljava/lang/String;)Z
     125: ifeq          138
     128: aload         4
     130: aload         5
     132: invokevirtual #295                // Method com/virtual/ssv/server/rs/client/entity/RsUser.getImageUrl:()Ljava/lang/String;
     135: invokevirtual #296                // Method com/virtual/ssv/server/user/LoginInfo.setImageUrl:(Ljava/lang/String;)V
     138: ldc2_w        #297                // long 600l
     141: lstore        6
     143: aload_0
     144: getfield      #1                  // Field reqHandle:Lcom/virtual/ssv/server/rs/client/RequestHandle;
     147: aload         5
     149: invokevirtual #281                // Method com/virtual/ssv/server/rs/client/entity/RsUser.getId:()J
     152: invokestatic  #164                // Method java/lang/Long.valueOf:(J)Ljava/lang/Long;
     155: invokevirtual #254                // Method com/virtual/ssv/server/rs/client/RequestHandle.getUserSetting:(Ljava/lang/Long;)Lcom/virtual/ssv/server/rs/client/entity/UserSetting;
     158: astore        8
     160: aload         8
     162: ifnull        190
     165: aload         8
     167: invokevirtual #299                // Method com/virtual/ssv/server/rs/client/entity/UserSetting.getTimeout:()Ljava/lang/Long;
     170: ifnull        190
     173: aload         8
     175: invokevirtual #299                // Method com/virtual/ssv/server/rs/client/entity/UserSetting.getTimeout:()Ljava/lang/Long;
     178: invokevirtual #157                // Method java/lang/Long.longValue:()J
     181: ldc2_w        #300                // long 60l
     184: lmul
     185: lstore        6
     187: goto          195
     190: ldc2_w        #297                // long 600l
     193: lstore        6
     195: aload         4
     197: lload         6
     199: invokevirtual #302                // Method com/virtual/ssv/server/user/LoginInfo.setIdleTimeout:(J)V
     202: goto          220
     205: new           #275                // class com/virtual/common/AppException
     208: dup
     209: bipush        101
     211: bipush        101
     213: invokestatic  #174                // Method com/virtual/common/ErrorCodes.getErrorMessage:(I)Ljava/lang/String;
     216: invokespecial #303                // Method com/virtual/common/AppException."<init>":(ILjava/lang/String;)V
     219: athrow
     220: goto          276
     223: astore        5
     225: aload         4
     227: aload         5
     229: invokevirtual #276                // Method com/virtual/common/AppException.getErrorCode:()I
     232: invokestatic  #162                // Method java/lang/Integer.valueOf:(I)Ljava/lang/Integer;
     235: invokevirtual #277                // Method com/virtual/ssv/server/user/LoginInfo.setErrorCode:(Ljava/lang/Integer;)V
     238: aload         5
     240: invokevirtual #276                // Method com/virtual/common/AppException.getErrorCode:()I
     243: bipush        103
     245: if_icmpne     266
     248: aload         4
     250: aload_0
     251: getfield      #304                // Field commonSm:Lcom/virtual/common/StringManager;
     254: ldc_w         #305                // String connetCicError
     257: invokevirtual #124                // Method com/virtual/common/StringManager.getString:(Ljava/lang/String;)Ljava/lang/String;
     260: invokevirtual #221                // Method com/virtual/ssv/server/user/LoginInfo.setLoginFailMessage:(Ljava/lang/String;)V
     263: goto          276
     266: aload         4
     268: aload         5
     270: invokevirtual #278                // Method com/virtual/common/AppException.getMessage:()Ljava/lang/String;
     273: invokevirtual #221                // Method com/virtual/ssv/server/user/LoginInfo.setLoginFailMessage:(Ljava/lang/String;)V
     276: aload         4
     278: areturn
    Exception table:
       from    to  target type
           9   220   223   Class com/virtual/common/AppException

  void onLogin(com.virtual.ssv.server.user.LoginInfo, java.util.Date);
    Code:
       0: new           #207                // class java/util/Date
       3: dup
       4: invokespecial #208                // Method java/util/Date."<init>":()V
       7: astore_3
       8: new           #306                // class com/virtual/ssv/server/rs/client/entity/RsOperateLog
      11: dup
      12: invokespecial #307                // Method com/virtual/ssv/server/rs/client/entity/RsOperateLog."<init>":()V
      15: astore        4
      17: aload         4
      19: aload_1
      20: invokevirtual #253                // Method com/virtual/ssv/server/user/LoginInfo.getId:()Ljava/lang/Long;
      23: invokevirtual #308                // Method com/virtual/ssv/server/rs/client/entity/RsOperateLog.setUserId:(Ljava/lang/Long;)V
      26: aload         4
      28: aload_1
      29: invokevirtual #309                // Method com/virtual/ssv/server/user/LoginInfo.getOrgId:()Ljava/lang/Long;
      32: invokevirtual #310                // Method com/virtual/ssv/server/rs/client/entity/RsOperateLog.setOrgId:(Ljava/lang/Long;)V
      35: aload         4
      37: aload_1
      38: invokevirtual #311                // Method com/virtual/ssv/server/user/LoginInfo.getLoginIp:()Ljava/lang/String;
      41: invokevirtual #312                // Method com/virtual/ssv/server/rs/client/entity/RsOperateLog.setAddress:(Ljava/lang/String;)V
      44: aload         4
      46: iconst_1
      47: invokestatic  #162                // Method java/lang/Integer.valueOf:(I)Ljava/lang/Integer;
      50: invokevirtual #314                // Method com/virtual/ssv/server/rs/client/entity/RsOperateLog.setCategory:(Ljava/lang/Integer;)V
      53: aload         4
      55: aload_0
      56: getfield      #165                // Field logSm:Lcom/virtual/common/StringManager;
      59: ldc_w         #315                // String login.operation
      62: invokevirtual #124                // Method com/virtual/common/StringManager.getString:(Ljava/lang/String;)Ljava/lang/String;
      65: invokevirtual #316                // Method com/virtual/ssv/server/rs/client/entity/RsOperateLog.setDescription:(Ljava/lang/String;)V
      68: aload         4
      70: aload_1
      71: invokevirtual #317                // Method com/virtual/ssv/server/user/LoginInfo.getLoginName:()Ljava/lang/String;
      74: invokevirtual #318                // Method com/virtual/ssv/server/rs/client/entity/RsOperateLog.setLoginName:(Ljava/lang/String;)V
      77: aload         4
      79: getstatic     #319                // Field com/virtual/ssv/server/rs/client/entity/RsOperateLog.RESULT_SUCCESS:Ljava/lang/Integer;
      82: invokevirtual #320                // Method com/virtual/ssv/server/rs/client/entity/RsOperateLog.setResult:(Ljava/lang/Integer;)V
      85: aload         4
      87: aload_1
      88: invokevirtual #268                // Method com/virtual/ssv/server/user/LoginInfo.getUserName:()Ljava/lang/String;
      91: invokevirtual #321                // Method com/virtual/ssv/server/rs/client/entity/RsOperateLog.setUserName:(Ljava/lang/String;)V
      94: aload         4
      96: aload_2
      97: invokevirtual #322                // Method com/virtual/ssv/server/rs/client/entity/RsOperateLog.setStartTime:(Ljava/util/Date;)V
     100: aload         4
     102: aload_3
     103: invokevirtual #323                // Method com/virtual/ssv/server/rs/client/entity/RsOperateLog.setEndTime:(Ljava/util/Date;)V
     106: aload_0
     107: getfield      #1                  // Field reqHandle:Lcom/virtual/ssv/server/rs/client/RequestHandle;
     110: aload         4
     112: invokevirtual #324                // Method com/virtual/ssv/server/rs/client/RequestHandle.addUserLog:(Lcom/virtual/ssv/server/rs/client/entity/RsOperateLog;)Ljava/lang/Long;
     115: pop
     116: goto          132
     119: astore        4
     121: getstatic     #79                 // Field log:Lorg/apache/commons/logging/Log;
     124: aconst_null
     125: aload         4
     127: invokeinterface #212,  3          // InterfaceMethod org/apache/commons/logging/Log.error:(Ljava/lang/Object;Ljava/lang/Throwable;)V
     132: return
    Exception table:
       from    to  target type
           8   116   119   Class com/virtual/common/AppException

  void onLogout(com.virtual.ssv.server.user.LoginInfo, java.util.Date, javax.servlet.http.HttpSession);
    Code:
       0: new           #207                // class java/util/Date
       3: dup
       4: invokespecial #208                // Method java/util/Date."<init>":()V
       7: astore        4
       9: new           #306                // class com/virtual/ssv/server/rs/client/entity/RsOperateLog
      12: dup
      13: invokespecial #307                // Method com/virtual/ssv/server/rs/client/entity/RsOperateLog."<init>":()V
      16: astore        5
      18: aload         5
      20: aload_1
      21: invokevirtual #253                // Method com/virtual/ssv/server/user/LoginInfo.getId:()Ljava/lang/Long;
      24: invokevirtual #308                // Method com/virtual/ssv/server/rs/client/entity/RsOperateLog.setUserId:(Ljava/lang/Long;)V
      27: aload         5
      29: aload_1
      30: invokevirtual #309                // Method com/virtual/ssv/server/user/LoginInfo.getOrgId:()Ljava/lang/Long;
      33: invokevirtual #310                // Method com/virtual/ssv/server/rs/client/entity/RsOperateLog.setOrgId:(Ljava/lang/Long;)V
      36: aload         5
      38: aload_1
      39: invokevirtual #311                // Method com/virtual/ssv/server/user/LoginInfo.getLoginIp:()Ljava/lang/String;
      42: invokevirtual #312                // Method com/virtual/ssv/server/rs/client/entity/RsOperateLog.setAddress:(Ljava/lang/String;)V
      45: aload         5
      47: iconst_1
      48: invokestatic  #162                // Method java/lang/Integer.valueOf:(I)Ljava/lang/Integer;
      51: invokevirtual #314                // Method com/virtual/ssv/server/rs/client/entity/RsOperateLog.setCategory:(Ljava/lang/Integer;)V
      54: aload_3
      55: ifnull        125
      58: aload_3
      59: ldc_w         #325                // String autoLogout
      62: invokeinterface #51,  2           // InterfaceMethod javax/servlet/http/HttpSession.getAttribute:(Ljava/lang/String;)Ljava/lang/Object;
      67: astore        6
      69: aconst_null
      70: aload         6
      72: if_acmpeq     107
      75: ldc_w         #326                // String false
      78: aload         6
      80: checkcast     #327                // class java/lang/String
      83: invokevirtual #31                 // Method java/lang/String.equals:(Ljava/lang/Object;)Z
      86: ifeq          107
      89: aload         5
      91: aload_0
      92: getfield      #165                // Field logSm:Lcom/virtual/common/StringManager;
      95: ldc_w         #328                // String logout.operation
      98: invokevirtual #124                // Method com/virtual/common/StringManager.getString:(Ljava/lang/String;)Ljava/lang/String;
     101: invokevirtual #316                // Method com/virtual/ssv/server/rs/client/entity/RsOperateLog.setDescription:(Ljava/lang/String;)V
     104: goto          122
     107: aload         5
     109: aload_0
     110: getfield      #165                // Field logSm:Lcom/virtual/common/StringManager;
     113: ldc_w         #329                // String autologout.operation
     116: invokevirtual #124                // Method com/virtual/common/StringManager.getString:(Ljava/lang/String;)Ljava/lang/String;
     119: invokevirtual #316                // Method com/virtual/ssv/server/rs/client/entity/RsOperateLog.setDescription:(Ljava/lang/String;)V
     122: goto          140
     125: aload         5
     127: aload_0
     128: getfield      #165                // Field logSm:Lcom/virtual/common/StringManager;
     131: ldc_w         #328                // String logout.operation
     134: invokevirtual #124                // Method com/virtual/common/StringManager.getString:(Ljava/lang/String;)Ljava/lang/String;
     137: invokevirtual #316                // Method com/virtual/ssv/server/rs/client/entity/RsOperateLog.setDescription:(Ljava/lang/String;)V
     140: aload         5
     142: aload_1
     143: invokevirtual #317                // Method com/virtual/ssv/server/user/LoginInfo.getLoginName:()Ljava/lang/String;
     146: invokevirtual #318                // Method com/virtual/ssv/server/rs/client/entity/RsOperateLog.setLoginName:(Ljava/lang/String;)V
     149: aload         5
     151: getstatic     #319                // Field com/virtual/ssv/server/rs/client/entity/RsOperateLog.RESULT_SUCCESS:Ljava/lang/Integer;
     154: invokevirtual #320                // Method com/virtual/ssv/server/rs/client/entity/RsOperateLog.setResult:(Ljava/lang/Integer;)V
     157: aload         5
     159: aload_1
     160: invokevirtual #268                // Method com/virtual/ssv/server/user/LoginInfo.getUserName:()Ljava/lang/String;
     163: invokevirtual #321                // Method com/virtual/ssv/server/rs/client/entity/RsOperateLog.setUserName:(Ljava/lang/String;)V
     166: aload         5
     168: aload_2
     169: invokevirtual #322                // Method com/virtual/ssv/server/rs/client/entity/RsOperateLog.setStartTime:(Ljava/util/Date;)V
     172: aload         5
     174: aload         4
     176: invokevirtual #323                // Method com/virtual/ssv/server/rs/client/entity/RsOperateLog.setEndTime:(Ljava/util/Date;)V
     179: aload_0
     180: getfield      #1                  // Field reqHandle:Lcom/virtual/ssv/server/rs/client/RequestHandle;
     183: aload         5
     185: invokevirtual #324                // Method com/virtual/ssv/server/rs/client/RequestHandle.addUserLog:(Lcom/virtual/ssv/server/rs/client/entity/RsOperateLog;)Ljava/lang/Long;
     188: pop
     189: goto          205
     192: astore        5
     194: getstatic     #79                 // Field log:Lorg/apache/commons/logging/Log;
     197: aconst_null
     198: aload         5
     200: invokeinterface #212,  3          // InterfaceMethod org/apache/commons/logging/Log.error:(Ljava/lang/Object;Ljava/lang/Throwable;)V
     205: return
    Exception table:
       from    to  target type
           9   189   192   Class com/virtual/common/AppException

  public void doLogout(javax.servlet.http.HttpServletRequest, javax.servlet.http.HttpServletResponse);
    Code:
       0: aload_1
       1: iconst_0
       2: invokeinterface #330,  2          // InterfaceMethod javax/servlet/http/HttpServletRequest.getSession:(Z)Ljavax/servlet/http/HttpSession;
       7: astore_3
       8: aload_3
       9: ifnonnull     21
      12: aload_0
      13: aload_2
      14: ldc_w         #331                // String success
      17: invokevirtual #87                 // Method write:(Ljavax/servlet/http/HttpServletResponse;Ljava/lang/String;)V
      20: return
      21: aload_3
      22: ldc           #50                 // String loginInfo
      24: invokeinterface #51,  2           // InterfaceMethod javax/servlet/http/HttpSession.getAttribute:(Ljava/lang/String;)Ljava/lang/Object;
      29: checkcast     #52                 // class com/virtual/ssv/server/user/LoginInfo
      32: astore        4
      34: aload         4
      36: ifnull        106
      39: aload         4
      41: invokevirtual #253                // Method com/virtual/ssv/server/user/LoginInfo.getId:()Ljava/lang/Long;
      44: astore        5
      46: aload_3
      47: ldc           #50                 // String loginInfo
      49: invokeinterface #177,  2          // InterfaceMethod javax/servlet/http/HttpSession.removeAttribute:(Ljava/lang/String;)V
      54: aload_3
      55: ldc           #150                // String loginName
      57: invokeinterface #177,  2          // InterfaceMethod javax/servlet/http/HttpSession.removeAttribute:(Ljava/lang/String;)V
      62: aload_3
      63: ldc_w         #325                // String autoLogout
      66: aload_1
      67: ldc_w         #325                // String autoLogout
      70: invokeinterface #29,  2           // InterfaceMethod javax/servlet/http/HttpServletRequest.getParameter:(Ljava/lang/String;)Ljava/lang/String;
      75: invokeinterface #163,  3          // InterfaceMethod javax/servlet/http/HttpSession.setAttribute:(Ljava/lang/String;Ljava/lang/Object;)V
      80: aload_3
      81: invokeinterface #332,  1          // InterfaceMethod javax/servlet/http/HttpSession.invalidate:()V
      86: new           #333                // class java/lang/Thread
      89: dup
      90: new           #334                // class com/virtual/ssv/server/user/LoginServlet$1
      93: dup
      94: aload_0
      95: aload         5
      97: invokespecial #335                // Method com/virtual/ssv/server/user/LoginServlet$1."<init>":(Lcom/virtual/ssv/server/user/LoginServlet;Ljava/lang/Long;)V
     100: invokespecial #336                // Method java/lang/Thread."<init>":(Ljava/lang/Runnable;)V
     103: invokevirtual #337                // Method java/lang/Thread.start:()V
     106: aload_0
     107: aload_2
     108: ldc_w         #331                // String success
     111: invokevirtual #87                 // Method write:(Ljavax/servlet/http/HttpServletResponse;Ljava/lang/String;)V
     114: return

  private void getUser(javax.servlet.http.HttpServletRequest, javax.servlet.http.HttpServletResponse, com.virtual.ssv.server.user.LoginInfo);
    Code:
       0: new           #191                // class com/virtual/ssv/server/rs/client/entity/RsUser
       3: dup
       4: invokespecial #192                // Method com/virtual/ssv/server/rs/client/entity/RsUser."<init>":()V
       7: astore        4
       9: new           #72                 // class com/virtual/ssv/server/entity/ResultJson
      12: dup
      13: invokespecial #73                 // Method com/virtual/ssv/server/entity/ResultJson."<init>":()V
      16: astore        5
      18: aload_0
      19: getfield      #1                  // Field reqHandle:Lcom/virtual/ssv/server/rs/client/RequestHandle;
      22: aload_3
      23: invokevirtual #253                // Method com/virtual/ssv/server/user/LoginInfo.getId:()Ljava/lang/Long;
      26: invokevirtual #338                // Method com/virtual/ssv/server/rs/client/RequestHandle.getUser:(Ljava/lang/Long;)Lcom/virtual/ssv/server/rs/client/entity/RsUser;
      29: astore        4
      31: aload         4
      33: invokevirtual #295                // Method com/virtual/ssv/server/rs/client/entity/RsUser.getImageUrl:()Ljava/lang/String;
      36: astore        6
      38: aload         6
      40: invokestatic  #152                // Method org/apache/commons/lang/StringUtils.isEmpty:(Ljava/lang/String;)Z
      43: ifeq          62
      46: ldc_w         #339                // String icons/portrait.png
      49: astore        6
      51: aload         4
      53: ldc_w         #339                // String icons/portrait.png
      56: invokevirtual #340                // Method com/virtual/ssv/server/rs/client/entity/RsUser.setImageUrl:(Ljava/lang/String;)V
      59: goto          169
      62: aload_1
      63: invokeinterface #49,  1           // InterfaceMethod javax/servlet/http/HttpServletRequest.getSession:()Ljavax/servlet/http/HttpSession;
      68: invokeinterface #341,  1          // InterfaceMethod javax/servlet/http/HttpSession.getServletContext:()Ljavax/servlet/ServletContext;
      73: ldc_w         #342                // String /
      76: invokeinterface #343,  2          // InterfaceMethod javax/servlet/ServletContext.getRealPath:(Ljava/lang/String;)Ljava/lang/String;
      81: astore        7
      83: new           #258                // class java/lang/StringBuilder
      86: dup
      87: invokespecial #259                // Method java/lang/StringBuilder."<init>":()V
      90: aload         7
      92: invokevirtual #262                // Method java/lang/StringBuilder.append:(Ljava/lang/String;)Ljava/lang/StringBuilder;
      95: getstatic     #344                // Field java/io/File.separator:Ljava/lang/String;
      98: invokevirtual #262                // Method java/lang/StringBuilder.append:(Ljava/lang/String;)Ljava/lang/StringBuilder;
     101: ldc_w         #345                // String images
     104: invokevirtual #262                // Method java/lang/StringBuilder.append:(Ljava/lang/String;)Ljava/lang/StringBuilder;
     107: getstatic     #344                // Field java/io/File.separator:Ljava/lang/String;
     110: invokevirtual #262                // Method java/lang/StringBuilder.append:(Ljava/lang/String;)Ljava/lang/StringBuilder;
     113: aload         6
     115: invokevirtual #262                // Method java/lang/StringBuilder.append:(Ljava/lang/String;)Ljava/lang/StringBuilder;
     118: invokevirtual #263                // Method java/lang/StringBuilder.toString:()Ljava/lang/String;
     121: astore        8
     123: new           #346                // class java/io/File
     126: dup
     127: aload         8
     129: invokespecial #347                // Method java/io/File."<init>":(Ljava/lang/String;)V
     132: invokevirtual #348                // Method java/io/File.exists:()Z
     135: ifeq          164
     138: new           #258                // class java/lang/StringBuilder
     141: dup
     142: invokespecial #259                // Method java/lang/StringBuilder."<init>":()V
     145: ldc_w         #349                // String images/
     148: invokevirtual #262                // Method java/lang/StringBuilder.append:(Ljava/lang/String;)Ljava/lang/StringBuilder;
     151: aload         6
     153: invokevirtual #262                // Method java/lang/StringBuilder.append:(Ljava/lang/String;)Ljava/lang/StringBuilder;
     156: invokevirtual #263                // Method java/lang/StringBuilder.toString:()Ljava/lang/String;
     159: astore        6
     161: goto          169
     164: ldc_w         #339                // String icons/portrait.png
     167: astore        6
     169: aload         4
     171: aload         6
     173: invokevirtual #340                // Method com/virtual/ssv/server/rs/client/entity/RsUser.setImageUrl:(Ljava/lang/String;)V
     176: aload_0
     177: getfield      #1                  // Field reqHandle:Lcom/virtual/ssv/server/rs/client/RequestHandle;
     180: aload_3
     181: invokevirtual #253                // Method com/virtual/ssv/server/user/LoginInfo.getId:()Ljava/lang/Long;
     184: invokevirtual #254                // Method com/virtual/ssv/server/rs/client/RequestHandle.getUserSetting:(Ljava/lang/Long;)Lcom/virtual/ssv/server/rs/client/entity/UserSetting;
     187: astore        7
     189: new           #94                 // class java/util/ArrayList
     192: dup
     193: invokespecial #95                 // Method java/util/ArrayList."<init>":()V
     196: astore        8
     198: aload         8
     200: aload         4
     202: invokeinterface #350,  2          // InterfaceMethod java/util/List.add:(Ljava/lang/Object;)Z
     207: pop
     208: aload         7
     210: ifnull        223
     213: aload         8
     215: aload         7
     217: invokeinterface #350,  2          // InterfaceMethod java/util/List.add:(Ljava/lang/Object;)Z
     222: pop
     223: aload_0
     224: getfield      #145                // Field gson:Lcom/google/gson/Gson;
     227: aload         8
     229: invokevirtual #86                 // Method com/google/gson/Gson.toJson:(Ljava/lang/Object;)Ljava/lang/String;
     232: astore        9
     234: aload_0
     235: aload_2
     236: aload         9
     238: invokevirtual #87                 // Method write:(Ljavax/servlet/http/HttpServletResponse;Ljava/lang/String;)V
     241: goto          267
     244: astore        6
     246: aload         6
     248: aload         5
     250: invokestatic  #175                // Method com/virtual/ssv/server/ServerUtils.handleException:(Ljava/lang/Exception;Lcom/virtual/ssv/server/entity/ResultJson;)V
     253: aload_0
     254: aload_2
     255: aload_0
     256: getfield      #85                 // Field filterJson:Lcom/google/gson/Gson;
     259: aload         5
     261: invokevirtual #86                 // Method com/google/gson/Gson.toJson:(Ljava/lang/Object;)Ljava/lang/String;
     264: invokevirtual #87                 // Method write:(Ljavax/servlet/http/HttpServletResponse;Ljava/lang/String;)V
     267: return
    Exception table:
       from    to  target type
          18   241   244   Class java/lang/Exception

  private void editUser(javax.servlet.http.HttpServletRequest, javax.servlet.http.HttpServletResponse, com.virtual.ssv.server.user.LoginInfo);
    Code:
       0: new           #72                 // class com/virtual/ssv/server/entity/ResultJson
       3: dup
       4: invokespecial #73                 // Method com/virtual/ssv/server/entity/ResultJson."<init>":()V
       7: astore        4
       9: aload_1
      10: ldc_w         #351                // String xml
      13: invokeinterface #29,  2           // InterfaceMethod javax/servlet/http/HttpServletRequest.getParameter:(Ljava/lang/String;)Ljava/lang/String;
      18: astore        5
      20: aload         5
      22: ldc           #76                 // String UTF-8
      24: invokestatic  #77                 // Method java/net/URLDecoder.decode:(Ljava/lang/String;Ljava/lang/String;)Ljava/lang/String;
      27: astore        5
      29: aload_1
      30: ldc_w         #352                // String oldpwd
      33: invokeinterface #29,  2           // InterfaceMethod javax/servlet/http/HttpServletRequest.getParameter:(Ljava/lang/String;)Ljava/lang/String;
      38: astore        6
      40: aload         6
      42: invokestatic  #213                // Method com/virtual/common/FuncUtil.decryptData:(Ljava/lang/String;)Ljava/lang/String;
      45: astore        6
      47: aload_1
      48: ldc           #182                // String userName
      50: invokeinterface #29,  2           // InterfaceMethod javax/servlet/http/HttpServletRequest.getParameter:(Ljava/lang/String;)Ljava/lang/String;
      55: astore        7
      57: aload_1
      58: invokeinterface #49,  1           // InterfaceMethod javax/servlet/http/HttpServletRequest.getSession:()Ljavax/servlet/http/HttpSession;
      63: astore        8
      65: aload         8
      67: ldc           #182                // String userName
      69: aload         7
      71: invokeinterface #163,  3          // InterfaceMethod javax/servlet/http/HttpSession.setAttribute:(Ljava/lang/String;Ljava/lang/Object;)V
      76: aload         8
      78: ldc           #50                 // String loginInfo
      80: invokeinterface #51,  2           // InterfaceMethod javax/servlet/http/HttpSession.getAttribute:(Ljava/lang/String;)Ljava/lang/Object;
      85: checkcast     #52                 // class com/virtual/ssv/server/user/LoginInfo
      88: aload         7
      90: invokevirtual #287                // Method com/virtual/ssv/server/user/LoginInfo.setUserName:(Ljava/lang/String;)V
      93: aload         6
      95: invokestatic  #109                // Method org/apache/commons/lang/StringUtils.isNotEmpty:(Ljava/lang/String;)Z
      98: ifeq          171
     101: aload         6
     103: invokestatic  #279                // Method com/virtual/common/FuncUtil.encryptData:(Ljava/lang/String;)Ljava/lang/String;
     106: astore        6
     108: aload_0
     109: getfield      #1                  // Field reqHandle:Lcom/virtual/ssv/server/rs/client/RequestHandle;
     112: aload_3
     113: invokevirtual #317                // Method com/virtual/ssv/server/user/LoginInfo.getLoginName:()Ljava/lang/String;
     116: aload         6
     118: invokevirtual #280                // Method com/virtual/ssv/server/rs/client/RequestHandle.userAuth:(Ljava/lang/String;Ljava/lang/String;)Lcom/virtual/ssv/server/rs/client/entity/RsUser;
     121: astore        9
     123: aload         9
     125: ifnonnull     160
     128: aload         4
     130: aload_0
     131: getfield      #165                // Field logSm:Lcom/virtual/common/StringManager;
     134: ldc_w         #353                // String oldpwdError
     137: invokevirtual #124                // Method com/virtual/common/StringManager.getString:(Ljava/lang/String;)Ljava/lang/String;
     140: invokevirtual #84                 // Method com/virtual/ssv/server/entity/ResultJson.setErrorMsg:(Ljava/lang/String;)V
     143: aload_0
     144: aload_2
     145: aload_0
     146: getfield      #145                // Field gson:Lcom/google/gson/Gson;
     149: aload         4
     151: invokevirtual #86                 // Method com/google/gson/Gson.toJson:(Ljava/lang/Object;)Ljava/lang/String;
     154: invokevirtual #87                 // Method write:(Ljavax/servlet/http/HttpServletResponse;Ljava/lang/String;)V
     157: goto          168
     160: aload_0
     161: aload_2
     162: aload_3
     163: aload         5
     165: invokespecial #354                // Method updateUser:(Ljavax/servlet/http/HttpServletResponse;Lcom/virtual/ssv/server/user/LoginInfo;Ljava/lang/String;)V
     168: goto          179
     171: aload_0
     172: aload_2
     173: aload_3
     174: aload         5
     176: invokespecial #354                // Method updateUser:(Ljavax/servlet/http/HttpServletResponse;Lcom/virtual/ssv/server/user/LoginInfo;Ljava/lang/String;)V
     179: goto          205
     182: astore        5
     184: aload         5
     186: aload         4
     188: invokestatic  #175                // Method com/virtual/ssv/server/ServerUtils.handleException:(Ljava/lang/Exception;Lcom/virtual/ssv/server/entity/ResultJson;)V
     191: aload_0
     192: aload_2
     193: aload_0
     194: getfield      #85                 // Field filterJson:Lcom/google/gson/Gson;
     197: aload         4
     199: invokevirtual #86                 // Method com/google/gson/Gson.toJson:(Ljava/lang/Object;)Ljava/lang/String;
     202: invokevirtual #87                 // Method write:(Ljavax/servlet/http/HttpServletResponse;Ljava/lang/String;)V
     205: return
    Exception table:
       from    to  target type
           9   179   182   Class java/lang/Exception

  private void updateUser(javax.servlet.http.HttpServletResponse, com.virtual.ssv.server.user.LoginInfo, java.lang.String);
    Code:
       0: new           #207                // class java/util/Date
       3: dup
       4: invokespecial #208                // Method java/util/Date."<init>":()V
       7: astore        4
       9: new           #72                 // class com/virtual/ssv/server/entity/ResultJson
      12: dup
      13: invokespecial #73                 // Method com/virtual/ssv/server/entity/ResultJson."<init>":()V
      16: astore        5
      18: aload_0
      19: getfield      #1                  // Field reqHandle:Lcom/virtual/ssv/server/rs/client/RequestHandle;
      22: aload_2
      23: invokevirtual #253                // Method com/virtual/ssv/server/user/LoginInfo.getId:()Ljava/lang/Long;
      26: aload_2
      27: invokevirtual #268                // Method com/virtual/ssv/server/user/LoginInfo.getUserName:()Ljava/lang/String;
      30: aload_3
      31: invokevirtual #355                // Method com/virtual/ssv/server/rs/client/RequestHandle.updateUser:(Ljava/lang/Long;Ljava/lang/String;Ljava/lang/String;)Lcom/virtual/ssv/server/entity/ResultJson;
      34: astore        5
      36: new           #207                // class java/util/Date
      39: dup
      40: invokespecial #208                // Method java/util/Date."<init>":()V
      43: astore        6
      45: new           #306                // class com/virtual/ssv/server/rs/client/entity/RsOperateLog
      48: dup
      49: invokespecial #307                // Method com/virtual/ssv/server/rs/client/entity/RsOperateLog."<init>":()V
      52: astore        7
      54: aload         7
      56: aload_2
      57: invokevirtual #253                // Method com/virtual/ssv/server/user/LoginInfo.getId:()Ljava/lang/Long;
      60: invokevirtual #308                // Method com/virtual/ssv/server/rs/client/entity/RsOperateLog.setUserId:(Ljava/lang/Long;)V
      63: aload         7
      65: aload_2
      66: invokevirtual #309                // Method com/virtual/ssv/server/user/LoginInfo.getOrgId:()Ljava/lang/Long;
      69: invokevirtual #310                // Method com/virtual/ssv/server/rs/client/entity/RsOperateLog.setOrgId:(Ljava/lang/Long;)V
      72: aload         7
      74: aload_2
      75: invokevirtual #311                // Method com/virtual/ssv/server/user/LoginInfo.getLoginIp:()Ljava/lang/String;
      78: invokevirtual #312                // Method com/virtual/ssv/server/rs/client/entity/RsOperateLog.setAddress:(Ljava/lang/String;)V
      81: aload         7
      83: iconst_1
      84: invokestatic  #162                // Method java/lang/Integer.valueOf:(I)Ljava/lang/Integer;
      87: invokevirtual #314                // Method com/virtual/ssv/server/rs/client/entity/RsOperateLog.setCategory:(Ljava/lang/Integer;)V
      90: aload         7
      92: aload_2
      93: invokevirtual #317                // Method com/virtual/ssv/server/user/LoginInfo.getLoginName:()Ljava/lang/String;
      96: invokevirtual #318                // Method com/virtual/ssv/server/rs/client/entity/RsOperateLog.setLoginName:(Ljava/lang/String;)V
      99: aload         7
     101: aload_2
     102: invokevirtual #268                // Method com/virtual/ssv/server/user/LoginInfo.getUserName:()Ljava/lang/String;
     105: invokevirtual #321                // Method com/virtual/ssv/server/rs/client/entity/RsOperateLog.setUserName:(Ljava/lang/String;)V
     108: aload         7
     110: aload_0
     111: getfield      #165                // Field logSm:Lcom/virtual/common/StringManager;
     114: ldc_w         #356                // String personalInfo.edit.operation
     117: invokevirtual #124                // Method com/virtual/common/StringManager.getString:(Ljava/lang/String;)Ljava/lang/String;
     120: invokevirtual #316                // Method com/virtual/ssv/server/rs/client/entity/RsOperateLog.setDescription:(Ljava/lang/String;)V
     123: aload         5
     125: invokevirtual #357                // Method com/virtual/ssv/server/entity/ResultJson.isSuccess:()Z
     128: ifeq          142
     131: aload         7
     133: getstatic     #319                // Field com/virtual/ssv/server/rs/client/entity/RsOperateLog.RESULT_SUCCESS:Ljava/lang/Integer;
     136: invokevirtual #320                // Method com/virtual/ssv/server/rs/client/entity/RsOperateLog.setResult:(Ljava/lang/Integer;)V
     139: goto          160
     142: aload         7
     144: aload         5
     146: invokevirtual #358                // Method com/virtual/ssv/server/entity/ResultJson.getMessage:()Ljava/lang/String;
     149: invokevirtual #359                // Method com/virtual/ssv/server/rs/client/entity/RsOperateLog.setFailureReason:(Ljava/lang/String;)V
     152: aload         7
     154: getstatic     #360                // Field com/virtual/ssv/server/rs/client/entity/RsOperateLog.RESULT_FAILURE:Ljava/lang/Integer;
     157: invokevirtual #320                // Method com/virtual/ssv/server/rs/client/entity/RsOperateLog.setResult:(Ljava/lang/Integer;)V
     160: aload         7
     162: aload         4
     164: invokevirtual #322                // Method com/virtual/ssv/server/rs/client/entity/RsOperateLog.setStartTime:(Ljava/util/Date;)V
     167: aload         7
     169: aload         6
     171: invokevirtual #323                // Method com/virtual/ssv/server/rs/client/entity/RsOperateLog.setEndTime:(Ljava/util/Date;)V
     174: aload_0
     175: getfield      #1                  // Field reqHandle:Lcom/virtual/ssv/server/rs/client/RequestHandle;
     178: aload         7
     180: invokevirtual #324                // Method com/virtual/ssv/server/rs/client/RequestHandle.addUserLog:(Lcom/virtual/ssv/server/rs/client/entity/RsOperateLog;)Ljava/lang/Long;
     183: pop
     184: goto          228
     187: astore        6
     189: aload         6
     191: aload         5
     193: invokestatic  #175                // Method com/virtual/ssv/server/ServerUtils.handleException:(Ljava/lang/Exception;Lcom/virtual/ssv/server/entity/ResultJson;)V
     196: aload         6
     198: instanceof    #275                // class com/virtual/common/AppException
     201: ifeq          228
     204: aload         6
     206: checkcast     #275                // class com/virtual/common/AppException
     209: astore        7
     211: aload         7
     213: invokevirtual #276                // Method com/virtual/common/AppException.getErrorCode:()I
     216: bipush        23
     218: if_icmpne     228
     221: aload         5
     223: ldc           #89                 // String 23
     225: invokevirtual #84                 // Method com/virtual/ssv/server/entity/ResultJson.setErrorMsg:(Ljava/lang/String;)V
     228: aload_0
     229: aload_1
     230: aload_0
     231: getfield      #85                 // Field filterJson:Lcom/google/gson/Gson;
     234: aload         5
     236: invokevirtual #86                 // Method com/google/gson/Gson.toJson:(Ljava/lang/Object;)Ljava/lang/String;
     239: invokevirtual #87                 // Method write:(Ljavax/servlet/http/HttpServletResponse;Ljava/lang/String;)V
     242: return
    Exception table:
       from    to  target type
          18   184   187   Class java/lang/Exception

  private void saveUserSetting(javax.servlet.http.HttpServletRequest, javax.servlet.http.HttpServletResponse, com.virtual.ssv.server.user.LoginInfo);
    Code:
       0: new           #207                // class java/util/Date
       3: dup
       4: invokespecial #208                // Method java/util/Date."<init>":()V
       7: astore        4
       9: new           #72                 // class com/virtual/ssv/server/entity/ResultJson
      12: dup
      13: invokespecial #73                 // Method com/virtual/ssv/server/entity/ResultJson."<init>":()V
      16: astore        5
      18: aload_1
      19: ldc_w         #361                // String monitorSelect
      22: invokeinterface #29,  2           // InterfaceMethod javax/servlet/http/HttpServletRequest.getParameter:(Ljava/lang/String;)Ljava/lang/String;
      27: astore        6
      29: aload_1
      30: ldc_w         #362                // String moreRate
      33: invokeinterface #29,  2           // InterfaceMethod javax/servlet/http/HttpServletRequest.getParameter:(Ljava/lang/String;)Ljava/lang/String;
      38: astore        7
      40: aload_1
      41: ldc_w         #363                // String capacityMore
      44: invokeinterface #29,  2           // InterfaceMethod javax/servlet/http/HttpServletRequest.getParameter:(Ljava/lang/String;)Ljava/lang/String;
      49: astore        8
      51: aload_1
      52: ldc_w         #364                // String lastTime
      55: invokeinterface #29,  2           // InterfaceMethod javax/servlet/http/HttpServletRequest.getParameter:(Ljava/lang/String;)Ljava/lang/String;
      60: astore        9
      62: aload_1
      63: ldc_w         #365                // String checkInterval
      66: invokeinterface #29,  2           // InterfaceMethod javax/servlet/http/HttpServletRequest.getParameter:(Ljava/lang/String;)Ljava/lang/String;
      71: astore        10
      73: aload_1
      74: ldc_w         #366                // String inter
      77: invokeinterface #29,  2           // InterfaceMethod javax/servlet/http/HttpServletRequest.getParameter:(Ljava/lang/String;)Ljava/lang/String;
      82: astore        11
      84: aload_1
      85: ldc           #75                 // String email
      87: invokeinterface #29,  2           // InterfaceMethod javax/servlet/http/HttpServletRequest.getParameter:(Ljava/lang/String;)Ljava/lang/String;
      92: astore        12
      94: aload_1
      95: ldc_w         #367                // String message
      98: invokeinterface #29,  2           // InterfaceMethod javax/servlet/http/HttpServletRequest.getParameter:(Ljava/lang/String;)Ljava/lang/String;
     103: astore        13
     105: new           #368                // class com/virtual/ssv/server/rs/client/entity/UserSetting
     108: dup
     109: invokespecial #369                // Method com/virtual/ssv/server/rs/client/entity/UserSetting."<init>":()V
     112: astore        14
     114: aload         14
     116: aload_3
     117: invokevirtual #253                // Method com/virtual/ssv/server/user/LoginInfo.getId:()Ljava/lang/Long;
     120: invokevirtual #370                // Method com/virtual/ssv/server/rs/client/entity/UserSetting.setUserId:(Ljava/lang/Long;)V
     123: ldc           #189                // String
     125: astore        15
     127: ldc_w         #371                // String on
     130: aload         11
     132: invokevirtual #372                // Method java/lang/String.equalsIgnoreCase:(Ljava/lang/String;)Z
     135: ifeq          164
     138: new           #258                // class java/lang/StringBuilder
     141: dup
     142: invokespecial #259                // Method java/lang/StringBuilder."<init>":()V
     145: aload         15
     147: invokevirtual #262                // Method java/lang/StringBuilder.append:(Ljava/lang/String;)Ljava/lang/StringBuilder;
     150: ldc_w         #373                // String 1
     153: invokevirtual #262                // Method java/lang/StringBuilder.append:(Ljava/lang/String;)Ljava/lang/StringBuilder;
     156: invokevirtual #263                // Method java/lang/StringBuilder.toString:()Ljava/lang/String;
     159: astore        15
     161: goto          187
     164: new           #258                // class java/lang/StringBuilder
     167: dup
     168: invokespecial #259                // Method java/lang/StringBuilder."<init>":()V
     171: aload         15
     173: invokevirtual #262                // Method java/lang/StringBuilder.append:(Ljava/lang/String;)Ljava/lang/StringBuilder;
     176: ldc_w         #374                // String 0
     179: invokevirtual #262                // Method java/lang/StringBuilder.append:(Ljava/lang/String;)Ljava/lang/StringBuilder;
     182: invokevirtual #263                // Method java/lang/StringBuilder.toString:()Ljava/lang/String;
     185: astore        15
     187: ldc_w         #371                // String on
     190: aload         12
     192: invokevirtual #372                // Method java/lang/String.equalsIgnoreCase:(Ljava/lang/String;)Z
     195: ifeq          224
     198: new           #258                // class java/lang/StringBuilder
     201: dup
     202: invokespecial #259                // Method java/lang/StringBuilder."<init>":()V
     205: aload         15
     207: invokevirtual #262                // Method java/lang/StringBuilder.append:(Ljava/lang/String;)Ljava/lang/StringBuilder;
     210: ldc_w         #373                // String 1
     213: invokevirtual #262                // Method java/lang/StringBuilder.append:(Ljava/lang/String;)Ljava/lang/StringBuilder;
     216: invokevirtual #263                // Method java/lang/StringBuilder.toString:()Ljava/lang/String;
     219: astore        15
     221: goto          247
     224: new           #258                // class java/lang/StringBuilder
     227: dup
     228: invokespecial #259                // Method java/lang/StringBuilder."<init>":()V
     231: aload         15
     233: invokevirtual #262                // Method java/lang/StringBuilder.append:(Ljava/lang/String;)Ljava/lang/StringBuilder;
     236: ldc_w         #374                // String 0
     239: invokevirtual #262                // Method java/lang/StringBuilder.append:(Ljava/lang/String;)Ljava/lang/StringBuilder;
     242: invokevirtual #263                // Method java/lang/StringBuilder.toString:()Ljava/lang/String;
     245: astore        15
     247: ldc_w         #371                // String on
     250: aload         13
     252: invokevirtual #372                // Method java/lang/String.equalsIgnoreCase:(Ljava/lang/String;)Z
     255: ifeq          284
     258: new           #258                // class java/lang/StringBuilder
     261: dup
     262: invokespecial #259                // Method java/lang/StringBuilder."<init>":()V
     265: aload         15
     267: invokevirtual #262                // Method java/lang/StringBuilder.append:(Ljava/lang/String;)Ljava/lang/StringBuilder;
     270: ldc_w         #373                // String 1
     273: invokevirtual #262                // Method java/lang/StringBuilder.append:(Ljava/lang/String;)Ljava/lang/StringBuilder;
     276: invokevirtual #263                // Method java/lang/StringBuilder.toString:()Ljava/lang/String;
     279: astore        15
     281: goto          307
     284: new           #258                // class java/lang/StringBuilder
     287: dup
     288: invokespecial #259                // Method java/lang/StringBuilder."<init>":()V
     291: aload         15
     293: invokevirtual #262                // Method java/lang/StringBuilder.append:(Ljava/lang/String;)Ljava/lang/StringBuilder;
     296: ldc_w         #374                // String 0
     299: invokevirtual #262                // Method java/lang/StringBuilder.append:(Ljava/lang/String;)Ljava/lang/StringBuilder;
     302: invokevirtual #263                // Method java/lang/StringBuilder.toString:()Ljava/lang/String;
     305: astore        15
     307: aload         14
     309: aload         15
     311: invokevirtual #375                // Method com/virtual/ssv/server/rs/client/entity/UserSetting.setNoticeType:(Ljava/lang/String;)V
     314: aload         14
     316: aload         6
     318: invokevirtual #376                // Method com/virtual/ssv/server/rs/client/entity/UserSetting.setMonitorType:(Ljava/lang/String;)V
     321: ldc_w         #373                // String 1
     324: aload         6
     326: invokevirtual #31                 // Method java/lang/String.equals:(Ljava/lang/Object;)Z
     329: ifeq          395
     332: aload         10
     334: invokestatic  #109                // Method org/apache/commons/lang/StringUtils.isNotEmpty:(Ljava/lang/String;)Z
     337: ifeq          353
     340: aload         14
     342: aload         10
     344: invokestatic  #377                // Method java/lang/Long.parseLong:(Ljava/lang/String;)J
     347: invokestatic  #164                // Method java/lang/Long.valueOf:(J)Ljava/lang/Long;
     350: invokevirtual #378                // Method com/virtual/ssv/server/rs/client/entity/UserSetting.setCpuCheckInterval:(Ljava/lang/Long;)V
     353: aload         9
     355: invokestatic  #109                // Method org/apache/commons/lang/StringUtils.isNotEmpty:(Ljava/lang/String;)Z
     358: ifeq          374
     361: aload         14
     363: aload         9
     365: invokestatic  #377                // Method java/lang/Long.parseLong:(Ljava/lang/String;)J
     368: invokestatic  #164                // Method java/lang/Long.valueOf:(J)Ljava/lang/Long;
     371: invokevirtual #379                // Method com/virtual/ssv/server/rs/client/entity/UserSetting.setCpuDuration:(Ljava/lang/Long;)V
     374: aload         7
     376: invokestatic  #109                // Method org/apache/commons/lang/StringUtils.isNotEmpty:(Ljava/lang/String;)Z
     379: ifeq          498
     382: aload         14
     384: aload         7
     386: invokestatic  #380                // Method java/lang/Short.valueOf:(Ljava/lang/String;)Ljava/lang/Short;
     389: invokevirtual #381                // Method com/virtual/ssv/server/rs/client/entity/UserSetting.setCpuMaxrate:(Ljava/lang/Short;)V
     392: goto          498
     395: ldc_w         #382                // String 2
     398: aload         6
     400: invokevirtual #31                 // Method java/lang/String.equals:(Ljava/lang/Object;)Z
     403: ifeq          469
     406: aload         10
     408: invokestatic  #109                // Method org/apache/commons/lang/StringUtils.isNotEmpty:(Ljava/lang/String;)Z
     411: ifeq          427
     414: aload         14
     416: aload         10
     418: invokestatic  #377                // Method java/lang/Long.parseLong:(Ljava/lang/String;)J
     421: invokestatic  #164                // Method java/lang/Long.valueOf:(J)Ljava/lang/Long;
     424: invokevirtual #383                // Method com/virtual/ssv/server/rs/client/entity/UserSetting.setMemoryCheckInterval:(Ljava/lang/Long;)V
     427: aload         9
     429: invokestatic  #109                // Method org/apache/commons/lang/StringUtils.isNotEmpty:(Ljava/lang/String;)Z
     432: ifeq          448
     435: aload         14
     437: aload         9
     439: invokestatic  #377                // Method java/lang/Long.parseLong:(Ljava/lang/String;)J
     442: invokestatic  #164                // Method java/lang/Long.valueOf:(J)Ljava/lang/Long;
     445: invokevirtual #384                // Method com/virtual/ssv/server/rs/client/entity/UserSetting.setMemoryDuration:(Ljava/lang/Long;)V
     448: aload         7
     450: invokestatic  #109                // Method org/apache/commons/lang/StringUtils.isNotEmpty:(Ljava/lang/String;)Z
     453: ifeq          498
     456: aload         14
     458: aload         7
     460: invokestatic  #380                // Method java/lang/Short.valueOf:(Ljava/lang/String;)Ljava/lang/Short;
     463: invokevirtual #385                // Method com/virtual/ssv/server/rs/client/entity/UserSetting.setMemoryMaxrate:(Ljava/lang/Short;)V
     466: goto          498
     469: ldc_w         #386                // String 3
     472: aload         6
     474: invokevirtual #31                 // Method java/lang/String.equals:(Ljava/lang/Object;)Z
     477: ifeq          498
     480: aload         8
     482: invokestatic  #109                // Method org/apache/commons/lang/StringUtils.isNotEmpty:(Ljava/lang/String;)Z
     485: ifeq          498
     488: aload         14
     490: aload         8
     492: invokestatic  #380                // Method java/lang/Short.valueOf:(Ljava/lang/String;)Ljava/lang/Short;
     495: invokevirtual #387                // Method com/virtual/ssv/server/rs/client/entity/UserSetting.setDiskMaxRate:(Ljava/lang/Short;)V
     498: aload_0
     499: getfield      #1                  // Field reqHandle:Lcom/virtual/ssv/server/rs/client/RequestHandle;
     502: aload         14
     504: aload_3
     505: invokevirtual #253                // Method com/virtual/ssv/server/user/LoginInfo.getId:()Ljava/lang/Long;
     508: aload_3
     509: invokevirtual #268                // Method com/virtual/ssv/server/user/LoginInfo.getUserName:()Ljava/lang/String;
     512: invokevirtual #388                // Method com/virtual/ssv/server/rs/client/RequestHandle.saveOrUpdateUserSetting:(Lcom/virtual/ssv/server/rs/client/entity/UserSetting;Ljava/lang/Long;Ljava/lang/String;)Lcom/virtual/ssv/server/entity/ResultJson;
     515: astore        5
     517: new           #207                // class java/util/Date
     520: dup
     521: invokespecial #208                // Method java/util/Date."<init>":()V
     524: astore        16
     526: new           #306                // class com/virtual/ssv/server/rs/client/entity/RsOperateLog
     529: dup
     530: invokespecial #307                // Method com/virtual/ssv/server/rs/client/entity/RsOperateLog."<init>":()V
     533: astore        17
     535: aload         17
     537: aload_3
     538: invokevirtual #253                // Method com/virtual/ssv/server/user/LoginInfo.getId:()Ljava/lang/Long;
     541: invokevirtual #308                // Method com/virtual/ssv/server/rs/client/entity/RsOperateLog.setUserId:(Ljava/lang/Long;)V
     544: aload         17
     546: aload_3
     547: invokevirtual #309                // Method com/virtual/ssv/server/user/LoginInfo.getOrgId:()Ljava/lang/Long;
     550: invokevirtual #310                // Method com/virtual/ssv/server/rs/client/entity/RsOperateLog.setOrgId:(Ljava/lang/Long;)V
     553: aload         17
     555: aload_3
     556: invokevirtual #311                // Method com/virtual/ssv/server/user/LoginInfo.getLoginIp:()Ljava/lang/String;
     559: invokevirtual #312                // Method com/virtual/ssv/server/rs/client/entity/RsOperateLog.setAddress:(Ljava/lang/String;)V
     562: aload         17
     564: iconst_1
     565: invokestatic  #162                // Method java/lang/Integer.valueOf:(I)Ljava/lang/Integer;
     568: invokevirtual #314                // Method com/virtual/ssv/server/rs/client/entity/RsOperateLog.setCategory:(Ljava/lang/Integer;)V
     571: aload         17
     573: aload_0
     574: getfield      #165                // Field logSm:Lcom/virtual/common/StringManager;
     577: ldc_w         #389                // String personalAlarm.edit.operation
     580: invokevirtual #124                // Method com/virtual/common/StringManager.getString:(Ljava/lang/String;)Ljava/lang/String;
     583: invokevirtual #316                // Method com/virtual/ssv/server/rs/client/entity/RsOperateLog.setDescription:(Ljava/lang/String;)V
     586: aload         17
     588: aload_3
     589: invokevirtual #317                // Method com/virtual/ssv/server/user/LoginInfo.getLoginName:()Ljava/lang/String;
     592: invokevirtual #318                // Method com/virtual/ssv/server/rs/client/entity/RsOperateLog.setLoginName:(Ljava/lang/String;)V
     595: aload         5
     597: invokevirtual #357                // Method com/virtual/ssv/server/entity/ResultJson.isSuccess:()Z
     600: ifeq          614
     603: aload         17
     605: getstatic     #319                // Field com/virtual/ssv/server/rs/client/entity/RsOperateLog.RESULT_SUCCESS:Ljava/lang/Integer;
     608: invokevirtual #320                // Method com/virtual/ssv/server/rs/client/entity/RsOperateLog.setResult:(Ljava/lang/Integer;)V
     611: goto          632
     614: aload         17
     616: getstatic     #360                // Field com/virtual/ssv/server/rs/client/entity/RsOperateLog.RESULT_FAILURE:Ljava/lang/Integer;
     619: invokevirtual #320                // Method com/virtual/ssv/server/rs/client/entity/RsOperateLog.setResult:(Ljava/lang/Integer;)V
     622: aload         17
     624: aload         5
     626: invokevirtual #358                // Method com/virtual/ssv/server/entity/ResultJson.getMessage:()Ljava/lang/String;
     629: invokevirtual #359                // Method com/virtual/ssv/server/rs/client/entity/RsOperateLog.setFailureReason:(Ljava/lang/String;)V
     632: aload         17
     634: aload_3
     635: invokevirtual #268                // Method com/virtual/ssv/server/user/LoginInfo.getUserName:()Ljava/lang/String;
     638: invokevirtual #321                // Method com/virtual/ssv/server/rs/client/entity/RsOperateLog.setUserName:(Ljava/lang/String;)V
     641: aload         17
     643: aload         4
     645: invokevirtual #322                // Method com/virtual/ssv/server/rs/client/entity/RsOperateLog.setStartTime:(Ljava/util/Date;)V
     648: aload         17
     650: aload         16
     652: invokevirtual #323                // Method com/virtual/ssv/server/rs/client/entity/RsOperateLog.setEndTime:(Ljava/util/Date;)V
     655: aload_0
     656: getfield      #1                  // Field reqHandle:Lcom/virtual/ssv/server/rs/client/RequestHandle;
     659: aload         17
     661: invokevirtual #324                // Method com/virtual/ssv/server/rs/client/RequestHandle.addUserLog:(Lcom/virtual/ssv/server/rs/client/entity/RsOperateLog;)Ljava/lang/Long;
     664: pop
     665: goto          677
     668: astore        6
     670: aload         6
     672: aload         5
     674: invokestatic  #175                // Method com/virtual/ssv/server/ServerUtils.handleException:(Ljava/lang/Exception;Lcom/virtual/ssv/server/entity/ResultJson;)V
     677: aload_0
     678: aload_2
     679: aload_0
     680: getfield      #85                 // Field filterJson:Lcom/google/gson/Gson;
     683: aload         5
     685: invokevirtual #86                 // Method com/google/gson/Gson.toJson:(Ljava/lang/Object;)Ljava/lang/String;
     688: invokevirtual #87                 // Method write:(Ljavax/servlet/http/HttpServletResponse;Ljava/lang/String;)V
     691: return
    Exception table:
       from    to  target type
          18   665   668   Class java/lang/Exception

  private void getUserSetting(javax.servlet.http.HttpServletRequest, javax.servlet.http.HttpServletResponse, com.virtual.ssv.server.user.LoginInfo);
    Code:
       0: new           #72                 // class com/virtual/ssv/server/entity/ResultJson
       3: dup
       4: invokespecial #73                 // Method com/virtual/ssv/server/entity/ResultJson."<init>":()V
       7: astore        4
       9: aload_0
      10: getfield      #1                  // Field reqHandle:Lcom/virtual/ssv/server/rs/client/RequestHandle;
      13: aload_3
      14: invokevirtual #253                // Method com/virtual/ssv/server/user/LoginInfo.getId:()Ljava/lang/Long;
      17: invokevirtual #254                // Method com/virtual/ssv/server/rs/client/RequestHandle.getUserSetting:(Ljava/lang/Long;)Lcom/virtual/ssv/server/rs/client/entity/UserSetting;
      20: astore        5
      22: aload         5
      24: ifnull        41
      27: aload_0
      28: aload_2
      29: aload_0
      30: getfield      #145                // Field gson:Lcom/google/gson/Gson;
      33: aload         5
      35: invokevirtual #86                 // Method com/google/gson/Gson.toJson:(Ljava/lang/Object;)Ljava/lang/String;
      38: invokevirtual #87                 // Method write:(Ljavax/servlet/http/HttpServletResponse;Ljava/lang/String;)V
      41: goto          67
      44: astore        5
      46: aload         5
      48: aload         4
      50: invokestatic  #175                // Method com/virtual/ssv/server/ServerUtils.handleException:(Ljava/lang/Exception;Lcom/virtual/ssv/server/entity/ResultJson;)V
      53: aload_0
      54: aload_2
      55: aload_0
      56: getfield      #85                 // Field filterJson:Lcom/google/gson/Gson;
      59: aload         4
      61: invokevirtual #86                 // Method com/google/gson/Gson.toJson:(Ljava/lang/Object;)Ljava/lang/String;
      64: invokevirtual #87                 // Method write:(Ljavax/servlet/http/HttpServletResponse;Ljava/lang/String;)V
      67: return
    Exception table:
       from    to  target type
           9    41    44   Class java/lang/Exception

  private void saveOtherUserSetting(javax.servlet.http.HttpServletRequest, javax.servlet.http.HttpServletResponse, com.virtual.ssv.server.user.LoginInfo);
    Code:
       0: new           #207                // class java/util/Date
       3: dup
       4: invokespecial #208                // Method java/util/Date."<init>":()V
       7: astore        4
       9: new           #72                 // class com/virtual/ssv/server/entity/ResultJson
      12: dup
      13: invokespecial #73                 // Method com/virtual/ssv/server/entity/ResultJson."<init>":()V
      16: astore        5
      18: aload_1
      19: ldc_w         #390                // String timeout
      22: invokeinterface #29,  2           // InterfaceMethod javax/servlet/http/HttpServletRequest.getParameter:(Ljava/lang/String;)Ljava/lang/String;
      27: astore        6
      29: new           #368                // class com/virtual/ssv/server/rs/client/entity/UserSetting
      32: dup
      33: invokespecial #369                // Method com/virtual/ssv/server/rs/client/entity/UserSetting."<init>":()V
      36: astore        7
      38: aload         7
      40: aload_3
      41: invokevirtual #253                // Method com/virtual/ssv/server/user/LoginInfo.getId:()Ljava/lang/Long;
      44: invokevirtual #370                // Method com/virtual/ssv/server/rs/client/entity/UserSetting.setUserId:(Ljava/lang/Long;)V
      47: aload         7
      49: ldc_w         #391                // String 4
      52: invokevirtual #376                // Method com/virtual/ssv/server/rs/client/entity/UserSetting.setMonitorType:(Ljava/lang/String;)V
      55: aload         6
      57: invokestatic  #109                // Method org/apache/commons/lang/StringUtils.isNotEmpty:(Ljava/lang/String;)Z
      60: ifeq          99
      63: aload         7
      65: aload         6
      67: invokestatic  #377                // Method java/lang/Long.parseLong:(Ljava/lang/String;)J
      70: invokestatic  #164                // Method java/lang/Long.valueOf:(J)Ljava/lang/Long;
      73: invokevirtual #392                // Method com/virtual/ssv/server/rs/client/entity/UserSetting.setTimeout:(Ljava/lang/Long;)V
      76: aload_1
      77: invokeinterface #49,  1           // InterfaceMethod javax/servlet/http/HttpServletRequest.getSession:()Ljavax/servlet/http/HttpSession;
      82: astore        8
      84: aload         8
      86: aload         6
      88: invokestatic  #8                  // Method java/lang/Integer.parseInt:(Ljava/lang/String;)I
      91: bipush        60
      93: imul
      94: invokeinterface #264,  2          // InterfaceMethod javax/servlet/http/HttpSession.setMaxInactiveInterval:(I)V
      99: aload_0
     100: getfield      #1                  // Field reqHandle:Lcom/virtual/ssv/server/rs/client/RequestHandle;
     103: aload         7
     105: aload_3
     106: invokevirtual #253                // Method com/virtual/ssv/server/user/LoginInfo.getId:()Ljava/lang/Long;
     109: aload_3
     110: invokevirtual #268                // Method com/virtual/ssv/server/user/LoginInfo.getUserName:()Ljava/lang/String;
     113: invokevirtual #388                // Method com/virtual/ssv/server/rs/client/RequestHandle.saveOrUpdateUserSetting:(Lcom/virtual/ssv/server/rs/client/entity/UserSetting;Ljava/lang/Long;Ljava/lang/String;)Lcom/virtual/ssv/server/entity/ResultJson;
     116: astore        5
     118: new           #207                // class java/util/Date
     121: dup
     122: invokespecial #208                // Method java/util/Date."<init>":()V
     125: astore        8
     127: new           #306                // class com/virtual/ssv/server/rs/client/entity/RsOperateLog
     130: dup
     131: invokespecial #307                // Method com/virtual/ssv/server/rs/client/entity/RsOperateLog."<init>":()V
     134: astore        9
     136: aload         9
     138: aload_3
     139: invokevirtual #253                // Method com/virtual/ssv/server/user/LoginInfo.getId:()Ljava/lang/Long;
     142: invokevirtual #308                // Method com/virtual/ssv/server/rs/client/entity/RsOperateLog.setUserId:(Ljava/lang/Long;)V
     145: aload         9
     147: aload_3
     148: invokevirtual #309                // Method com/virtual/ssv/server/user/LoginInfo.getOrgId:()Ljava/lang/Long;
     151: invokevirtual #310                // Method com/virtual/ssv/server/rs/client/entity/RsOperateLog.setOrgId:(Ljava/lang/Long;)V
     154: aload         9
     156: aload_3
     157: invokevirtual #311                // Method com/virtual/ssv/server/user/LoginInfo.getLoginIp:()Ljava/lang/String;
     160: invokevirtual #312                // Method com/virtual/ssv/server/rs/client/entity/RsOperateLog.setAddress:(Ljava/lang/String;)V
     163: aload         9
     165: iconst_1
     166: invokestatic  #162                // Method java/lang/Integer.valueOf:(I)Ljava/lang/Integer;
     169: invokevirtual #314                // Method com/virtual/ssv/server/rs/client/entity/RsOperateLog.setCategory:(Ljava/lang/Integer;)V
     172: aload         9
     174: aload_0
     175: getfield      #165                // Field logSm:Lcom/virtual/common/StringManager;
     178: ldc_w         #393                // String personalTimeout.edit.operation
     181: invokevirtual #124                // Method com/virtual/common/StringManager.getString:(Ljava/lang/String;)Ljava/lang/String;
     184: invokevirtual #316                // Method com/virtual/ssv/server/rs/client/entity/RsOperateLog.setDescription:(Ljava/lang/String;)V
     187: aload         9
     189: aload_3
     190: invokevirtual #317                // Method com/virtual/ssv/server/user/LoginInfo.getLoginName:()Ljava/lang/String;
     193: invokevirtual #318                // Method com/virtual/ssv/server/rs/client/entity/RsOperateLog.setLoginName:(Ljava/lang/String;)V
     196: aload         5
     198: invokevirtual #357                // Method com/virtual/ssv/server/entity/ResultJson.isSuccess:()Z
     201: ifeq          215
     204: aload         9
     206: getstatic     #319                // Field com/virtual/ssv/server/rs/client/entity/RsOperateLog.RESULT_SUCCESS:Ljava/lang/Integer;
     209: invokevirtual #320                // Method com/virtual/ssv/server/rs/client/entity/RsOperateLog.setResult:(Ljava/lang/Integer;)V
     212: goto          233
     215: aload         9
     217: getstatic     #360                // Field com/virtual/ssv/server/rs/client/entity/RsOperateLog.RESULT_FAILURE:Ljava/lang/Integer;
     220: invokevirtual #320                // Method com/virtual/ssv/server/rs/client/entity/RsOperateLog.setResult:(Ljava/lang/Integer;)V
     223: aload         9
     225: aload         5
     227: invokevirtual #358                // Method com/virtual/ssv/server/entity/ResultJson.getMessage:()Ljava/lang/String;
     230: invokevirtual #359                // Method com/virtual/ssv/server/rs/client/entity/RsOperateLog.setFailureReason:(Ljava/lang/String;)V
     233: aload         9
     235: aload_3
     236: invokevirtual #268                // Method com/virtual/ssv/server/user/LoginInfo.getUserName:()Ljava/lang/String;
     239: invokevirtual #321                // Method com/virtual/ssv/server/rs/client/entity/RsOperateLog.setUserName:(Ljava/lang/String;)V
     242: aload         9
     244: aload         4
     246: invokevirtual #322                // Method com/virtual/ssv/server/rs/client/entity/RsOperateLog.setStartTime:(Ljava/util/Date;)V
     249: aload         9
     251: aload         8
     253: invokevirtual #323                // Method com/virtual/ssv/server/rs/client/entity/RsOperateLog.setEndTime:(Ljava/util/Date;)V
     256: aload_0
     257: getfield      #1                  // Field reqHandle:Lcom/virtual/ssv/server/rs/client/RequestHandle;
     260: aload         9
     262: invokevirtual #324                // Method com/virtual/ssv/server/rs/client/RequestHandle.addUserLog:(Lcom/virtual/ssv/server/rs/client/entity/RsOperateLog;)Ljava/lang/Long;
     265: pop
     266: goto          278
     269: astore        6
     271: aload         6
     273: aload         5
     275: invokestatic  #175                // Method com/virtual/ssv/server/ServerUtils.handleException:(Ljava/lang/Exception;Lcom/virtual/ssv/server/entity/ResultJson;)V
     278: aload_0
     279: aload_2
     280: aload_0
     281: getfield      #85                 // Field filterJson:Lcom/google/gson/Gson;
     284: aload         5
     286: invokevirtual #86                 // Method com/google/gson/Gson.toJson:(Ljava/lang/Object;)Ljava/lang/String;
     289: invokevirtual #87                 // Method write:(Ljavax/servlet/http/HttpServletResponse;Ljava/lang/String;)V
     292: return
    Exception table:
       from    to  target type
          18   266   269   Class java/lang/Exception

  private void saveTheme(javax.servlet.http.HttpServletRequest, javax.servlet.http.HttpServletResponse, com.virtual.ssv.server.user.LoginInfo);
    Code:
       0: new           #207                // class java/util/Date
       3: dup
       4: invokespecial #208                // Method java/util/Date."<init>":()V
       7: astore        4
       9: new           #72                 // class com/virtual/ssv/server/entity/ResultJson
      12: dup
      13: invokespecial #73                 // Method com/virtual/ssv/server/entity/ResultJson."<init>":()V
      16: astore        5
      18: aload_1
      19: ldc_w         #394                // String theme
      22: invokeinterface #29,  2           // InterfaceMethod javax/servlet/http/HttpServletRequest.getParameter:(Ljava/lang/String;)Ljava/lang/String;
      27: astore        6
      29: new           #368                // class com/virtual/ssv/server/rs/client/entity/UserSetting
      32: dup
      33: invokespecial #369                // Method com/virtual/ssv/server/rs/client/entity/UserSetting."<init>":()V
      36: astore        7
      38: aload         7
      40: aload_3
      41: invokevirtual #253                // Method com/virtual/ssv/server/user/LoginInfo.getId:()Ljava/lang/Long;
      44: invokevirtual #370                // Method com/virtual/ssv/server/rs/client/entity/UserSetting.setUserId:(Ljava/lang/Long;)V
      47: aload         7
      49: aload         6
      51: invokevirtual #395                // Method com/virtual/ssv/server/rs/client/entity/UserSetting.setTheme:(Ljava/lang/String;)V
      54: aload_0
      55: getfield      #1                  // Field reqHandle:Lcom/virtual/ssv/server/rs/client/RequestHandle;
      58: aload         7
      60: aload_3
      61: invokevirtual #253                // Method com/virtual/ssv/server/user/LoginInfo.getId:()Ljava/lang/Long;
      64: aload_3
      65: invokevirtual #268                // Method com/virtual/ssv/server/user/LoginInfo.getUserName:()Ljava/lang/String;
      68: invokevirtual #388                // Method com/virtual/ssv/server/rs/client/RequestHandle.saveOrUpdateUserSetting:(Lcom/virtual/ssv/server/rs/client/entity/UserSetting;Ljava/lang/Long;Ljava/lang/String;)Lcom/virtual/ssv/server/entity/ResultJson;
      71: astore        5
      73: new           #207                // class java/util/Date
      76: dup
      77: invokespecial #208                // Method java/util/Date."<init>":()V
      80: astore        8
      82: new           #306                // class com/virtual/ssv/server/rs/client/entity/RsOperateLog
      85: dup
      86: invokespecial #307                // Method com/virtual/ssv/server/rs/client/entity/RsOperateLog."<init>":()V
      89: astore        9
      91: aload         9
      93: aload_3
      94: invokevirtual #253                // Method com/virtual/ssv/server/user/LoginInfo.getId:()Ljava/lang/Long;
      97: invokevirtual #308                // Method com/virtual/ssv/server/rs/client/entity/RsOperateLog.setUserId:(Ljava/lang/Long;)V
     100: aload         9
     102: aload_3
     103: invokevirtual #309                // Method com/virtual/ssv/server/user/LoginInfo.getOrgId:()Ljava/lang/Long;
     106: invokevirtual #310                // Method com/virtual/ssv/server/rs/client/entity/RsOperateLog.setOrgId:(Ljava/lang/Long;)V
     109: aload         9
     111: aload_3
     112: invokevirtual #311                // Method com/virtual/ssv/server/user/LoginInfo.getLoginIp:()Ljava/lang/String;
     115: invokevirtual #312                // Method com/virtual/ssv/server/rs/client/entity/RsOperateLog.setAddress:(Ljava/lang/String;)V
     118: aload         9
     120: iconst_1
     121: invokestatic  #162                // Method java/lang/Integer.valueOf:(I)Ljava/lang/Integer;
     124: invokevirtual #314                // Method com/virtual/ssv/server/rs/client/entity/RsOperateLog.setCategory:(Ljava/lang/Integer;)V
     127: aload         9
     129: getstatic     #122                // Field strMng:Lcom/virtual/common/StringManager;
     132: ldc_w         #396                // String updateTheme.successMsg
     135: invokevirtual #124                // Method com/virtual/common/StringManager.getString:(Ljava/lang/String;)Ljava/lang/String;
     138: invokevirtual #316                // Method com/virtual/ssv/server/rs/client/entity/RsOperateLog.setDescription:(Ljava/lang/String;)V
     141: aload         9
     143: aload_3
     144: invokevirtual #317                // Method com/virtual/ssv/server/user/LoginInfo.getLoginName:()Ljava/lang/String;
     147: invokevirtual #318                // Method com/virtual/ssv/server/rs/client/entity/RsOperateLog.setLoginName:(Ljava/lang/String;)V
     150: aload         5
     152: invokevirtual #357                // Method com/virtual/ssv/server/entity/ResultJson.isSuccess:()Z
     155: ifeq          217
     158: aload         9
     160: getstatic     #319                // Field com/virtual/ssv/server/rs/client/entity/RsOperateLog.RESULT_SUCCESS:Ljava/lang/Integer;
     163: invokevirtual #320                // Method com/virtual/ssv/server/rs/client/entity/RsOperateLog.setResult:(Ljava/lang/Integer;)V
     166: aload         5
     168: getstatic     #122                // Field strMng:Lcom/virtual/common/StringManager;
     171: ldc_w         #331                // String success
     174: invokevirtual #124                // Method com/virtual/common/StringManager.getString:(Ljava/lang/String;)Ljava/lang/String;
     177: invokevirtual #397                // Method com/virtual/ssv/server/entity/ResultJson.setTitle:(Ljava/lang/String;)V
     180: aload         5
     182: getstatic     #122                // Field strMng:Lcom/virtual/common/StringManager;
     185: ldc_w         #396                // String updateTheme.successMsg
     188: invokevirtual #124                // Method com/virtual/common/StringManager.getString:(Ljava/lang/String;)Ljava/lang/String;
     191: invokevirtual #398                // Method com/virtual/ssv/server/entity/ResultJson.setMessage:(Ljava/lang/String;)V
     194: aload_1
     195: invokeinterface #49,  1           // InterfaceMethod javax/servlet/http/HttpServletRequest.getSession:()Ljavax/servlet/http/HttpSession;
     200: astore        10
     202: aload         10
     204: ldc_w         #256                // String userTheme
     207: aload         6
     209: invokeinterface #163,  3          // InterfaceMethod javax/servlet/http/HttpSession.setAttribute:(Ljava/lang/String;Ljava/lang/Object;)V
     214: goto          235
     217: aload         9
     219: getstatic     #360                // Field com/virtual/ssv/server/rs/client/entity/RsOperateLog.RESULT_FAILURE:Ljava/lang/Integer;
     222: invokevirtual #320                // Method com/virtual/ssv/server/rs/client/entity/RsOperateLog.setResult:(Ljava/lang/Integer;)V
     225: aload         9
     227: aload         5
     229: invokevirtual #358                // Method com/virtual/ssv/server/entity/ResultJson.getMessage:()Ljava/lang/String;
     232: invokevirtual #359                // Method com/virtual/ssv/server/rs/client/entity/RsOperateLog.setFailureReason:(Ljava/lang/String;)V
     235: aload         9
     237: aload_3
     238: invokevirtual #268                // Method com/virtual/ssv/server/user/LoginInfo.getUserName:()Ljava/lang/String;
     241: invokevirtual #321                // Method com/virtual/ssv/server/rs/client/entity/RsOperateLog.setUserName:(Ljava/lang/String;)V
     244: aload         9
     246: aload         4
     248: invokevirtual #322                // Method com/virtual/ssv/server/rs/client/entity/RsOperateLog.setStartTime:(Ljava/util/Date;)V
     251: aload         9
     253: aload         8
     255: invokevirtual #323                // Method com/virtual/ssv/server/rs/client/entity/RsOperateLog.setEndTime:(Ljava/util/Date;)V
     258: aload_0
     259: getfield      #1                  // Field reqHandle:Lcom/virtual/ssv/server/rs/client/RequestHandle;
     262: aload         9
     264: invokevirtual #324                // Method com/virtual/ssv/server/rs/client/RequestHandle.addUserLog:(Lcom/virtual/ssv/server/rs/client/entity/RsOperateLog;)Ljava/lang/Long;
     267: pop
     268: aload_0
     269: aload_2
     270: aload_0
     271: getfield      #85                 // Field filterJson:Lcom/google/gson/Gson;
     274: aload         5
     276: invokevirtual #86                 // Method com/google/gson/Gson.toJson:(Ljava/lang/Object;)Ljava/lang/String;
     279: invokevirtual #87                 // Method write:(Ljavax/servlet/http/HttpServletResponse;Ljava/lang/String;)V
     282: goto          308
     285: astore        6
     287: aload         6
     289: aload         5
     291: invokestatic  #175                // Method com/virtual/ssv/server/ServerUtils.handleException:(Ljava/lang/Exception;Lcom/virtual/ssv/server/entity/ResultJson;)V
     294: aload_0
     295: aload_2
     296: aload_0
     297: getfield      #85                 // Field filterJson:Lcom/google/gson/Gson;
     300: aload         5
     302: invokevirtual #86                 // Method com/google/gson/Gson.toJson:(Ljava/lang/Object;)Ljava/lang/String;
     305: invokevirtual #87                 // Method write:(Ljavax/servlet/http/HttpServletResponse;Ljava/lang/String;)V
     308: return
    Exception table:
       from    to  target type
          18   282   285   Class java/lang/Exception

  private void isOldPassword(javax.servlet.http.HttpServletRequest, javax.servlet.http.HttpServletResponse, com.virtual.ssv.server.user.LoginInfo);
    Code:
       0: new           #191                // class com/virtual/ssv/server/rs/client/entity/RsUser
       3: dup
       4: invokespecial #192                // Method com/virtual/ssv/server/rs/client/entity/RsUser."<init>":()V
       7: astore        4
       9: aload_1
      10: ldc           #151                // String password
      12: invokeinterface #29,  2           // InterfaceMethod javax/servlet/http/HttpServletRequest.getParameter:(Ljava/lang/String;)Ljava/lang/String;
      17: astore        5
      19: aconst_null
      20: astore        6
      22: aload_0
      23: getfield      #1                  // Field reqHandle:Lcom/virtual/ssv/server/rs/client/RequestHandle;
      26: aload_3
      27: invokevirtual #253                // Method com/virtual/ssv/server/user/LoginInfo.getId:()Ljava/lang/Long;
      30: invokevirtual #338                // Method com/virtual/ssv/server/rs/client/RequestHandle.getUser:(Ljava/lang/Long;)Lcom/virtual/ssv/server/rs/client/entity/RsUser;
      33: astore        4
      35: aload         5
      37: ifnull        60
      40: aload         5
      42: aload         4
      44: invokevirtual #399                // Method com/virtual/ssv/server/rs/client/entity/RsUser.getPassword:()Ljava/lang/String;
      47: invokevirtual #31                 // Method java/lang/String.equals:(Ljava/lang/Object;)Z
      50: ifeq          60
      53: ldc           #211                // String true
      55: astore        6
      57: goto          65
      60: ldc_w         #326                // String false
      63: astore        6
      65: aload_0
      66: aload_2
      67: aload_0
      68: getfield      #85                 // Field filterJson:Lcom/google/gson/Gson;
      71: aload         6
      73: invokevirtual #86                 // Method com/google/gson/Gson.toJson:(Ljava/lang/Object;)Ljava/lang/String;
      76: invokevirtual #87                 // Method write:(Ljavax/servlet/http/HttpServletResponse;Ljava/lang/String;)V
      79: goto          94
      82: astore        7
      84: getstatic     #79                 // Field log:Lorg/apache/commons/logging/Log;
      87: aload         7
      89: invokeinterface #80,  2           // InterfaceMethod org/apache/commons/logging/Log.error:(Ljava/lang/Object;)V
      94: return
    Exception table:
       from    to  target type
          22    79    82   Class java/lang/Exception

  private void checkAndSaveHttpChanges(javax.servlet.http.HttpServletRequest);
    Code:
       0: invokestatic  #400                // Method com/virtual/ssv/server/rs/client/RequestHandleParameter.getProtocol:()Ljava/lang/String;
       3: ifnull        70
       6: invokestatic  #400                // Method com/virtual/ssv/server/rs/client/RequestHandleParameter.getProtocol:()Ljava/lang/String;
       9: aload_1
      10: invokeinterface #401,  1          // InterfaceMethod javax/servlet/http/HttpServletRequest.getScheme:()Ljava/lang/String;
      15: invokevirtual #31                 // Method java/lang/String.equals:(Ljava/lang/Object;)Z
      18: ifne          70
      21: aload_0
      22: getfield      #402                // Field httpManager:Lcom/virtual/ssv/server/rs/client/HttpConnectionManager;
      25: aload_1
      26: invokeinterface #401,  1          // InterfaceMethod javax/servlet/http/HttpServletRequest.getScheme:()Ljava/lang/String;
      31: invokestatic  #403                // Method com/virtual/ssv/server/rs/client/RequestHandleParameter.getServerIp:()Ljava/lang/String;
      34: aload_1
      35: invokeinterface #404,  1          // InterfaceMethod javax/servlet/http/HttpServletRequest.getServerPort:()I
      40: invokestatic  #405                // Method com/virtual/ssv/server/rs/client/RequestHandleParameter.getLoginName:()Ljava/lang/String;
      43: invokestatic  #406                // Method com/virtual/ssv/server/rs/client/RequestHandleParameter.getPassword:()Ljava/lang/String;
      46: invokevirtual #407                // Method com/virtual/ssv/server/rs/client/HttpConnectionManager.setLoginConfig:(Ljava/lang/String;Ljava/lang/String;ILjava/lang/String;Ljava/lang/String;)V
      49: aload_1
      50: invokeinterface #401,  1          // InterfaceMethod javax/servlet/http/HttpServletRequest.getScheme:()Ljava/lang/String;
      55: invokestatic  #408                // Method com/virtual/ssv/server/rs/client/RequestHandleParameter.setProtocol:(Ljava/lang/String;)V
      58: aload_1
      59: invokeinterface #404,  1          // InterfaceMethod javax/servlet/http/HttpServletRequest.getServerPort:()I
      64: invokestatic  #409                // Method java/lang/String.valueOf:(I)Ljava/lang/String;
      67: invokestatic  #410                // Method com/virtual/ssv/server/rs/client/RequestHandleParameter.setServerPort:(Ljava/lang/String;)V
      70: return

  private void test(javax.servlet.http.HttpServletRequest, javax.servlet.http.HttpServletResponse);
    Code:
       0: ldc_w         #411                // String SUCCESS
       3: astore_3
       4: aload_0
       5: aload_2
       6: aload_0
       7: getfield      #85                 // Field filterJson:Lcom/google/gson/Gson;
      10: aload_3
      11: invokevirtual #86                 // Method com/google/gson/Gson.toJson:(Ljava/lang/Object;)Ljava/lang/String;
      14: invokevirtual #87                 // Method write:(Ljavax/servlet/http/HttpServletResponse;Ljava/lang/String;)V
      17: return

  static com.virtual.ssv.server.rs.client.RequestHandle access$000(com.virtual.ssv.server.user.LoginServlet);
    Code:
       0: aload_0
       1: getfield      #1                  // Field reqHandle:Lcom/virtual/ssv/server/rs/client/RequestHandle;
       4: areturn

  static {};
    Code:
       0: ldc_w         #412                // String com.virtual.common
       3: invokestatic  #413                // Method com/virtual/common/StringManager.getManager:(Ljava/lang/String;)Lcom/virtual/common/StringManager;
       6: putstatic     #122                // Field strMng:Lcom/virtual/common/StringManager;
       9: ldc_w         #414                // String LOGIN_SERVLET_IN_CONTEXT
      12: putstatic     #13                 // Field ATTR_LOGIN_SERVLET_IN_CONTEXT:Ljava/lang/String;
      15: return
}
