Compiled from "AlarmServlet.java"
public class com.virtual.ssv.server.alarm.AlarmServlet extends com.virtual.ssv.server.BaseServlet {
  private static final long serialVersionUID;

  public com.virtual.ssv.server.alarm.AlarmServlet();
    Code:
       0: aload_0
       1: invokespecial #1                  // Method com/virtual/ssv/server/BaseServlet."<init>":()V
       4: return

  protected void doPost(javax.servlet.http.HttpServletRequest, javax.servlet.http.HttpServletResponse) throws javax.servlet.ServletException, java.io.IOException;
    Code:
       0: aload_0
       1: aload_1
       2: aload_2
       3: invokevirtual #2                  // Method doGet:(Ljavax/servlet/http/HttpServletRequest;Ljavax/servlet/http/HttpServletResponse;)V
       6: return

  protected void doGet(javax.servlet.http.HttpServletRequest, javax.servlet.http.HttpServletResponse) throws javax.servlet.ServletException, java.io.IOException;
    Code:
       0: aload_1
       1: invokeinterface #3,  1            // InterfaceMethod javax/servlet/http/HttpServletRequest.getSession:()Ljavax/servlet/http/HttpSession;
       6: astore_3
       7: aload_3
       8: ldc           #4                  // String loginInfo
      10: invokeinterface #5,  2            // InterfaceMethod javax/servlet/http/HttpSession.getAttribute:(Ljava/lang/String;)Ljava/lang/Object;
      15: checkcast     #6                  // class com/virtual/ssv/server/user/LoginInfo
      18: astore        4
      20: aload         4
      22: ifnull        206
      25: aload_0
      26: aload_1
      27: aload_2
      28: invokevirtual #7                  // Method checkUserState:(Ljavax/servlet/http/HttpServletRequest;Ljavax/servlet/http/HttpServletResponse;)V
      31: aload_1
      32: ldc           #8                  // String way
      34: invokeinterface #9,  2            // InterfaceMethod javax/servlet/http/HttpServletRequest.getParameter:(Ljava/lang/String;)Ljava/lang/String;
      39: astore        5
      41: ldc           #10                 // String list
      43: aload         5
      45: invokevirtual #11                 // Method java/lang/String.equals:(Ljava/lang/Object;)Z
      48: ifeq          62
      51: aload_0
      52: aload_1
      53: aload_2
      54: aload         4
      56: invokespecial #12                 // Method queryAlarmInfoList:(Ljavax/servlet/http/HttpServletRequest;Ljavax/servlet/http/HttpServletResponse;Lcom/virtual/ssv/server/user/LoginInfo;)V
      59: goto          206
      62: ldc           #13                 // String queryAlarmState
      64: aload         5
      66: invokevirtual #11                 // Method java/lang/String.equals:(Ljava/lang/Object;)Z
      69: ifeq          83
      72: aload_0
      73: aload_1
      74: aload_2
      75: aload         4
      77: invokespecial #14                 // Method queryAlarmStrategy:(Ljavax/servlet/http/HttpServletRequest;Ljavax/servlet/http/HttpServletResponse;Lcom/virtual/ssv/server/user/LoginInfo;)V
      80: goto          206
      83: ldc           #15                 // String start
      85: aload         5
      87: invokevirtual #11                 // Method java/lang/String.equals:(Ljava/lang/Object;)Z
      90: ifeq          104
      93: aload_0
      94: aload_1
      95: aload_2
      96: aload         4
      98: invokespecial #16                 // Method startAlarm:(Ljavax/servlet/http/HttpServletRequest;Ljavax/servlet/http/HttpServletResponse;Lcom/virtual/ssv/server/user/LoginInfo;)V
     101: goto          206
     104: ldc           #17                 // String close
     106: aload         5
     108: invokevirtual #11                 // Method java/lang/String.equals:(Ljava/lang/Object;)Z
     111: ifeq          125
     114: aload_0
     115: aload_1
     116: aload_2
     117: aload         4
     119: invokespecial #18                 // Method closeAlarm:(Ljavax/servlet/http/HttpServletRequest;Ljavax/servlet/http/HttpServletResponse;Lcom/virtual/ssv/server/user/LoginInfo;)V
     122: goto          206
     125: ldc           #19                 // String removeAlarmVm
     127: aload         5
     129: invokevirtual #11                 // Method java/lang/String.equals:(Ljava/lang/Object;)Z
     132: ifeq          146
     135: aload_0
     136: aload_1
     137: aload_2
     138: aload         4
     140: invokespecial #20                 // Method removeAlarmVm:(Ljavax/servlet/http/HttpServletRequest;Ljavax/servlet/http/HttpServletResponse;Lcom/virtual/ssv/server/user/LoginInfo;)V
     143: goto          206
     146: ldc           #21                 // String addAlarmVm
     148: aload         5
     150: invokevirtual #11                 // Method java/lang/String.equals:(Ljava/lang/Object;)Z
     153: ifeq          167
     156: aload_0
     157: aload_1
     158: aload_2
     159: aload         4
     161: invokespecial #22                 // Method addAlarmVm:(Ljavax/servlet/http/HttpServletRequest;Ljavax/servlet/http/HttpServletResponse;Lcom/virtual/ssv/server/user/LoginInfo;)V
     164: goto          206
     167: ldc           #23                 // String unselect
     169: aload         5
     171: invokevirtual #11                 // Method java/lang/String.equals:(Ljava/lang/Object;)Z
     174: ifeq          188
     177: aload_0
     178: aload_1
     179: aload_2
     180: aload         4
     182: invokespecial #24                 // Method unselectedAlarmDomains:(Ljavax/servlet/http/HttpServletRequest;Ljavax/servlet/http/HttpServletResponse;Lcom/virtual/ssv/server/user/LoginInfo;)V
     185: goto          206
     188: ldc           #25                 // String select
     190: aload         5
     192: invokevirtual #11                 // Method java/lang/String.equals:(Ljava/lang/Object;)Z
     195: ifeq          206
     198: aload_0
     199: aload_1
     200: aload_2
     201: aload         4
     203: invokespecial #26                 // Method selectedAlarmDomains:(Ljavax/servlet/http/HttpServletRequest;Ljavax/servlet/http/HttpServletResponse;Lcom/virtual/ssv/server/user/LoginInfo;)V
     206: return

  private void queryAlarmInfoList(javax.servlet.http.HttpServletRequest, javax.servlet.http.HttpServletResponse, com.virtual.ssv.server.user.LoginInfo);
    Code:
       0: aload_3
       1: invokevirtual #27                 // Method com/virtual/ssv/server/user/LoginInfo.getId:()Ljava/lang/Long;
       4: astore        4
       6: aload_1
       7: ldc           #28                 // String domainId
       9: invokeinterface #9,  2            // InterfaceMethod javax/servlet/http/HttpServletRequest.getParameter:(Ljava/lang/String;)Ljava/lang/String;
      14: astore        5
      16: aload_1
      17: ldc           #29                 // String domainTitle
      19: invokeinterface #9,  2            // InterfaceMethod javax/servlet/http/HttpServletRequest.getParameter:(Ljava/lang/String;)Ljava/lang/String;
      24: astore        6
      26: aload_1
      27: ldc           #30                 // String category
      29: invokeinterface #9,  2            // InterfaceMethod javax/servlet/http/HttpServletRequest.getParameter:(Ljava/lang/String;)Ljava/lang/String;
      34: astore        7
      36: aload_1
      37: ldc           #31                 // String level
      39: invokeinterface #9,  2            // InterfaceMethod javax/servlet/http/HttpServletRequest.getParameter:(Ljava/lang/String;)Ljava/lang/String;
      44: astore        8
      46: aload         5
      48: ifnull        82
      51: ldc           #32                 // String [1-9]\\d*
      53: astore        9
      55: aload         9
      57: invokestatic  #33                 // Method java/util/regex/Pattern.compile:(Ljava/lang/String;)Ljava/util/regex/Pattern;
      60: astore        10
      62: aload         10
      64: aload         5
      66: invokevirtual #34                 // Method java/util/regex/Pattern.matcher:(Ljava/lang/CharSequence;)Ljava/util/regex/Matcher;
      69: astore        11
      71: aload         11
      73: invokevirtual #35                 // Method java/util/regex/Matcher.matches:()Z
      76: ifne          82
      79: aconst_null
      80: astore        5
      82: new           #36                 // class com/virtual/ssv/server/entity/CommonListJson
      85: dup
      86: invokespecial #37                 // Method com/virtual/ssv/server/entity/CommonListJson."<init>":()V
      89: astore        9
      91: aload_0
      92: aload_1
      93: invokevirtual #38                 // Method getPagingConfig:(Ljavax/servlet/http/HttpServletRequest;)Lcom/virtual/ssv/server/entity/PagingLoadConfig;
      96: astore        10
      98: aload         10
     100: invokevirtual #39                 // Method com/virtual/ssv/server/entity/PagingLoadConfig.getSortField:()Ljava/lang/String;
     103: invokestatic  #40                 // Method org/apache/commons/lang/StringUtils.isEmpty:(Ljava/lang/String;)Z
     106: ifeq          123
     109: aload         10
     111: ldc           #41                 // String id
     113: invokevirtual #42                 // Method com/virtual/ssv/server/entity/PagingLoadConfig.setSortField:(Ljava/lang/String;)V
     116: aload         10
     118: ldc           #43                 // String Desc
     120: invokevirtual #44                 // Method com/virtual/ssv/server/entity/PagingLoadConfig.setSortDir:(Ljava/lang/String;)V
     123: aload_0
     124: getfield      #45                 // Field reqHandle:Lcom/virtual/ssv/server/rs/client/RequestHandle;
     127: aload         10
     129: aload         4
     131: aload         5
     133: aload         7
     135: aload         8
     137: aload         6
     139: invokevirtual #46                 // Method com/virtual/ssv/server/rs/client/RequestHandle.getAlarmInfoList:(Lcom/virtual/ssv/server/entity/PagingLoadConfig;Ljava/lang/Long;Ljava/lang/String;Ljava/lang/String;Ljava/lang/String;Ljava/lang/String;)Lcom/virtual/ssv/server/entity/CommonListJson;
     142: astore        9
     144: aload_0
     145: aload_2
     146: aload_0
     147: getfield      #47                 // Field gson:Lcom/google/gson/Gson;
     150: aload         9
     152: invokevirtual #48                 // Method com/google/gson/Gson.toJson:(Ljava/lang/Object;)Ljava/lang/String;
     155: invokevirtual #49                 // Method write:(Ljavax/servlet/http/HttpServletResponse;Ljava/lang/String;)V
     158: goto          274
     161: astore        11
     163: aload         9
     165: aload_0
     166: getfield      #51                 // Field logSm:Lcom/virtual/common/StringManager;
     169: ldc           #52                 // String operError
     171: invokevirtual #53                 // Method com/virtual/common/StringManager.getString:(Ljava/lang/String;)Ljava/lang/String;
     174: invokevirtual #54                 // Method com/virtual/ssv/server/entity/CommonListJson.setTitle:(Ljava/lang/String;)V
     177: aload         11
     179: invokevirtual #55                 // Method com/virtual/common/AppException.getErrorCode:()I
     182: bipush        102
     184: if_icmpne     200
     187: aload         9
     189: bipush        102
     191: invokestatic  #57                 // Method com/virtual/common/ErrorCodes.getErrorMessage:(I)Ljava/lang/String;
     194: invokevirtual #58                 // Method com/virtual/ssv/server/entity/CommonListJson.setMessage:(Ljava/lang/String;)V
     197: goto          256
     200: aload         11
     202: invokevirtual #55                 // Method com/virtual/common/AppException.getErrorCode:()I
     205: bipush        103
     207: if_icmpne     223
     210: aload         9
     212: bipush        103
     214: invokestatic  #57                 // Method com/virtual/common/ErrorCodes.getErrorMessage:(I)Ljava/lang/String;
     217: invokevirtual #58                 // Method com/virtual/ssv/server/entity/CommonListJson.setMessage:(Ljava/lang/String;)V
     220: goto          256
     223: aload         11
     225: invokevirtual #55                 // Method com/virtual/common/AppException.getErrorCode:()I
     228: bipush        11
     230: if_icmpne     246
     233: aload         9
     235: bipush        11
     237: invokestatic  #57                 // Method com/virtual/common/ErrorCodes.getErrorMessage:(I)Ljava/lang/String;
     240: invokevirtual #58                 // Method com/virtual/ssv/server/entity/CommonListJson.setMessage:(Ljava/lang/String;)V
     243: goto          256
     246: aload         9
     248: aload         11
     250: invokevirtual #59                 // Method com/virtual/common/AppException.getMessage:()Ljava/lang/String;
     253: invokevirtual #58                 // Method com/virtual/ssv/server/entity/CommonListJson.setMessage:(Ljava/lang/String;)V
     256: aload         9
     258: iconst_0
     259: invokevirtual #60                 // Method com/virtual/ssv/server/entity/CommonListJson.setState:(I)V
     262: aload         9
     264: new           #61                 // class java/util/ArrayList
     267: dup
     268: invokespecial #62                 // Method java/util/ArrayList."<init>":()V
     271: invokevirtual #63                 // Method com/virtual/ssv/server/entity/CommonListJson.setRows:(Ljava/util/List;)V
     274: aload_0
     275: aload_2
     276: aload_0
     277: getfield      #47                 // Field gson:Lcom/google/gson/Gson;
     280: aload         9
     282: invokevirtual #48                 // Method com/google/gson/Gson.toJson:(Ljava/lang/Object;)Ljava/lang/String;
     285: invokevirtual #49                 // Method write:(Ljavax/servlet/http/HttpServletResponse;Ljava/lang/String;)V
     288: return
    Exception table:
       from    to  target type
         123   158   161   Class com/virtual/common/AppException

  private void queryAlarmStrategy(javax.servlet.http.HttpServletRequest, javax.servlet.http.HttpServletResponse, com.virtual.ssv.server.user.LoginInfo);
    Code:
       0: new           #64                 // class com/virtual/ssv/server/entity/ResultJson
       3: dup
       4: invokespecial #65                 // Method com/virtual/ssv/server/entity/ResultJson."<init>":()V
       7: astore        4
       9: aload_3
      10: invokevirtual #27                 // Method com/virtual/ssv/server/user/LoginInfo.getId:()Ljava/lang/Long;
      13: astore        5
      15: aload_0
      16: getfield      #45                 // Field reqHandle:Lcom/virtual/ssv/server/rs/client/RequestHandle;
      19: aload         5
      21: invokevirtual #66                 // Method com/virtual/ssv/server/rs/client/RequestHandle.queryAlarmStrategy:(Ljava/lang/Long;)Lcom/virtual/ssv/server/rs/client/entity/RsEventStrategy;
      24: astore        6
      26: aload_0
      27: getfield      #47                 // Field gson:Lcom/google/gson/Gson;
      30: aload         6
      32: invokevirtual #48                 // Method com/google/gson/Gson.toJson:(Ljava/lang/Object;)Ljava/lang/String;
      35: astore        7
      37: aload_0
      38: aload_2
      39: aload         7
      41: invokevirtual #49                 // Method write:(Ljavax/servlet/http/HttpServletResponse;Ljava/lang/String;)V
      44: goto          142
      47: astore        5
      49: aload         5
      51: invokevirtual #55                 // Method com/virtual/common/AppException.getErrorCode:()I
      54: bipush        102
      56: if_icmpne     72
      59: aload         4
      61: bipush        102
      63: invokestatic  #57                 // Method com/virtual/common/ErrorCodes.getErrorMessage:(I)Ljava/lang/String;
      66: invokevirtual #67                 // Method com/virtual/ssv/server/entity/ResultJson.setErrorMsg:(Ljava/lang/String;)V
      69: goto          128
      72: aload         5
      74: invokevirtual #55                 // Method com/virtual/common/AppException.getErrorCode:()I
      77: bipush        103
      79: if_icmpne     95
      82: aload         4
      84: bipush        103
      86: invokestatic  #57                 // Method com/virtual/common/ErrorCodes.getErrorMessage:(I)Ljava/lang/String;
      89: invokevirtual #67                 // Method com/virtual/ssv/server/entity/ResultJson.setErrorMsg:(Ljava/lang/String;)V
      92: goto          128
      95: aload         5
      97: invokevirtual #55                 // Method com/virtual/common/AppException.getErrorCode:()I
     100: bipush        11
     102: if_icmpne     118
     105: aload         4
     107: bipush        11
     109: invokestatic  #57                 // Method com/virtual/common/ErrorCodes.getErrorMessage:(I)Ljava/lang/String;
     112: invokevirtual #67                 // Method com/virtual/ssv/server/entity/ResultJson.setErrorMsg:(Ljava/lang/String;)V
     115: goto          128
     118: aload         4
     120: aload         5
     122: invokevirtual #59                 // Method com/virtual/common/AppException.getMessage:()Ljava/lang/String;
     125: invokevirtual #67                 // Method com/virtual/ssv/server/entity/ResultJson.setErrorMsg:(Ljava/lang/String;)V
     128: aload_0
     129: aload_2
     130: aload_0
     131: getfield      #68                 // Field filterJson:Lcom/google/gson/Gson;
     134: aload         4
     136: invokevirtual #48                 // Method com/google/gson/Gson.toJson:(Ljava/lang/Object;)Ljava/lang/String;
     139: invokevirtual #49                 // Method write:(Ljavax/servlet/http/HttpServletResponse;Ljava/lang/String;)V
     142: return
    Exception table:
       from    to  target type
           9    44    47   Class com/virtual/common/AppException

  private void startAlarm(javax.servlet.http.HttpServletRequest, javax.servlet.http.HttpServletResponse, com.virtual.ssv.server.user.LoginInfo);
    Code:
       0: new           #69                 // class java/util/Date
       3: dup
       4: invokespecial #70                 // Method java/util/Date."<init>":()V
       7: astore        4
       9: new           #64                 // class com/virtual/ssv/server/entity/ResultJson
      12: dup
      13: invokespecial #65                 // Method com/virtual/ssv/server/entity/ResultJson."<init>":()V
      16: astore        5
      18: aload_1
      19: ldc           #71                 // String strategyId
      21: invokeinterface #9,  2            // InterfaceMethod javax/servlet/http/HttpServletRequest.getParameter:(Ljava/lang/String;)Ljava/lang/String;
      26: astore        6
      28: aload_3
      29: invokevirtual #27                 // Method com/virtual/ssv/server/user/LoginInfo.getId:()Ljava/lang/Long;
      32: astore        7
      34: aload_0
      35: getfield      #45                 // Field reqHandle:Lcom/virtual/ssv/server/rs/client/RequestHandle;
      38: aload         6
      40: invokestatic  #72                 // Method java/lang/Long.parseLong:(Ljava/lang/String;)J
      43: invokestatic  #73                 // Method java/lang/Long.valueOf:(J)Ljava/lang/Long;
      46: aload         7
      48: invokevirtual #74                 // Method com/virtual/ssv/server/rs/client/RequestHandle.startAlarm:(Ljava/lang/Long;Ljava/lang/Long;)Lcom/virtual/ssv/server/entity/ResultJson;
      51: astore        5
      53: new           #69                 // class java/util/Date
      56: dup
      57: invokespecial #70                 // Method java/util/Date."<init>":()V
      60: astore        8
      62: new           #75                 // class com/virtual/ssv/server/rs/client/entity/RsOperateLog
      65: dup
      66: invokespecial #76                 // Method com/virtual/ssv/server/rs/client/entity/RsOperateLog."<init>":()V
      69: astore        9
      71: aload         9
      73: aload_3
      74: invokevirtual #27                 // Method com/virtual/ssv/server/user/LoginInfo.getId:()Ljava/lang/Long;
      77: invokevirtual #77                 // Method com/virtual/ssv/server/rs/client/entity/RsOperateLog.setUserId:(Ljava/lang/Long;)V
      80: aload         9
      82: aload_3
      83: invokevirtual #78                 // Method com/virtual/ssv/server/user/LoginInfo.getOrgId:()Ljava/lang/Long;
      86: invokevirtual #79                 // Method com/virtual/ssv/server/rs/client/entity/RsOperateLog.setOrgId:(Ljava/lang/Long;)V
      89: aload         9
      91: aload_3
      92: invokevirtual #80                 // Method com/virtual/ssv/server/user/LoginInfo.getLoginName:()Ljava/lang/String;
      95: invokevirtual #81                 // Method com/virtual/ssv/server/rs/client/entity/RsOperateLog.setLoginName:(Ljava/lang/String;)V
      98: aload         9
     100: aload_3
     101: invokevirtual #82                 // Method com/virtual/ssv/server/user/LoginInfo.getUserName:()Ljava/lang/String;
     104: invokevirtual #83                 // Method com/virtual/ssv/server/rs/client/entity/RsOperateLog.setUserName:(Ljava/lang/String;)V
     107: aload         9
     109: aload_3
     110: invokevirtual #84                 // Method com/virtual/ssv/server/user/LoginInfo.getLoginIp:()Ljava/lang/String;
     113: invokevirtual #85                 // Method com/virtual/ssv/server/rs/client/entity/RsOperateLog.setAddress:(Ljava/lang/String;)V
     116: aload         9
     118: bipush        30
     120: invokestatic  #87                 // Method java/lang/Integer.valueOf:(I)Ljava/lang/Integer;
     123: invokevirtual #88                 // Method com/virtual/ssv/server/rs/client/entity/RsOperateLog.setCategory:(Ljava/lang/Integer;)V
     126: aload         9
     128: aload_0
     129: getfield      #51                 // Field logSm:Lcom/virtual/common/StringManager;
     132: ldc           #89                 // String start.alarm
     134: invokevirtual #53                 // Method com/virtual/common/StringManager.getString:(Ljava/lang/String;)Ljava/lang/String;
     137: invokevirtual #90                 // Method com/virtual/ssv/server/rs/client/entity/RsOperateLog.setDescription:(Ljava/lang/String;)V
     140: aload         9
     142: aload         4
     144: invokevirtual #91                 // Method com/virtual/ssv/server/rs/client/entity/RsOperateLog.setStartTime:(Ljava/util/Date;)V
     147: aload         9
     149: aload         8
     151: invokevirtual #92                 // Method com/virtual/ssv/server/rs/client/entity/RsOperateLog.setEndTime:(Ljava/util/Date;)V
     154: aload         5
     156: invokevirtual #93                 // Method com/virtual/ssv/server/entity/ResultJson.getState:()I
     159: iconst_1
     160: if_icmpne     174
     163: aload         9
     165: getstatic     #94                 // Field com/virtual/ssv/server/rs/client/entity/RsOperateLog.RESULT_SUCCESS:Ljava/lang/Integer;
     168: invokevirtual #95                 // Method com/virtual/ssv/server/rs/client/entity/RsOperateLog.setResult:(Ljava/lang/Integer;)V
     171: goto          192
     174: aload         9
     176: getstatic     #96                 // Field com/virtual/ssv/server/rs/client/entity/RsOperateLog.RESULT_FAILURE:Ljava/lang/Integer;
     179: invokevirtual #95                 // Method com/virtual/ssv/server/rs/client/entity/RsOperateLog.setResult:(Ljava/lang/Integer;)V
     182: aload         9
     184: aload         5
     186: invokevirtual #97                 // Method com/virtual/ssv/server/entity/ResultJson.getMessage:()Ljava/lang/String;
     189: invokevirtual #98                 // Method com/virtual/ssv/server/rs/client/entity/RsOperateLog.setFailureReason:(Ljava/lang/String;)V
     192: aload_0
     193: getfield      #45                 // Field reqHandle:Lcom/virtual/ssv/server/rs/client/RequestHandle;
     196: aload         9
     198: invokevirtual #99                 // Method com/virtual/ssv/server/rs/client/RequestHandle.addUserLog:(Lcom/virtual/ssv/server/rs/client/entity/RsOperateLog;)Ljava/lang/Long;
     201: pop
     202: aload_0
     203: getfield      #68                 // Field filterJson:Lcom/google/gson/Gson;
     206: aload         5
     208: invokevirtual #48                 // Method com/google/gson/Gson.toJson:(Ljava/lang/Object;)Ljava/lang/String;
     211: astore        10
     213: aload_0
     214: aload_2
     215: aload         10
     217: invokevirtual #49                 // Method write:(Ljavax/servlet/http/HttpServletResponse;Ljava/lang/String;)V
     220: goto          318
     223: astore        6
     225: aload         6
     227: invokevirtual #55                 // Method com/virtual/common/AppException.getErrorCode:()I
     230: bipush        102
     232: if_icmpne     248
     235: aload         5
     237: bipush        102
     239: invokestatic  #57                 // Method com/virtual/common/ErrorCodes.getErrorMessage:(I)Ljava/lang/String;
     242: invokevirtual #67                 // Method com/virtual/ssv/server/entity/ResultJson.setErrorMsg:(Ljava/lang/String;)V
     245: goto          304
     248: aload         6
     250: invokevirtual #55                 // Method com/virtual/common/AppException.getErrorCode:()I
     253: bipush        103
     255: if_icmpne     271
     258: aload         5
     260: bipush        103
     262: invokestatic  #57                 // Method com/virtual/common/ErrorCodes.getErrorMessage:(I)Ljava/lang/String;
     265: invokevirtual #67                 // Method com/virtual/ssv/server/entity/ResultJson.setErrorMsg:(Ljava/lang/String;)V
     268: goto          304
     271: aload         6
     273: invokevirtual #55                 // Method com/virtual/common/AppException.getErrorCode:()I
     276: bipush        11
     278: if_icmpne     294
     281: aload         5
     283: bipush        11
     285: invokestatic  #57                 // Method com/virtual/common/ErrorCodes.getErrorMessage:(I)Ljava/lang/String;
     288: invokevirtual #67                 // Method com/virtual/ssv/server/entity/ResultJson.setErrorMsg:(Ljava/lang/String;)V
     291: goto          304
     294: aload         5
     296: aload         6
     298: invokevirtual #59                 // Method com/virtual/common/AppException.getMessage:()Ljava/lang/String;
     301: invokevirtual #67                 // Method com/virtual/ssv/server/entity/ResultJson.setErrorMsg:(Ljava/lang/String;)V
     304: aload_0
     305: aload_2
     306: aload_0
     307: getfield      #68                 // Field filterJson:Lcom/google/gson/Gson;
     310: aload         5
     312: invokevirtual #48                 // Method com/google/gson/Gson.toJson:(Ljava/lang/Object;)Ljava/lang/String;
     315: invokevirtual #49                 // Method write:(Ljavax/servlet/http/HttpServletResponse;Ljava/lang/String;)V
     318: return
    Exception table:
       from    to  target type
          18   220   223   Class com/virtual/common/AppException

  private void closeAlarm(javax.servlet.http.HttpServletRequest, javax.servlet.http.HttpServletResponse, com.virtual.ssv.server.user.LoginInfo);
    Code:
       0: new           #69                 // class java/util/Date
       3: dup
       4: invokespecial #70                 // Method java/util/Date."<init>":()V
       7: astore        4
       9: new           #64                 // class com/virtual/ssv/server/entity/ResultJson
      12: dup
      13: invokespecial #65                 // Method com/virtual/ssv/server/entity/ResultJson."<init>":()V
      16: astore        5
      18: aload_1
      19: ldc           #71                 // String strategyId
      21: invokeinterface #9,  2            // InterfaceMethod javax/servlet/http/HttpServletRequest.getParameter:(Ljava/lang/String;)Ljava/lang/String;
      26: astore        6
      28: aload_0
      29: getfield      #45                 // Field reqHandle:Lcom/virtual/ssv/server/rs/client/RequestHandle;
      32: aload         6
      34: invokestatic  #72                 // Method java/lang/Long.parseLong:(Ljava/lang/String;)J
      37: invokestatic  #73                 // Method java/lang/Long.valueOf:(J)Ljava/lang/Long;
      40: invokevirtual #100                // Method com/virtual/ssv/server/rs/client/RequestHandle.closeAlarm:(Ljava/lang/Long;)Lcom/virtual/ssv/server/entity/ResultJson;
      43: astore        5
      45: new           #69                 // class java/util/Date
      48: dup
      49: invokespecial #70                 // Method java/util/Date."<init>":()V
      52: astore        7
      54: new           #75                 // class com/virtual/ssv/server/rs/client/entity/RsOperateLog
      57: dup
      58: invokespecial #76                 // Method com/virtual/ssv/server/rs/client/entity/RsOperateLog."<init>":()V
      61: astore        8
      63: aload         8
      65: aload_3
      66: invokevirtual #27                 // Method com/virtual/ssv/server/user/LoginInfo.getId:()Ljava/lang/Long;
      69: invokevirtual #77                 // Method com/virtual/ssv/server/rs/client/entity/RsOperateLog.setUserId:(Ljava/lang/Long;)V
      72: aload         8
      74: aload_3
      75: invokevirtual #78                 // Method com/virtual/ssv/server/user/LoginInfo.getOrgId:()Ljava/lang/Long;
      78: invokevirtual #79                 // Method com/virtual/ssv/server/rs/client/entity/RsOperateLog.setOrgId:(Ljava/lang/Long;)V
      81: aload         8
      83: aload_3
      84: invokevirtual #80                 // Method com/virtual/ssv/server/user/LoginInfo.getLoginName:()Ljava/lang/String;
      87: invokevirtual #81                 // Method com/virtual/ssv/server/rs/client/entity/RsOperateLog.setLoginName:(Ljava/lang/String;)V
      90: aload         8
      92: aload_3
      93: invokevirtual #82                 // Method com/virtual/ssv/server/user/LoginInfo.getUserName:()Ljava/lang/String;
      96: invokevirtual #83                 // Method com/virtual/ssv/server/rs/client/entity/RsOperateLog.setUserName:(Ljava/lang/String;)V
      99: aload         8
     101: aload_3
     102: invokevirtual #84                 // Method com/virtual/ssv/server/user/LoginInfo.getLoginIp:()Ljava/lang/String;
     105: invokevirtual #85                 // Method com/virtual/ssv/server/rs/client/entity/RsOperateLog.setAddress:(Ljava/lang/String;)V
     108: aload         8
     110: bipush        30
     112: invokestatic  #87                 // Method java/lang/Integer.valueOf:(I)Ljava/lang/Integer;
     115: invokevirtual #88                 // Method com/virtual/ssv/server/rs/client/entity/RsOperateLog.setCategory:(Ljava/lang/Integer;)V
     118: aload         8
     120: aload_0
     121: getfield      #51                 // Field logSm:Lcom/virtual/common/StringManager;
     124: ldc           #101                // String close.alarm
     126: invokevirtual #53                 // Method com/virtual/common/StringManager.getString:(Ljava/lang/String;)Ljava/lang/String;
     129: invokevirtual #90                 // Method com/virtual/ssv/server/rs/client/entity/RsOperateLog.setDescription:(Ljava/lang/String;)V
     132: aload         8
     134: aload         4
     136: invokevirtual #91                 // Method com/virtual/ssv/server/rs/client/entity/RsOperateLog.setStartTime:(Ljava/util/Date;)V
     139: aload         8
     141: aload         7
     143: invokevirtual #92                 // Method com/virtual/ssv/server/rs/client/entity/RsOperateLog.setEndTime:(Ljava/util/Date;)V
     146: aload         5
     148: invokevirtual #93                 // Method com/virtual/ssv/server/entity/ResultJson.getState:()I
     151: iconst_1
     152: if_icmpne     166
     155: aload         8
     157: getstatic     #94                 // Field com/virtual/ssv/server/rs/client/entity/RsOperateLog.RESULT_SUCCESS:Ljava/lang/Integer;
     160: invokevirtual #95                 // Method com/virtual/ssv/server/rs/client/entity/RsOperateLog.setResult:(Ljava/lang/Integer;)V
     163: goto          184
     166: aload         8
     168: getstatic     #96                 // Field com/virtual/ssv/server/rs/client/entity/RsOperateLog.RESULT_FAILURE:Ljava/lang/Integer;
     171: invokevirtual #95                 // Method com/virtual/ssv/server/rs/client/entity/RsOperateLog.setResult:(Ljava/lang/Integer;)V
     174: aload         8
     176: aload         5
     178: invokevirtual #97                 // Method com/virtual/ssv/server/entity/ResultJson.getMessage:()Ljava/lang/String;
     181: invokevirtual #98                 // Method com/virtual/ssv/server/rs/client/entity/RsOperateLog.setFailureReason:(Ljava/lang/String;)V
     184: aload_0
     185: getfield      #45                 // Field reqHandle:Lcom/virtual/ssv/server/rs/client/RequestHandle;
     188: aload         8
     190: invokevirtual #99                 // Method com/virtual/ssv/server/rs/client/RequestHandle.addUserLog:(Lcom/virtual/ssv/server/rs/client/entity/RsOperateLog;)Ljava/lang/Long;
     193: pop
     194: aload_0
     195: getfield      #68                 // Field filterJson:Lcom/google/gson/Gson;
     198: aload         5
     200: invokevirtual #48                 // Method com/google/gson/Gson.toJson:(Ljava/lang/Object;)Ljava/lang/String;
     203: astore        9
     205: aload_0
     206: aload_2
     207: aload         9
     209: invokevirtual #49                 // Method write:(Ljavax/servlet/http/HttpServletResponse;Ljava/lang/String;)V
     212: goto          310
     215: astore        6
     217: aload         6
     219: invokevirtual #55                 // Method com/virtual/common/AppException.getErrorCode:()I
     222: bipush        102
     224: if_icmpne     240
     227: aload         5
     229: bipush        102
     231: invokestatic  #57                 // Method com/virtual/common/ErrorCodes.getErrorMessage:(I)Ljava/lang/String;
     234: invokevirtual #67                 // Method com/virtual/ssv/server/entity/ResultJson.setErrorMsg:(Ljava/lang/String;)V
     237: goto          296
     240: aload         6
     242: invokevirtual #55                 // Method com/virtual/common/AppException.getErrorCode:()I
     245: bipush        103
     247: if_icmpne     263
     250: aload         5
     252: bipush        103
     254: invokestatic  #57                 // Method com/virtual/common/ErrorCodes.getErrorMessage:(I)Ljava/lang/String;
     257: invokevirtual #67                 // Method com/virtual/ssv/server/entity/ResultJson.setErrorMsg:(Ljava/lang/String;)V
     260: goto          296
     263: aload         6
     265: invokevirtual #55                 // Method com/virtual/common/AppException.getErrorCode:()I
     268: bipush        11
     270: if_icmpne     286
     273: aload         5
     275: bipush        11
     277: invokestatic  #57                 // Method com/virtual/common/ErrorCodes.getErrorMessage:(I)Ljava/lang/String;
     280: invokevirtual #67                 // Method com/virtual/ssv/server/entity/ResultJson.setErrorMsg:(Ljava/lang/String;)V
     283: goto          296
     286: aload         5
     288: aload         6
     290: invokevirtual #59                 // Method com/virtual/common/AppException.getMessage:()Ljava/lang/String;
     293: invokevirtual #67                 // Method com/virtual/ssv/server/entity/ResultJson.setErrorMsg:(Ljava/lang/String;)V
     296: aload_0
     297: aload_2
     298: aload_0
     299: getfield      #68                 // Field filterJson:Lcom/google/gson/Gson;
     302: aload         5
     304: invokevirtual #48                 // Method com/google/gson/Gson.toJson:(Ljava/lang/Object;)Ljava/lang/String;
     307: invokevirtual #49                 // Method write:(Ljavax/servlet/http/HttpServletResponse;Ljava/lang/String;)V
     310: return
    Exception table:
       from    to  target type
          18   212   215   Class com/virtual/common/AppException

  private void removeAlarmVm(javax.servlet.http.HttpServletRequest, javax.servlet.http.HttpServletResponse, com.virtual.ssv.server.user.LoginInfo);
    Code:
       0: new           #64                 // class com/virtual/ssv/server/entity/ResultJson
       3: dup
       4: invokespecial #65                 // Method com/virtual/ssv/server/entity/ResultJson."<init>":()V
       7: astore        4
       9: new           #69                 // class java/util/Date
      12: dup
      13: invokespecial #70                 // Method java/util/Date."<init>":()V
      16: astore        5
      18: aconst_null
      19: astore        6
      21: aload_1
      22: ldc           #102                // String json
      24: invokeinterface #9,  2            // InterfaceMethod javax/servlet/http/HttpServletRequest.getParameter:(Ljava/lang/String;)Ljava/lang/String;
      29: ldc           #103                // String UTF-8
      31: invokestatic  #104                // Method java/net/URLDecoder.decode:(Ljava/lang/String;Ljava/lang/String;)Ljava/lang/String;
      34: astore        7
      36: aload_1
      37: ldc           #105                // String names
      39: invokeinterface #9,  2            // InterfaceMethod javax/servlet/http/HttpServletRequest.getParameter:(Ljava/lang/String;)Ljava/lang/String;
      44: ldc           #103                // String UTF-8
      46: invokestatic  #104                // Method java/net/URLDecoder.decode:(Ljava/lang/String;Ljava/lang/String;)Ljava/lang/String;
      49: astore        8
      51: aload         7
      53: ifnull        240
      56: aload_0
      57: getfield      #47                 // Field gson:Lcom/google/gson/Gson;
      60: aload         7
      62: ldc           #106                // class com/virtual/ssv/server/rs/client/entity/RsEventStrategyDomain
      64: invokevirtual #107                // Method com/google/gson/Gson.fromJson:(Ljava/lang/String;Ljava/lang/Class;)Ljava/lang/Object;
      67: checkcast     #106                // class com/virtual/ssv/server/rs/client/entity/RsEventStrategyDomain
      70: astore        6
      72: aload_0
      73: getfield      #45                 // Field reqHandle:Lcom/virtual/ssv/server/rs/client/RequestHandle;
      76: aload         6
      78: invokevirtual #108                // Method com/virtual/ssv/server/rs/client/RequestHandle.removeAlarmVm:(Lcom/virtual/ssv/server/rs/client/entity/RsEventStrategyDomain;)Lcom/virtual/ssv/server/entity/ResultJson;
      81: astore        4
      83: new           #69                 // class java/util/Date
      86: dup
      87: invokespecial #70                 // Method java/util/Date."<init>":()V
      90: astore        9
      92: new           #75                 // class com/virtual/ssv/server/rs/client/entity/RsOperateLog
      95: dup
      96: invokespecial #76                 // Method com/virtual/ssv/server/rs/client/entity/RsOperateLog."<init>":()V
      99: astore        10
     101: aload         10
     103: aload_3
     104: invokevirtual #27                 // Method com/virtual/ssv/server/user/LoginInfo.getId:()Ljava/lang/Long;
     107: invokevirtual #77                 // Method com/virtual/ssv/server/rs/client/entity/RsOperateLog.setUserId:(Ljava/lang/Long;)V
     110: aload         10
     112: aload_3
     113: invokevirtual #78                 // Method com/virtual/ssv/server/user/LoginInfo.getOrgId:()Ljava/lang/Long;
     116: invokevirtual #79                 // Method com/virtual/ssv/server/rs/client/entity/RsOperateLog.setOrgId:(Ljava/lang/Long;)V
     119: aload         10
     121: aload_3
     122: invokevirtual #80                 // Method com/virtual/ssv/server/user/LoginInfo.getLoginName:()Ljava/lang/String;
     125: invokevirtual #81                 // Method com/virtual/ssv/server/rs/client/entity/RsOperateLog.setLoginName:(Ljava/lang/String;)V
     128: aload         10
     130: aload_3
     131: invokevirtual #82                 // Method com/virtual/ssv/server/user/LoginInfo.getUserName:()Ljava/lang/String;
     134: invokevirtual #83                 // Method com/virtual/ssv/server/rs/client/entity/RsOperateLog.setUserName:(Ljava/lang/String;)V
     137: aload         10
     139: aload_3
     140: invokevirtual #84                 // Method com/virtual/ssv/server/user/LoginInfo.getLoginIp:()Ljava/lang/String;
     143: invokevirtual #85                 // Method com/virtual/ssv/server/rs/client/entity/RsOperateLog.setAddress:(Ljava/lang/String;)V
     146: aload         10
     148: bipush        30
     150: invokestatic  #87                 // Method java/lang/Integer.valueOf:(I)Ljava/lang/Integer;
     153: invokevirtual #88                 // Method com/virtual/ssv/server/rs/client/entity/RsOperateLog.setCategory:(Ljava/lang/Integer;)V
     156: aload         10
     158: aload_0
     159: getfield      #51                 // Field logSm:Lcom/virtual/common/StringManager;
     162: ldc           #109                // String remove.alarm.vm
     164: iconst_1
     165: anewarray     #110                // class java/lang/Object
     168: dup
     169: iconst_0
     170: aload         8
     172: aastore
     173: invokevirtual #111                // Method com/virtual/common/StringManager.getString:(Ljava/lang/String;[Ljava/lang/Object;)Ljava/lang/String;
     176: invokevirtual #90                 // Method com/virtual/ssv/server/rs/client/entity/RsOperateLog.setDescription:(Ljava/lang/String;)V
     179: aload         4
     181: invokevirtual #112                // Method com/virtual/ssv/server/entity/ResultJson.isSuccess:()Z
     184: ifeq          198
     187: aload         10
     189: getstatic     #94                 // Field com/virtual/ssv/server/rs/client/entity/RsOperateLog.RESULT_SUCCESS:Ljava/lang/Integer;
     192: invokevirtual #95                 // Method com/virtual/ssv/server/rs/client/entity/RsOperateLog.setResult:(Ljava/lang/Integer;)V
     195: goto          216
     198: aload         10
     200: getstatic     #96                 // Field com/virtual/ssv/server/rs/client/entity/RsOperateLog.RESULT_FAILURE:Ljava/lang/Integer;
     203: invokevirtual #95                 // Method com/virtual/ssv/server/rs/client/entity/RsOperateLog.setResult:(Ljava/lang/Integer;)V
     206: aload         10
     208: aload         4
     210: invokevirtual #97                 // Method com/virtual/ssv/server/entity/ResultJson.getMessage:()Ljava/lang/String;
     213: invokevirtual #98                 // Method com/virtual/ssv/server/rs/client/entity/RsOperateLog.setFailureReason:(Ljava/lang/String;)V
     216: aload         10
     218: aload         5
     220: invokevirtual #91                 // Method com/virtual/ssv/server/rs/client/entity/RsOperateLog.setStartTime:(Ljava/util/Date;)V
     223: aload         10
     225: aload         9
     227: invokevirtual #92                 // Method com/virtual/ssv/server/rs/client/entity/RsOperateLog.setEndTime:(Ljava/util/Date;)V
     230: aload_0
     231: getfield      #45                 // Field reqHandle:Lcom/virtual/ssv/server/rs/client/RequestHandle;
     234: aload         10
     236: invokevirtual #99                 // Method com/virtual/ssv/server/rs/client/RequestHandle.addUserLog:(Lcom/virtual/ssv/server/rs/client/entity/RsOperateLog;)Ljava/lang/Long;
     239: pop
     240: goto          364
     243: astore        5
     245: aload         5
     247: invokevirtual #55                 // Method com/virtual/common/AppException.getErrorCode:()I
     250: bipush        102
     252: if_icmpne     268
     255: aload         4
     257: bipush        102
     259: invokestatic  #57                 // Method com/virtual/common/ErrorCodes.getErrorMessage:(I)Ljava/lang/String;
     262: invokevirtual #67                 // Method com/virtual/ssv/server/entity/ResultJson.setErrorMsg:(Ljava/lang/String;)V
     265: goto          349
     268: aload         5
     270: invokevirtual #55                 // Method com/virtual/common/AppException.getErrorCode:()I
     273: bipush        103
     275: if_icmpne     291
     278: aload         4
     280: bipush        103
     282: invokestatic  #57                 // Method com/virtual/common/ErrorCodes.getErrorMessage:(I)Ljava/lang/String;
     285: invokevirtual #67                 // Method com/virtual/ssv/server/entity/ResultJson.setErrorMsg:(Ljava/lang/String;)V
     288: goto          349
     291: aload         5
     293: invokevirtual #55                 // Method com/virtual/common/AppException.getErrorCode:()I
     296: bipush        11
     298: if_icmpne     314
     301: aload         4
     303: bipush        11
     305: invokestatic  #57                 // Method com/virtual/common/ErrorCodes.getErrorMessage:(I)Ljava/lang/String;
     308: invokevirtual #67                 // Method com/virtual/ssv/server/entity/ResultJson.setErrorMsg:(Ljava/lang/String;)V
     311: goto          349
     314: aload         5
     316: invokevirtual #55                 // Method com/virtual/common/AppException.getErrorCode:()I
     319: sipush        1003
     322: if_icmpne     339
     325: aload         4
     327: sipush        1003
     330: invokestatic  #57                 // Method com/virtual/common/ErrorCodes.getErrorMessage:(I)Ljava/lang/String;
     333: invokevirtual #67                 // Method com/virtual/ssv/server/entity/ResultJson.setErrorMsg:(Ljava/lang/String;)V
     336: goto          349
     339: aload         4
     341: aload         5
     343: invokevirtual #59                 // Method com/virtual/common/AppException.getMessage:()Ljava/lang/String;
     346: invokevirtual #67                 // Method com/virtual/ssv/server/entity/ResultJson.setErrorMsg:(Ljava/lang/String;)V
     349: goto          364
     352: astore        5
     354: aload         4
     356: aload         5
     358: invokevirtual #114                // Method java/io/UnsupportedEncodingException.getMessage:()Ljava/lang/String;
     361: invokevirtual #67                 // Method com/virtual/ssv/server/entity/ResultJson.setErrorMsg:(Ljava/lang/String;)V
     364: aload_0
     365: aload_2
     366: aload_0
     367: getfield      #68                 // Field filterJson:Lcom/google/gson/Gson;
     370: aload         4
     372: invokevirtual #48                 // Method com/google/gson/Gson.toJson:(Ljava/lang/Object;)Ljava/lang/String;
     375: invokevirtual #49                 // Method write:(Ljavax/servlet/http/HttpServletResponse;Ljava/lang/String;)V
     378: return
    Exception table:
       from    to  target type
           9   240   243   Class com/virtual/common/AppException
           9   240   352   Class java/io/UnsupportedEncodingException

  private void addAlarmVm(javax.servlet.http.HttpServletRequest, javax.servlet.http.HttpServletResponse, com.virtual.ssv.server.user.LoginInfo);
    Code:
       0: new           #64                 // class com/virtual/ssv/server/entity/ResultJson
       3: dup
       4: invokespecial #65                 // Method com/virtual/ssv/server/entity/ResultJson."<init>":()V
       7: astore        4
       9: new           #69                 // class java/util/Date
      12: dup
      13: invokespecial #70                 // Method java/util/Date."<init>":()V
      16: astore        5
      18: aconst_null
      19: astore        6
      21: aload_1
      22: ldc           #102                // String json
      24: invokeinterface #9,  2            // InterfaceMethod javax/servlet/http/HttpServletRequest.getParameter:(Ljava/lang/String;)Ljava/lang/String;
      29: ldc           #103                // String UTF-8
      31: invokestatic  #104                // Method java/net/URLDecoder.decode:(Ljava/lang/String;Ljava/lang/String;)Ljava/lang/String;
      34: astore        7
      36: aload_1
      37: ldc           #105                // String names
      39: invokeinterface #9,  2            // InterfaceMethod javax/servlet/http/HttpServletRequest.getParameter:(Ljava/lang/String;)Ljava/lang/String;
      44: ldc           #103                // String UTF-8
      46: invokestatic  #104                // Method java/net/URLDecoder.decode:(Ljava/lang/String;Ljava/lang/String;)Ljava/lang/String;
      49: astore        8
      51: aload         7
      53: ifnull        240
      56: aload_0
      57: getfield      #47                 // Field gson:Lcom/google/gson/Gson;
      60: aload         7
      62: ldc           #106                // class com/virtual/ssv/server/rs/client/entity/RsEventStrategyDomain
      64: invokevirtual #107                // Method com/google/gson/Gson.fromJson:(Ljava/lang/String;Ljava/lang/Class;)Ljava/lang/Object;
      67: checkcast     #106                // class com/virtual/ssv/server/rs/client/entity/RsEventStrategyDomain
      70: astore        6
      72: aload_0
      73: getfield      #45                 // Field reqHandle:Lcom/virtual/ssv/server/rs/client/RequestHandle;
      76: aload         6
      78: invokevirtual #115                // Method com/virtual/ssv/server/rs/client/RequestHandle.addAlarmVm:(Lcom/virtual/ssv/server/rs/client/entity/RsEventStrategyDomain;)Lcom/virtual/ssv/server/entity/ResultJson;
      81: astore        4
      83: new           #69                 // class java/util/Date
      86: dup
      87: invokespecial #70                 // Method java/util/Date."<init>":()V
      90: astore        9
      92: new           #75                 // class com/virtual/ssv/server/rs/client/entity/RsOperateLog
      95: dup
      96: invokespecial #76                 // Method com/virtual/ssv/server/rs/client/entity/RsOperateLog."<init>":()V
      99: astore        10
     101: aload         10
     103: aload_3
     104: invokevirtual #27                 // Method com/virtual/ssv/server/user/LoginInfo.getId:()Ljava/lang/Long;
     107: invokevirtual #77                 // Method com/virtual/ssv/server/rs/client/entity/RsOperateLog.setUserId:(Ljava/lang/Long;)V
     110: aload         10
     112: aload_3
     113: invokevirtual #78                 // Method com/virtual/ssv/server/user/LoginInfo.getOrgId:()Ljava/lang/Long;
     116: invokevirtual #79                 // Method com/virtual/ssv/server/rs/client/entity/RsOperateLog.setOrgId:(Ljava/lang/Long;)V
     119: aload         10
     121: aload_3
     122: invokevirtual #80                 // Method com/virtual/ssv/server/user/LoginInfo.getLoginName:()Ljava/lang/String;
     125: invokevirtual #81                 // Method com/virtual/ssv/server/rs/client/entity/RsOperateLog.setLoginName:(Ljava/lang/String;)V
     128: aload         10
     130: aload_3
     131: invokevirtual #82                 // Method com/virtual/ssv/server/user/LoginInfo.getUserName:()Ljava/lang/String;
     134: invokevirtual #83                 // Method com/virtual/ssv/server/rs/client/entity/RsOperateLog.setUserName:(Ljava/lang/String;)V
     137: aload         10
     139: aload_3
     140: invokevirtual #84                 // Method com/virtual/ssv/server/user/LoginInfo.getLoginIp:()Ljava/lang/String;
     143: invokevirtual #85                 // Method com/virtual/ssv/server/rs/client/entity/RsOperateLog.setAddress:(Ljava/lang/String;)V
     146: aload         10
     148: bipush        30
     150: invokestatic  #87                 // Method java/lang/Integer.valueOf:(I)Ljava/lang/Integer;
     153: invokevirtual #88                 // Method com/virtual/ssv/server/rs/client/entity/RsOperateLog.setCategory:(Ljava/lang/Integer;)V
     156: aload         10
     158: aload_0
     159: getfield      #51                 // Field logSm:Lcom/virtual/common/StringManager;
     162: ldc           #116                // String add.alarm.vm
     164: iconst_1
     165: anewarray     #110                // class java/lang/Object
     168: dup
     169: iconst_0
     170: aload         8
     172: aastore
     173: invokevirtual #111                // Method com/virtual/common/StringManager.getString:(Ljava/lang/String;[Ljava/lang/Object;)Ljava/lang/String;
     176: invokevirtual #90                 // Method com/virtual/ssv/server/rs/client/entity/RsOperateLog.setDescription:(Ljava/lang/String;)V
     179: aload         4
     181: invokevirtual #112                // Method com/virtual/ssv/server/entity/ResultJson.isSuccess:()Z
     184: ifeq          198
     187: aload         10
     189: getstatic     #94                 // Field com/virtual/ssv/server/rs/client/entity/RsOperateLog.RESULT_SUCCESS:Ljava/lang/Integer;
     192: invokevirtual #95                 // Method com/virtual/ssv/server/rs/client/entity/RsOperateLog.setResult:(Ljava/lang/Integer;)V
     195: goto          216
     198: aload         10
     200: getstatic     #96                 // Field com/virtual/ssv/server/rs/client/entity/RsOperateLog.RESULT_FAILURE:Ljava/lang/Integer;
     203: invokevirtual #95                 // Method com/virtual/ssv/server/rs/client/entity/RsOperateLog.setResult:(Ljava/lang/Integer;)V
     206: aload         10
     208: aload         4
     210: invokevirtual #97                 // Method com/virtual/ssv/server/entity/ResultJson.getMessage:()Ljava/lang/String;
     213: invokevirtual #98                 // Method com/virtual/ssv/server/rs/client/entity/RsOperateLog.setFailureReason:(Ljava/lang/String;)V
     216: aload         10
     218: aload         5
     220: invokevirtual #91                 // Method com/virtual/ssv/server/rs/client/entity/RsOperateLog.setStartTime:(Ljava/util/Date;)V
     223: aload         10
     225: aload         9
     227: invokevirtual #92                 // Method com/virtual/ssv/server/rs/client/entity/RsOperateLog.setEndTime:(Ljava/util/Date;)V
     230: aload_0
     231: getfield      #45                 // Field reqHandle:Lcom/virtual/ssv/server/rs/client/RequestHandle;
     234: aload         10
     236: invokevirtual #99                 // Method com/virtual/ssv/server/rs/client/RequestHandle.addUserLog:(Lcom/virtual/ssv/server/rs/client/entity/RsOperateLog;)Ljava/lang/Long;
     239: pop
     240: goto          364
     243: astore        5
     245: aload         5
     247: invokevirtual #55                 // Method com/virtual/common/AppException.getErrorCode:()I
     250: bipush        102
     252: if_icmpne     268
     255: aload         4
     257: bipush        102
     259: invokestatic  #57                 // Method com/virtual/common/ErrorCodes.getErrorMessage:(I)Ljava/lang/String;
     262: invokevirtual #67                 // Method com/virtual/ssv/server/entity/ResultJson.setErrorMsg:(Ljava/lang/String;)V
     265: goto          349
     268: aload         5
     270: invokevirtual #55                 // Method com/virtual/common/AppException.getErrorCode:()I
     273: bipush        103
     275: if_icmpne     291
     278: aload         4
     280: bipush        103
     282: invokestatic  #57                 // Method com/virtual/common/ErrorCodes.getErrorMessage:(I)Ljava/lang/String;
     285: invokevirtual #67                 // Method com/virtual/ssv/server/entity/ResultJson.setErrorMsg:(Ljava/lang/String;)V
     288: goto          349
     291: aload         5
     293: invokevirtual #55                 // Method com/virtual/common/AppException.getErrorCode:()I
     296: bipush        11
     298: if_icmpne     314
     301: aload         4
     303: bipush        11
     305: invokestatic  #57                 // Method com/virtual/common/ErrorCodes.getErrorMessage:(I)Ljava/lang/String;
     308: invokevirtual #67                 // Method com/virtual/ssv/server/entity/ResultJson.setErrorMsg:(Ljava/lang/String;)V
     311: goto          349
     314: aload         5
     316: invokevirtual #55                 // Method com/virtual/common/AppException.getErrorCode:()I
     319: sipush        1003
     322: if_icmpne     339
     325: aload         4
     327: sipush        1003
     330: invokestatic  #57                 // Method com/virtual/common/ErrorCodes.getErrorMessage:(I)Ljava/lang/String;
     333: invokevirtual #67                 // Method com/virtual/ssv/server/entity/ResultJson.setErrorMsg:(Ljava/lang/String;)V
     336: goto          349
     339: aload         4
     341: aload         5
     343: invokevirtual #59                 // Method com/virtual/common/AppException.getMessage:()Ljava/lang/String;
     346: invokevirtual #67                 // Method com/virtual/ssv/server/entity/ResultJson.setErrorMsg:(Ljava/lang/String;)V
     349: goto          364
     352: astore        5
     354: aload         4
     356: aload         5
     358: invokevirtual #114                // Method java/io/UnsupportedEncodingException.getMessage:()Ljava/lang/String;
     361: invokevirtual #67                 // Method com/virtual/ssv/server/entity/ResultJson.setErrorMsg:(Ljava/lang/String;)V
     364: aload_0
     365: aload_2
     366: aload_0
     367: getfield      #68                 // Field filterJson:Lcom/google/gson/Gson;
     370: aload         4
     372: invokevirtual #48                 // Method com/google/gson/Gson.toJson:(Ljava/lang/Object;)Ljava/lang/String;
     375: invokevirtual #49                 // Method write:(Ljavax/servlet/http/HttpServletResponse;Ljava/lang/String;)V
     378: return
    Exception table:
       from    to  target type
           9   240   243   Class com/virtual/common/AppException
           9   240   352   Class java/io/UnsupportedEncodingException

  private void unselectedAlarmDomains(javax.servlet.http.HttpServletRequest, javax.servlet.http.HttpServletResponse, com.virtual.ssv.server.user.LoginInfo);
    Code:
       0: new           #36                 // class com/virtual/ssv/server/entity/CommonListJson
       3: dup
       4: invokespecial #37                 // Method com/virtual/ssv/server/entity/CommonListJson."<init>":()V
       7: astore        4
       9: aload_0
      10: getfield      #45                 // Field reqHandle:Lcom/virtual/ssv/server/rs/client/RequestHandle;
      13: aload_3
      14: invokevirtual #117                // Method com/virtual/ssv/server/rs/client/RequestHandle.queryUnselectedAlarmDomains:(Lcom/virtual/ssv/server/user/LoginInfo;)Lcom/virtual/ssv/server/entity/ListResult;
      17: astore        5
      19: aload         4
      21: aload         5
      23: invokevirtual #118                // Method com/virtual/ssv/server/entity/ListResult.getSize:()J
      26: invokevirtual #119                // Method com/virtual/ssv/server/entity/CommonListJson.setTotal:(J)V
      29: aload         4
      31: aload         5
      33: invokevirtual #120                // Method com/virtual/ssv/server/entity/ListResult.getData:()Ljava/util/List;
      36: ifnull        47
      39: aload         5
      41: invokevirtual #120                // Method com/virtual/ssv/server/entity/ListResult.getData:()Ljava/util/List;
      44: goto          54
      47: new           #61                 // class java/util/ArrayList
      50: dup
      51: invokespecial #62                 // Method java/util/ArrayList."<init>":()V
      54: invokevirtual #63                 // Method com/virtual/ssv/server/entity/CommonListJson.setRows:(Ljava/util/List;)V
      57: goto          173
      60: astore        5
      62: aload         4
      64: aload_0
      65: getfield      #51                 // Field logSm:Lcom/virtual/common/StringManager;
      68: ldc           #52                 // String operError
      70: invokevirtual #53                 // Method com/virtual/common/StringManager.getString:(Ljava/lang/String;)Ljava/lang/String;
      73: invokevirtual #54                 // Method com/virtual/ssv/server/entity/CommonListJson.setTitle:(Ljava/lang/String;)V
      76: aload         5
      78: invokevirtual #55                 // Method com/virtual/common/AppException.getErrorCode:()I
      81: bipush        102
      83: if_icmpne     99
      86: aload         4
      88: bipush        102
      90: invokestatic  #57                 // Method com/virtual/common/ErrorCodes.getErrorMessage:(I)Ljava/lang/String;
      93: invokevirtual #58                 // Method com/virtual/ssv/server/entity/CommonListJson.setMessage:(Ljava/lang/String;)V
      96: goto          155
      99: aload         5
     101: invokevirtual #55                 // Method com/virtual/common/AppException.getErrorCode:()I
     104: bipush        103
     106: if_icmpne     122
     109: aload         4
     111: bipush        103
     113: invokestatic  #57                 // Method com/virtual/common/ErrorCodes.getErrorMessage:(I)Ljava/lang/String;
     116: invokevirtual #58                 // Method com/virtual/ssv/server/entity/CommonListJson.setMessage:(Ljava/lang/String;)V
     119: goto          155
     122: aload         5
     124: invokevirtual #55                 // Method com/virtual/common/AppException.getErrorCode:()I
     127: bipush        11
     129: if_icmpne     145
     132: aload         4
     134: bipush        11
     136: invokestatic  #57                 // Method com/virtual/common/ErrorCodes.getErrorMessage:(I)Ljava/lang/String;
     139: invokevirtual #58                 // Method com/virtual/ssv/server/entity/CommonListJson.setMessage:(Ljava/lang/String;)V
     142: goto          155
     145: aload         4
     147: aload         5
     149: invokevirtual #59                 // Method com/virtual/common/AppException.getMessage:()Ljava/lang/String;
     152: invokevirtual #58                 // Method com/virtual/ssv/server/entity/CommonListJson.setMessage:(Ljava/lang/String;)V
     155: aload         4
     157: iconst_0
     158: invokevirtual #60                 // Method com/virtual/ssv/server/entity/CommonListJson.setState:(I)V
     161: aload         4
     163: new           #61                 // class java/util/ArrayList
     166: dup
     167: invokespecial #62                 // Method java/util/ArrayList."<init>":()V
     170: invokevirtual #63                 // Method com/virtual/ssv/server/entity/CommonListJson.setRows:(Ljava/util/List;)V
     173: aload_0
     174: aload_2
     175: aload_0
     176: getfield      #47                 // Field gson:Lcom/google/gson/Gson;
     179: aload         4
     181: invokevirtual #48                 // Method com/google/gson/Gson.toJson:(Ljava/lang/Object;)Ljava/lang/String;
     184: invokevirtual #49                 // Method write:(Ljavax/servlet/http/HttpServletResponse;Ljava/lang/String;)V
     187: return
    Exception table:
       from    to  target type
           9    57    60   Class com/virtual/common/AppException

  private void selectedAlarmDomains(javax.servlet.http.HttpServletRequest, javax.servlet.http.HttpServletResponse, com.virtual.ssv.server.user.LoginInfo);
    Code:
       0: new           #36                 // class com/virtual/ssv/server/entity/CommonListJson
       3: dup
       4: invokespecial #37                 // Method com/virtual/ssv/server/entity/CommonListJson."<init>":()V
       7: astore        4
       9: aload_1
      10: ldc           #71                 // String strategyId
      12: invokeinterface #9,  2            // InterfaceMethod javax/servlet/http/HttpServletRequest.getParameter:(Ljava/lang/String;)Ljava/lang/String;
      17: astore        5
      19: aload_1
      20: ldc           #121                // String type
      22: invokeinterface #9,  2            // InterfaceMethod javax/servlet/http/HttpServletRequest.getParameter:(Ljava/lang/String;)Ljava/lang/String;
      27: astore        6
      29: aload_1
      30: ldc           #122                // String page
      32: invokeinterface #9,  2            // InterfaceMethod javax/servlet/http/HttpServletRequest.getParameter:(Ljava/lang/String;)Ljava/lang/String;
      37: astore        7
      39: aload_1
      40: ldc           #123                // String rows
      42: invokeinterface #9,  2            // InterfaceMethod javax/servlet/http/HttpServletRequest.getParameter:(Ljava/lang/String;)Ljava/lang/String;
      47: astore        8
      49: iconst_0
      50: istore        9
      52: aload         7
      54: invokestatic  #124                // Method org/apache/commons/lang/StringUtils.isNotEmpty:(Ljava/lang/String;)Z
      57: ifeq          67
      60: aload         7
      62: invokestatic  #125                // Method java/lang/Integer.parseInt:(Ljava/lang/String;)I
      65: istore        9
      67: iconst_0
      68: istore        10
      70: aload         7
      72: invokestatic  #124                // Method org/apache/commons/lang/StringUtils.isNotEmpty:(Ljava/lang/String;)Z
      75: ifeq          85
      78: aload         8
      80: invokestatic  #125                // Method java/lang/Integer.parseInt:(Ljava/lang/String;)I
      83: istore        10
      85: iload         10
      87: iload         9
      89: iconst_1
      90: isub
      91: imul
      92: istore        11
      94: aload_0
      95: getfield      #45                 // Field reqHandle:Lcom/virtual/ssv/server/rs/client/RequestHandle;
      98: aload_3
      99: iload         11
     101: iload         10
     103: aload         5
     105: aload         6
     107: invokevirtual #126                // Method com/virtual/ssv/server/rs/client/RequestHandle.querySelectedAlarmDomains:(Lcom/virtual/ssv/server/user/LoginInfo;IILjava/lang/String;Ljava/lang/String;)Lcom/virtual/ssv/server/entity/ListResult;
     110: astore        12
     112: aload         12
     114: invokevirtual #120                // Method com/virtual/ssv/server/entity/ListResult.getData:()Ljava/util/List;
     117: ifnull        128
     120: aload         12
     122: invokevirtual #120                // Method com/virtual/ssv/server/entity/ListResult.getData:()Ljava/util/List;
     125: goto          135
     128: new           #61                 // class java/util/ArrayList
     131: dup
     132: invokespecial #62                 // Method java/util/ArrayList."<init>":()V
     135: astore        13
     137: aload         6
     139: invokestatic  #124                // Method org/apache/commons/lang/StringUtils.isNotEmpty:(Ljava/lang/String;)Z
     142: ifeq          160
     145: aload_0
     146: aload_2
     147: aload_0
     148: getfield      #47                 // Field gson:Lcom/google/gson/Gson;
     151: aload         13
     153: invokevirtual #48                 // Method com/google/gson/Gson.toJson:(Ljava/lang/Object;)Ljava/lang/String;
     156: invokevirtual #49                 // Method write:(Ljavax/servlet/http/HttpServletResponse;Ljava/lang/String;)V
     159: return
     160: aload         4
     162: aload         12
     164: invokevirtual #118                // Method com/virtual/ssv/server/entity/ListResult.getSize:()J
     167: invokevirtual #119                // Method com/virtual/ssv/server/entity/CommonListJson.setTotal:(J)V
     170: aload         4
     172: aload         13
     174: invokevirtual #63                 // Method com/virtual/ssv/server/entity/CommonListJson.setRows:(Ljava/util/List;)V
     177: goto          293
     180: astore        5
     182: aload         4
     184: aload_0
     185: getfield      #51                 // Field logSm:Lcom/virtual/common/StringManager;
     188: ldc           #52                 // String operError
     190: invokevirtual #53                 // Method com/virtual/common/StringManager.getString:(Ljava/lang/String;)Ljava/lang/String;
     193: invokevirtual #54                 // Method com/virtual/ssv/server/entity/CommonListJson.setTitle:(Ljava/lang/String;)V
     196: aload         5
     198: invokevirtual #55                 // Method com/virtual/common/AppException.getErrorCode:()I
     201: bipush        102
     203: if_icmpne     219
     206: aload         4
     208: bipush        102
     210: invokestatic  #57                 // Method com/virtual/common/ErrorCodes.getErrorMessage:(I)Ljava/lang/String;
     213: invokevirtual #58                 // Method com/virtual/ssv/server/entity/CommonListJson.setMessage:(Ljava/lang/String;)V
     216: goto          275
     219: aload         5
     221: invokevirtual #55                 // Method com/virtual/common/AppException.getErrorCode:()I
     224: bipush        103
     226: if_icmpne     242
     229: aload         4
     231: bipush        103
     233: invokestatic  #57                 // Method com/virtual/common/ErrorCodes.getErrorMessage:(I)Ljava/lang/String;
     236: invokevirtual #58                 // Method com/virtual/ssv/server/entity/CommonListJson.setMessage:(Ljava/lang/String;)V
     239: goto          275
     242: aload         5
     244: invokevirtual #55                 // Method com/virtual/common/AppException.getErrorCode:()I
     247: bipush        11
     249: if_icmpne     265
     252: aload         4
     254: bipush        11
     256: invokestatic  #57                 // Method com/virtual/common/ErrorCodes.getErrorMessage:(I)Ljava/lang/String;
     259: invokevirtual #58                 // Method com/virtual/ssv/server/entity/CommonListJson.setMessage:(Ljava/lang/String;)V
     262: goto          275
     265: aload         4
     267: aload         5
     269: invokevirtual #59                 // Method com/virtual/common/AppException.getMessage:()Ljava/lang/String;
     272: invokevirtual #58                 // Method com/virtual/ssv/server/entity/CommonListJson.setMessage:(Ljava/lang/String;)V
     275: aload         4
     277: iconst_0
     278: invokevirtual #60                 // Method com/virtual/ssv/server/entity/CommonListJson.setState:(I)V
     281: aload         4
     283: new           #61                 // class java/util/ArrayList
     286: dup
     287: invokespecial #62                 // Method java/util/ArrayList."<init>":()V
     290: invokevirtual #63                 // Method com/virtual/ssv/server/entity/CommonListJson.setRows:(Ljava/util/List;)V
     293: aload_0
     294: aload_2
     295: aload_0
     296: getfield      #47                 // Field gson:Lcom/google/gson/Gson;
     299: aload         4
     301: invokevirtual #48                 // Method com/google/gson/Gson.toJson:(Ljava/lang/Object;)Ljava/lang/String;
     304: invokevirtual #49                 // Method write:(Ljavax/servlet/http/HttpServletResponse;Ljava/lang/String;)V
     307: return
    Exception table:
       from    to  target type
           9   159   180   Class com/virtual/common/AppException
         160   177   180   Class com/virtual/common/AppException
}
