Compiled from "FirewallServlet.java"
public class com.virtual.ssv.server.firewall.FirewallServlet extends com.virtual.ssv.server.BaseServlet {
  private static final long serialVersionUID;

  private static com.virtual.common.StringManager sm;

  public com.virtual.ssv.server.firewall.FirewallServlet();
    Code:
       0: aload_0
       1: invokespecial #1                  // Method com/virtual/ssv/server/BaseServlet."<init>":()V
       4: return

  protected void doGet(javax.servlet.http.HttpServletRequest, javax.servlet.http.HttpServletResponse) throws javax.servlet.ServletException, java.io.IOException;
    Code:
       0: aload_1
       1: invokeinterface #2,  1            // InterfaceMethod javax/servlet/http/HttpServletRequest.getSession:()Ljavax/servlet/http/HttpSession;
       6: astore_3
       7: aload_3
       8: ldc           #3                  // String loginInfo
      10: invokeinterface #4,  2            // InterfaceMethod javax/servlet/http/HttpSession.getAttribute:(Ljava/lang/String;)Ljava/lang/Object;
      15: checkcast     #5                  // class com/virtual/ssv/server/user/LoginInfo
      18: astore        4
      20: aload         4
      22: ifnull        290
      25: aload_0
      26: aload_1
      27: aload_2
      28: invokevirtual #6                  // Method checkUserState:(Ljavax/servlet/http/HttpServletRequest;Ljavax/servlet/http/HttpServletResponse;)V
      31: aload_1
      32: ldc           #7                  // String way
      34: invokeinterface #8,  2            // InterfaceMethod javax/servlet/http/HttpServletRequest.getParameter:(Ljava/lang/String;)Ljava/lang/String;
      39: astore        5
      41: ldc           #9                  // String fwStrategyList
      43: aload         5
      45: invokevirtual #10                 // Method java/lang/String.equals:(Ljava/lang/Object;)Z
      48: ifeq          62
      51: aload_0
      52: aload_1
      53: aload_2
      54: aload         4
      56: invokespecial #11                 // Method getFwStrategyList:(Ljavax/servlet/http/HttpServletRequest;Ljavax/servlet/http/HttpServletResponse;Lcom/virtual/ssv/server/user/LoginInfo;)V
      59: goto          290
      62: ldc           #12                 // String applyFwStrategy
      64: aload         5
      66: invokevirtual #10                 // Method java/lang/String.equals:(Ljava/lang/Object;)Z
      69: ifeq          83
      72: aload_0
      73: aload_1
      74: aload_2
      75: aload         4
      77: invokespecial #13                 // Method applyFwStrategy:(Ljavax/servlet/http/HttpServletRequest;Ljavax/servlet/http/HttpServletResponse;Lcom/virtual/ssv/server/user/LoginInfo;)V
      80: goto          290
      83: ldc           #14                 // String getFwStrategyById
      85: aload         5
      87: invokevirtual #10                 // Method java/lang/String.equals:(Ljava/lang/Object;)Z
      90: ifeq          104
      93: aload_0
      94: aload_1
      95: aload_2
      96: aload         4
      98: invokespecial #15                 // Method getFwStrategyById:(Ljavax/servlet/http/HttpServletRequest;Ljavax/servlet/http/HttpServletResponse;Lcom/virtual/ssv/server/user/LoginInfo;)V
     101: goto          290
     104: ldc           #16                 // String modifyFwStrategy
     106: aload         5
     108: invokevirtual #10                 // Method java/lang/String.equals:(Ljava/lang/Object;)Z
     111: ifeq          125
     114: aload_0
     115: aload_1
     116: aload_2
     117: aload         4
     119: invokespecial #17                 // Method modifyFwStrategy:(Ljavax/servlet/http/HttpServletRequest;Ljavax/servlet/http/HttpServletResponse;Lcom/virtual/ssv/server/user/LoginInfo;)V
     122: goto          290
     125: ldc           #18                 // String deleteFwStrategy
     127: aload         5
     129: invokevirtual #10                 // Method java/lang/String.equals:(Ljava/lang/Object;)Z
     132: ifeq          146
     135: aload_0
     136: aload_1
     137: aload_2
     138: aload         4
     140: invokespecial #19                 // Method deleteFwStrategy:(Ljavax/servlet/http/HttpServletRequest;Ljavax/servlet/http/HttpServletResponse;Lcom/virtual/ssv/server/user/LoginInfo;)V
     143: goto          290
     146: ldc           #20                 // String getRuleList
     148: aload         5
     150: invokevirtual #10                 // Method java/lang/String.equals:(Ljava/lang/Object;)Z
     153: ifeq          167
     156: aload_0
     157: aload_1
     158: aload_2
     159: aload         4
     161: invokespecial #21                 // Method getRuleList:(Ljavax/servlet/http/HttpServletRequest;Ljavax/servlet/http/HttpServletResponse;Lcom/virtual/ssv/server/user/LoginInfo;)V
     164: goto          290
     167: ldc           #22                 // String applyAclRule
     169: aload         5
     171: invokevirtual #10                 // Method java/lang/String.equals:(Ljava/lang/Object;)Z
     174: ifeq          188
     177: aload_0
     178: aload_1
     179: aload_2
     180: aload         4
     182: invokespecial #23                 // Method applyAclRule:(Ljavax/servlet/http/HttpServletRequest;Ljavax/servlet/http/HttpServletResponse;Lcom/virtual/ssv/server/user/LoginInfo;)V
     185: goto          290
     188: ldc           #24                 // String getAclRuleRuleById
     190: aload         5
     192: invokevirtual #10                 // Method java/lang/String.equals:(Ljava/lang/Object;)Z
     195: ifeq          209
     198: aload_0
     199: aload_1
     200: aload_2
     201: aload         4
     203: invokespecial #25                 // Method getAclRuleById:(Ljavax/servlet/http/HttpServletRequest;Ljavax/servlet/http/HttpServletResponse;Lcom/virtual/ssv/server/user/LoginInfo;)V
     206: goto          290
     209: ldc           #26                 // String modifyAclRule
     211: aload         5
     213: invokevirtual #10                 // Method java/lang/String.equals:(Ljava/lang/Object;)Z
     216: ifeq          230
     219: aload_0
     220: aload_1
     221: aload_2
     222: aload         4
     224: invokespecial #27                 // Method modifyAclRule:(Ljavax/servlet/http/HttpServletRequest;Ljavax/servlet/http/HttpServletResponse;Lcom/virtual/ssv/server/user/LoginInfo;)V
     227: goto          290
     230: ldc           #28                 // String deleteAclRule
     232: aload         5
     234: invokevirtual #10                 // Method java/lang/String.equals:(Ljava/lang/Object;)Z
     237: ifeq          251
     240: aload_0
     241: aload_1
     242: aload_2
     243: aload         4
     245: invokespecial #29                 // Method deleteAclRule:(Ljavax/servlet/http/HttpServletRequest;Ljavax/servlet/http/HttpServletResponse;Lcom/virtual/ssv/server/user/LoginInfo;)V
     248: goto          290
     251: ldc           #30                 // String checkStrategyReName
     253: aload         5
     255: invokevirtual #10                 // Method java/lang/String.equals:(Ljava/lang/Object;)Z
     258: ifeq          272
     261: aload_0
     262: aload_1
     263: aload_2
     264: aload         4
     266: invokespecial #31                 // Method checkStrategyReName:(Ljavax/servlet/http/HttpServletRequest;Ljavax/servlet/http/HttpServletResponse;Lcom/virtual/ssv/server/user/LoginInfo;)V
     269: goto          290
     272: ldc           #32                 // String applyToHost
     274: aload         5
     276: invokevirtual #10                 // Method java/lang/String.equals:(Ljava/lang/Object;)Z
     279: ifeq          290
     282: aload_0
     283: aload_1
     284: aload_2
     285: aload         4
     287: invokespecial #33                 // Method applyFwStrategyToDomain:(Ljavax/servlet/http/HttpServletRequest;Ljavax/servlet/http/HttpServletResponse;Lcom/virtual/ssv/server/user/LoginInfo;)V
     290: return

  private void modifyAclRule(javax.servlet.http.HttpServletRequest, javax.servlet.http.HttpServletResponse, com.virtual.ssv.server.user.LoginInfo);
    Code:
       0: new           #34                 // class com/virtual/ssv/server/entity/ResultJson
       3: dup
       4: invokespecial #35                 // Method com/virtual/ssv/server/entity/ResultJson."<init>":()V
       7: astore        4
       9: new           #36                 // class java/util/Date
      12: dup
      13: invokespecial #37                 // Method java/util/Date."<init>":()V
      16: astore        5
      18: aconst_null
      19: astore        6
      21: aload_1
      22: ldc           #38                 // String xml
      24: invokeinterface #8,  2            // InterfaceMethod javax/servlet/http/HttpServletRequest.getParameter:(Ljava/lang/String;)Ljava/lang/String;
      29: ldc           #39                 // String UTF-8
      31: invokestatic  #40                 // Method java/net/URLDecoder.decode:(Ljava/lang/String;Ljava/lang/String;)Ljava/lang/String;
      34: astore        7
      36: aconst_null
      37: aload         7
      39: if_acmpeq     212
      42: aload         7
      44: ldc           #41                 // class com/virtual/ssv/server/rs/client/entity/RsFirewallRule
      46: invokestatic  #42                 // Method com/virtual/common/FuncUtil.convertXmlToObject:(Ljava/lang/String;Ljava/lang/Class;)Ljava/lang/Object;
      49: checkcast     #41                 // class com/virtual/ssv/server/rs/client/entity/RsFirewallRule
      52: astore        6
      54: aload_0
      55: getfield      #43                 // Field reqHandle:Lcom/virtual/ssv/server/rs/client/RequestHandle;
      58: aload         6
      60: invokevirtual #44                 // Method com/virtual/ssv/server/rs/client/RequestHandle.modifyAclRule:(Lcom/virtual/ssv/server/rs/client/entity/RsFirewallRule;)Lcom/virtual/ssv/server/entity/ResultJson;
      63: astore        4
      65: new           #36                 // class java/util/Date
      68: dup
      69: invokespecial #37                 // Method java/util/Date."<init>":()V
      72: astore        8
      74: new           #45                 // class com/virtual/ssv/server/rs/client/entity/RsOperateLog
      77: dup
      78: invokespecial #46                 // Method com/virtual/ssv/server/rs/client/entity/RsOperateLog."<init>":()V
      81: astore        9
      83: aload         9
      85: aload_3
      86: invokevirtual #47                 // Method com/virtual/ssv/server/user/LoginInfo.getId:()Ljava/lang/Long;
      89: invokevirtual #48                 // Method com/virtual/ssv/server/rs/client/entity/RsOperateLog.setUserId:(Ljava/lang/Long;)V
      92: aload         9
      94: aload_3
      95: invokevirtual #49                 // Method com/virtual/ssv/server/user/LoginInfo.getOrgId:()Ljava/lang/Long;
      98: invokevirtual #50                 // Method com/virtual/ssv/server/rs/client/entity/RsOperateLog.setOrgId:(Ljava/lang/Long;)V
     101: aload         9
     103: aload_3
     104: invokevirtual #51                 // Method com/virtual/ssv/server/user/LoginInfo.getLoginName:()Ljava/lang/String;
     107: invokevirtual #52                 // Method com/virtual/ssv/server/rs/client/entity/RsOperateLog.setLoginName:(Ljava/lang/String;)V
     110: aload         9
     112: aload_3
     113: invokevirtual #53                 // Method com/virtual/ssv/server/user/LoginInfo.getUserName:()Ljava/lang/String;
     116: invokevirtual #54                 // Method com/virtual/ssv/server/rs/client/entity/RsOperateLog.setUserName:(Ljava/lang/String;)V
     119: aload         9
     121: aload_3
     122: invokevirtual #55                 // Method com/virtual/ssv/server/user/LoginInfo.getLoginIp:()Ljava/lang/String;
     125: invokevirtual #56                 // Method com/virtual/ssv/server/rs/client/entity/RsOperateLog.setAddress:(Ljava/lang/String;)V
     128: aload         9
     130: iconst_1
     131: invokestatic  #58                 // Method java/lang/Integer.valueOf:(I)Ljava/lang/Integer;
     134: invokevirtual #59                 // Method com/virtual/ssv/server/rs/client/entity/RsOperateLog.setCategory:(Ljava/lang/Integer;)V
     137: aload         9
     139: getstatic     #60                 // Field sm:Lcom/virtual/common/StringManager;
     142: ldc           #61                 // String firewall.rule.modify.operation
     144: invokevirtual #62                 // Method com/virtual/common/StringManager.getString:(Ljava/lang/String;)Ljava/lang/String;
     147: invokevirtual #63                 // Method com/virtual/ssv/server/rs/client/entity/RsOperateLog.setDescription:(Ljava/lang/String;)V
     150: aload         4
     152: invokevirtual #64                 // Method com/virtual/ssv/server/entity/ResultJson.getState:()I
     155: iconst_1
     156: if_icmpne     170
     159: aload         9
     161: getstatic     #65                 // Field com/virtual/ssv/server/rs/client/entity/RsOperateLog.RESULT_SUCCESS:Ljava/lang/Integer;
     164: invokevirtual #66                 // Method com/virtual/ssv/server/rs/client/entity/RsOperateLog.setResult:(Ljava/lang/Integer;)V
     167: goto          188
     170: aload         9
     172: getstatic     #67                 // Field com/virtual/ssv/server/rs/client/entity/RsOperateLog.RESULT_FAILURE:Ljava/lang/Integer;
     175: invokevirtual #66                 // Method com/virtual/ssv/server/rs/client/entity/RsOperateLog.setResult:(Ljava/lang/Integer;)V
     178: aload         9
     180: aload         4
     182: invokevirtual #68                 // Method com/virtual/ssv/server/entity/ResultJson.getMessage:()Ljava/lang/String;
     185: invokevirtual #69                 // Method com/virtual/ssv/server/rs/client/entity/RsOperateLog.setFailureReason:(Ljava/lang/String;)V
     188: aload         9
     190: aload         5
     192: invokevirtual #70                 // Method com/virtual/ssv/server/rs/client/entity/RsOperateLog.setStartTime:(Ljava/util/Date;)V
     195: aload         9
     197: aload         8
     199: invokevirtual #71                 // Method com/virtual/ssv/server/rs/client/entity/RsOperateLog.setEndTime:(Ljava/util/Date;)V
     202: aload_0
     203: getfield      #43                 // Field reqHandle:Lcom/virtual/ssv/server/rs/client/RequestHandle;
     206: aload         9
     208: invokevirtual #72                 // Method com/virtual/ssv/server/rs/client/RequestHandle.addUserLog:(Lcom/virtual/ssv/server/rs/client/entity/RsOperateLog;)Ljava/lang/Long;
     211: pop
     212: goto          311
     215: astore        5
     217: aload         5
     219: invokevirtual #74                 // Method com/virtual/common/AppException.getErrorCode:()I
     222: bipush        102
     224: if_icmpne     240
     227: aload         4
     229: bipush        102
     231: invokestatic  #76                 // Method com/virtual/common/ErrorCodes.getErrorMessage:(I)Ljava/lang/String;
     234: invokevirtual #77                 // Method com/virtual/ssv/server/entity/ResultJson.setErrorMsg:(Ljava/lang/String;)V
     237: goto          296
     240: aload         5
     242: invokevirtual #74                 // Method com/virtual/common/AppException.getErrorCode:()I
     245: bipush        103
     247: if_icmpne     263
     250: aload         4
     252: bipush        103
     254: invokestatic  #76                 // Method com/virtual/common/ErrorCodes.getErrorMessage:(I)Ljava/lang/String;
     257: invokevirtual #77                 // Method com/virtual/ssv/server/entity/ResultJson.setErrorMsg:(Ljava/lang/String;)V
     260: goto          296
     263: aload         5
     265: invokevirtual #74                 // Method com/virtual/common/AppException.getErrorCode:()I
     268: bipush        11
     270: if_icmpne     286
     273: aload         4
     275: bipush        11
     277: invokestatic  #76                 // Method com/virtual/common/ErrorCodes.getErrorMessage:(I)Ljava/lang/String;
     280: invokevirtual #77                 // Method com/virtual/ssv/server/entity/ResultJson.setErrorMsg:(Ljava/lang/String;)V
     283: goto          296
     286: aload         4
     288: aload         5
     290: invokevirtual #78                 // Method com/virtual/common/AppException.getMessage:()Ljava/lang/String;
     293: invokevirtual #77                 // Method com/virtual/ssv/server/entity/ResultJson.setErrorMsg:(Ljava/lang/String;)V
     296: goto          311
     299: astore        5
     301: aload         4
     303: aload         5
     305: invokevirtual #80                 // Method java/io/UnsupportedEncodingException.getMessage:()Ljava/lang/String;
     308: invokevirtual #77                 // Method com/virtual/ssv/server/entity/ResultJson.setErrorMsg:(Ljava/lang/String;)V
     311: aload_0
     312: aload_2
     313: aload_0
     314: getfield      #81                 // Field filterJson:Lcom/google/gson/Gson;
     317: aload         4
     319: invokevirtual #82                 // Method com/google/gson/Gson.toJson:(Ljava/lang/Object;)Ljava/lang/String;
     322: invokevirtual #83                 // Method write:(Ljavax/servlet/http/HttpServletResponse;Ljava/lang/String;)V
     325: return
    Exception table:
       from    to  target type
           9   212   215   Class com/virtual/common/AppException
           9   212   299   Class java/io/UnsupportedEncodingException

  private void deleteAclRule(javax.servlet.http.HttpServletRequest, javax.servlet.http.HttpServletResponse, com.virtual.ssv.server.user.LoginInfo);
    Code:
       0: new           #34                 // class com/virtual/ssv/server/entity/ResultJson
       3: dup
       4: invokespecial #35                 // Method com/virtual/ssv/server/entity/ResultJson."<init>":()V
       7: astore        4
       9: new           #36                 // class java/util/Date
      12: dup
      13: invokespecial #37                 // Method java/util/Date."<init>":()V
      16: astore        5
      18: aload_1
      19: ldc           #84                 // String ids
      21: invokeinterface #8,  2            // InterfaceMethod javax/servlet/http/HttpServletRequest.getParameter:(Ljava/lang/String;)Ljava/lang/String;
      26: astore        6
      28: aload         6
      30: invokestatic  #85                 // Method org/apache/commons/lang/StringUtils.isNotBlank:(Ljava/lang/String;)Z
      33: ifeq          194
      36: aload_0
      37: getfield      #43                 // Field reqHandle:Lcom/virtual/ssv/server/rs/client/RequestHandle;
      40: aload         6
      42: invokevirtual #86                 // Method com/virtual/ssv/server/rs/client/RequestHandle.deleteAclRuleById:(Ljava/lang/String;)Lcom/virtual/ssv/server/entity/ResultJson;
      45: astore        4
      47: new           #36                 // class java/util/Date
      50: dup
      51: invokespecial #37                 // Method java/util/Date."<init>":()V
      54: astore        7
      56: new           #45                 // class com/virtual/ssv/server/rs/client/entity/RsOperateLog
      59: dup
      60: invokespecial #46                 // Method com/virtual/ssv/server/rs/client/entity/RsOperateLog."<init>":()V
      63: astore        8
      65: aload         8
      67: aload_3
      68: invokevirtual #47                 // Method com/virtual/ssv/server/user/LoginInfo.getId:()Ljava/lang/Long;
      71: invokevirtual #48                 // Method com/virtual/ssv/server/rs/client/entity/RsOperateLog.setUserId:(Ljava/lang/Long;)V
      74: aload         8
      76: aload_3
      77: invokevirtual #49                 // Method com/virtual/ssv/server/user/LoginInfo.getOrgId:()Ljava/lang/Long;
      80: invokevirtual #50                 // Method com/virtual/ssv/server/rs/client/entity/RsOperateLog.setOrgId:(Ljava/lang/Long;)V
      83: aload         8
      85: aload_3
      86: invokevirtual #51                 // Method com/virtual/ssv/server/user/LoginInfo.getLoginName:()Ljava/lang/String;
      89: invokevirtual #52                 // Method com/virtual/ssv/server/rs/client/entity/RsOperateLog.setLoginName:(Ljava/lang/String;)V
      92: aload         8
      94: aload_3
      95: invokevirtual #53                 // Method com/virtual/ssv/server/user/LoginInfo.getUserName:()Ljava/lang/String;
      98: invokevirtual #54                 // Method com/virtual/ssv/server/rs/client/entity/RsOperateLog.setUserName:(Ljava/lang/String;)V
     101: aload         8
     103: aload_3
     104: invokevirtual #55                 // Method com/virtual/ssv/server/user/LoginInfo.getLoginIp:()Ljava/lang/String;
     107: invokevirtual #56                 // Method com/virtual/ssv/server/rs/client/entity/RsOperateLog.setAddress:(Ljava/lang/String;)V
     110: aload         8
     112: iconst_1
     113: invokestatic  #58                 // Method java/lang/Integer.valueOf:(I)Ljava/lang/Integer;
     116: invokevirtual #59                 // Method com/virtual/ssv/server/rs/client/entity/RsOperateLog.setCategory:(Ljava/lang/Integer;)V
     119: aload         8
     121: getstatic     #60                 // Field sm:Lcom/virtual/common/StringManager;
     124: ldc           #87                 // String firewall.rule.delete.operation
     126: invokevirtual #62                 // Method com/virtual/common/StringManager.getString:(Ljava/lang/String;)Ljava/lang/String;
     129: invokevirtual #63                 // Method com/virtual/ssv/server/rs/client/entity/RsOperateLog.setDescription:(Ljava/lang/String;)V
     132: aload         4
     134: invokevirtual #64                 // Method com/virtual/ssv/server/entity/ResultJson.getState:()I
     137: iconst_1
     138: if_icmpne     152
     141: aload         8
     143: getstatic     #65                 // Field com/virtual/ssv/server/rs/client/entity/RsOperateLog.RESULT_SUCCESS:Ljava/lang/Integer;
     146: invokevirtual #66                 // Method com/virtual/ssv/server/rs/client/entity/RsOperateLog.setResult:(Ljava/lang/Integer;)V
     149: goto          170
     152: aload         8
     154: getstatic     #67                 // Field com/virtual/ssv/server/rs/client/entity/RsOperateLog.RESULT_FAILURE:Ljava/lang/Integer;
     157: invokevirtual #66                 // Method com/virtual/ssv/server/rs/client/entity/RsOperateLog.setResult:(Ljava/lang/Integer;)V
     160: aload         8
     162: aload         4
     164: invokevirtual #68                 // Method com/virtual/ssv/server/entity/ResultJson.getMessage:()Ljava/lang/String;
     167: invokevirtual #69                 // Method com/virtual/ssv/server/rs/client/entity/RsOperateLog.setFailureReason:(Ljava/lang/String;)V
     170: aload         8
     172: aload         5
     174: invokevirtual #70                 // Method com/virtual/ssv/server/rs/client/entity/RsOperateLog.setStartTime:(Ljava/util/Date;)V
     177: aload         8
     179: aload         7
     181: invokevirtual #71                 // Method com/virtual/ssv/server/rs/client/entity/RsOperateLog.setEndTime:(Ljava/util/Date;)V
     184: aload_0
     185: getfield      #43                 // Field reqHandle:Lcom/virtual/ssv/server/rs/client/RequestHandle;
     188: aload         8
     190: invokevirtual #72                 // Method com/virtual/ssv/server/rs/client/RequestHandle.addUserLog:(Lcom/virtual/ssv/server/rs/client/entity/RsOperateLog;)Ljava/lang/Long;
     193: pop
     194: goto          278
     197: astore        5
     199: aload         5
     201: invokevirtual #74                 // Method com/virtual/common/AppException.getErrorCode:()I
     204: bipush        102
     206: if_icmpne     222
     209: aload         4
     211: bipush        102
     213: invokestatic  #76                 // Method com/virtual/common/ErrorCodes.getErrorMessage:(I)Ljava/lang/String;
     216: invokevirtual #77                 // Method com/virtual/ssv/server/entity/ResultJson.setErrorMsg:(Ljava/lang/String;)V
     219: goto          278
     222: aload         5
     224: invokevirtual #74                 // Method com/virtual/common/AppException.getErrorCode:()I
     227: bipush        103
     229: if_icmpne     245
     232: aload         4
     234: bipush        103
     236: invokestatic  #76                 // Method com/virtual/common/ErrorCodes.getErrorMessage:(I)Ljava/lang/String;
     239: invokevirtual #77                 // Method com/virtual/ssv/server/entity/ResultJson.setErrorMsg:(Ljava/lang/String;)V
     242: goto          278
     245: aload         5
     247: invokevirtual #74                 // Method com/virtual/common/AppException.getErrorCode:()I
     250: bipush        11
     252: if_icmpne     268
     255: aload         4
     257: bipush        11
     259: invokestatic  #76                 // Method com/virtual/common/ErrorCodes.getErrorMessage:(I)Ljava/lang/String;
     262: invokevirtual #77                 // Method com/virtual/ssv/server/entity/ResultJson.setErrorMsg:(Ljava/lang/String;)V
     265: goto          278
     268: aload         4
     270: aload         5
     272: invokevirtual #78                 // Method com/virtual/common/AppException.getMessage:()Ljava/lang/String;
     275: invokevirtual #77                 // Method com/virtual/ssv/server/entity/ResultJson.setErrorMsg:(Ljava/lang/String;)V
     278: aload_0
     279: aload_2
     280: aload_0
     281: getfield      #81                 // Field filterJson:Lcom/google/gson/Gson;
     284: aload         4
     286: invokevirtual #82                 // Method com/google/gson/Gson.toJson:(Ljava/lang/Object;)Ljava/lang/String;
     289: invokevirtual #83                 // Method write:(Ljavax/servlet/http/HttpServletResponse;Ljava/lang/String;)V
     292: return
    Exception table:
       from    to  target type
           9   194   197   Class com/virtual/common/AppException

  private void getAclRuleById(javax.servlet.http.HttpServletRequest, javax.servlet.http.HttpServletResponse, com.virtual.ssv.server.user.LoginInfo);
    Code:
       0: new           #34                 // class com/virtual/ssv/server/entity/ResultJson
       3: dup
       4: invokespecial #35                 // Method com/virtual/ssv/server/entity/ResultJson."<init>":()V
       7: astore        4
       9: aload_1
      10: ldc           #88                 // String id
      12: invokeinterface #8,  2            // InterfaceMethod javax/servlet/http/HttpServletRequest.getParameter:(Ljava/lang/String;)Ljava/lang/String;
      17: astore        5
      19: aload         5
      21: invokestatic  #89                 // Method org/apache/commons/lang/StringUtils.isNotEmpty:(Ljava/lang/String;)Z
      24: ifeq          56
      27: aload_0
      28: getfield      #43                 // Field reqHandle:Lcom/virtual/ssv/server/rs/client/RequestHandle;
      31: aload         5
      33: invokevirtual #90                 // Method com/virtual/ssv/server/rs/client/RequestHandle.getAclRuleById:(Ljava/lang/String;)Lcom/virtual/ssv/server/rs/client/entity/RsUserAclRule;
      36: astore        6
      38: aload_0
      39: getfield      #91                 // Field gson:Lcom/google/gson/Gson;
      42: aload         6
      44: invokevirtual #82                 // Method com/google/gson/Gson.toJson:(Ljava/lang/Object;)Ljava/lang/String;
      47: astore        7
      49: aload_0
      50: aload_2
      51: aload         7
      53: invokevirtual #83                 // Method write:(Ljavax/servlet/http/HttpServletResponse;Ljava/lang/String;)V
      56: goto          154
      59: astore        5
      61: aload         5
      63: invokevirtual #74                 // Method com/virtual/common/AppException.getErrorCode:()I
      66: bipush        102
      68: if_icmpne     84
      71: aload         4
      73: bipush        102
      75: invokestatic  #76                 // Method com/virtual/common/ErrorCodes.getErrorMessage:(I)Ljava/lang/String;
      78: invokevirtual #77                 // Method com/virtual/ssv/server/entity/ResultJson.setErrorMsg:(Ljava/lang/String;)V
      81: goto          140
      84: aload         5
      86: invokevirtual #74                 // Method com/virtual/common/AppException.getErrorCode:()I
      89: bipush        103
      91: if_icmpne     107
      94: aload         4
      96: bipush        103
      98: invokestatic  #76                 // Method com/virtual/common/ErrorCodes.getErrorMessage:(I)Ljava/lang/String;
     101: invokevirtual #77                 // Method com/virtual/ssv/server/entity/ResultJson.setErrorMsg:(Ljava/lang/String;)V
     104: goto          140
     107: aload         5
     109: invokevirtual #74                 // Method com/virtual/common/AppException.getErrorCode:()I
     112: bipush        11
     114: if_icmpne     130
     117: aload         4
     119: bipush        11
     121: invokestatic  #76                 // Method com/virtual/common/ErrorCodes.getErrorMessage:(I)Ljava/lang/String;
     124: invokevirtual #77                 // Method com/virtual/ssv/server/entity/ResultJson.setErrorMsg:(Ljava/lang/String;)V
     127: goto          140
     130: aload         4
     132: aload         5
     134: invokevirtual #78                 // Method com/virtual/common/AppException.getMessage:()Ljava/lang/String;
     137: invokevirtual #77                 // Method com/virtual/ssv/server/entity/ResultJson.setErrorMsg:(Ljava/lang/String;)V
     140: aload_0
     141: aload_2
     142: aload_0
     143: getfield      #81                 // Field filterJson:Lcom/google/gson/Gson;
     146: aload         4
     148: invokevirtual #82                 // Method com/google/gson/Gson.toJson:(Ljava/lang/Object;)Ljava/lang/String;
     151: invokevirtual #83                 // Method write:(Ljavax/servlet/http/HttpServletResponse;Ljava/lang/String;)V
     154: return
    Exception table:
       from    to  target type
           9    56    59   Class com/virtual/common/AppException

  private void applyAclRule(javax.servlet.http.HttpServletRequest, javax.servlet.http.HttpServletResponse, com.virtual.ssv.server.user.LoginInfo);
    Code:
       0: new           #34                 // class com/virtual/ssv/server/entity/ResultJson
       3: dup
       4: invokespecial #35                 // Method com/virtual/ssv/server/entity/ResultJson."<init>":()V
       7: astore        4
       9: new           #36                 // class java/util/Date
      12: dup
      13: invokespecial #37                 // Method java/util/Date."<init>":()V
      16: astore        5
      18: aconst_null
      19: astore        6
      21: aload_1
      22: ldc           #38                 // String xml
      24: invokeinterface #8,  2            // InterfaceMethod javax/servlet/http/HttpServletRequest.getParameter:(Ljava/lang/String;)Ljava/lang/String;
      29: ldc           #39                 // String UTF-8
      31: invokestatic  #40                 // Method java/net/URLDecoder.decode:(Ljava/lang/String;Ljava/lang/String;)Ljava/lang/String;
      34: astore        7
      36: aconst_null
      37: aload         7
      39: if_acmpeq     226
      42: aload         7
      44: ldc           #41                 // class com/virtual/ssv/server/rs/client/entity/RsFirewallRule
      46: invokestatic  #42                 // Method com/virtual/common/FuncUtil.convertXmlToObject:(Ljava/lang/String;Ljava/lang/Class;)Ljava/lang/Object;
      49: checkcast     #41                 // class com/virtual/ssv/server/rs/client/entity/RsFirewallRule
      52: astore        6
      54: aload_0
      55: getfield      #43                 // Field reqHandle:Lcom/virtual/ssv/server/rs/client/RequestHandle;
      58: aload         6
      60: invokevirtual #92                 // Method com/virtual/ssv/server/rs/client/RequestHandle.addAclRule:(Lcom/virtual/ssv/server/rs/client/entity/RsFirewallRule;)Lcom/virtual/ssv/server/entity/ResultJson;
      63: astore        4
      65: new           #36                 // class java/util/Date
      68: dup
      69: invokespecial #37                 // Method java/util/Date."<init>":()V
      72: astore        8
      74: new           #45                 // class com/virtual/ssv/server/rs/client/entity/RsOperateLog
      77: dup
      78: invokespecial #46                 // Method com/virtual/ssv/server/rs/client/entity/RsOperateLog."<init>":()V
      81: astore        9
      83: aload         9
      85: aload_3
      86: invokevirtual #47                 // Method com/virtual/ssv/server/user/LoginInfo.getId:()Ljava/lang/Long;
      89: invokevirtual #48                 // Method com/virtual/ssv/server/rs/client/entity/RsOperateLog.setUserId:(Ljava/lang/Long;)V
      92: aload         9
      94: aload_3
      95: invokevirtual #49                 // Method com/virtual/ssv/server/user/LoginInfo.getOrgId:()Ljava/lang/Long;
      98: invokevirtual #50                 // Method com/virtual/ssv/server/rs/client/entity/RsOperateLog.setOrgId:(Ljava/lang/Long;)V
     101: aload         9
     103: aload_3
     104: invokevirtual #51                 // Method com/virtual/ssv/server/user/LoginInfo.getLoginName:()Ljava/lang/String;
     107: invokevirtual #52                 // Method com/virtual/ssv/server/rs/client/entity/RsOperateLog.setLoginName:(Ljava/lang/String;)V
     110: aload         9
     112: aload_3
     113: invokevirtual #53                 // Method com/virtual/ssv/server/user/LoginInfo.getUserName:()Ljava/lang/String;
     116: invokevirtual #54                 // Method com/virtual/ssv/server/rs/client/entity/RsOperateLog.setUserName:(Ljava/lang/String;)V
     119: aload         9
     121: aload_3
     122: invokevirtual #55                 // Method com/virtual/ssv/server/user/LoginInfo.getLoginIp:()Ljava/lang/String;
     125: invokevirtual #56                 // Method com/virtual/ssv/server/rs/client/entity/RsOperateLog.setAddress:(Ljava/lang/String;)V
     128: aload         9
     130: iconst_1
     131: invokestatic  #58                 // Method java/lang/Integer.valueOf:(I)Ljava/lang/Integer;
     134: invokevirtual #59                 // Method com/virtual/ssv/server/rs/client/entity/RsOperateLog.setCategory:(Ljava/lang/Integer;)V
     137: aload         9
     139: getstatic     #60                 // Field sm:Lcom/virtual/common/StringManager;
     142: ldc           #93                 // String firewall.rule.add.operation
     144: invokevirtual #62                 // Method com/virtual/common/StringManager.getString:(Ljava/lang/String;)Ljava/lang/String;
     147: invokevirtual #63                 // Method com/virtual/ssv/server/rs/client/entity/RsOperateLog.setDescription:(Ljava/lang/String;)V
     150: aload         4
     152: invokevirtual #64                 // Method com/virtual/ssv/server/entity/ResultJson.getState:()I
     155: iconst_1
     156: if_icmpne     170
     159: aload         9
     161: getstatic     #65                 // Field com/virtual/ssv/server/rs/client/entity/RsOperateLog.RESULT_SUCCESS:Ljava/lang/Integer;
     164: invokevirtual #66                 // Method com/virtual/ssv/server/rs/client/entity/RsOperateLog.setResult:(Ljava/lang/Integer;)V
     167: goto          188
     170: aload         9
     172: getstatic     #67                 // Field com/virtual/ssv/server/rs/client/entity/RsOperateLog.RESULT_FAILURE:Ljava/lang/Integer;
     175: invokevirtual #66                 // Method com/virtual/ssv/server/rs/client/entity/RsOperateLog.setResult:(Ljava/lang/Integer;)V
     178: aload         9
     180: aload         4
     182: invokevirtual #68                 // Method com/virtual/ssv/server/entity/ResultJson.getMessage:()Ljava/lang/String;
     185: invokevirtual #69                 // Method com/virtual/ssv/server/rs/client/entity/RsOperateLog.setFailureReason:(Ljava/lang/String;)V
     188: aload         9
     190: aload         5
     192: invokevirtual #70                 // Method com/virtual/ssv/server/rs/client/entity/RsOperateLog.setStartTime:(Ljava/util/Date;)V
     195: aload         9
     197: aload         8
     199: invokevirtual #71                 // Method com/virtual/ssv/server/rs/client/entity/RsOperateLog.setEndTime:(Ljava/util/Date;)V
     202: aload_0
     203: getfield      #43                 // Field reqHandle:Lcom/virtual/ssv/server/rs/client/RequestHandle;
     206: aload         9
     208: invokevirtual #72                 // Method com/virtual/ssv/server/rs/client/RequestHandle.addUserLog:(Lcom/virtual/ssv/server/rs/client/entity/RsOperateLog;)Ljava/lang/Long;
     211: pop
     212: aload_0
     213: aload_2
     214: aload_0
     215: getfield      #81                 // Field filterJson:Lcom/google/gson/Gson;
     218: aload         4
     220: invokevirtual #82                 // Method com/google/gson/Gson.toJson:(Ljava/lang/Object;)Ljava/lang/String;
     223: invokevirtual #83                 // Method write:(Ljavax/servlet/http/HttpServletResponse;Ljava/lang/String;)V
     226: goto          339
     229: astore        5
     231: aload         5
     233: invokevirtual #74                 // Method com/virtual/common/AppException.getErrorCode:()I
     236: bipush        102
     238: if_icmpne     254
     241: aload         4
     243: bipush        102
     245: invokestatic  #76                 // Method com/virtual/common/ErrorCodes.getErrorMessage:(I)Ljava/lang/String;
     248: invokevirtual #77                 // Method com/virtual/ssv/server/entity/ResultJson.setErrorMsg:(Ljava/lang/String;)V
     251: goto          310
     254: aload         5
     256: invokevirtual #74                 // Method com/virtual/common/AppException.getErrorCode:()I
     259: bipush        103
     261: if_icmpne     277
     264: aload         4
     266: bipush        103
     268: invokestatic  #76                 // Method com/virtual/common/ErrorCodes.getErrorMessage:(I)Ljava/lang/String;
     271: invokevirtual #77                 // Method com/virtual/ssv/server/entity/ResultJson.setErrorMsg:(Ljava/lang/String;)V
     274: goto          310
     277: aload         5
     279: invokevirtual #74                 // Method com/virtual/common/AppException.getErrorCode:()I
     282: bipush        11
     284: if_icmpne     300
     287: aload         4
     289: bipush        11
     291: invokestatic  #76                 // Method com/virtual/common/ErrorCodes.getErrorMessage:(I)Ljava/lang/String;
     294: invokevirtual #77                 // Method com/virtual/ssv/server/entity/ResultJson.setErrorMsg:(Ljava/lang/String;)V
     297: goto          310
     300: aload         4
     302: aload         5
     304: invokevirtual #78                 // Method com/virtual/common/AppException.getMessage:()Ljava/lang/String;
     307: invokevirtual #77                 // Method com/virtual/ssv/server/entity/ResultJson.setErrorMsg:(Ljava/lang/String;)V
     310: aload_0
     311: aload_2
     312: aload_0
     313: getfield      #81                 // Field filterJson:Lcom/google/gson/Gson;
     316: aload         4
     318: invokevirtual #82                 // Method com/google/gson/Gson.toJson:(Ljava/lang/Object;)Ljava/lang/String;
     321: invokevirtual #83                 // Method write:(Ljavax/servlet/http/HttpServletResponse;Ljava/lang/String;)V
     324: goto          339
     327: astore        5
     329: aload         4
     331: aload         5
     333: invokevirtual #80                 // Method java/io/UnsupportedEncodingException.getMessage:()Ljava/lang/String;
     336: invokevirtual #77                 // Method com/virtual/ssv/server/entity/ResultJson.setErrorMsg:(Ljava/lang/String;)V
     339: return
    Exception table:
       from    to  target type
           9   226   229   Class com/virtual/common/AppException
           9   226   327   Class java/io/UnsupportedEncodingException

  private void getRuleList(javax.servlet.http.HttpServletRequest, javax.servlet.http.HttpServletResponse, com.virtual.ssv.server.user.LoginInfo);
    Code:
       0: new           #94                 // class com/virtual/ssv/server/entity/CommonListJson
       3: dup
       4: invokespecial #95                 // Method com/virtual/ssv/server/entity/CommonListJson."<init>":()V
       7: astore        4
       9: aload_1
      10: ldc           #88                 // String id
      12: invokeinterface #8,  2            // InterfaceMethod javax/servlet/http/HttpServletRequest.getParameter:(Ljava/lang/String;)Ljava/lang/String;
      17: astore        5
      19: aload_1
      20: ldc           #96                 // String direction
      22: invokeinterface #8,  2            // InterfaceMethod javax/servlet/http/HttpServletRequest.getParameter:(Ljava/lang/String;)Ljava/lang/String;
      27: astore        6
      29: aload         5
      31: invokestatic  #89                 // Method org/apache/commons/lang/StringUtils.isNotEmpty:(Ljava/lang/String;)Z
      34: ifeq          131
      37: aload_1
      38: ldc           #97                 // String page
      40: invokeinterface #8,  2            // InterfaceMethod javax/servlet/http/HttpServletRequest.getParameter:(Ljava/lang/String;)Ljava/lang/String;
      45: astore        7
      47: aload_1
      48: ldc           #98                 // String rows
      50: invokeinterface #8,  2            // InterfaceMethod javax/servlet/http/HttpServletRequest.getParameter:(Ljava/lang/String;)Ljava/lang/String;
      55: astore        8
      57: aconst_null
      58: astore        9
      60: aconst_null
      61: astore        10
      63: aconst_null
      64: astore        11
      66: aload         7
      68: ifnull        114
      71: aload         8
      73: ifnull        114
      76: aload         7
      78: invokestatic  #99                 // Method java/lang/Integer.parseInt:(Ljava/lang/String;)I
      81: invokestatic  #58                 // Method java/lang/Integer.valueOf:(I)Ljava/lang/Integer;
      84: astore        9
      86: aload         8
      88: invokestatic  #99                 // Method java/lang/Integer.parseInt:(Ljava/lang/String;)I
      91: invokestatic  #58                 // Method java/lang/Integer.valueOf:(I)Ljava/lang/Integer;
      94: astore        10
      96: aload         10
      98: invokevirtual #100                // Method java/lang/Integer.intValue:()I
     101: aload         9
     103: invokevirtual #100                // Method java/lang/Integer.intValue:()I
     106: iconst_1
     107: isub
     108: imul
     109: invokestatic  #58                 // Method java/lang/Integer.valueOf:(I)Ljava/lang/Integer;
     112: astore        11
     114: aload_0
     115: getfield      #43                 // Field reqHandle:Lcom/virtual/ssv/server/rs/client/RequestHandle;
     118: aload         11
     120: aload         10
     122: aload         5
     124: aload         6
     126: invokevirtual #101                // Method com/virtual/ssv/server/rs/client/RequestHandle.getAclRuleList:(Ljava/lang/Integer;Ljava/lang/Integer;Ljava/lang/String;Ljava/lang/String;)Lcom/virtual/ssv/server/entity/CommonListJson;
     129: astore        4
     131: goto          246
     134: astore        5
     136: aload         4
     138: getstatic     #60                 // Field sm:Lcom/virtual/common/StringManager;
     141: ldc           #102                // String operError
     143: invokevirtual #62                 // Method com/virtual/common/StringManager.getString:(Ljava/lang/String;)Ljava/lang/String;
     146: invokevirtual #103                // Method com/virtual/ssv/server/entity/CommonListJson.setTitle:(Ljava/lang/String;)V
     149: aload         5
     151: invokevirtual #74                 // Method com/virtual/common/AppException.getErrorCode:()I
     154: bipush        102
     156: if_icmpne     172
     159: aload         4
     161: bipush        102
     163: invokestatic  #76                 // Method com/virtual/common/ErrorCodes.getErrorMessage:(I)Ljava/lang/String;
     166: invokevirtual #104                // Method com/virtual/ssv/server/entity/CommonListJson.setMessage:(Ljava/lang/String;)V
     169: goto          228
     172: aload         5
     174: invokevirtual #74                 // Method com/virtual/common/AppException.getErrorCode:()I
     177: bipush        103
     179: if_icmpne     195
     182: aload         4
     184: bipush        103
     186: invokestatic  #76                 // Method com/virtual/common/ErrorCodes.getErrorMessage:(I)Ljava/lang/String;
     189: invokevirtual #104                // Method com/virtual/ssv/server/entity/CommonListJson.setMessage:(Ljava/lang/String;)V
     192: goto          228
     195: aload         5
     197: invokevirtual #74                 // Method com/virtual/common/AppException.getErrorCode:()I
     200: bipush        11
     202: if_icmpne     218
     205: aload         4
     207: bipush        11
     209: invokestatic  #76                 // Method com/virtual/common/ErrorCodes.getErrorMessage:(I)Ljava/lang/String;
     212: invokevirtual #104                // Method com/virtual/ssv/server/entity/CommonListJson.setMessage:(Ljava/lang/String;)V
     215: goto          228
     218: aload         4
     220: aload         5
     222: invokevirtual #78                 // Method com/virtual/common/AppException.getMessage:()Ljava/lang/String;
     225: invokevirtual #104                // Method com/virtual/ssv/server/entity/CommonListJson.setMessage:(Ljava/lang/String;)V
     228: aload         4
     230: iconst_0
     231: invokevirtual #105                // Method com/virtual/ssv/server/entity/CommonListJson.setState:(I)V
     234: aload         4
     236: new           #106                // class java/util/ArrayList
     239: dup
     240: invokespecial #107                // Method java/util/ArrayList."<init>":()V
     243: invokevirtual #108                // Method com/virtual/ssv/server/entity/CommonListJson.setRows:(Ljava/util/List;)V
     246: aload_0
     247: aload_2
     248: aload_0
     249: getfield      #91                 // Field gson:Lcom/google/gson/Gson;
     252: aload         4
     254: invokevirtual #82                 // Method com/google/gson/Gson.toJson:(Ljava/lang/Object;)Ljava/lang/String;
     257: invokevirtual #83                 // Method write:(Ljavax/servlet/http/HttpServletResponse;Ljava/lang/String;)V
     260: return
    Exception table:
       from    to  target type
           9   131   134   Class com/virtual/common/AppException

  private void deleteFwStrategy(javax.servlet.http.HttpServletRequest, javax.servlet.http.HttpServletResponse, com.virtual.ssv.server.user.LoginInfo);
    Code:
       0: new           #34                 // class com/virtual/ssv/server/entity/ResultJson
       3: dup
       4: invokespecial #35                 // Method com/virtual/ssv/server/entity/ResultJson."<init>":()V
       7: astore        4
       9: new           #36                 // class java/util/Date
      12: dup
      13: invokespecial #37                 // Method java/util/Date."<init>":()V
      16: astore        5
      18: aload_1
      19: ldc           #88                 // String id
      21: invokeinterface #8,  2            // InterfaceMethod javax/servlet/http/HttpServletRequest.getParameter:(Ljava/lang/String;)Ljava/lang/String;
      26: astore        6
      28: aload_1
      29: ldc           #109                // String name
      31: invokeinterface #8,  2            // InterfaceMethod javax/servlet/http/HttpServletRequest.getParameter:(Ljava/lang/String;)Ljava/lang/String;
      36: astore        7
      38: aload         6
      40: invokestatic  #89                 // Method org/apache/commons/lang/StringUtils.isNotEmpty:(Ljava/lang/String;)Z
      43: ifeq          229
      46: aload_0
      47: getfield      #43                 // Field reqHandle:Lcom/virtual/ssv/server/rs/client/RequestHandle;
      50: aload         6
      52: aload         7
      54: invokevirtual #110                // Method com/virtual/ssv/server/rs/client/RequestHandle.deleteFwStrategyById:(Ljava/lang/String;Ljava/lang/String;)Lcom/virtual/ssv/server/entity/ResultJson;
      57: astore        8
      59: new           #36                 // class java/util/Date
      62: dup
      63: invokespecial #37                 // Method java/util/Date."<init>":()V
      66: astore        9
      68: new           #45                 // class com/virtual/ssv/server/rs/client/entity/RsOperateLog
      71: dup
      72: invokespecial #46                 // Method com/virtual/ssv/server/rs/client/entity/RsOperateLog."<init>":()V
      75: astore        10
      77: aload         10
      79: aload_3
      80: invokevirtual #47                 // Method com/virtual/ssv/server/user/LoginInfo.getId:()Ljava/lang/Long;
      83: invokevirtual #48                 // Method com/virtual/ssv/server/rs/client/entity/RsOperateLog.setUserId:(Ljava/lang/Long;)V
      86: aload         10
      88: aload_3
      89: invokevirtual #49                 // Method com/virtual/ssv/server/user/LoginInfo.getOrgId:()Ljava/lang/Long;
      92: invokevirtual #50                 // Method com/virtual/ssv/server/rs/client/entity/RsOperateLog.setOrgId:(Ljava/lang/Long;)V
      95: aload         10
      97: aload_3
      98: invokevirtual #51                 // Method com/virtual/ssv/server/user/LoginInfo.getLoginName:()Ljava/lang/String;
     101: invokevirtual #52                 // Method com/virtual/ssv/server/rs/client/entity/RsOperateLog.setLoginName:(Ljava/lang/String;)V
     104: aload         10
     106: aload_3
     107: invokevirtual #53                 // Method com/virtual/ssv/server/user/LoginInfo.getUserName:()Ljava/lang/String;
     110: invokevirtual #54                 // Method com/virtual/ssv/server/rs/client/entity/RsOperateLog.setUserName:(Ljava/lang/String;)V
     113: aload         10
     115: aload_3
     116: invokevirtual #55                 // Method com/virtual/ssv/server/user/LoginInfo.getLoginIp:()Ljava/lang/String;
     119: invokevirtual #56                 // Method com/virtual/ssv/server/rs/client/entity/RsOperateLog.setAddress:(Ljava/lang/String;)V
     122: aload         10
     124: iconst_1
     125: invokestatic  #58                 // Method java/lang/Integer.valueOf:(I)Ljava/lang/Integer;
     128: invokevirtual #59                 // Method com/virtual/ssv/server/rs/client/entity/RsOperateLog.setCategory:(Ljava/lang/Integer;)V
     131: aload         10
     133: getstatic     #60                 // Field sm:Lcom/virtual/common/StringManager;
     136: ldc           #111                // String firewall.strategy.delete.operation
     138: iconst_1
     139: anewarray     #112                // class java/lang/Object
     142: dup
     143: iconst_0
     144: aload         7
     146: aastore
     147: invokevirtual #113                // Method com/virtual/common/StringManager.getString:(Ljava/lang/String;[Ljava/lang/Object;)Ljava/lang/String;
     150: invokevirtual #63                 // Method com/virtual/ssv/server/rs/client/entity/RsOperateLog.setDescription:(Ljava/lang/String;)V
     153: aload         8
     155: invokevirtual #64                 // Method com/virtual/ssv/server/entity/ResultJson.getState:()I
     158: iconst_1
     159: if_icmpne     173
     162: aload         10
     164: getstatic     #65                 // Field com/virtual/ssv/server/rs/client/entity/RsOperateLog.RESULT_SUCCESS:Ljava/lang/Integer;
     167: invokevirtual #66                 // Method com/virtual/ssv/server/rs/client/entity/RsOperateLog.setResult:(Ljava/lang/Integer;)V
     170: goto          191
     173: aload         10
     175: getstatic     #67                 // Field com/virtual/ssv/server/rs/client/entity/RsOperateLog.RESULT_FAILURE:Ljava/lang/Integer;
     178: invokevirtual #66                 // Method com/virtual/ssv/server/rs/client/entity/RsOperateLog.setResult:(Ljava/lang/Integer;)V
     181: aload         10
     183: aload         8
     185: invokevirtual #68                 // Method com/virtual/ssv/server/entity/ResultJson.getMessage:()Ljava/lang/String;
     188: invokevirtual #69                 // Method com/virtual/ssv/server/rs/client/entity/RsOperateLog.setFailureReason:(Ljava/lang/String;)V
     191: aload         10
     193: aload         5
     195: invokevirtual #70                 // Method com/virtual/ssv/server/rs/client/entity/RsOperateLog.setStartTime:(Ljava/util/Date;)V
     198: aload         10
     200: aload         9
     202: invokevirtual #71                 // Method com/virtual/ssv/server/rs/client/entity/RsOperateLog.setEndTime:(Ljava/util/Date;)V
     205: aload_0
     206: getfield      #43                 // Field reqHandle:Lcom/virtual/ssv/server/rs/client/RequestHandle;
     209: aload         10
     211: invokevirtual #72                 // Method com/virtual/ssv/server/rs/client/RequestHandle.addUserLog:(Lcom/virtual/ssv/server/rs/client/entity/RsOperateLog;)Ljava/lang/Long;
     214: pop
     215: aload_0
     216: aload_2
     217: aload_0
     218: getfield      #81                 // Field filterJson:Lcom/google/gson/Gson;
     221: aload         8
     223: invokevirtual #82                 // Method com/google/gson/Gson.toJson:(Ljava/lang/Object;)Ljava/lang/String;
     226: invokevirtual #83                 // Method write:(Ljavax/servlet/http/HttpServletResponse;Ljava/lang/String;)V
     229: goto          327
     232: astore        5
     234: aload         5
     236: invokevirtual #74                 // Method com/virtual/common/AppException.getErrorCode:()I
     239: bipush        102
     241: if_icmpne     257
     244: aload         4
     246: bipush        102
     248: invokestatic  #76                 // Method com/virtual/common/ErrorCodes.getErrorMessage:(I)Ljava/lang/String;
     251: invokevirtual #77                 // Method com/virtual/ssv/server/entity/ResultJson.setErrorMsg:(Ljava/lang/String;)V
     254: goto          313
     257: aload         5
     259: invokevirtual #74                 // Method com/virtual/common/AppException.getErrorCode:()I
     262: bipush        103
     264: if_icmpne     280
     267: aload         4
     269: bipush        103
     271: invokestatic  #76                 // Method com/virtual/common/ErrorCodes.getErrorMessage:(I)Ljava/lang/String;
     274: invokevirtual #77                 // Method com/virtual/ssv/server/entity/ResultJson.setErrorMsg:(Ljava/lang/String;)V
     277: goto          313
     280: aload         5
     282: invokevirtual #74                 // Method com/virtual/common/AppException.getErrorCode:()I
     285: bipush        11
     287: if_icmpne     303
     290: aload         4
     292: bipush        11
     294: invokestatic  #76                 // Method com/virtual/common/ErrorCodes.getErrorMessage:(I)Ljava/lang/String;
     297: invokevirtual #77                 // Method com/virtual/ssv/server/entity/ResultJson.setErrorMsg:(Ljava/lang/String;)V
     300: goto          313
     303: aload         4
     305: aload         5
     307: invokevirtual #78                 // Method com/virtual/common/AppException.getMessage:()Ljava/lang/String;
     310: invokevirtual #77                 // Method com/virtual/ssv/server/entity/ResultJson.setErrorMsg:(Ljava/lang/String;)V
     313: aload_0
     314: aload_2
     315: aload_0
     316: getfield      #81                 // Field filterJson:Lcom/google/gson/Gson;
     319: aload         4
     321: invokevirtual #82                 // Method com/google/gson/Gson.toJson:(Ljava/lang/Object;)Ljava/lang/String;
     324: invokevirtual #83                 // Method write:(Ljavax/servlet/http/HttpServletResponse;Ljava/lang/String;)V
     327: return
    Exception table:
       from    to  target type
           9   229   232   Class com/virtual/common/AppException

  private void modifyFwStrategy(javax.servlet.http.HttpServletRequest, javax.servlet.http.HttpServletResponse, com.virtual.ssv.server.user.LoginInfo);
    Code:
       0: new           #34                 // class com/virtual/ssv/server/entity/ResultJson
       3: dup
       4: invokespecial #35                 // Method com/virtual/ssv/server/entity/ResultJson."<init>":()V
       7: astore        4
       9: new           #36                 // class java/util/Date
      12: dup
      13: invokespecial #37                 // Method java/util/Date."<init>":()V
      16: astore        5
      18: aconst_null
      19: astore        6
      21: aload_1
      22: ldc           #38                 // String xml
      24: invokeinterface #8,  2            // InterfaceMethod javax/servlet/http/HttpServletRequest.getParameter:(Ljava/lang/String;)Ljava/lang/String;
      29: ldc           #39                 // String UTF-8
      31: invokestatic  #40                 // Method java/net/URLDecoder.decode:(Ljava/lang/String;Ljava/lang/String;)Ljava/lang/String;
      34: astore        7
      36: aconst_null
      37: aload         7
      39: if_acmpeq     238
      42: aload         7
      44: ldc           #114                // class com/virtual/ssv/server/rs/client/entity/RsUserFirewall
      46: invokestatic  #42                 // Method com/virtual/common/FuncUtil.convertXmlToObject:(Ljava/lang/String;Ljava/lang/Class;)Ljava/lang/Object;
      49: checkcast     #114                // class com/virtual/ssv/server/rs/client/entity/RsUserFirewall
      52: astore        6
      54: aload_0
      55: getfield      #43                 // Field reqHandle:Lcom/virtual/ssv/server/rs/client/RequestHandle;
      58: aload         6
      60: invokevirtual #115                // Method com/virtual/ssv/server/rs/client/RequestHandle.modifyFwStrategy:(Lcom/virtual/ssv/server/rs/client/entity/RsUserFirewall;)Lcom/virtual/ssv/server/entity/ResultJson;
      63: astore        8
      65: new           #36                 // class java/util/Date
      68: dup
      69: invokespecial #37                 // Method java/util/Date."<init>":()V
      72: astore        9
      74: new           #45                 // class com/virtual/ssv/server/rs/client/entity/RsOperateLog
      77: dup
      78: invokespecial #46                 // Method com/virtual/ssv/server/rs/client/entity/RsOperateLog."<init>":()V
      81: astore        10
      83: aload         10
      85: aload_3
      86: invokevirtual #47                 // Method com/virtual/ssv/server/user/LoginInfo.getId:()Ljava/lang/Long;
      89: invokevirtual #48                 // Method com/virtual/ssv/server/rs/client/entity/RsOperateLog.setUserId:(Ljava/lang/Long;)V
      92: aload         10
      94: aload_3
      95: invokevirtual #49                 // Method com/virtual/ssv/server/user/LoginInfo.getOrgId:()Ljava/lang/Long;
      98: invokevirtual #50                 // Method com/virtual/ssv/server/rs/client/entity/RsOperateLog.setOrgId:(Ljava/lang/Long;)V
     101: aload         10
     103: aload_3
     104: invokevirtual #51                 // Method com/virtual/ssv/server/user/LoginInfo.getLoginName:()Ljava/lang/String;
     107: invokevirtual #52                 // Method com/virtual/ssv/server/rs/client/entity/RsOperateLog.setLoginName:(Ljava/lang/String;)V
     110: aload         10
     112: aload_3
     113: invokevirtual #53                 // Method com/virtual/ssv/server/user/LoginInfo.getUserName:()Ljava/lang/String;
     116: invokevirtual #54                 // Method com/virtual/ssv/server/rs/client/entity/RsOperateLog.setUserName:(Ljava/lang/String;)V
     119: aload         10
     121: aload_3
     122: invokevirtual #55                 // Method com/virtual/ssv/server/user/LoginInfo.getLoginIp:()Ljava/lang/String;
     125: invokevirtual #56                 // Method com/virtual/ssv/server/rs/client/entity/RsOperateLog.setAddress:(Ljava/lang/String;)V
     128: aload         10
     130: iconst_1
     131: invokestatic  #58                 // Method java/lang/Integer.valueOf:(I)Ljava/lang/Integer;
     134: invokevirtual #59                 // Method com/virtual/ssv/server/rs/client/entity/RsOperateLog.setCategory:(Ljava/lang/Integer;)V
     137: aload         10
     139: getstatic     #60                 // Field sm:Lcom/virtual/common/StringManager;
     142: ldc           #116                // String firewall.strategy.modify.operation
     144: iconst_1
     145: anewarray     #112                // class java/lang/Object
     148: dup
     149: iconst_0
     150: aload         6
     152: invokevirtual #117                // Method com/virtual/ssv/server/rs/client/entity/RsUserFirewall.getName:()Ljava/lang/String;
     155: aastore
     156: invokevirtual #113                // Method com/virtual/common/StringManager.getString:(Ljava/lang/String;[Ljava/lang/Object;)Ljava/lang/String;
     159: invokevirtual #63                 // Method com/virtual/ssv/server/rs/client/entity/RsOperateLog.setDescription:(Ljava/lang/String;)V
     162: aload         8
     164: invokevirtual #64                 // Method com/virtual/ssv/server/entity/ResultJson.getState:()I
     167: iconst_1
     168: if_icmpne     182
     171: aload         10
     173: getstatic     #65                 // Field com/virtual/ssv/server/rs/client/entity/RsOperateLog.RESULT_SUCCESS:Ljava/lang/Integer;
     176: invokevirtual #66                 // Method com/virtual/ssv/server/rs/client/entity/RsOperateLog.setResult:(Ljava/lang/Integer;)V
     179: goto          200
     182: aload         10
     184: getstatic     #67                 // Field com/virtual/ssv/server/rs/client/entity/RsOperateLog.RESULT_FAILURE:Ljava/lang/Integer;
     187: invokevirtual #66                 // Method com/virtual/ssv/server/rs/client/entity/RsOperateLog.setResult:(Ljava/lang/Integer;)V
     190: aload         10
     192: aload         8
     194: invokevirtual #68                 // Method com/virtual/ssv/server/entity/ResultJson.getMessage:()Ljava/lang/String;
     197: invokevirtual #69                 // Method com/virtual/ssv/server/rs/client/entity/RsOperateLog.setFailureReason:(Ljava/lang/String;)V
     200: aload         10
     202: aload         5
     204: invokevirtual #70                 // Method com/virtual/ssv/server/rs/client/entity/RsOperateLog.setStartTime:(Ljava/util/Date;)V
     207: aload         10
     209: aload         9
     211: invokevirtual #71                 // Method com/virtual/ssv/server/rs/client/entity/RsOperateLog.setEndTime:(Ljava/util/Date;)V
     214: aload_0
     215: getfield      #43                 // Field reqHandle:Lcom/virtual/ssv/server/rs/client/RequestHandle;
     218: aload         10
     220: invokevirtual #72                 // Method com/virtual/ssv/server/rs/client/RequestHandle.addUserLog:(Lcom/virtual/ssv/server/rs/client/entity/RsOperateLog;)Ljava/lang/Long;
     223: pop
     224: aload_0
     225: aload_2
     226: aload_0
     227: getfield      #81                 // Field filterJson:Lcom/google/gson/Gson;
     230: aload         8
     232: invokevirtual #82                 // Method com/google/gson/Gson.toJson:(Ljava/lang/Object;)Ljava/lang/String;
     235: invokevirtual #83                 // Method write:(Ljavax/servlet/http/HttpServletResponse;Ljava/lang/String;)V
     238: goto          351
     241: astore        5
     243: aload         5
     245: invokevirtual #74                 // Method com/virtual/common/AppException.getErrorCode:()I
     248: bipush        102
     250: if_icmpne     266
     253: aload         4
     255: bipush        102
     257: invokestatic  #76                 // Method com/virtual/common/ErrorCodes.getErrorMessage:(I)Ljava/lang/String;
     260: invokevirtual #77                 // Method com/virtual/ssv/server/entity/ResultJson.setErrorMsg:(Ljava/lang/String;)V
     263: goto          322
     266: aload         5
     268: invokevirtual #74                 // Method com/virtual/common/AppException.getErrorCode:()I
     271: bipush        103
     273: if_icmpne     289
     276: aload         4
     278: bipush        103
     280: invokestatic  #76                 // Method com/virtual/common/ErrorCodes.getErrorMessage:(I)Ljava/lang/String;
     283: invokevirtual #77                 // Method com/virtual/ssv/server/entity/ResultJson.setErrorMsg:(Ljava/lang/String;)V
     286: goto          322
     289: aload         5
     291: invokevirtual #74                 // Method com/virtual/common/AppException.getErrorCode:()I
     294: bipush        11
     296: if_icmpne     312
     299: aload         4
     301: bipush        11
     303: invokestatic  #76                 // Method com/virtual/common/ErrorCodes.getErrorMessage:(I)Ljava/lang/String;
     306: invokevirtual #77                 // Method com/virtual/ssv/server/entity/ResultJson.setErrorMsg:(Ljava/lang/String;)V
     309: goto          322
     312: aload         4
     314: aload         5
     316: invokevirtual #78                 // Method com/virtual/common/AppException.getMessage:()Ljava/lang/String;
     319: invokevirtual #77                 // Method com/virtual/ssv/server/entity/ResultJson.setErrorMsg:(Ljava/lang/String;)V
     322: aload_0
     323: aload_2
     324: aload_0
     325: getfield      #81                 // Field filterJson:Lcom/google/gson/Gson;
     328: aload         4
     330: invokevirtual #82                 // Method com/google/gson/Gson.toJson:(Ljava/lang/Object;)Ljava/lang/String;
     333: invokevirtual #83                 // Method write:(Ljavax/servlet/http/HttpServletResponse;Ljava/lang/String;)V
     336: goto          351
     339: astore        5
     341: aload         4
     343: aload         5
     345: invokevirtual #80                 // Method java/io/UnsupportedEncodingException.getMessage:()Ljava/lang/String;
     348: invokevirtual #77                 // Method com/virtual/ssv/server/entity/ResultJson.setErrorMsg:(Ljava/lang/String;)V
     351: return
    Exception table:
       from    to  target type
           9   238   241   Class com/virtual/common/AppException
           9   238   339   Class java/io/UnsupportedEncodingException

  private void getFwStrategyById(javax.servlet.http.HttpServletRequest, javax.servlet.http.HttpServletResponse, com.virtual.ssv.server.user.LoginInfo);
    Code:
       0: new           #34                 // class com/virtual/ssv/server/entity/ResultJson
       3: dup
       4: invokespecial #35                 // Method com/virtual/ssv/server/entity/ResultJson."<init>":()V
       7: astore        4
       9: aload_1
      10: ldc           #88                 // String id
      12: invokeinterface #8,  2            // InterfaceMethod javax/servlet/http/HttpServletRequest.getParameter:(Ljava/lang/String;)Ljava/lang/String;
      17: astore        5
      19: aload         5
      21: invokestatic  #89                 // Method org/apache/commons/lang/StringUtils.isNotEmpty:(Ljava/lang/String;)Z
      24: ifeq          56
      27: aload_0
      28: getfield      #43                 // Field reqHandle:Lcom/virtual/ssv/server/rs/client/RequestHandle;
      31: aload         5
      33: invokevirtual #118                // Method com/virtual/ssv/server/rs/client/RequestHandle.getFwStrategyById:(Ljava/lang/String;)Lcom/virtual/ssv/server/rs/client/entity/RsUserFirewall;
      36: astore        6
      38: aload_0
      39: getfield      #91                 // Field gson:Lcom/google/gson/Gson;
      42: aload         6
      44: invokevirtual #82                 // Method com/google/gson/Gson.toJson:(Ljava/lang/Object;)Ljava/lang/String;
      47: astore        7
      49: aload_0
      50: aload_2
      51: aload         7
      53: invokevirtual #83                 // Method write:(Ljavax/servlet/http/HttpServletResponse;Ljava/lang/String;)V
      56: goto          154
      59: astore        5
      61: aload         5
      63: invokevirtual #74                 // Method com/virtual/common/AppException.getErrorCode:()I
      66: bipush        102
      68: if_icmpne     84
      71: aload         4
      73: bipush        102
      75: invokestatic  #76                 // Method com/virtual/common/ErrorCodes.getErrorMessage:(I)Ljava/lang/String;
      78: invokevirtual #77                 // Method com/virtual/ssv/server/entity/ResultJson.setErrorMsg:(Ljava/lang/String;)V
      81: goto          140
      84: aload         5
      86: invokevirtual #74                 // Method com/virtual/common/AppException.getErrorCode:()I
      89: bipush        103
      91: if_icmpne     107
      94: aload         4
      96: bipush        103
      98: invokestatic  #76                 // Method com/virtual/common/ErrorCodes.getErrorMessage:(I)Ljava/lang/String;
     101: invokevirtual #77                 // Method com/virtual/ssv/server/entity/ResultJson.setErrorMsg:(Ljava/lang/String;)V
     104: goto          140
     107: aload         5
     109: invokevirtual #74                 // Method com/virtual/common/AppException.getErrorCode:()I
     112: bipush        11
     114: if_icmpne     130
     117: aload         4
     119: bipush        11
     121: invokestatic  #76                 // Method com/virtual/common/ErrorCodes.getErrorMessage:(I)Ljava/lang/String;
     124: invokevirtual #77                 // Method com/virtual/ssv/server/entity/ResultJson.setErrorMsg:(Ljava/lang/String;)V
     127: goto          140
     130: aload         4
     132: aload         5
     134: invokevirtual #78                 // Method com/virtual/common/AppException.getMessage:()Ljava/lang/String;
     137: invokevirtual #77                 // Method com/virtual/ssv/server/entity/ResultJson.setErrorMsg:(Ljava/lang/String;)V
     140: aload_0
     141: aload_2
     142: aload_0
     143: getfield      #81                 // Field filterJson:Lcom/google/gson/Gson;
     146: aload         4
     148: invokevirtual #82                 // Method com/google/gson/Gson.toJson:(Ljava/lang/Object;)Ljava/lang/String;
     151: invokevirtual #83                 // Method write:(Ljavax/servlet/http/HttpServletResponse;Ljava/lang/String;)V
     154: return
    Exception table:
       from    to  target type
           9    56    59   Class com/virtual/common/AppException

  private void getFwStrategyList(javax.servlet.http.HttpServletRequest, javax.servlet.http.HttpServletResponse, com.virtual.ssv.server.user.LoginInfo);
    Code:
       0: new           #94                 // class com/virtual/ssv/server/entity/CommonListJson
       3: dup
       4: invokespecial #95                 // Method com/virtual/ssv/server/entity/CommonListJson."<init>":()V
       7: astore        4
       9: aload_3
      10: invokevirtual #47                 // Method com/virtual/ssv/server/user/LoginInfo.getId:()Ljava/lang/Long;
      13: astore        5
      15: aload         5
      17: ifnull        78
      20: aload_1
      21: ldc           #97                 // String page
      23: invokeinterface #8,  2            // InterfaceMethod javax/servlet/http/HttpServletRequest.getParameter:(Ljava/lang/String;)Ljava/lang/String;
      28: astore        6
      30: aload_1
      31: ldc           #98                 // String rows
      33: invokeinterface #8,  2            // InterfaceMethod javax/servlet/http/HttpServletRequest.getParameter:(Ljava/lang/String;)Ljava/lang/String;
      38: astore        7
      40: aload         6
      42: invokestatic  #99                 // Method java/lang/Integer.parseInt:(Ljava/lang/String;)I
      45: istore        8
      47: aload         7
      49: invokestatic  #99                 // Method java/lang/Integer.parseInt:(Ljava/lang/String;)I
      52: istore        9
      54: iload         9
      56: iload         8
      58: iconst_1
      59: isub
      60: imul
      61: istore        10
      63: aload_0
      64: getfield      #43                 // Field reqHandle:Lcom/virtual/ssv/server/rs/client/RequestHandle;
      67: iload         10
      69: iload         9
      71: aload         5
      73: invokevirtual #119                // Method com/virtual/ssv/server/rs/client/RequestHandle.queryFwStrategyList:(IILjava/lang/Long;)Lcom/virtual/ssv/server/entity/CommonListJson;
      76: astore        4
      78: goto          193
      81: astore        5
      83: aload         4
      85: getstatic     #60                 // Field sm:Lcom/virtual/common/StringManager;
      88: ldc           #102                // String operError
      90: invokevirtual #62                 // Method com/virtual/common/StringManager.getString:(Ljava/lang/String;)Ljava/lang/String;
      93: invokevirtual #103                // Method com/virtual/ssv/server/entity/CommonListJson.setTitle:(Ljava/lang/String;)V
      96: aload         5
      98: invokevirtual #74                 // Method com/virtual/common/AppException.getErrorCode:()I
     101: bipush        102
     103: if_icmpne     119
     106: aload         4
     108: bipush        102
     110: invokestatic  #76                 // Method com/virtual/common/ErrorCodes.getErrorMessage:(I)Ljava/lang/String;
     113: invokevirtual #104                // Method com/virtual/ssv/server/entity/CommonListJson.setMessage:(Ljava/lang/String;)V
     116: goto          175
     119: aload         5
     121: invokevirtual #74                 // Method com/virtual/common/AppException.getErrorCode:()I
     124: bipush        103
     126: if_icmpne     142
     129: aload         4
     131: bipush        103
     133: invokestatic  #76                 // Method com/virtual/common/ErrorCodes.getErrorMessage:(I)Ljava/lang/String;
     136: invokevirtual #104                // Method com/virtual/ssv/server/entity/CommonListJson.setMessage:(Ljava/lang/String;)V
     139: goto          175
     142: aload         5
     144: invokevirtual #74                 // Method com/virtual/common/AppException.getErrorCode:()I
     147: bipush        11
     149: if_icmpne     165
     152: aload         4
     154: bipush        11
     156: invokestatic  #76                 // Method com/virtual/common/ErrorCodes.getErrorMessage:(I)Ljava/lang/String;
     159: invokevirtual #104                // Method com/virtual/ssv/server/entity/CommonListJson.setMessage:(Ljava/lang/String;)V
     162: goto          175
     165: aload         4
     167: aload         5
     169: invokevirtual #78                 // Method com/virtual/common/AppException.getMessage:()Ljava/lang/String;
     172: invokevirtual #104                // Method com/virtual/ssv/server/entity/CommonListJson.setMessage:(Ljava/lang/String;)V
     175: aload         4
     177: iconst_0
     178: invokevirtual #105                // Method com/virtual/ssv/server/entity/CommonListJson.setState:(I)V
     181: aload         4
     183: new           #106                // class java/util/ArrayList
     186: dup
     187: invokespecial #107                // Method java/util/ArrayList."<init>":()V
     190: invokevirtual #108                // Method com/virtual/ssv/server/entity/CommonListJson.setRows:(Ljava/util/List;)V
     193: aload_0
     194: aload_2
     195: aload_0
     196: getfield      #91                 // Field gson:Lcom/google/gson/Gson;
     199: aload         4
     201: invokevirtual #82                 // Method com/google/gson/Gson.toJson:(Ljava/lang/Object;)Ljava/lang/String;
     204: invokevirtual #83                 // Method write:(Ljavax/servlet/http/HttpServletResponse;Ljava/lang/String;)V
     207: return
    Exception table:
       from    to  target type
           9    78    81   Class com/virtual/common/AppException

  private void applyFwStrategy(javax.servlet.http.HttpServletRequest, javax.servlet.http.HttpServletResponse, com.virtual.ssv.server.user.LoginInfo);
    Code:
       0: new           #34                 // class com/virtual/ssv/server/entity/ResultJson
       3: dup
       4: invokespecial #35                 // Method com/virtual/ssv/server/entity/ResultJson."<init>":()V
       7: astore        4
       9: new           #36                 // class java/util/Date
      12: dup
      13: invokespecial #37                 // Method java/util/Date."<init>":()V
      16: astore        5
      18: aconst_null
      19: astore        6
      21: aload_1
      22: ldc           #38                 // String xml
      24: invokeinterface #8,  2            // InterfaceMethod javax/servlet/http/HttpServletRequest.getParameter:(Ljava/lang/String;)Ljava/lang/String;
      29: ldc           #39                 // String UTF-8
      31: invokestatic  #40                 // Method java/net/URLDecoder.decode:(Ljava/lang/String;Ljava/lang/String;)Ljava/lang/String;
      34: astore        7
      36: aload_3
      37: invokevirtual #47                 // Method com/virtual/ssv/server/user/LoginInfo.getId:()Ljava/lang/Long;
      40: astore        8
      42: aload         8
      44: ifnull        81
      47: aload         7
      49: ldc           #120                // String </rsFirewall>
      51: new           #121                // class java/lang/StringBuilder
      54: dup
      55: invokespecial #122                // Method java/lang/StringBuilder."<init>":()V
      58: ldc           #123                // String <userId>
      60: invokevirtual #124                // Method java/lang/StringBuilder.append:(Ljava/lang/String;)Ljava/lang/StringBuilder;
      63: aload         8
      65: invokevirtual #125                // Method java/lang/StringBuilder.append:(Ljava/lang/Object;)Ljava/lang/StringBuilder;
      68: ldc           #126                // String </userId></rsFirewall>
      70: invokevirtual #124                // Method java/lang/StringBuilder.append:(Ljava/lang/String;)Ljava/lang/StringBuilder;
      73: invokevirtual #127                // Method java/lang/StringBuilder.toString:()Ljava/lang/String;
      76: invokevirtual #128                // Method java/lang/String.replace:(Ljava/lang/CharSequence;Ljava/lang/CharSequence;)Ljava/lang/String;
      79: astore        7
      81: aconst_null
      82: aload         7
      84: if_acmpeq     283
      87: aload         7
      89: ldc           #114                // class com/virtual/ssv/server/rs/client/entity/RsUserFirewall
      91: invokestatic  #42                 // Method com/virtual/common/FuncUtil.convertXmlToObject:(Ljava/lang/String;Ljava/lang/Class;)Ljava/lang/Object;
      94: checkcast     #114                // class com/virtual/ssv/server/rs/client/entity/RsUserFirewall
      97: astore        6
      99: aload_0
     100: getfield      #43                 // Field reqHandle:Lcom/virtual/ssv/server/rs/client/RequestHandle;
     103: aload         6
     105: invokevirtual #129                // Method com/virtual/ssv/server/rs/client/RequestHandle.addFwStrategy:(Lcom/virtual/ssv/server/rs/client/entity/RsUserFirewall;)Lcom/virtual/ssv/server/entity/ResultJson;
     108: astore        9
     110: new           #36                 // class java/util/Date
     113: dup
     114: invokespecial #37                 // Method java/util/Date."<init>":()V
     117: astore        10
     119: new           #45                 // class com/virtual/ssv/server/rs/client/entity/RsOperateLog
     122: dup
     123: invokespecial #46                 // Method com/virtual/ssv/server/rs/client/entity/RsOperateLog."<init>":()V
     126: astore        11
     128: aload         11
     130: aload_3
     131: invokevirtual #47                 // Method com/virtual/ssv/server/user/LoginInfo.getId:()Ljava/lang/Long;
     134: invokevirtual #48                 // Method com/virtual/ssv/server/rs/client/entity/RsOperateLog.setUserId:(Ljava/lang/Long;)V
     137: aload         11
     139: aload_3
     140: invokevirtual #49                 // Method com/virtual/ssv/server/user/LoginInfo.getOrgId:()Ljava/lang/Long;
     143: invokevirtual #50                 // Method com/virtual/ssv/server/rs/client/entity/RsOperateLog.setOrgId:(Ljava/lang/Long;)V
     146: aload         11
     148: aload_3
     149: invokevirtual #51                 // Method com/virtual/ssv/server/user/LoginInfo.getLoginName:()Ljava/lang/String;
     152: invokevirtual #52                 // Method com/virtual/ssv/server/rs/client/entity/RsOperateLog.setLoginName:(Ljava/lang/String;)V
     155: aload         11
     157: aload_3
     158: invokevirtual #53                 // Method com/virtual/ssv/server/user/LoginInfo.getUserName:()Ljava/lang/String;
     161: invokevirtual #54                 // Method com/virtual/ssv/server/rs/client/entity/RsOperateLog.setUserName:(Ljava/lang/String;)V
     164: aload         11
     166: aload_3
     167: invokevirtual #55                 // Method com/virtual/ssv/server/user/LoginInfo.getLoginIp:()Ljava/lang/String;
     170: invokevirtual #56                 // Method com/virtual/ssv/server/rs/client/entity/RsOperateLog.setAddress:(Ljava/lang/String;)V
     173: aload         11
     175: iconst_1
     176: invokestatic  #58                 // Method java/lang/Integer.valueOf:(I)Ljava/lang/Integer;
     179: invokevirtual #59                 // Method com/virtual/ssv/server/rs/client/entity/RsOperateLog.setCategory:(Ljava/lang/Integer;)V
     182: aload         11
     184: getstatic     #60                 // Field sm:Lcom/virtual/common/StringManager;
     187: ldc           #130                // String firewall.strategy.add.operation
     189: iconst_1
     190: anewarray     #112                // class java/lang/Object
     193: dup
     194: iconst_0
     195: aload         6
     197: invokevirtual #117                // Method com/virtual/ssv/server/rs/client/entity/RsUserFirewall.getName:()Ljava/lang/String;
     200: aastore
     201: invokevirtual #113                // Method com/virtual/common/StringManager.getString:(Ljava/lang/String;[Ljava/lang/Object;)Ljava/lang/String;
     204: invokevirtual #63                 // Method com/virtual/ssv/server/rs/client/entity/RsOperateLog.setDescription:(Ljava/lang/String;)V
     207: aload         9
     209: invokevirtual #64                 // Method com/virtual/ssv/server/entity/ResultJson.getState:()I
     212: iconst_1
     213: if_icmpne     227
     216: aload         11
     218: getstatic     #65                 // Field com/virtual/ssv/server/rs/client/entity/RsOperateLog.RESULT_SUCCESS:Ljava/lang/Integer;
     221: invokevirtual #66                 // Method com/virtual/ssv/server/rs/client/entity/RsOperateLog.setResult:(Ljava/lang/Integer;)V
     224: goto          245
     227: aload         11
     229: getstatic     #67                 // Field com/virtual/ssv/server/rs/client/entity/RsOperateLog.RESULT_FAILURE:Ljava/lang/Integer;
     232: invokevirtual #66                 // Method com/virtual/ssv/server/rs/client/entity/RsOperateLog.setResult:(Ljava/lang/Integer;)V
     235: aload         11
     237: aload         9
     239: invokevirtual #68                 // Method com/virtual/ssv/server/entity/ResultJson.getMessage:()Ljava/lang/String;
     242: invokevirtual #69                 // Method com/virtual/ssv/server/rs/client/entity/RsOperateLog.setFailureReason:(Ljava/lang/String;)V
     245: aload         11
     247: aload         5
     249: invokevirtual #70                 // Method com/virtual/ssv/server/rs/client/entity/RsOperateLog.setStartTime:(Ljava/util/Date;)V
     252: aload         11
     254: aload         10
     256: invokevirtual #71                 // Method com/virtual/ssv/server/rs/client/entity/RsOperateLog.setEndTime:(Ljava/util/Date;)V
     259: aload_0
     260: getfield      #43                 // Field reqHandle:Lcom/virtual/ssv/server/rs/client/RequestHandle;
     263: aload         11
     265: invokevirtual #72                 // Method com/virtual/ssv/server/rs/client/RequestHandle.addUserLog:(Lcom/virtual/ssv/server/rs/client/entity/RsOperateLog;)Ljava/lang/Long;
     268: pop
     269: aload_0
     270: aload_2
     271: aload_0
     272: getfield      #81                 // Field filterJson:Lcom/google/gson/Gson;
     275: aload         9
     277: invokevirtual #82                 // Method com/google/gson/Gson.toJson:(Ljava/lang/Object;)Ljava/lang/String;
     280: invokevirtual #83                 // Method write:(Ljavax/servlet/http/HttpServletResponse;Ljava/lang/String;)V
     283: goto          396
     286: astore        5
     288: aload         5
     290: invokevirtual #74                 // Method com/virtual/common/AppException.getErrorCode:()I
     293: bipush        102
     295: if_icmpne     311
     298: aload         4
     300: bipush        102
     302: invokestatic  #76                 // Method com/virtual/common/ErrorCodes.getErrorMessage:(I)Ljava/lang/String;
     305: invokevirtual #77                 // Method com/virtual/ssv/server/entity/ResultJson.setErrorMsg:(Ljava/lang/String;)V
     308: goto          367
     311: aload         5
     313: invokevirtual #74                 // Method com/virtual/common/AppException.getErrorCode:()I
     316: bipush        103
     318: if_icmpne     334
     321: aload         4
     323: bipush        103
     325: invokestatic  #76                 // Method com/virtual/common/ErrorCodes.getErrorMessage:(I)Ljava/lang/String;
     328: invokevirtual #77                 // Method com/virtual/ssv/server/entity/ResultJson.setErrorMsg:(Ljava/lang/String;)V
     331: goto          367
     334: aload         5
     336: invokevirtual #74                 // Method com/virtual/common/AppException.getErrorCode:()I
     339: bipush        11
     341: if_icmpne     357
     344: aload         4
     346: bipush        11
     348: invokestatic  #76                 // Method com/virtual/common/ErrorCodes.getErrorMessage:(I)Ljava/lang/String;
     351: invokevirtual #77                 // Method com/virtual/ssv/server/entity/ResultJson.setErrorMsg:(Ljava/lang/String;)V
     354: goto          367
     357: aload         4
     359: aload         5
     361: invokevirtual #78                 // Method com/virtual/common/AppException.getMessage:()Ljava/lang/String;
     364: invokevirtual #77                 // Method com/virtual/ssv/server/entity/ResultJson.setErrorMsg:(Ljava/lang/String;)V
     367: aload_0
     368: aload_2
     369: aload_0
     370: getfield      #81                 // Field filterJson:Lcom/google/gson/Gson;
     373: aload         4
     375: invokevirtual #82                 // Method com/google/gson/Gson.toJson:(Ljava/lang/Object;)Ljava/lang/String;
     378: invokevirtual #83                 // Method write:(Ljavax/servlet/http/HttpServletResponse;Ljava/lang/String;)V
     381: goto          396
     384: astore        5
     386: aload         4
     388: aload         5
     390: invokevirtual #80                 // Method java/io/UnsupportedEncodingException.getMessage:()Ljava/lang/String;
     393: invokevirtual #77                 // Method com/virtual/ssv/server/entity/ResultJson.setErrorMsg:(Ljava/lang/String;)V
     396: return
    Exception table:
       from    to  target type
           9   283   286   Class com/virtual/common/AppException
           9   283   384   Class java/io/UnsupportedEncodingException

  private void checkStrategyReName(javax.servlet.http.HttpServletRequest, javax.servlet.http.HttpServletResponse, com.virtual.ssv.server.user.LoginInfo);
    Code:
       0: ldc           #131                // String
       2: astore        4
       4: aload_1
       5: ldc           #132                // String strategyName
       7: invokeinterface #8,  2            // InterfaceMethod javax/servlet/http/HttpServletRequest.getParameter:(Ljava/lang/String;)Ljava/lang/String;
      12: astore        5
      14: aload         5
      16: ifnull        31
      19: aload_0
      20: getfield      #43                 // Field reqHandle:Lcom/virtual/ssv/server/rs/client/RequestHandle;
      23: aload         5
      25: aload_3
      26: invokevirtual #133                // Method com/virtual/ssv/server/rs/client/RequestHandle.checkFirewallStrategyName:(Ljava/lang/String;Lcom/virtual/ssv/server/user/LoginInfo;)Ljava/lang/String;
      29: astore        4
      31: goto          46
      34: astore        5
      36: getstatic     #135                // Field log:Lorg/apache/commons/logging/Log;
      39: aload         5
      41: invokeinterface #136,  2          // InterfaceMethod org/apache/commons/logging/Log.error:(Ljava/lang/Object;)V
      46: aload_0
      47: aload_2
      48: aload_0
      49: getfield      #81                 // Field filterJson:Lcom/google/gson/Gson;
      52: aload         4
      54: invokevirtual #82                 // Method com/google/gson/Gson.toJson:(Ljava/lang/Object;)Ljava/lang/String;
      57: invokevirtual #83                 // Method write:(Ljavax/servlet/http/HttpServletResponse;Ljava/lang/String;)V
      60: return
    Exception table:
       from    to  target type
           4    31    34   Class java/lang/Exception

  private void applyFwStrategyToDomain(javax.servlet.http.HttpServletRequest, javax.servlet.http.HttpServletResponse, com.virtual.ssv.server.user.LoginInfo);
    Code:
       0: new           #34                 // class com/virtual/ssv/server/entity/ResultJson
       3: dup
       4: invokespecial #35                 // Method com/virtual/ssv/server/entity/ResultJson."<init>":()V
       7: astore        4
       9: aload_1
      10: ldc           #137                // String uuid
      12: invokeinterface #8,  2            // InterfaceMethod javax/servlet/http/HttpServletRequest.getParameter:(Ljava/lang/String;)Ljava/lang/String;
      17: astore        5
      19: aload_1
      20: ldc           #138                // String vmIds
      22: invokeinterface #8,  2            // InterfaceMethod javax/servlet/http/HttpServletRequest.getParameter:(Ljava/lang/String;)Ljava/lang/String;
      27: astore        6
      29: aload_1
      30: ldc           #139                // String vmMacs
      32: invokeinterface #8,  2            // InterfaceMethod javax/servlet/http/HttpServletRequest.getParameter:(Ljava/lang/String;)Ljava/lang/String;
      37: astore        7
      39: aload_1
      40: ldc           #140                // String vmTitles
      42: invokeinterface #8,  2            // InterfaceMethod javax/servlet/http/HttpServletRequest.getParameter:(Ljava/lang/String;)Ljava/lang/String;
      47: astore        8
      49: aload         5
      51: invokestatic  #141                // Method org/apache/commons/lang/StringUtils.isEmpty:(Ljava/lang/String;)Z
      54: ifne          67
      57: aload         6
      59: ifnull        67
      62: aload         7
      64: ifnonnull     68
      67: return
      68: aload_0
      69: getfield      #43                 // Field reqHandle:Lcom/virtual/ssv/server/rs/client/RequestHandle;
      72: aload_3
      73: invokevirtual #47                 // Method com/virtual/ssv/server/user/LoginInfo.getId:()Ljava/lang/Long;
      76: invokevirtual #142                // Method com/virtual/ssv/server/rs/client/RequestHandle.getPublicCloudByUserId:(Ljava/lang/Long;)Lcom/virtual/ssv/server/rs/client/entity/PublicCloud;
      79: astore        9
      81: aload         6
      83: ldc           #143                // String ,
      85: invokevirtual #144                // Method java/lang/String.split:(Ljava/lang/String;)[Ljava/lang/String;
      88: astore        10
      90: aload         7
      92: ldc           #143                // String ,
      94: invokevirtual #144                // Method java/lang/String.split:(Ljava/lang/String;)[Ljava/lang/String;
      97: astore        11
      99: aload         8
     101: ldc           #143                // String ,
     103: invokevirtual #144                // Method java/lang/String.split:(Ljava/lang/String;)[Ljava/lang/String;
     106: astore        12
     108: new           #145                // class com/virtual/ssv/server/rs/client/entity/RsDomainFirewallsInfo
     111: dup
     112: invokespecial #146                // Method com/virtual/ssv/server/rs/client/entity/RsDomainFirewallsInfo."<init>":()V
     115: astore        13
     117: new           #106                // class java/util/ArrayList
     120: dup
     121: invokespecial #107                // Method java/util/ArrayList."<init>":()V
     124: astore        14
     126: aload         13
     128: aload         5
     130: invokevirtual #147                // Method com/virtual/ssv/server/rs/client/entity/RsDomainFirewallsInfo.setFirewallUUid:(Ljava/lang/String;)V
     133: iconst_0
     134: istore        15
     136: iload         15
     138: aload         10
     140: arraylength
     141: if_icmpge     242
     144: new           #148                // class com/virtual/ssv/server/rs/client/entity/RsDomainForFirewall
     147: dup
     148: invokespecial #149                // Method com/virtual/ssv/server/rs/client/entity/RsDomainForFirewall."<init>":()V
     151: astore        16
     153: aload         11
     155: iload         15
     157: aaload
     158: ifnull        236
     161: ldc           #131                // String
     163: aload         11
     165: iload         15
     167: aaload
     168: invokevirtual #10                 // Method java/lang/String.equals:(Ljava/lang/Object;)Z
     171: ifeq          177
     174: goto          236
     177: aload         16
     179: aload         11
     181: iload         15
     183: aaload
     184: invokevirtual #150                // Method com/virtual/ssv/server/rs/client/entity/RsDomainForFirewall.setMac:(Ljava/lang/String;)V
     187: aload         16
     189: aload         9
     191: invokevirtual #151                // Method com/virtual/ssv/server/rs/client/entity/PublicCloud.getId:()Ljava/lang/Long;
     194: invokevirtual #152                // Method com/virtual/ssv/server/rs/client/entity/RsDomainForFirewall.setCloudId:(Ljava/lang/Long;)V
     197: aload         16
     199: aload         12
     201: iload         15
     203: aaload
     204: invokevirtual #153                // Method com/virtual/ssv/server/rs/client/entity/RsDomainForFirewall.setTitle:(Ljava/lang/String;)V
     207: aload         16
     209: aload         10
     211: iload         15
     213: aaload
     214: invokevirtual #154                // Method com/virtual/ssv/server/rs/client/entity/RsDomainForFirewall.setUniqueKey:(Ljava/lang/String;)V
     217: aload         16
     219: iconst_0
     220: invokestatic  #58                 // Method java/lang/Integer.valueOf:(I)Ljava/lang/Integer;
     223: invokevirtual #155                // Method com/virtual/ssv/server/rs/client/entity/RsDomainForFirewall.setOperType:(Ljava/lang/Integer;)V
     226: aload         14
     228: aload         16
     230: invokeinterface #156,  2          // InterfaceMethod java/util/List.add:(Ljava/lang/Object;)Z
     235: pop
     236: iinc          15, 1
     239: goto          136
     242: aload         13
     244: aload         14
     246: invokevirtual #157                // Method com/virtual/ssv/server/rs/client/entity/RsDomainFirewallsInfo.setRsDomainForFirewalls:(Ljava/util/List;)V
     249: aload_0
     250: getfield      #43                 // Field reqHandle:Lcom/virtual/ssv/server/rs/client/RequestHandle;
     253: aload         13
     255: invokevirtual #158                // Method com/virtual/ssv/server/rs/client/RequestHandle.applyFwToHosts:(Lcom/virtual/ssv/server/rs/client/entity/RsDomainFirewallsInfo;)Lcom/virtual/ssv/server/entity/ResultJson;
     258: astore        4
     260: goto          286
     263: astore        5
     265: getstatic     #135                // Field log:Lorg/apache/commons/logging/Log;
     268: aconst_null
     269: aload         5
     271: invokeinterface #159,  3          // InterfaceMethod org/apache/commons/logging/Log.error:(Ljava/lang/Object;Ljava/lang/Throwable;)V
     276: aload         4
     278: aload         5
     280: invokevirtual #160                // Method com/virtual/common/AppException.getErrorMessage:()Ljava/lang/String;
     283: invokevirtual #161                // Method com/virtual/ssv/server/entity/ResultJson.setFailtureReson:(Ljava/lang/String;)V
     286: aload_0
     287: aload_2
     288: aload_0
     289: getfield      #81                 // Field filterJson:Lcom/google/gson/Gson;
     292: aload         4
     294: invokevirtual #82                 // Method com/google/gson/Gson.toJson:(Ljava/lang/Object;)Ljava/lang/String;
     297: invokevirtual #83                 // Method write:(Ljavax/servlet/http/HttpServletResponse;Ljava/lang/String;)V
     300: return
    Exception table:
       from    to  target type
           9    67   263   Class com/virtual/common/AppException
          68   260   263   Class com/virtual/common/AppException

  static {};
    Code:
       0: ldc           #162                // String com.virtual.common
       2: invokestatic  #163                // Method com/virtual/common/StringManager.getManager:(Ljava/lang/String;)Lcom/virtual/common/StringManager;
       5: putstatic     #60                 // Field sm:Lcom/virtual/common/StringManager;
       8: return
}
