l	Z	d
e!e j
Z(d Z)d!Z*d"Z+d#Z,d$Z-d%e
Z.d(d)
Z/d*e/j
Z0d+d,
Z1d-d.
Z2d/e1j
Z3d0e2j
Z4d1d2
Z5d3d4
Z6d5d6
Z7d7d8
Z8d9e8j
e!e8j
Z9d:e9e!e8j
e!e8j
Z:d;e:e!e8j
d<d=
d>d?
d?e=
Z>d@e
j?j@d
r<dAn
ZAeB
dEdF
ZCdGZDeCjEj
jFd	
ZGdHZHdIZIdJZJdKZKdLdM
ZLdNZMG
dOdP
d5dQdR
ZOdSdT
ZPd	ZQeOj
ZReOj
ZSeSj
ZTeSjFd
ZUeUj
ZVd	ZWe
jXZXeXdUdVdWdXdYd
dZd[
eXd\d]d
d^d^d
dZd[
eXd\d]d	d_d_d&d
dZd[
eXd`dad
dbdcd
dZd[
eXdUdVd
eSeYeS
dZd[
eXdUdVd&dddedfd
dZd[
eXdgdhdididjdkd
dZd[
eXdldmd
dndndod
dZd[
eXdpdqd
drdrdsdtdZd[
eXdudvd
d^d^dwd
dZd[
eXdudvd	d_d_dxd
dZd[
eXdUdVd'dbdydzd
dZd[
eXdUdVdcd	d{d|d
dZd[
eXd}d~d
dZd[
dZd[
eXdUdVdtd
dZd[
dtdtdbd
dZd[
dZd[
dndnd
dWdZd[
dZd[
ZZeXdUdVd'd
dZd[
eXd\d]d
d^d^d
dZd[
eXd\d]d
d_d_d&d
dZd[
eXd\d]d
dZd[
eXd\d]d	d
dZd[
eXd`dad&d&dbdfd
dZd[
eXdUdVd
eUeYeU
dZd[
eXdUdVd&d
dZd[
eXdgdhdididjdsd
dZd[
eXdldmd
dZd[
eXdpdqd
drdrdxd'dZd[
eXdudvd
d^d^dzd
dZd[
eXdudvd
d_d_d|d
dZd[
eXdudvd
dZd[
eXdudvd	d
dZd[
d&d&dbd
dZd[
dZd[
dcdZd[
dZd[
Z[eXdpdqd
drdrd
d&dZd[
eXdudvd
d^d^d
dZd[
eXdudvd	d_d_d&d
dZd[
eXdudvd
dZd[
eXdudvd
dZd[
dZd[
d	dndndkd
dZd[
dcdcdbdod
dZd[
dbdsd
dZd[
eXdUdVd
dZd[
dbdxd
dZd[
Z\eXdpdqd
dZd[
eXdUdVd	dfd
dZd[
d	d	dbd&d
dZd[
dbdcd
dZd[
dCd[
eXdldmd
dZd[
eXdpdqd	drdrdkd&dZd[
dZd[
d	d	dbdsd
dZd[
dbdwd
dZd[
dxd'dZd[
eXdUdVd
dZd[
dZd[
dZd[
dWdWdbd
dcdZd[
dtdCd[
eXdUdVd
dZd[
dZd[
dWdWdbd
dZd[
dWdZd[
dZd[
dWdWdbd
dZd[
eXdpdqd	drdrd
dfdCd[
eXdUdVd&d
dZd[
d	d	dbd
dZd[
dZd[
dCd[
dZd[
eXdpdqd	drdrd
dkdZd[
dZd[
d	d	dbd
dZd[
dZd[
dZd[
eXdUdVd'd	d{d
dZd[
dZd[
eXdldmd
dZd[
dodZd[
eXdUdVd
dZd[
dZd[
dZd[
dZd[
dsdCd[
eXdUdVd
dZd[
dZd[
dZd[
dadadbd
dZd[
dZd[
eXdpdqd	drdrd
dCd[
eXdUdVdcd
dZd[
d	d	dbd
dZd[
dbdVd
dZd[
dadxdCd[
dZd[
eXdUdVd'd	d{d
dZd[
eXdUdVdtd
dZd[
dZd[
dZd[
dZd[
dZd[
dzdCd[
eXdpdqd
dZd[
dZd[
dZd[
dZd[
dZd[
eXdpdqd	drdrd
dZd[
eXdUdVdWd
dZd[
d	d	dbd
dZd[
dbdvd
dZd[
dZd[
dZd[
dCd[
dCd[
dZd[
eXdldmd	
dZd[
eXdpdqd	drdr
dZd[
eXdUdVdi
dZd[
d	d	db
dZd[
dZd[
dZd[
eXdUdVd
dZd[
dZd[
dZd[
dZd[
dZd[
dZd[
dCd[
dZd[
dZd[
dCd[
dZd[
dZd[
dZd[
dZd[
dCd[
eXdpdqd	drdr
dZd[
eXdUdVdf
dZd[
d	d	db
dZd[
dZd[
dZd[
eXdpdqd	drdrd
dCd[
eXdUdVdf
dZd[
d	d	db
dZd[
dZd[
dZd[
eXdUdVd
dCd[
dZd[
gkZ]
Z^eXdUdVd
dZd[
dZd[
d2eb
captured_stdout)
BytecodeTestCaseNc
	Exception
__traceback__)
%/usr/lib64/python3.9/test/test_dis.py
_error
get_tb.<locals>._error)
tb_next)
get_tb
selfr
__init__
_C.__init__c
_C.smc
clsr
_C.cmN)
__name__
__module__
__qualname__r
staticmethodr
classmethodr
%3d           0 LOAD_FAST                1 (x)
              2 LOAD_CONST               1 (1)
              4 COMPARE_OP               2 (==)
              6 LOAD_FAST                0 (self)
              8 STORE_ATTR               0 (x)
             10 LOAD_CONST               0 (None)
             12 RETURN_VALUE
          0 LOAD_FAST                1 (1)
          2 LOAD_CONST               1 (1)
          4 COMPARE_OP               2 (==)
          6 LOAD_FAST                0 (0)
          8 STORE_ATTR               0 (0)
         10 LOAD_CONST               0 (0)
         12 RETURN_VALUE
%3d           0 LOAD_FAST                1 (x)
              2 LOAD_CONST               1 (1)
              4 COMPARE_OP               2 (==)
              6 LOAD_FAST                0 (cls)
              8 STORE_ATTR               0 (x)
             10 LOAD_CONST               0 (None)
             12 RETURN_VALUE
%3d           0 LOAD_FAST                0 (x)
              2 LOAD_CONST               1 (1)
              4 COMPARE_OP               2 (==)
              6 STORE_FAST               0 (x)
              8 LOAD_CONST               0 (None)
             10 RETURN_VALUE
zBDisassembly of %s:
Disassembly of %s:
Disassembly of %s:
print)
%3d           0 LOAD_GLOBAL              0 (print)
              2 LOAD_FAST                0 (a)
              4 CALL_FUNCTION            1
              6 POP_TOP
%3d           8 LOAD_CONST               1 (1)
             10 RETURN_VALUE
          0 LOAD_GLOBAL              0 (0)
          2 LOAD_FAST                0 (0)
          4 CALL_FUNCTION            1
          6 POP_TOP
          8 LOAD_CONST               1 (1)
         10 RETURN_VALUE
range)
resr
	bug708901u
%3d           0 LOAD_GLOBAL              0 (range)
              2 LOAD_CONST               1 (1)
%3d           4 LOAD_CONST               2 (10)
%3d           6 CALL_FUNCTION            2
              8 GET_ITER
        >>   10 FOR_ITER                 4 (to 16)
             12 STORE_FAST               0 (res)
%3d          14 JUMP_ABSOLUTE           10
        >>   16 LOAD_CONST               0 (None)
             18 RETURN_VALUE
<listcomp>
bug1333982.<locals>.<listcomp>r
bug1333982
%3d           0 LOAD_CONST               1 (0)
              2 POP_JUMP_IF_TRUE        26
              4 LOAD_ASSERTION_ERROR
              6 LOAD_CONST               2 (<code object <listcomp> at 0x..., file "%s", line %d>)
              8 LOAD_CONST               3 ('bug1333982.<locals>.<listcomp>')
             10 MAKE_FUNCTION            0
             12 LOAD_FAST                0 (x)
             14 GET_ITER
             16 CALL_FUNCTION            1
%3d          18 LOAD_CONST               4 (1)
%3d          20 BINARY_ADD
             22 CALL_FUNCTION            1
             24 RAISE_VARARGS            1
%3d     >>   26 LOAD_CONST               0 (None)
             28 RETURN_VALUE
%3d           0 LOAD_GLOBAL              0 (spam)
              2 POP_TOP
              4 LOAD_CONST               0 (None)
              6 RETURN_VALUE
%4d           0 LOAD_GLOBAL              0 (spam)
               2 POP_TOP
               4 LOAD_CONST               0 (None)
               6 RETURN_VALUE
Disassembly of f:
  4           0 LOAD_CONST               0 (None)
              2 RETURN_VALUE
Disassembly of g:
  5           0 LOAD_CONST               0 (None)
              2 RETURN_VALUE
x + 1z
  1           0 LOAD_NAME                0 (x)
              2 LOAD_CONST               0 (1)
              4 BINARY_ADD
              6 RETURN_VALUE
	x = x + 1z
  1           0 LOAD_NAME                0 (x)
              2 LOAD_CONST               0 (1)
              4 BINARY_ADD
              6 STORE_NAME               0 (x)
              8 LOAD_CONST               1 (None)
             10 RETURN_VALUE
x: int = 1
y: fun(1)
lst[fun(0)]: int = 1
  2           0 SETUP_ANNOTATIONS
              2 LOAD_CONST               0 (1)
              4 STORE_NAME               0 (x)
              6 LOAD_NAME                1 (int)
              8 LOAD_NAME                2 (__annotations__)
             10 LOAD_CONST               1 ('x')
             12 STORE_SUBSCR
  3          14 LOAD_NAME                3 (fun)
             16 LOAD_CONST               0 (1)
             18 CALL_FUNCTION            1
             20 LOAD_NAME                2 (__annotations__)
             22 LOAD_CONST               2 ('y')
             24 STORE_SUBSCR
  4          26 LOAD_CONST               0 (1)
             28 LOAD_NAME                4 (lst)
             30 LOAD_NAME                3 (fun)
             32 LOAD_CONST               3 (0)
             34 CALL_FUNCTION            1
             36 STORE_SUBSCR
             38 LOAD_NAME                1 (int)
             40 POP_TOP
             42 LOAD_CONST               4 (None)
             44 RETURN_VALUE
x = 0
while 1:
    x += 1a
  1           0 LOAD_CONST               0 (0)
              2 STORE_NAME               0 (x)
  3     >>    4 LOAD_NAME                0 (x)
              6 LOAD_CONST               1 (1)
              8 INPLACE_ADD
             10 STORE_NAME               0 (x)
             12 JUMP_ABSOLUTE            4
             14 LOAD_CONST               2 (None)
             16 RETURN_VALUE
%3d           0 SETUP_FINALLY           12 (to 14)
%3d           2 LOAD_CONST               1 (1)
              4 LOAD_CONST               2 (0)
    -->       6 BINARY_TRUE_DIVIDE
              8 POP_TOP
             10 POP_BLOCK
             12 JUMP_FORWARD            42 (to 56)
%3d     >>   14 DUP_TOP
             16 LOAD_GLOBAL              0 (Exception)
             18 JUMP_IF_NOT_EXC_MATCH    54
             20 POP_TOP
             22 STORE_FAST               0 (e)
             24 POP_TOP
             26 SETUP_FINALLY           18 (to 46)
%3d          28 LOAD_FAST                0 (e)
             30 LOAD_ATTR                1 (__traceback__)
             32 STORE_FAST               1 (tb)
             34 POP_BLOCK
             36 POP_EXCEPT
             38 LOAD_CONST               0 (None)
             40 STORE_FAST               0 (e)
             42 DELETE_FAST              0 (e)
             44 JUMP_FORWARD            10 (to 56)
        >>   46 LOAD_CONST               0 (None)
             48 STORE_FAST               0 (e)
             50 DELETE_FAST              0 (e)
             52 RERAISE
        >>   54 RERAISE
%3d     >>   56 LOAD_FAST                1 (tb)
             58 RETURN_VALUE
_fstring:
%3d           0 LOAD_FAST                0 (a)
              2 FORMAT_VALUE             0
              4 LOAD_CONST               1 (' ')
              6 LOAD_FAST                1 (b)
              8 LOAD_CONST               2 ('4')
             10 FORMAT_VALUE             4 (with format)
             12 LOAD_CONST               1 (' ')
             14 LOAD_FAST                2 (c)
             16 FORMAT_VALUE             2 (repr)
             18 LOAD_CONST               1 (' ')
             20 LOAD_FAST                3 (d)
             22 LOAD_CONST               2 ('4')
             24 FORMAT_VALUE             6 (repr, with format)
             26 BUILD_STRING             7
             28 RETURN_VALUE
_tryfinallyO
_tryfinallyconstU
%3d           0 SETUP_FINALLY           12 (to 14)
%3d           2 LOAD_FAST                0 (a)
              4 POP_BLOCK
%3d           6 LOAD_FAST                1 (b)
              8 CALL_FUNCTION            0
             10 POP_TOP
%3d          12 RETURN_VALUE
%3d     >>   14 LOAD_FAST                1 (b)
             16 CALL_FUNCTION            0
             18 POP_TOP
             20 RERAISE
             22 LOAD_CONST               0 (None)
             24 RETURN_VALUE
%3d           0 SETUP_FINALLY           12 (to 14)
%3d           2 POP_BLOCK
%3d           4 LOAD_FAST                0 (b)
              6 CALL_FUNCTION            0
              8 POP_TOP
%3d          10 LOAD_CONST               1 (1)
             12 RETURN_VALUE
%3d     >>   14 LOAD_FAST                0 (b)
             16 CALL_FUNCTION            0
             18 POP_TOP
             20 RERAISE
             22 LOAD_CONST               0 (None)
             24 RETURN_VALUE
itemr
funcdocc
z#_h.<locals>.foo.<locals>.<listcomp>r
_h.<locals>.foor
%3d           0 LOAD_CLOSURE             0 (y)
              2 BUILD_TUPLE              1
              4 LOAD_CONST               1 (<code object foo at 0x..., file "%s", line %d>)
              6 LOAD_CONST               2 ('_h.<locals>.foo')
              8 MAKE_FUNCTION            8 (closure)
             10 STORE_FAST               1 (foo)
%3d          12 LOAD_FAST                1 (foo)
             14 RETURN_VALUE
Disassembly of <code object foo at 0x..., file "%s", line %d>:
%3d           0 LOAD_CLOSURE             0 (x)
              2 BUILD_TUPLE              1
              4 LOAD_CONST               1 (<code object <listcomp> at 0x..., file "%s", line %d>)
              6 LOAD_CONST               2 ('_h.<locals>.foo.<locals>.<listcomp>')
              8 MAKE_FUNCTION            8 (closure)
             10 LOAD_DEREF               1 (y)
             12 GET_ITER
             14 CALL_FUNCTION            1
             16 RETURN_VALUE
Disassembly of <code object <listcomp> at 0x..., file "%s", line %d>:
%3d           0 BUILD_LIST               0
              2 LOAD_FAST                0 (.0)
        >>    4 FOR_ITER                12 (to 18)
              6 STORE_FAST               1 (z)
              8 LOAD_DEREF               0 (x)
             10 LOAD_FAST                1 (z)
             12 BINARY_ADD
             14 LIST_APPEND              2
             16 JUMP_ABSOLUTE            4
        >>   18 RETURN_VALUE
d d!
d"d#
d$d%
d&d'
d(d)
d*d+
d,d-
d.d/
d0d1
d2d3
d4d5
d6d7
d8d9
d:d;
d<d=
DisTestsN
StringIO
contextlib
redirect_stdout
disassemble
getvalue
func
lasti
wrapper
kwargs
outputr
get_disassembly
DisTests.get_disassemblyc
get_disassemble_as_string
z"DisTests.get_disassemble_as_stringc
\b0x[0-9A-Fa-f]+\bz
0x...)
sub)
textr
strip_addresses
DisTests.strip_addressesc
depth)
assertEqual)
expectedZ
gotr
do_disassembly_test
DisTests.do_disassembly_testc
LOAD_CONST
STORE_NAME)
opmapZ
assertInZ
hasconstZ
hasname
test_opmap
DisTests.test_opmapc
	LOAD_FAST)
opnamer_
test_opname
DisTests.test_opnamec
EXTENDED_ARGr^
HAVE_ARGUMENTr`
test_boundaries
DisTests.test_boundariesc
BUILD_MAP_UNPACK_WITH_CALLZ
BUILD_TUPLE_UNPACK_WITH_CALL
JUMP_IF_NOT_EXC_MATCH)
	enumeraterI
subTestZ
_OPNAME_WIDTHrf
_OPARG_WIDTHZ
assertLessEqual
len)
opcoderc
widthr
test_widths
DisTests.test_widthsc
dis_fr`
test_dis
DisTests.test_disc
dis_bug708901r`
test_bug_708901
DisTests.test_bug_708901c
dis_bug1333982r`
test_bug_1333982
DisTests.test_bug_1333982c
qnd	d
def foo():
spam
join
exec
count
	namespacerM
z'DisTests.test_big_linenos.<locals>.funcr
dis_module)
_BIG_LINENO_FORMATr[
_BIG_LINENO_FORMAT2
testr}
dis_module_expected_results)
test_big_linenos
DisTests.test_big_linenosc
def foo(x):
 return xrA
z'DisTests.test_big_offsets.<locals>.funcc
           %*d LOAD_FAST                0 (x)
           %*d LOAD_CONST               1 (1)
           %*d BINARY_ADD
           %*d STORE_FAST               0 (x)
z?DisTests.test_big_offsets.<locals>.expected.<locals>.<listcomp>zK
  3        %*d LOAD_FAST                0 (x)
           %*d RETURN_VALUE
  2r
z+DisTests.test_big_offsets.<locals>.expectedr
test_big_offsets+
DisTests.test_big_offsetsc
)	r[
expr_str
dis_expr_str
simple_stmt_str
dis_simple_stmt_str
annot_stmt_str
dis_annot_stmt_str
compound_stmt_str
dis_compound_stmt_strr`
test_disassemble_strG
DisTests.test_disassemble_strc
__code__
co_code
dis_f_co_coder`
test_disassemble_bytesM
DisTests.test_disassemble_bytesc
dis_cr`
test_disassemble_classP
DisTests.test_disassemble_classc
dis_c_instance_methodr`
 test_disassemble_instance_methodS
z)DisTests.test_disassemble_instance_methodc
dis_c_instance_method_bytes)
method_bytecoder
&test_disassemble_instance_method_bytesV
z/DisTests.test_disassemble_instance_method_bytesc
dis_c_static_methodr`
test_disassemble_static_methodZ
z'DisTests.test_disassemble_static_methodc
dis_c_class_methodr`
test_disassemble_class_method]
z&DisTests.test_disassemble_class_methodc
gen_func_disasZ	gen_disasr
test_disassemble_generator`
z#DisTests.test_disassemble_generatorc
agen_func_disasZ
agen_disasr
 test_disassemble_async_generatore
z)DisTests.test_disassemble_async_generatorc
closerY
coro_func_disas
coroZ
coro_disasr
test_disassemble_coroutinej
z#DisTests.test_disassemble_coroutinec
dis_fstringr`
test_disassemble_fstringq
z!DisTests.test_disassemble_fstringc
dis_tryfinallyr9
dis_tryfinallyconstr`
test_disassemble_try_finallyt
z%DisTests.test_disassemble_try_finallyc
last_traceback
AttributeError
assertRaises
RuntimeErrorrI
test_dis_nonex
DisTests.test_dis_nonec
tb_frame
f_code
tb_lastir[
tb_disr
test_dis_traceback
DisTests.test_dis_tracebackc
	TypeErrorrI
objectr`
test_dis_object
DisTests.test_dis_objectc
check
z2DisTests.test_disassemble_recursive.<locals>.checkr
dis_nested_0
dis_nested_1
dis_nested_2)
test_disassemble_recursive
z#DisTests.test_disassemble_recursive)
maxDiffrR
DisWithFileTestsrD
file)
z DisWithFileTests.get_disassemblyN)
Name:              code_info
Filename:          (.*)
Argument count:    1
Positional-only arguments: 0
Kw-only arguments: 0
Number of locals:  1
Stack size:        3
Flags:             OPTIMIZED, NEWLOCALS, NOFREE
Constants:
   0: %r
Names:
   0: _format_code_info
   1: _get_code_object
Variable names:
   0: x)
z1Formatted details of methods, functions, or code.r6
tricky.<locals>.fr
args
kwdsr
tricky
Name:              tricky
Filename:          (.*)
Argument count:    5
Positional-only arguments: 2
Kw-only arguments: 3
Number of locals:  10
Stack size:        9
Flags:             OPTIMIZED, NEWLOCALS, VARARGS, VARKEYWORDS, GENERATOR
Constants:
   0: None
   1: <code object f at (.*), file "(.*)", line (.*)>
   2: 'tricky.<locals>.f'
Variable names:
   0: a
   1: b
   2: x
   3: y
   4: z
   5: c
   6: d
   7: e
   8: args
   9: kwds
Cell variables:
   0: [abedfxyz]
   1: [abedfxyz]
   2: [abedfxyz]
   3: [abedfxyz]
   4: [abedfxyz]
   5: [abedfxyz]ap
Filename:          (.*)
Argument count:    1
Positional-only arguments: 0
Kw-only arguments: 0
Number of locals:  1
Stack size:        10
Flags:             OPTIMIZED, NEWLOCALS, NESTED
Constants:
   0: None
Names:
   0: print
Variable names:
   0: c
Free variables:
   0: [abedfxyz]
   1: [abedfxyz]
   2: [abedfxyz]
   3: [abedfxyz]
   4: [abedfxyz]
   5: [abedfxyz]z
Name:              <module>
Filename:          <disassembly>
Argument count:    0
Positional-only arguments: 0
Kw-only arguments: 0
Number of locals:  0
Stack size:        2
Flags:             NOFREE
Constants:
   0: 1
Names:
   0: xz
Name:              <module>
Filename:          <disassembly>
Argument count:    0
Positional-only arguments: 0
Kw-only arguments: 0
Number of locals:  0
Stack size:        2
Flags:             NOFREE
Constants:
   0: 1
   1: None
Names:
   0: xz
Name:              <module>
Filename:          <disassembly>
Argument count:    0
Positional-only arguments: 0
Kw-only arguments: 0
Number of locals:  0
Stack size:        2
Flags:             NOFREE
Constants:
   0: 0
   1: 1
   2: None
Names:
   0: xc
	async_def+
Name:              async_def
Filename:          (.*)
Argument count:    0
Positional-only arguments: 0
Kw-only arguments: 0
Number of locals:  2
Stack size:        9
Flags:             OPTIMIZED, NEWLOCALS, NOFREE, COROUTINE
Constants:
   0: None
   1: 1
Names:
   0: b
   1: c
Variable names:
   0: a
   1: dc
CodeInfoTestsc
test_pairs
assertRegexrI
	code_info)
test_code_infoN
CodeInfoTests.test_code_infoc
Z	show_coder
test_show_codeS
CodeInfoTests.test_show_codec
test_code_info_object]
z#CodeInfoTests.test_code_info_objectc
0x0)
pretty_flagsr`
test_pretty_flags_no_flags`
z(CodeInfoTests.test_pretty_flags_no_flagsN)
code_info_code_infor
code_info_tricky
co_tricky_nested_f
code_info_tricky_nested_fr
code_info_expr_strr
code_info_simple_stmt_strr
code_info_compound_stmt_strr
code_info_async_defr
)	Nr&
innerh
outer.<locals>.f.<locals>.inner)
outer.<locals>.fru
Hello world!)
outerf
rRq4|
r4qfq4t
I can haz else clause?r
%Who let lolcatz into this test suite?r
%Here we go, here we go, here we go...
Never reach this
OK, now we're done)
ZeroDivisionError)
dodgyr
jumpyo
(3, 4)F)
argZ
argvalZ
argrepr
offsetZ
starts_lineZ
is_jump_targetZ
LOAD_CLOSURE
BUILD_TUPLE
'outer.<locals>.f'r"
MAKE_FUNCTION
defaults, closure
STORE_FAST
LOAD_GLOBAL
LOAD_DEREF
BUILD_LIST
Z	BUILD_MAP
'Hello world!'
CALL_FUNCTION
POP_TOP
RETURN_VALUE
(5, 6)r3
z!'outer.<locals>.f.<locals>.inner'r
Noner#
GET_ITER
FOR_ITER
to 44r
COMPARE_OP
POP_JUMP_IF_FALSE
JUMP_ABSOLUTE
'I can haz else clause?'
INPLACE_SUBTRACT
z''Who let lolcatz into this test suite?'
SETUP_FINALLY
to 200
to 118
BINARY_TRUE_DIVIDE
Z	POP_BLOCK
JUMP_FORWARD
to 144Z
DUP_TOPr
z''Here we go, here we go, here we go...'
POP_EXCEPT
to 188
RERAISE
SETUP_WITH
to 172
'Never reach this'
WITH_EXCEPT_START
POP_JUMP_IF_TRUE
"OK, now we're done"
to 210
simpleS
InstructionTestsc
superr
	__class__r
InstructionTests.__init__c
get_instructionsrm
list
expected_opinfo_simple
actualr
test_default_first_line`
z(InstructionTests.test_default_first_linec
first_linerr
test_first_line_set_to_Noned
z,InstructionTests.test_first_line_set_to_Nonec
expected_outer_linerY
expected_opinfo_outerrv
test_outerh
InstructionTests.test_outerc
expected_f_linerY
expected_opinfo_f)
test_nestedl
InstructionTests.test_nestedc
expected_inner_linerY
expected_opinfo_inner)
test_doubly_nestedr
z#InstructionTests.test_doubly_nestedc
expected_jumpy_linerY
expected_opinfo_jumpyrv
test_jumpyx
InstructionTests.test_jumpy)
__classcell__r
BytecodeTestsc
a=1)
obj)
BytecodeZ
assertIsInstanceZ
codeobj
types
CodeTyper
test_instantiation
z BytecodeTests.test_instantiationc
via_objectZ
via_generatorr
test_iteration
BytecodeTests.test_iterationc
test_explicit_first_line
z&BytecodeTests.test_explicit_first_linec
350)	rI
strip
	partition
strr
co_firstlinenorY
test_source_line_in_disassembly
z-BytecodeTests.test_source_line_in_disassemblyc
info)
	test_info
BytecodeTests.test_infoc
test_disassembled
BytecodeTests.test_disassembledc
from_tracebackr
current_offsetr
test_from_traceback
z!BytecodeTests.test_from_tracebackc
dis_tracebackr
test_from_traceback_dis
z%BytecodeTests.test_from_traceback_disN)
TestDisTracebackN)
returnc
setUpr`
TestDisTraceback.setUpc
distbrK
z TestDisTraceback.get_disassemblyc
test_distb_empty
z!TestDisTraceback.test_distb_emptyc
test_distb_last_traceback
z*TestDisTraceback.test_distb_last_tracebackc
test_distb_explicit_arg
z(TestDisTraceback.test_distb_explicit_arg)	r
TestDisTracebackWithFilec
z(TestDisTracebackWithFile.get_disassemblyNr
__main__)
test.supportr
test.support.bytecode_helperr
unittestr
TRACEBACK_CODEr
__file__rs
TestCaserC
flags
optimizer
__func__
	co_constsr
_line_offsetZ
code_object_fr
code_object_innerr
Instruction
reprr}
mainr
<module>
